Workbook
Name شت8: 'cost.4.25'!$H$18

Sheet Total
A1: Site Name | B1: Day | C1: Month | D1: Year | E1: Total Electricity Kwh | F1: Electricity Tariff ($/Kwh) | G1: LPG (Liters) | H1: LPG $/Liters | I1: Total Fuel Oil (Liter) | J1: Fuel Oil $/Liter | K1: Water Utility Supply (m3) m3 | L1: Water Utility Supply (m3) $/m3 | M1: Room Nights | N1: Total Guests
A2: Grand Rotana Sharm El Cheikh | B2: 1 | C2: 4 | D2: 2025 | E2: ='cost.4.25'!J8 -> 34640 | F2: 1.49 | G2: ='cost.4.25'!AN8 -> 874.712 | H2: ='cost.4.25'!AS8/'cost.4.25'!AN8 -> 3.8150123 | I2: ='cost.4.25'!O8 -> 0 | J2: ='cost.4.25'!T8/'cost.4.25'!O8 -> #DIV/0! | K2: ='cost.4.25'!V8 -> 777 | L2: ='cost.4.25'!Z8/'cost.4.25'!V8 -> 5.1 | M2: ='cost.4.25'!F8 -> 459.1454
A3: Grand Rotana Sharm El Cheikh | B3: =B2+1 -> 2 | C3: 4 | D3: 2025 | E3: ='cost.4.25'!J9 -> 33760 | F3: 1.49 | G3: ='cost.4.25'!AN9 -> 925.306 | H3: ='cost.4.25'!AS9/'cost.4.25'!AN9 -> 3.8076397 | I3: ='cost.4.25'!O9 -> 0 | J3: ='cost.4.25'!T9/'cost.4.25'!O9 -> #DIV/0! | K3: ='cost.4.25'!V9 -> 754 | L3: ='cost.4.25'!Z9/'cost.4.25'!V9 -> 5.1 | M3: ='cost.4.25'!F9 -> 461.9858
A4: Grand Rotana Sharm El Cheikh | B4: =B3+1 -> 3 | C4: 4 | D4: 2025 | E4: ='cost.4.25'!J10 -> 35000 | F4: 1.49 | G4: ='cost.4.25'!AN10 -> 1031.626 | H4: ='cost.4.25'!AS10/'cost.4.25'!AN10 -> 3.8057468 | I4: ='cost.4.25'!O10 -> 0 | J4: ='cost.4.25'!T10/'cost.4.25'!O10 -> #DIV/0! | K4: ='cost.4.25'!V10 -> 753 | L4: ='cost.4.25'!Z10/'cost.4.25'!V10 -> 5.1 | M4: ='cost.4.25'!F10 -> 444.996
A5: Grand Rotana Sharm El Cheikh | B5: =B4+1 -> 4 | C5: 4 | D5: 2025 | E5: ='cost.4.25'!J11 -> 0 | F5: 1.49 | G5: ='cost.4.25'!AN11 -> 0 | H5: ='cost.4.25'!AS11/'cost.4.25'!AN11 -> #DIV/0! | I5: ='cost.4.25'!O11 -> 0 | J5: ='cost.4.25'!T11/'cost.4.25'!O11 -> #DIV/0! | K5: ='cost.4.25'!V11 -> 0 | L5: ='cost.4.25'!Z11/'cost.4.25'!V11 -> #DIV/0! | M5: ='cost.4.25'!F11 -> 0
A6: Grand Rotana Sharm El Cheikh | B6: =B5+1 -> 5 | C6: 4 | D6: 2025 | E6: ='cost.4.25'!J12 -> 0 | F6: 1.49 | G6: ='cost.4.25'!AN12 -> 0 | H6: ='cost.4.25'!AS12/'cost.4.25'!AN12 -> #DIV/0! | I6: ='cost.4.25'!O12 -> 0 | J6: ='cost.4.25'!T12/'cost.4.25'!O12 -> #DIV/0! | K6: ='cost.4.25'!V12 -> 0 | L6: ='cost.4.25'!Z12/'cost.4.25'!V12 -> #DIV/0! | M6: ='cost.4.25'!F12 -> 0
A7: Grand Rotana Sharm El Cheikh | B7: =B6+1 -> 6 | C7: 4 | D7: 2025 | E7: ='cost.4.25'!J13 -> 0 | F7: 1.49 | G7: ='cost.4.25'!AN13 -> 0 | H7: ='cost.4.25'!AS13/'cost.4.25'!AN13 -> #DIV/0! | I7: ='cost.4.25'!O13 -> 0 | J7: ='cost.4.25'!T13/'cost.4.25'!O13 -> #DIV/0! | K7: ='cost.4.25'!V13 -> 0 | L7: ='cost.4.25'!Z13/'cost.4.25'!V13 -> #DIV/0! | M7: ='cost.4.25'!F13 -> 0
A8: Grand Rotana Sharm El Cheikh | B8: =B7+1 -> 7 | C8: 4 | D8: 2025 | E8: ='cost.4.25'!J14 -> 0 | F8: 1.49 | G8: ='cost.4.25'!AN14 -> 0 | H8: ='cost.4.25'!AS14/'cost.4.25'!AN14 -> #DIV/0! | I8: ='cost.4.25'!O14 -> 0 | J8: ='cost.4.25'!T14/'cost.4.25'!O14 -> #DIV/0! | K8: ='cost.4.25'!V14 -> 0 | L8: ='cost.4.25'!Z14/'cost.4.25'!V14 -> #DIV/0! | M8: ='cost.4.25'!F14 -> 0
A9: Grand Rotana Sharm El Cheikh | B9: =B8+1 -> 8 | C9: 4 | D9: 2025 | E9: ='cost.4.25'!J15 -> 0 | F9: 1.49 | G9: ='cost.4.25'!AN15 -> 0 | H9: ='cost.4.25'!AS15/'cost.4.25'!AN15 -> #DIV/0! | I9: ='cost.4.25'!O15 -> 0 | J9: ='cost.4.25'!T15/'cost.4.25'!O15 -> #DIV/0! | K9: ='cost.4.25'!V15 -> 0 | L9: ='cost.4.25'!Z15/'cost.4.25'!V15 -> #DIV/0! | M9: ='cost.4.25'!F15 -> 0
A10: Grand Rotana Sharm El Cheikh | B10: =B9+1 -> 9 | C10: 4 | D10: 2025 | E10: ='cost.4.25'!J16 -> 0 | F10: 1.49 | G10: ='cost.4.25'!AN16 -> 0 | H10: ='cost.4.25'!AS16/'cost.4.25'!AN16 -> #DIV/0! | I10: ='cost.4.25'!O16 -> 0 | J10: ='cost.4.25'!T16/'cost.4.25'!O16 -> #DIV/0! | K10: ='cost.4.25'!V16 -> 0 | L10: ='cost.4.25'!Z16/'cost.4.25'!V16 -> #DIV/0! | M10: ='cost.4.25'!F16 -> 0
A11: Grand Rotana Sharm El Cheikh | B11: =B10+1 -> 10 | C11: 4 | D11: 2025 | E11: ='cost.4.25'!J17 -> 0 | F11: 1.49 | G11: ='cost.4.25'!AN17 -> 0 | H11: ='cost.4.25'!AS17/'cost.4.25'!AN17 -> #DIV/0! | I11: ='cost.4.25'!O17 -> 0 | J11: ='cost.4.25'!T17/'cost.4.25'!O17 -> #DIV/0! | K11: ='cost.4.25'!V17 -> 0 | L11: ='cost.4.25'!Z17/'cost.4.25'!V17 -> #DIV/0! | M11: ='cost.4.25'!F17 -> 0
A12: Grand Rotana Sharm El Cheikh | B12: =B11+1 -> 11 | C12: 4 | D12: 2025 | E12: ='cost.4.25'!J18 -> 0 | F12: 1.49 | G12: ='cost.4.25'!AN18 -> 0 | H12: ='cost.4.25'!AS18/'cost.4.25'!AN18 -> #DIV/0! | I12: ='cost.4.25'!O18 -> 0 | J12: ='cost.4.25'!T18/'cost.4.25'!O18 -> #DIV/0! | K12: ='cost.4.25'!V18 -> 0 | L12: ='cost.4.25'!Z18/'cost.4.25'!V18 -> #DIV/0! | M12: ='cost.4.25'!F18 -> 0
A13: Grand Rotana Sharm El Cheikh | B13: =B12+1 -> 12 | C13: 4 | D13: 2025 | E13: ='cost.4.25'!J19 -> 0 | F13: 1.49 | G13: ='cost.4.25'!AN19 -> 0 | H13: ='cost.4.25'!AS19/'cost.4.25'!AN19 -> #DIV/0! | I13: ='cost.4.25'!O19 -> 0 | J13: ='cost.4.25'!T19/'cost.4.25'!O19 -> #DIV/0! | K13: ='cost.4.25'!V19 -> 0 | L13: ='cost.4.25'!Z19/'cost.4.25'!V19 -> #DIV/0! | M13: ='cost.4.25'!F19 -> 0
A14: Grand Rotana Sharm El Cheikh | B14: =B13+1 -> 13 | C14: 4 | D14: 2025 | E14: ='cost.4.25'!J20 -> 0 | F14: 1.49 | G14: ='cost.4.25'!AN20 -> 0 | H14: ='cost.4.25'!AS20/'cost.4.25'!AN20 -> #DIV/0! | I14: ='cost.4.25'!O20 -> 0 | J14: ='cost.4.25'!T20/'cost.4.25'!O20 -> #DIV/0! | K14: ='cost.4.25'!V20 -> 0 | L14: ='cost.4.25'!Z20/'cost.4.25'!V20 -> #DIV/0! | M14: ='cost.4.25'!F20 -> 0
... A31: Grand Rotana Sharm El Cheikh | B31: =B30+1 -> 30 | C31: 4 | D31: 2025 | E31: ='cost.4.25'!J37 -> 0 | F31: 1.49 | G31: ='cost.4.25'!AN37 -> 0 | H31: ='cost.4.25'!AS37/'cost.4.25'!AN37 -> #DIV/0! | I31: ='cost.4.25'!O37 -> 0 | J31: ='cost.4.25'!T37/'cost.4.25'!O37 -> #DIV/0! | K31: ='cost.4.25'!V37 -> 0 | L31: ='cost.4.25'!Z37/'cost.4.25'!V37 -> #DIV/0! | M31: ='cost.4.25'!F37 -> 0
A32: Grand Rotana Sharm El Cheikh | B32: =B31+1 -> 31 | C32: 4 | D32: 2025 | I32: ='cost.4.25'!O38 -> 0 | J32: ='cost.4.25'!T38/'cost.4.25'!O38 -> #DIV/0!

Sheet Daily Consumption
A1: Date: | B1: =TODAY()-1 -> 45752
A2: Energy Consumption
L3: Month To Date Energy Cost per Occupied Room
B4: Today | F4: Month To Date
B5: Actual | C5: Budget | D5: Act Vs Bdgt | E5: Forecast | F5: Actual | G5: Budget | H5: Act Vs Bdgt | I5: Act Vs Forcast | J5: Forecast
A7: Occupied Rooms | B7: =VLOOKUP(B1,'Reading.4.25'!A5:EL35,39,FALSE) -> 0 | C7: ='Reading.4.25'!AO6 -> 341.9 | D7: =B7-C7 -> -341.9 | E7: 431.3 | F7: ='Reading.4.25'!AM36 -> 1366.1272 | G7: =C7*DAY(B1) -> 1709.5 | H7: =(F7-G7)/F7 -> -0.25134761 | I7: =(F7-J7)/F7 -> -0.57854993 | J7: =E7*DAY(B1) -> 2156.5
A8: Occupancy | B8: =VLOOKUP(B1,'Reading.4.25'!A5:EL35,35,FALSE) -> 0 | C8: ='Reading.4.25'!AK6 -> 0.65 | D8: =B8-C8 -> -0.65 | E8: 0.82 | F8: ='Reading.4.25'!AI36 -> 0.86573333 | G8: =C8 -> 0.65 | H8: =F8-G8 -> 0.21573333 | I8: =F8-J8 -> 0.17673333 | J8: 0.689
A10: Electricity - KWH | B10: =VLOOKUP(B1,'Reading.4.25'!A5:EL35,31,FALSE) -> 0 | C10: ='Reading.4.25'!AG6 -> 26554.533 | D10: =B10-C10 -> -26554.533 | E10: 39500 | F10: ='Reading.4.25'!AE36 -> 103620 | G10: =C10*DAY(B1) -> 132772.67 | H10: =(F10-G10)/F10 -> -0.28134208 | I10: =(F10-J10)/F10 -> -0.9060027 | J10: =+E10*DAY(B1) -> 197500
A11: Fuel - Liter | B11: =VLOOKUP(B1,'Reading.4.25'!A5:EL35,20,FALSE) -> 0 | C11: ='cost.4.25'!P8 -> 83.967742 | D11: =B11-C11 -> -83.967742 | E11: 0 | F11: ='Reading.4.25'!T36 -> 0 | G11: =C11*DAY(B1) -> 419.83871 | H11: =F11-G11 -> -419.83871 | I11: =F11-J11 -> 0 | J11: 0
A13: Boilers Gas - Cu.Mt. | B13: =VLOOKUP(B1,'Reading.4.25'!A5:EL35,15,FALSE) -> 0 | C13: ='cost.4.25'!AD8 -> 487.5 | D13: =B13-C13 -> -487.5 | E13: 636 | F13: ='Reading.4.25'!O36 -> 2000.74 | G13: =C13*DAY(B1) -> 2437.5 | H13: =(F13-G13)/F13 -> -0.21829923 | I13: =(F13-J13)/F13 -> -0.58941192 | J13: =E13*DAY(B1) -> 3180
A14: Kitchens Gas - Cu. Mt. | B14: =VLOOKUP(B1,'Reading.4.25'!A5:EL35,11,FALSE) -> 0 | C14: ='cost.4.25'!AJ8 -> 162.5 | D14: =B14-C14 -> -162.5 | E14: 212 | F14: ='Reading.4.25'!K36 -> 830.904 | G14: =C14*DAY(B1) -> 812.5 | H14: =(F14-G14)/F14 -> 0.02214937 | I14: =(F14-J14)/F14 -> -0.27571898 | J14: =E14*DAY(B1) -> 1060
H15: =F15-G15 -> 0
A16: Water To Staff House - Cu.Mt. | B16: =VLOOKUP(B1,'Reading.4.25'!A2:EL35,88,FALSE) -> 0 | C16: 0 | D16: =B16-C16 -> 0 | E16: 0 | F16: 0 | G16: 0 | H16: =F16-G16 -> 0 | J16: 0
A17: Laundry Water - Cu.Mt. | B17: =VLOOKUP(B1,'Reading.4.25'!A5:EL35,73,FALSE) -> 0 | C17: 0 | D17: =-B17-C17 -> 0 | E17: 0 | F17: ='Reading.4.25'!BU36 -> 172 | G17: 0 | H17: =F17-G17 -> 172 | J17: 0
A18: Kitchen Water - Cu.Mt. | B18: =VLOOKUP(B1,'Reading.4.25'!A5:EL35,69,FALSE) -> 0 | C18: 0 | D18: =B18-C18 -> 0 | E18: 0 | F18: ='Reading.4.25'!BQ36 -> 140 | G18: 0 | H18: =F18-G18 -> 140 | J18: 0
A19: Hotel Water - Cu.Mt. | B19: =VLOOKUP(B1,'Reading.4.25'!A5:EL35,6,FALSE) -> 0 | C19: ='cost.4.25'!W8 -> 493.48387 | D19: =B19-C19 -> -493.48387 | E19: 656 | F19: ='cost.4.25'!V38 -> 2284 | G19: ='cost.4.25'!W38 -> 1480.4516 | H19: =(F19-G19)/F19 -> 0.35181628 | I19: =(F19-J19)/F19 -> -0.43607706 | J19: =E19*DAY(B1) -> 3280
A21: Total Energy Cost - L.E. | B21: =VLOOKUP(B1,'cost.4.25'!B8:BI37,56,FALSE) -> 0 | C21: ='cost.4.25'!BD8 -> 71443.809 | D21: =B21-C21 -> -71443.809 | E21: =(E10*1.94)+(E19*5.1)+((E13+E11)*4) -> 82519.6 | F21: ='cost.4.25'!BE38 -> 223030.78 | G21: =C21*DAY(B1) -> 357219.04 | H21: =(F21-G21)/F21 -> -0.60165807 | I21: =(F21-J21)/F21 -> -0.88798159 | J21: =+(J10*1.94)+((J13+J14)*5)+(J19*5.1) -> 421078
A22: Energy Cost per Occupied Room | B22: =B21/B7 -> #DIV/0! | C22: =C21/C7 -> 208.96112 | D22: =B22-C22 -> #DIV/0! | E22: =E21/E7 -> 191.32761 | F22: =F21/F7 -> 163.25769 | G22: =G21/G7 -> 208.96112 | H22: =(F22-G22)/F22 -> -0.27994657 | I22: =(F22-J22)/F22 -> -0.19602272 | J22: =J21/J7 -> 195.25991
A23: Energy Cost per Available Room | B23: =B21/526 -> 0 | C23: =C21/526 -> 135.82473 | D23: =B23-C23 -> -135.82473 | E23: =E21/526 -> 156.88137 | F23: =F21/(526*DAY(B1)) -> 84.802577 | G23: =G21/(DAY(B1)*526) -> 135.82473 | H23: =(F23-G23)/F23 -> -0.60165807 | I23: =(F23-J23)/F23 -> -0.88798159 | J23: =J21/(526*DAY(B1)) -> 160.1057
A45: Month To Date Electricity Consumption | E45: Month To Date Energy Consumption | L45: Month To Date Kitchens' Gas Consumption
E46: Laundry Performance | L46: Kitchens Performance
A47: Electricity Maximum Demand KW | B47: Today | E47: Target | F47: Last Year | H47: Elec.(Kw)/Room | I47: Today | J47: MTD | K47: Budgeted | L47: Act. LE | M47: Budget LE | N47: Act Vs Bdg | O47: % Budget | P47: forcast | Q47: Act Vs Fos | R47: %forcast
B48: Actual | C48: Last Period | E48: This Period | F48: This Period | I48: =B10/B7 -> #DIV/0! | J48: =F10/F7 -> 75.849452 | K48: =C10/C7 -> 77.667544 | L48: ='cost.4.25'!M38 -> 200596 | M48: ='cost.4.25'!K38 -> 198281.9 | N48: =L48-M48 -> 2314.1 | O48: =(L48/M48)-1 -> 0.011670758 | P48: =J10*1.94 -> 383150 | Q48: =L48-P48 -> -182554 | R48: =(L48/P48)-1 -> -0.4764557
B49: ='Reading.4.25'!AQ36 -> 1332 | C49: ='Reading.4.25'!AQ37 -> 2216 | E49: 2180 | F49: 2120
A51: Weather Temperature ⁰C | B51: Today | E51: Month To Date | H51: Water(l)/Room | I51: Today | J51: MTD | K51: Budgeted | L51: Act. LE | M51: Budget LE | N51: Diff | O51: % | P51: forcast | Q51: Act Vs Fos | R51: % forcast
B52: Actual | C52: Last year | E52: Actual | F52: Last Year | I52: =B19/B7 -> #DIV/0! | J52: =F19/F7 -> 1.6718795 | K52: =C19/C7 -> 1.4433573 | L52: ='cost.4.25'!Z38 -> 11648.4 | M52: ='cost.4.25'!X38 -> 8067.3 | N52: =L52-M52 -> 3581.1 | O52: =(L52/M52)-1 -> 0.44390316 | P52: =J19*5.1 -> 16728 | Q52: =L52-P52 -> -5079.6 | R52: =(L52/P52)-1 -> -0.30365854
B53: =VLOOKUP(B1,'Reading.4.25'!A5:EL35,55,FALSE) -> 0 | C53: =VLOOKUP(B1,'Reading.4.25'!A5:EL35,59,FALSE) -> 0 | E53: ='Reading.4.25'!BC36 -> 16 | F53: ='Reading.4.25'!BG36 -> 80
A54: Humidity % | B54: =VLOOKUP(B1,'Reading.4.25'!A5:EL35,58,FALSE) -> 0 | C54: 60 | E54: ='Reading.4.25'!BF36 -> 25 | F54: =VLOOKUP(B1,'Reading.4.25'!A5:EL35,62,FALSE) -> 0 | H54: Energy - MTD | I54: Energy - forcast | J54: Diff | K54: % | P54: Ro. Production | R54: =VLOOKUP(B1,'Reading.4.25'!A5:EL35,3,FALSE) -> 0
H55: =+F21 -> 223030.78 | I55: =+J21 -> 421078 | J55: =+H55-I55 -> -198047.22 | K55: =+(H55/I55)-1 -> -0.47033382 | P55: Hotel consumption | R55: =+B19 -> 0
A56: Comments: | P56: Diff. | R56: =+R54-R55 -> 0

Sheet Reading.4.25
A1: 1 | B1: 2 | C1: 3 | D1: 4 | E1: 5 | F1: 6 | G1: 7 | H1: 8 | I1: 9 | J1: 10 | K1: 11 | L1: 12 | M1: 13 | N1: 14 | O1: 15 | P1: 16 | Q1: 17 | R1: 18 | S1: 19 | T1: 20 | U1: 21 | V1: 22 | W1: 23 | X1: 24 | Y1: 25 | Z1: 26 | AA1: 27 | AB1: 28 | AC1: 29 | AD1: 30 | AE1: 31 | AF1: 32 | AG1: 33 | AH1: 34 | AI1: 35 | AJ1: 36 | AK1: 37 | AL1: 38 | AM1: 39 | AN1: 40 | AO1: 41 | AP1: 42 | AQ1: 43 | AR1: 44 | AS1: 45 | AT1: 46 | AU1: 47 | AV1: 48 | AW1: 49 | AX1: 50 | AY1: 51 | AZ1: 52 | BA1: 53 | BB1: 54 | BC1: 55 | BD1: 56 | BE1: 57 | BF1: 58 | BG1: 59 | BH1: 60 | BI1: 61 | BJ1: 62 | BK1: 63 | BL1: 64 | BM1: 65 | BN1: 66 | BO1: 67 | BP1: 68 | BQ1: 69 | BR1: 70 | BS1: 71 | BT1: 72 | BU1: 73 | BV1: 74 | BW1: 75 | BX1: 76 | BY1: 77 | BZ1: 78 | CA1: 79 | CB1: 80 | CC1: 81 | CD1: 82 | CE1: 83 | CF1: 84 | CG1: 85 | CH1: 86 | CI1: 87 | CJ1: 88 | CK1: 89 | CL1: 90 | CM1: 91 | CN1: 92 | CO1: 93 | CP1: 94 | CQ1: 95 | CR1: 96 | CS1: 97 | CT1: 98 | CU1: 99 | CV1: 100 | CW1: 101 | CX1: 102 | CY1: 103 | CZ1: 104 | DA1: 105 | DB1: 106 | DC1: 107 | DD1: 108 | DE1: 109 | DF1: 110 | DG1: 111 | DH1: 112 | DI1: 113 | DJ1: 114 | DK1: 115 | DL1: 116 | DM1: 117 | DN1: 118 | DO1: 119 | DP1: 120 | DQ1: 121 | DR1: 122 | DS1: 123 | DT1: 124 | DU1: 125 | DV1: 126 | DW1: 127 | DX1: 128 | DY1: 129 | DZ1: 130 | EA1: 131 | EB1: 132 | EC1: 133 | ED1: 134 | EE1: 135 | EF1: 136 | EG1: 137 | EH1: 138 | EI1: 139 | EJ1: 140 | EK1: 141 | EL1: 142
B2: WATER | J2: KITCHEN GAS | N2: BOILER GAS | R2: FUEL | W2: ELECTRICITY | AA2: GENERATORS | AE2: TOTAL KWH | AI2: Occupancy % | AM2: Rooms Occupied | AQ2: Max. Demand | AT2: Power Factor | AY2: More Data | BC2: Weather Temperature | BL2: Available Rooms | BN2: Water Sold Last Year | BP2: Kitchen Water | BT2: Laundry Water | BX2: Fountain Water | CB2: S. Pool Water | CF2: Heated Pool Water | CI2: Staff Houses Water | CM2: Total Facilities Cons. | CP2: STP | CV2: Dishwasher | CZ2: Staff Kitchen | DD2: Laundry Electricity | DH2: Kit. Equip. Electricity | DL2: Chiller 1 | DP2: Chiller 2 | DT2: Chiller 3 | DX2: Chilled Pumps KWH | DZ2: Total Chillers | EC2: RO Plant | EF2: Staff Kitchen Gas | EJ2: Rotary Oven Gas | EN2: Water Counter Reading | ES2: Jockey Pump | ET2: Consumption
A4: Date | B4: Reading | C4: Product. | D4: Sold | E4: Tanks Level | F4: Counters reading | G4: Consump. This Year | H4: Last Year | J4: Reading | K4: Consump. This Year | L4: Last Year | N4: Reading | O4: Consump. This Year | P4: Last Year | R4: Reading | S4: Add | T4: Consump. This Year | U4: Last Year | W4: Reading | X4: Consump. This Year | Y4: Consump. Last Year | AA4: Reading | AB4: Consump. This Year | AC4: Consump. Last Year | AE4: This Year | AF4: Last Year | AG4: Budget | AI4: This Year | AJ4: Last Year | AK4: Budget | AM4: This Year | AN4: Last Year | AO4: Budget | AQ4: This Year KW | AR4: Last Year KW | AT4: KVAR Reading | AU4: KVAR Cons. | AV4: Cos Ø | AY4: Last Year OCT 2023 | BC4: This Year - OCT 2024 | BG4: Last Year - OCT 2023 | BP4: Counter Reading | BQ4: Consumption This year | BR4: Consumption Last Year | BT4: Counter Reading | BU4: Consumption | BV4: Consumption Last Year | BX4: Counter Reading | BY4: Consumption | BZ4: Consumption Last Year | CB4: Counter Reading | CC4: Consumption | CD4: Consumption Last Year | CF4: Counter Reading | CG4: Consumption | CH4: Consumption Last Year | CI4: Counter Reading | CJ4: Consumption | CK4: Consumption Last Year | CM4: This Year | CN4: Last Year | CP4: Counter Reading | CQ4: Recycled Water this Year | CR4: % | CS4: Reccycled Water Last Year | CT4: % | CV4: Counter Reading | CW4: Cons. | CX4: Cons. Last Year | CZ4: Counter Reading | DA4: Cons. | DB4: Cons. Last Year | DD4: Counter Reading | DE4: Cons. | DF4: Cons. Last Year | DH4: Counter Reading | DI4: Cons. | DJ4: Cons. Last Year | DL4: Counter Reading | DM4: Cons. | DN4: Cons. Last Year | DP4: Counter Reading | DQ4: Cons. | DR4: Cons. Last Year | DT4: Counter Reading | DU4: Cons. | DV4: Cons. Last Year | DZ4: Cons. | EA4: Cons. Last Year | EC4: KWH This Year | ED4: KWH Last Year | EF4: Counter Reading | EG4: Cons. | EH4: Cons. Last Year | EJ4: Counter Reading | EK4: Cons. | EL4: Cons. Last Year | EN4: C1 | EO4: C2 | EP4: C3 | EQ4: Total
B5: 502969 | E5: 770 | G5: =F5+ET5 -> 0 | J5: 224175 | N5: 770511 | R5: 65800 | W5: 48917.4 | AA5: 535640 | AT5: 7557.67 | BL5: 526 | BP5: 80374 | BT5: 96123 | BX5: 4317 | CB5: 248910 | CF5: 9150 | CI5: 19771 | CP5: 83180 | CV5: 418 | CZ5: 2417 | DD5: 1739496 | DH5: 3947489 | DL5: 3363547 | DP5: 2900611 | DT5: 3582939 | DX5: 720 | EF5: 69556 | EJ5: 32597 | EN5: 35710 | EO5: 34971 | EP5: 34295 | ES5: 6974
A6: 45748 | B6: 503666 | C6: =B6-B5 -> 697 | E6: 800 | F6: =EQ6 -> 746 | G6: =F6+ET6 -> 777 | H6: ='Reading.4.24'!G6 -> 505 | J6: 224234 | K6: =(J6-J5)*4.668 -> 275.412 | L6: ='Reading.4.24'!K6 -> 112.032 | N6: 770641 | O6: =(N6-N5)*4.61 -> 599.3 | P6: ='Reading.4.24'!O6 -> 391.85 | R6: 65800 | T6: =(R5+S5)-R6 -> 0 | U6: ='Reading.4.24'!T6 -> 0 | W6: 48926.06 | X6: =(W6-W5)*4000 -> 34640 | Y6: ='Reading.4.24'!X6 -> 27720 | AA6: 535860 | AB6: =AA6-AA5 -> 220 | AC6: ='Reading.4.24'!AB6 -> 0 | AE6: =+X6+AB6 -> 34860 | AF6: ='Reading.4.24'!AE6 -> 27720 | AG6: =796636/30 -> 26554.533 | AI6: 0.8729 | AJ6: ='Reading.4.24'!AI6 -> 0.5209 | AK6: 0.65 | AM6: =AI6*526 -> 459.1454 | AN6: ='Reading.4.24'!AM6 -> 274 | AO6: =10257/30 -> 341.9 | AQ6: =333*4 -> 1332 | AR6: ='Reading.4.24'!AQ6 -> 1460 | AT6: 7559.13 | AU6: =(AT6-AT5)*4000 -> 5840 | AV6: =+X6/SQRT(((POWER((X6),2)+(POWER((AU6),2))))) -> 0.98608445 | AY6: ='Reading.4.24'!X6 -> 27720 | AZ6: ='Reading.4.24'!Y6 -> 25200 | BA6: =AY6+AZ6 -> 52920 | BC6: 16 | BD6: 20 | BE6: 18 | BF6: 25 | BG6: 80 | BH6: ='Reading.4.24'!BD6 -> 16.1 | BI6: ='Reading.4.24'!BE6 -> 12 | BJ6: ='Reading.4.24'!BF6 -> 56 | BL6: 526 | BN6: ='Reading.4.24'!E3 -> 0 | BP6: 80400 | BQ6: =BP6-BP5 -> 26 | BR6: ='Reading.4.24'!BQ6 -> 30 | BT6: 96172 | BU6: =BT6-BT5 -> 49 | BV6: ='Reading.4.24'!BU6 -> 30 | BX6: 4317 | BY6: =BX6-BX5 -> 0 | BZ6: ='Reading.4.24'!BY6 -> 11 | CB6: 248950 | CC6: =CB6-CB5 -> 40 | CD6: ='Reading.4.24'!CC6 -> 30 | CF6: 9160 | CG6: =CF6-CF5 -> 10 | CH6: ='Reading.4.24'!CG6 -> 10 | CI6: 19771 | CJ6: =CI6-CI5 -> 0 | CK6: ='Reading.4.24'!CJ6 -> -3 | CM6: =BQ6+BU6+BY6+CC6+CJ6 -> 115 | CN6: =BR6+BV6+BZ6+CD6+CK6 -> 98 | CP6: 83780 | CQ6: =CP6-CP5 -> 600 | CR6: =CQ6/G6 -> 0.77220077 | CS6: ='Reading.4.24'!CN6 -> 135 | CT6: ='Reading.4.24'!CR6 -> 0.67920792 | CV6: 419 | CW6: =CV6-CV5 -> 1 | CX6: ='Reading.4.24'!CW6 -> 2 | CZ6: 2423 | DA6: =CZ6-CZ5 -> 6 | DB6: ='Reading.4.24'!DA6 -> 3 | DD6: 1740450 | DE6: =DD6-DD5 -> 954 | DF6: ='Reading.4.24'!DE6 -> 757 | DH6: 3949300 | DI6: =DH6-DH5 -> 1811 | DJ6: ='Reading.4.24'!DI6 -> 1866 | DL6: 3365383 | DM6: =DL6-DL5 -> 1836 | DN6: ='Reading.4.24'!DM6 -> 3208 | DP6: 2902187 | DQ6: =DP6-DP5 -> 1576 | DR6: ='Reading.4.24'!DQ6 -> 31 | DT6: 3582953 | DU6: =DT6-DT5 -> 14 | DV6: ='Reading.4.24'!DU6 -> 31 | DX6: 720 | DZ6: =DM6+DQ6+DU6+DX6 -> 4146 | EA6: ='Reading.4.24'!DZ6 -> 3990 | EC6: =C6*5.2 -> 3624.4 | ED6: ='Reading.4.24'!EC6 -> 2158 | EF6: 69598 | EG6: =EF6-EF5 -> 42 | EH6: ='Reading.4.24'!EG6 -> 40 | EJ6: 32629 | EK6: =EJ6-EJ5 -> 32 | EL6: ='Reading.4.24'!EK6 -> 33 | EN6: 35728 | EO6: 35550 | EP6: 34444 | EQ6: =(EN6-EN5)+(EO6-EO5)+(EP6-EP5) -> 746 | ES6: 7005 | ET6: =+ES6-ES5 -> 31
A7: 45749 | B7: 504119 | C7: =B7-B6 -> 453 | E7: 800 | F7: =EQ7 -> 723 | G7: =F7+ET7 -> 754 | H7: ='Reading.4.24'!G7 -> 460 | J7: 224291 | K7: =(J7-J6)*4.668 -> 266.076 | L7: ='Reading.4.24'!K7 -> 121.368 | N7: 770784 | O7: =(N7-N6)*4.61 -> 659.23 | P7: ='Reading.4.24'!O7 -> 410.29 | R7: 65800 | T7: =(R6+S6)-R7 -> 0 | U7: ='Reading.4.24'!T7 -> 0 | W7: 48934.5 | X7: =(W7-W6)*4000 -> 33760 | Y7: ='Reading.4.24'!X7 -> 28600 | AA7: 535860 | AB7: =AA7-AA6 -> 0 | AC7: ='Reading.4.24'!AB7 -> 0 | AE7: =+X7+AB7 -> 33760 | AF7: ='Reading.4.24'!AE7 -> 28600 | AG7: =796636/30 -> 26554.533 | AI7: 0.8783 | AJ7: ='Reading.4.24'!AI7 -> 0.4924 | AK7: 0.65 | AM7: =AI7*526 -> 461.9858 | AN7: ='Reading.4.24'!AM7 -> 259 | AO7: =10257/30 -> 341.9 | AQ7: =333*4 -> 1332 | AR7: ='Reading.4.24'!AQ7 -> 1460 | AT7: 7560.53 | AU7: =(AT7-AT6)*4000 -> 5600 | AV7: =+X7/SQRT(((POWER((X7),2)+(POWER((AU7),2))))) -> 0.98652 | AY7: ='Reading.4.24'!X7 -> 28600 | AZ7: ='Reading.4.24'!Y7 -> 25640 | BA7: =AY7+AZ7 -> 54240 | BC7: 16 | BD7: 20 | BE7: 18 | BF7: 25 | BG7: 80 | BH7: ='Reading.4.24'!BD7 -> 16.1 | BI7: ='Reading.4.24'!BE7 -> 12 | BJ7: ='Reading.4.24'!BF7 -> 56 | BL7: 526 | BN7: ='Reading.4.24'!E4 -> Sold | BP7: 80432 | BQ7: =BP7-BP6 -> 32 | BR7: ='Reading.4.24'!BQ7 -> 18 | BT7: 96234 | BU7: =BT7-BT6 -> 62 | BV7: ='Reading.4.24'!BU7 -> 34 | BX7: 4317 | BY7: =BX7-BX6 -> 0 | BZ7: ='Reading.4.24'!BY7 -> 0 | CB7: 249030 | CC7: =CB7-CB6 -> 80 | CD7: ='Reading.4.24'!CC7 -> 20 | CF7: 9170 | CG7: =CF7-CF6 -> 10 | CH7: ='Reading.4.24'!CG7 -> 0 | CI7: 19771 | CJ7: =CI7-CI6 -> 0 | CK7: ='Reading.4.24'!CJ7 -> 0 | CM7: =BQ7+BU7+BY7+CC7+CJ7 -> 174 | CN7: =BR7+BV7+BZ7+CD7+CK7 -> 72 | CP7: 84400 | CQ7: =CP7-CP6 -> 620 | CR7: =CQ7/G7 -> 0.82228117 | CS7: ='Reading.4.24'!CN7 -> 148 | CT7: ='Reading.4.24'!CR7 -> 0.76086957 | CV7: 420 | CW7: =CV7-CV6 -> 1 | CX7: ='Reading.4.24'!CW7 -> 2 | CZ7: 2428 | DA7: =CZ7-CZ6 -> 5 | DB7: ='Reading.4.24'!DA7 -> 2 | DD7: 1741445 | DE7: =DD7-DD6 -> 995 | DF7: ='Reading.4.24'!DE7 -> 706 | DH7: 3951100 | DI7: =DH7-DH6 -> 1800 | DJ7: ='Reading.4.24'!DI7 -> 1144 | DL7: 3367398 | DM7: =DL7-DL6 -> 2015 | DN7: ='Reading.4.24'!DM7 -> 3552 | DP7: 2903962 | DQ7: =DP7-DP6 -> 1775 | DR7: ='Reading.4.24'!DQ7 -> 34 | DT7: 3582972 | DU7: =DT7-DT6 -> 19 | DV7: ='Reading.4.24'!DU7 -> 31 | DX7: 720 | DZ7: =DM7+DQ7+DU7+DX7 -> 4529 | EA7: ='Reading.4.24'!DZ7 -> 4337 | EC7: =C7*5.2 -> 2355.6 | ED7: ='Reading.4.24'!EC7 -> 2626 | EF7: 69645 | EG7: =EF7-EF6 -> 47 | EH7: ='Reading.4.24'!EG7 -> 49 | EJ7: 32665 | EK7: =EJ7-EJ6 -> 36 | EL7: ='Reading.4.24'!EK7 -> 17 | EN7: 35838 | EO7: 35716 | EP7: 34891 | EQ7: =(EN7-EN6)+(EO7-EO6)+(EP7-EP6) -> 723 | ES7: 7036 | ET7: =+ES7-ES6 -> 31
A8: 45750 | B8: 504871 | C8: =B8-B7 -> 752 | E8: 695 | F8: =EQ8 -> 718 | G8: =F8+ET8 -> 753 | H8: ='Reading.4.24'!G8 -> 552 | J8: 224353 | K8: =(J8-J7)*4.668 -> 289.416 | L8: ='Reading.4.24'!K8 -> 149.376 | N8: 770945 | O8: =(N8-N7)*4.61 -> 742.21 | P8: ='Reading.4.24'!O8 -> 387.24 | R8: 65800 | T8: =(R7+S7)-R8 -> 0 | U8: ='Reading.4.24'!T8 -> 0 | W8: 48943.25 | X8: =(W8-W7)*4000 -> 35000 | Y8: ='Reading.4.24'!X8 -> 29160 | AA8: 535860 | AB8: =AA8-AA7 -> 0 | AC8: ='Reading.4.24'!AB8 -> 0 | AE8: =+X8+AB8 -> 35000 | AF8: ='Reading.4.24'!AE8 -> 29160 | AG8: =796636/30 -> 26554.533 | AI8: 0.846 | AJ8: ='Reading.4.24'!AI8 -> 0.4943 | AK8: 0.65 | AM8: =AI8*526 -> 444.996 | AN8: ='Reading.4.24'!AM8 -> 260 | AO8: =10257/30 -> 341.9 | AQ8: =333*4 -> 1332 | AR8: ='Reading.4.24'!AQ8 -> 1548 | AT8: 7561.84 | AU8: =(AT8-AT7)*4000 -> 5240 | AV8: =+X8/SQRT(((POWER((X8),2)+(POWER((AU8),2))))) -> 0.98897777 | AY8: ='Reading.4.24'!X8 -> 29160 | AZ8: ='Reading.4.24'!Y8 -> 25760 | BA8: =AY8+AZ8 -> 54920 | BC8: 16 | BD8: 20 | BE8: 18 | BF8: 25 | BG8: 80 | BH8: ='Reading.4.24'!BD8 -> 16.1 | BI8: ='Reading.4.24'!BE8 -> 12 | BJ8: ='Reading.4.24'!BF8 -> 56 | BL8: 526 | BN8: ='Reading.4.24'!E5 -> 0 | BP8: 80514 | BQ8: =BP8-BP7 -> 82 | BR8: ='Reading.4.24'!BQ8 -> 18 | BT8: 96295 | BU8: =BT8-BT7 -> 61 | BV8: ='Reading.4.24'!BU8 -> 36 | BX8: 4317 | BY8: =BX8-BX7 -> 0 | BZ8: ='Reading.4.24'!BY8 -> 0 | CB8: 249050 | CC8: =CB8-CB7 -> 20 | CD8: ='Reading.4.24'!CC8 -> 30 | CF8: 9185 | CG8: =CF8-CF7 -> 15 | CH8: ='Reading.4.24'!CG8 -> 10 | CI8: 19771 | CJ8: =CI8-CI7 -> 0 | CK8: ='Reading.4.24'!CJ8 -> 0 | CM8: =BQ8+BU8+BY8+CC8+CJ8 -> 163 | CN8: =BR8+BV8+BZ8+CD8+CK8 -> 84 | CP8: 84950 | CQ8: =CP8-CP7 -> 550 | CR8: =CQ8/G8 -> 0.73041169 | CS8: ='Reading.4.24'!CN8 -> 122 | CT8: ='Reading.4.24'!CR8 -> 0.66123188 | CV8: 423 | CW8: =CV8-CV7 -> 3 | CX8: ='Reading.4.24'!CW8 -> 2 | CZ8: 2429 | DA8: =CZ8-CZ7 -> 1 | DB8: ='Reading.4.24'!DA8 -> 3 | DD8: 1742447 | DE8: =DD8-DD7 -> 1002 | DF8: ='Reading.4.24'!DE8 -> 695 | DH8: 3952437 | DI8: =DH8-DH7 -> 1337 | DJ8: ='Reading.4.24'!DI8 -> 1151 | DL8: 3369186 | DM8: =DL8-DL7 -> 1788 | DN8: ='Reading.4.24'!DM8 -> 3782 | DP8: 2905512 | DQ8: =DP8-DP7 -> 1550 | DR8: ='Reading.4.24'!DQ8 -> 31 | DT8: 3582989 | DU8: =DT8-DT7 -> 17 | DV8: ='Reading.4.24'!DU8 -> 32 | DX8: 720 | DZ8: =DM8+DQ8+DU8+DX8 -> 4075 | EA8: ='Reading.4.24'!DZ8 -> 4565 | EC8: =C8*5.2 -> 3910.4 | ED8: ='Reading.4.24'!EC8 -> 3026.4 | EF8: 69779 | EG8: =EF8-EF7 -> 134 | EH8: ='Reading.4.24'!EG8 -> 45 | EJ8: 32674 | EK8: =EJ8-EJ7 -> 9 | EL8: ='Reading.4.24'!EK8 -> 25 | EN8: 36388 | EO8: 35763 | EP8: 35012 | EQ8: =(EN8-EN7)+(EO8-EO7)+(EP8-EP7) -> 718 | ES8: 7071 | ET8: =+ES8-ES7 -> 35
A9: 45751
A10: 45752
A11: 45753
A12: 45754
A13: 45755
A14: 45756
A15: 45757
A16: 45758
A17: 45759
A18: 45760
A19: 45761
A20: 45762
... A35: 45777
C36: =AVERAGE(C6:C35) -> 634 | G36: =SUM(G6:G35) -> 2284 | H36: =SUM(H6:H35) -> 1517 | K36: =SUM(K6:K35) -> 830.904 | L36: =SUM(L6:L35) -> 382.776 | O36: =SUM(O6:O35) -> 2000.74 | P36: =SUM(P6:P35) -> 1189.38 | S36: =SUM(S6:S35) -> 0 | T36: =SUM(T6:T35) -> 0 | U36: =SUM(U6:U35) -> 0 | X36: =SUM(X6:X35) -> 103400 | Y36: =SUM(Y6:Y35) -> 85480 | AB36: =SUM(AB6:AB35) -> 220 | AC36: =SUM(AC6:AC35) -> 0 | AE36: =SUM(AE6:AE35) -> 103620 | AF36: =SUM(AF6:AF35) -> 85480 | AG36: =SUM(AG6:AG35) -> 79663.6 | AI36: =AVERAGE(AI6:AI35) -> 0.86573333 | AJ36: =AVERAGE(AJ6:AJ35) -> 0.50253333 | AK36: =AVERAGE(AK6:AK35) -> 0.65 | AM36: =SUM(AM6:AM35) -> 1366.1272 | AN36: =SUM(AN6:AN35) -> 793 | AO36: =SUM(AO6:AO35) -> 1025.7 | AQ36: =MAX(AQ6:AQ35) -> 1332 | AR36: =MAX(AR6:AR35) -> 1548 | AV36: =AVERAGE(AV6:AV35) -> 0.98719407 | AY36: =SUM(AY6:AY35) -> 85480 | AZ36: =SUM(AZ6:AZ35) -> 76600 | BA36: =SUM(BA6:BA35) -> 162080 | BC36: =AVERAGE(BC6:BC35) -> 16 | BD36: =AVERAGE(BD6:BD35) -> 20 | BE36: =AVERAGE(BE6:BE35) -> 18 | BF36: =AVERAGE(BF6:BF35) -> 25 | BG36: =AVERAGE(BG6:BG35) -> 80 | BH36: =AVERAGE(BH6:BH35) -> 16.1 | BI36: =AVERAGE(BI6:BI35) -> 12 | BJ36: =AVERAGE(BJ6:BJ35) -> 56 | BL36: =SUM(BL6:BL35) -> 1578 | BN36: =SUM(BN6:BN35) -> 0 | BQ36: =SUM(BQ6:BQ35) -> 140 | BR36: =SUM(BR6:BR35) -> 66 | BU36: =SUM(BU6:BU35) -> 172 | BV36: =SUM(BV6:BV35) -> 100 | BY36: =SUM(BY6:BY35) -> 0 | BZ36: =SUM(BZ6:BZ35) -> 11 | CC36: =SUM(CC6:CC35) -> 140 | CD36: =SUM(CD6:CD35) -> 80 | CG36: =SUM(CG6:CG35) -> 35 | CH36: =SUM(CH6:CH35) -> 20 | CJ36: =SUM(CJ6:CJ35) -> 0 | CK36: =SUM(CK6:CK35) -> -3 | CM36: =SUM(CM6:CM35) -> 452 | CN36: =SUM(CN6:CN35) -> 254 | CQ36: =SUM(CQ6:CQ35) -> 1770 | CR36: =AVERAGE(CR13:CR35) -> #DIV/0! | CS36: ='Reading.4.24'!CN35 -> 123 | CT36: ='Reading.4.24'!CO35 -> 0 | CW36: =SUM(CW6:CW35) -> 5 | CX36: ='Reading.4.24'!CT37 -> 0.52997602 | DA36: =SUM(DA6:DA35) -> 12 | DB36: =SUM(DB6:DB35) -> 8 | DE36: =SUM(DE6:DE35) -> 2951 | DF36: =SUM(DF6:DF35) -> 2158 | DI36: =SUM(DI6:DI35) -> 4948 | DJ36: =SUM(DJ6:DJ35) -> 4161 | DM36: =SUM(DM6:DM35) -> 5639 | DN36: =SUM(DN6:DN35) -> 10542 | DQ36: =SUM(DQ6:DQ35) -> 4901 | DR36: =SUM(DR6:DR35) -> 96 | DU36: =SUM(DU6:DU35) -> 50 | DV36: =SUM(DV6:DV35) -> 94 | DZ36: =SUM(DZ6:DZ35) -> 12750 | EA36: =SUM(EA6:EA35) -> 12892 | EC36: =SUM(EC6:EC35) -> 9890.4 | ED36: =SUM(ED6:ED35) -> 7810.4 | EG36: =SUM(EG6:EG35) -> 223 | EH36: =SUM(EH6:EH35) -> 134 | EK36: =SUM(EK6:EK35) -> 77 | EL36: =SUM(EL6:EL35) -> 75
C37: Average/Day | AP37: Last Period Max. Demand: | AQ37: 2216 | CQ37: 0
C38: =SUM(C6:C35) -> 1902 | AP38: This Period Max. Demand: | AQ38: 2160
B39: =+B31-B30 -> 0 | U39: ENERGY COST / OCCUPIED ROOM - LAST YEAR = | AB39: ='cost.4.25'!BG38 -> 109.50475 | AC39: L.E. | AF39: OCCUPANCY - LAST YEAR = | AJ39: =AJ36 -> 0.50253333 | AM39: KWH / OCCUPIED ROOM - LAST YEAR | AR39: =AF36/AN36 -> 107.79319 | AY39: https://www.wunderground.com/history/monthly/eg/sharm-el-shiekh/HESH/date/2024-10
U40: ENERGY COST / OCCUPIED ROOM - THIS YEAR = | AB40: ='cost.4.25'!BI38 -> 163.33877 | AC40: L.E. | AF40: OCCUPANCY - THIS YEAR = | AJ40: =AI36 -> 0.86573333 | AM40: KWH / OCCU[PIED ROOM - THIS YEAR | AR40: =AE36/AM36 -> 75.849452
N41: =X36*2 -> 206800 | U41: ENERGY COST / OCCUPIED ROOM - BUDGET = | AB41: ='cost.4.25'!BH38 -> 334.74341 | AC41: L.E. | AF41: OCCUPANCY - BUDGET= | AJ41: =AK36 -> 0.65 | AM41: KWH / OCCUPIED ROOM - BUDGET | AR41: =AG36/AO36 -> 77.667544 | CC41: =229975+25 -> 230000
AM43: KWH / AVAILABLE ROOM - LAST YEAR | AR43: =AF36/BL36 -> 54.169835
AM44: KWH / AVAILABLE ROOM - THIS YEAR | AR44: =AE36/BL36 -> 65.665399
AM45: KWH / AVAILABLE ROOM - BUDGET | AR45: =AG36/BL36 -> 50.483904
DM80: .
BQ150: .

Sheet cost.4.25
H1: =H8*31 -> 6616.2857 | K1: =K8*31 -> 2048913 | P1: =P8*31 -> 2603 | R1: =R8*31 -> 0 | W1: =W8*31 -> 15298 | X1: =X8*31 -> 83362.1 | AD1: =AD8*31 -> 15112.5 | AJ1: =AJ8*31 -> 5037.5 | AP1: =AP8*31 -> 20150 | AQ1: =AQ8*31 -> 82483
A2: Energy Cost April 2025 | AV2: Energy Cost - April 2024
B3: 1 | C3: 2 | D3: 3 | E3: 4 | F3: 5 | G3: 6 | H3: 7 | I3: 8 | J3: 9 | K3: 10 | L3: 11 | M3: 12 | N3: 13 | O3: 14 | P3: 15 | Q3: 16 | R3: 17 | S3: 18 | T3: 19 | U3: 20 | V3: 21 | W3: 22 | X3: 23 | Y3: 24 | Z3: 25 | AA3: 26 | AB3: 27 | AC3: 28 | AD3: 29 | AE3: 30 | AF3: 31 | AG3: 32 | AH3: 33 | AI3: 34 | AJ3: 35 | AK3: 36 | AL3: 37 | AM3: 38 | AN3: 39 | AO3: 40 | AP3: 41 | AQ3: 42 | AR3: 43 | AS3: 44 | AT3: 45 | AU3: 46 | AV3: 47 | AW3: 48 | AX3: 49 | AY3: 50 | AZ3: 51 | BA3: 52 | BB3: 53 | BC3: 54 | BD3: 55 | BE3: 56 | BF3: 57 | BG3: 58 | BH3: 59 | BI3: 60
J5: ELECTRICITY | O5: FUEL | V5: WATER | AB5: NATURAL GAS | AV5: ELECTRICITY | AX5: WATER | AZ5: NATURAL GAS | BC5: LAST YEAR TOTAL ENERGY L.E. | BD5: BUDGET TOTAL ENERGY L.E. | BE5: ACTUAL TOTAL ENERGY L.E. | BG5: ENERGY LAST YEAR / OCCUPIED ROOM | BH5: ENERGY BUDGET / OCCUPIED ROOM | BI5: ENERGY ACTUAL / OCCUPIED ROOM
B6: DATE | D6: Occ. | F6: Occupied Rooms | H6: Occupied Rooms Budget | J6: CONSUMP. KWH | K6: BUDGET L.E. | L6: LAST YEAR ACTUAL L.E. | M6: ACTUAL L.E. | O6: CONSUMP. LITRE | P6: BUDGET LITRE | Q6: GENERATOR KWH | R6: BUDGET L.E. | S6: LAST YEAR ACTUAL L.E. | T6: ACTUAL L.E. | V6: CONSUMP. M³ | W6: BUDGET M³ | X6: BUDGET L.E. | Y6: LAST YEAR ACTUAL L.E. | Z6: ACTUAL L.E. | AB6: BOILER CONSUMP. M³ | AC6: BOILER COST L.E. | AD6: BOILER BUDGET CONSUMP. M³ | AE6: BOILER BUDGET COST L.E. | AF6: BOILER CONSUMP. LAST YEAR M³ | AG6: BOILER COST LAST YEAR L.E. | AH6: KITCHEN CONSUMP. M³ | AI6: KITCHEN COST L.E. | AJ6: KITCHEN BUDGET CONSUMP. M³ | AK6: KITCHEN BUDGET COST L.E. | AL6: KITCHEN CONSUMP. LAST YEAR M³ | AM6: KITCHEN COST LAST YEAR L.E. | AN6: TOTAL CONSUMP. M³ | AO6: TOTAL CONSUMP. LAST YEAR M³ | AP6: BUDGET TOTAL CONSUMP. M³ | AQ6: BUDGET L.E. | AR6: LAST YEAR ACTUAL L.E. | AS6: ACTUAL L.E. | AV6: KWH / Occupied Room | AW6: L.E. / Occupied Room | AX6: Cu.Mt. / Occupied Room | AY6: L.E. / Occupied Room | AZ6: Cu.Mt. / Occupied Room | BA6: L.E. / Occupied Room
B8: 45748 | D8: ='Reading.4.25'!AI6 -> 0.8729 | F8: ='Reading.4.25'!AM6 -> 459.1454 | H8: =5976/28 -> 213.42857 | J8: ='Reading.4.25'!X6 -> 34640 | K8: =1982819/30 -> 66093.967 | L8: ='Cost.4.24'!M7 -> 0 | M8: =J8*1.94 -> 67201.6 | O8: ='Reading.4.25'!T6 -> 0 | P8: =2603/31 -> 83.967742 | Q8: ='Reading.4.25'!AB6 -> 220 | R8: =0/30 -> 0 | S8: ='Cost.4.24'!T7 -> 0 | T8: =O8*7.55 -> 0 | V8: ='Reading.4.25'!G6 -> 777 | W8: =15298/31 -> 493.48387 | X8: =80673/30 -> 2689.1 | Y8: ='Cost.4.24'!Z7 -> 0 | Z8: ='Reading.4.25'!G6*5.1 -> 3962.7 | AB8: ='Reading.4.25'!O6 -> 599.3 | AC8: =AB8*3.73 -> 2235.389 | AD8: =((19500/4)*3)/30 -> 487.5 | AE8: =((83461/4)*3)/30 -> 2086.525 | AF8: ='Cost.4.24'!AB7 -> 0 | AG8: ='Cost.4.24'!AC7 -> 0 | AH8: ='Reading.4.25'!K6 -> 275.412 | AI8: =AH8*4 -> 1101.648 | AJ8: =(19500/4)/30 -> 162.5 | AK8: =(83461/4)/30 -> 695.50833 | AL8: ='Cost.4.24'!AH7 -> 0 | AM8: ='Cost.4.24'!AI7 -> 0 | AN8: =AB8+AH8 -> 874.712 | AO8: =AF8+AL8 -> 0 | AP8: =AD8+AJ8 -> 650 | AQ8: =82483/31 -> 2660.7419 | AR8: ='Cost.4.24'!AS7 -> 0 | AS8: =AC8+AI8 -> 3337.037 | AV8: ='Reading.4.25'!AE6/'cost.4.25'!F8 -> 75.923662 | AW8: =(M8+T8)/F8 -> 146.36235 | AX8: =V8/F8 -> 1.6922744 | AY8: =Z8/F8 -> 8.6305994 | AZ8: =AN8/F8 -> 1.9050871 | BA8: =AS8/F8 -> 7.2679308 | BC8: ='Cost.4.24'!BE7 -> 0 | BD8: =K8+R8+X8+AQ8 -> 71443.809 | BE8: =M8+T8+Z8+AS8 -> 74501.337 | BG8: ='Cost.4.24'!BI7 -> 0 | BH8: =BD8/H8 -> 334.74341 | BI8: =BE8/F8 -> 162.26088
B9: 45749 | D9: ='Reading.4.25'!AI7 -> 0.8783 | F9: ='Reading.4.25'!AM7 -> 461.9858 | H9: =5976/28 -> 213.42857 | J9: ='Reading.4.25'!X7 -> 33760 | K9: =1982819/30 -> 66093.967 | L9: ='Cost.4.24'!M8 -> 38530.8 | M9: =J9*1.94 -> 65494.4 | O9: ='Reading.4.25'!T7 -> 0 | P9: =2603/31 -> 83.967742 | Q9: ='Reading.4.25'!AB7 -> 0 | R9: =0/30 -> 0 | S9: ='Cost.4.24'!T8 -> 0 | T9: =O9*7.55 -> 0 | V9: ='Reading.4.25'!G7 -> 754 | W9: =15298/31 -> 493.48387 | X9: =80673/30 -> 2689.1 | Y9: ='Cost.4.24'!Z8 -> 2454.3 | Z9: ='Reading.4.25'!G7*5.1 -> 3845.4 | AB9: ='Reading.4.25'!O7 -> 659.23 | AC9: =AB9*3.73 -> 2458.9279 | AD9: =((19500/4)*3)/30 -> 487.5 | AE9: =((83461/4)*3)/30 -> 2086.525 | AF9: ='Cost.4.24'!AB8 -> 391.85 | AG9: ='Cost.4.24'!AC8 -> 1461.6005 | AH9: ='Reading.4.25'!K7 -> 266.076 | AI9: =AH9*4 -> 1064.304 | AJ9: =(19500/4)/30 -> 162.5 | AK9: =(83461/4)/30 -> 695.50833 | AL9: ='Cost.4.24'!AH8 -> 112.032 | AM9: ='Cost.4.24'!AI8 -> 417.87936 | AN9: =AB9+AH9 -> 925.306 | AO9: =AF9+AL9 -> 503.882 | AP9: =AD9+AJ9 -> 650 | AQ9: =82483/31 -> 2660.7419 | AR9: ='Cost.4.24'!AS8 -> 1879.4799 | AS9: =AC9+AI9 -> 3523.2319 | AV9: ='Reading.4.25'!AE7/'cost.4.25'!F9 -> 73.075839 | AW9: =(M9+T9)/F9 -> 141.76713 | AX9: =V9/F9 -> 1.6320848 | AY9: =Z9/F9 -> 8.3236325 | AZ9: =AN9/F9 -> 2.0028884 | BA9: =AS9/F9 -> 7.6262775 | BC9: ='Cost.4.24'!BE8 -> 42864.58 | BD9: =K9+R9+X9+AQ9 -> 71443.809 | BE9: =M9+T9+Z9+AS9 -> 72863.032 | BG9: ='Cost.4.24'!BI8 -> 156.44007 | BH9: =BD9/H9 -> 334.74341 | BI9: =BE9/F9 -> 157.71704
B10: 45750 | D10: ='Reading.4.25'!AI8 -> 0.846 | F10: ='Reading.4.25'!AM8 -> 444.996 | H10: =5976/28 -> 213.42857 | J10: ='Reading.4.25'!X8 -> 35000 | K10: =1982819/30 -> 66093.967 | L10: ='Cost.4.24'!M9 -> 39754 | M10: =J10*1.94 -> 67900 | O10: ='Reading.4.25'!T8 -> 0 | P10: =2603/31 -> 83.967742 | Q10: ='Reading.4.25'!AB8 -> 0 | R10: =0/30 -> 0 | S10: ='Cost.4.24'!T9 -> 0 | T10: =O10*7.55 -> 0 | V10: ='Reading.4.25'!G8 -> 753 | W10: =15298/31 -> 493.48387 | X10: =80673/30 -> 2689.1 | Y10: ='Cost.4.24'!Z9 -> 2235.6 | Z10: ='Reading.4.25'!G8*5.1 -> 3840.3 | AB10: ='Reading.4.25'!O8 -> 742.21 | AC10: =AB10*3.73 -> 2768.4433 | AD10: =((19500/4)*3)/30 -> 487.5 | AE10: =((83461/4)*3)/30 -> 2086.525 | AF10: ='Cost.4.24'!AB9 -> 410.29 | AG10: ='Cost.4.24'!AC9 -> 1530.3817 | AH10: ='Reading.4.25'!K8 -> 289.416 | AI10: =AH10*4 -> 1157.664 | AJ10: =(19500/4)/30 -> 162.5 | AK10: =(83461/4)/30 -> 695.50833 | AL10: ='Cost.4.24'!AH9 -> 121.368 | AM10: ='Cost.4.24'!AI9 -> 452.70264 | AN10: =AB10+AH10 -> 1031.626 | AO10: =AF10+AL10 -> 531.658 | AP10: =AD10+AJ10 -> 650 | AQ10: =82483/31 -> 2660.7419 | AR10: ='Cost.4.24'!AS9 -> 1983.0843 | AS10: =AC10+AI10 -> 3926.1073 | AV10: ='Reading.4.25'!AE8/'cost.4.25'!F10 -> 78.652392 | AW10: =(M10+T10)/F10 -> 152.58564 | AX10: =V10/F10 -> 1.69215 | AY10: =Z10/F10 -> 8.6299652 | AZ10: =AN10/F10 -> 2.3182815 | BA10: =AS10/F10 -> 8.8227923 | BC10: ='Cost.4.24'!BE9 -> 43972.684 | BD10: =K10+R10+X10+AQ10 -> 71443.809 | BE10: =M10+T10+Z10+AS10 -> 75666.407 | BG10: ='Cost.4.24'!BI9 -> 169.7787 | BH10: =BD10/H10 -> 334.74341 | BI10: =BE10/F10 -> 170.0384
B11: 45751
B12: 45752
B13: 45753
B14: 45754
B15: 45755
B16: 45756
B17: 45757
B18: 45758
B19: 45759
B20: 45760
B21: 45761
B22: 45762
... B37: 45777
B38: TOTAL | D38: =AVERAGE(D8:D37) -> 0.86573333 | F38: =SUM(F8:F37) -> 1366.1272 | H38: =+SUM(H8:H37) -> 640.28571 | J38: =SUM(J8:J37) -> 103400 | K38: =SUM(K8:K37) -> 198281.9 | L38: =SUM(L8:L37) -> 78284.8 | M38: =SUM(M8:M37) -> 200596 | O38: =SUM(O8:O37) -> 0 | P38: =SUM(P8:P37) -> 251.90323 | Q38: =SUM(Q8:Q37) -> 220 | R38: =SUM(R8:R37) -> 0 | S38: =SUM(S8:S37) -> 0 | T38: =SUM(T8:T37) -> 0 | V38: =SUM(V8:V37) -> 2284 | W38: =SUM(W8:W37) -> 1480.4516 | X38: =SUM(X8:X37) -> 8067.3 | Y38: =SUM(Y8:Y37) -> 4689.9 | Z38: =SUM(Z8:Z37) -> 11648.4 | AB38: =SUM(AB8:AB37) -> 2000.74 | AC38: =SUM(AC8:AC37) -> 7462.7602 | AD38: =SUM(AD8:AD37) -> 1462.5 | AE38: =SUM(AE8:AE37) -> 6259.575 | AF38: =SUM(AF8:AF37) -> 802.14 | AG38: =SUM(AG8:AG37) -> 2991.9822 | AH38: =SUM(AH8:AH37) -> 830.904 | AI38: =SUM(AI8:AI37) -> 3323.616 | ... AS38: =SUM(AS8:AS37) -> 10786.376 | AV38: =AVERAGE(AV8:AV37) -> 75.883964 | AW38: =AVERAGE(AW8:AW37) -> 146.90504 | AX38: =AVERAGE(AX8:AX37) -> 1.6721697 | AY38: =AVERAGE(AY8:AY37) -> 8.5280657 | AZ38: =AVERAGE(AZ8:AZ37) -> 2.075419 | BA38: =AVERAGE(BA8:BA37) -> 7.9056669 | BC38: =SUM(BC8:BC37) -> 86837.264 | BD38: =SUM(BD8:BD37) -> 214331.43 | BE38: =SUM(BE8:BE37) -> 223030.78 | BG38: =BC38/'Reading.4.25'!AN36 -> 109.50475 | BH38: =AVERAGE(BH8:BH37) -> 334.74341 | BI38: =AVERAGE(BI8:BI37) -> 163.33877

Sheet Domestic Water
A5: Engineering Department
A6: Domestic Water Parameters | L6: Month : | M6: April | N6: 2025
A8: Day | B8: Hardness | D8: Alkalinity | G8: Chloride | H8: PH | I8: Conductivity | J8: TDS | K8: Fe | L8: CL | M8: T ºc | N8: Production
B9: CAL | C9: Total | D9: P | E9: M | F9: CH | G9: CL/NaCL
A10: 1
A11: 2
A12: 3
A13: 4
A14: 5
A15: 6
A16: 7
A17: 8
A18: 9
A19: 10
A20: 11
A21: 12
... A40: 31
H41: =AVERAGE(H10:H40) -> #DIV/0! | J41: =AVERAGE(J10:J40) -> #DIV/0! | L41: =AVERAGE(L10:L40) -> #DIV/0! | M41: =AVERAGE(M10:M40) -> #DIV/0! | N41: =SUM(N10:N40) -> 0

Sheet Main Pool
A5: Engineering Department
A6: Main Swimming Pool | M6: Month : | N6: April | O6: 2025
A8: Pool Parameters | I8: Fresh Water Add (M³) | J8: Chemicals | O8: Backwash
A9: Day | B9: Calcium Hardness | C9: Total Alkalinity | D9: PH | E9: TDS | F9: Cyan. Acid | G9: CL | H9: T ºc | J9: Chlorine 65% (Kg) | K9: Chlorine 90% (Kg) | L9: Soda Ash PH+ (Kg) | M9: HCL PH- (Lit) | N9: Other Chemicals
A10: 1
A11: 2
A12: 3
A13: 4
A14: 5
A15: 6
A16: 7
A17: 8
A18: 9
A19: 10
A20: 11
A21: 12
... A40: 31
D41: =AVERAGE(D10:D40) -> #DIV/0! | G41: =AVERAGE(G10:G40) -> #DIV/0! | H41: =AVERAGE(H10:H40) -> #DIV/0! | I41: =SUM(I10:I40) -> 0 | J41: =SUM(J10:J40) -> 0 | K41: =SUM(K10:K40) -> 0

Sheet Heated Pool
A5: Engineering Department
A6: Heated Pool | M6: Month : | N6: April | O6: 2025
A8: Pool Parameters | I8: Fresh Water Add (M³) | J8: Chemicals | O8: Backwash
A9: Day | B9: Calcium Hardness | C9: Total Alkalinity | D9: PH | E9: TDS | F9: Cyan. Acid | G9: CL | H9: T ºc | J9: Chlorine 65% (Kg) | K9: Chlorine 90% (Kg) | L9: Sda Ash PH+ (Kg) | M9: HCL PH- (Lit) | N9: Other Chemicals
A10: 1
A11: 2
A12: 3
A13: 4
A14: 5
A15: 6
A16: 7
A17: 8
A18: 9
A19: 10
A20: 11
A21: 12
... A40: 31
D41: =AVERAGE(D10:D40) -> #DIV/0! | G41: =AVERAGE(G10:G40) -> #DIV/0! | H41: =AVERAGE(H10:H40) -> #DIV/0! | I41: =AVERAGE(I10:I40) -> #DIV/0! | J41: =SUM(J10:J40) -> 0 | K41: =SUM(K10:K40) -> 0

Sheet Kids pool 
A5: Engineering Department
A6: Kids Pool | M6: Month : | N6: April | O6: 2025
A8: Pool Parameters | I8: Fresh Water Add (M³) | J8: Chemicals | O8: Backwash
A9: Day | B9: Calcium Hardness | C9: Total Alkalinity | D9: PH | E9: TDS | F9: Cyan. Acid | G9: CL | H9: T ºc | J9: Chlorine 65% (Kg) | K9: Chlorine 90% (Kg) | L9: Sda Ash PH+ (Kg) | M9: HCL PH- (Lit) | N9: Other Chemicals
A10: 1
A11: 2
A12: 3
A13: 4
A14: 5
A15: 6
A16: 7
A17: 8
A18: 9
A19: 10
A20: 11
A21: 12
... A40: 31
D41: =AVERAGE(D10:D40) -> #DIV/0! | G41: =AVERAGE(G10:G40) -> #DIV/0! | H41: =AVERAGE(H10:H40) -> #DIV/0! | I41: =AVERAGE(I10:I40) -> #DIV/0! | J41: =SUM(J10:J40) -> 0 | K41: =SUM(K10:K40) -> 0

Sheet Jacuzzi
A5: Engineering Department
A6: Infinity Pool | M6: Month : | N6: April | O6: 2025
A8: Pool Parameters | I8: Fresh Water Add (M³) | J8: Chemicals | O8: Backwash
A9: Day | B9: Calcium Hardness | C9: Total Alkalinity | D9: PH | E9: TDS | F9: Cyan. Acid | G9: CL | H9: T ºc | J9: Chlorine 65% (Kg) | K9: Chlorine 90% (Kg) | L9: Sda Ash PH+ (Kg) | M9: HCL PH- (Lit) | N9: Other Chemicals
A10: 1
A11: 2
A12: 3
A13: 4
A14: 5
A15: 6
A16: 7
A17: 8
A18: 9
A19: 10
A20: 11
A21: 12
... A40: 31
D41: =AVERAGE(D10:D40) -> #DIV/0! | G41: =AVERAGE(G10:G40) -> #DIV/0! | H41: =AVERAGE(H10:H40) -> #DIV/0! | J41: =SUM(J10:J40) -> 0 | K41: =SUM(K10:K40) -> 0

Sheet Fountains & Lagoons
A5: Engineering Department
A6: Fountains, Water Falls and Lagoons | I6: Month : | M6: April | N6: 2021 | O6: 2025
B8: Lagoons | E8: Water Falls | H8: Entrance Fountain | J8: Shops Fountain | M8: Main Tank | O8: Irrigation Tank
A9: Day | B9: PH | C9: CL | D9: Backwash | E9: PH | F9: CL | G9: Backwash | H9: PH | I9: CL | J9: PH | K9: CL | L9: Backwash | M9: PH | N9: CL | O9: PH | P9: CL
A10: 1
A11: 2
A12: 3
A13: 4
A14: 5
A15: 6
A16: 7
A17: 8
A18: 9
A19: 10
A20: 11
A21: 12
... A40: 31

Sheet Boilers
A5: Engineering Department
A6: Boilers Water Parameters | V6: Month : | X6: April | Y6: 2025
A8: Day | B8: Feed Tank | M8: Boiler Water
B9: Alkalinity | E9: Chloride | F9: PH | G9: Conduc- tivity | H9: TDS | I9: Fe | J9: TH | K9: TºC | M9: Alkalinity | P9: Chloride | Q9: PH | R9: Conduc- tivity | S9: TDS | T9: Fe | U9: Po4 | V9: Na2 So3 | W9: TH | X9: Boiler No. | Y9: Company
B10: P | C10: M | D10: OH | E10: CL/NaCL | M10: P | N10: M | O10: OH | P10: CL/NaCL
A11: 1
A12: 2
A13: 3
A14: 4
A15: 5
A16: 6
A17: 7
A18: 8
A19: 9
A20: 10
A21: 11
A22: 12
... A41: 31
H42: =AVERAGE(H11:H41) -> #DIV/0! | I42: =AVERAGE(I11:I41) -> #DIV/0! | J42: =AVERAGE(J11:J41) -> #DIV/0! | K42: =AVERAGE(K11:K41) -> #DIV/0! | Q42: =AVERAGE(Q11:Q41) -> #DIV/0! | S42: =AVERAGE(S11:S41) -> #DIV/0! | T42: =AVERAGE(T11:T41) -> #DIV/0!

Sheet Chillers
A5: Engineering Department
A6: Chilled Water Parameters | L6: HISTORY
A8: Date | C8: Main Chillers | J8: Gym & Spa Chillers | Q8: Company
C9: PH | D9: Conduc- tivity | E9: TDS | F9: Fe | G9: INH | H9: Cu. | J9: PH | K9: Conduc- tivity | L9: TDS | M9: Fe | N9: INH | O9: Cu.
A10: 38591 | C10: 10.5 | D10: 2550 | E10: 1700 | F10: 0.8 | G10: 600 | Q10: System Technique
A11: 38599 | C11: 9.7 | D11: 2055 | E11: 1370 | F11: 0.8 | G11: 600 | Q11: System Technique
A12: 38606 | C12: 9.8 | D12: 2160 | E12: 1440 | F12: 0.7 | G12: 650 | Q12: System Technique
A13: 38613 | C13: 9.7 | D13: 2250 | E13: 1500 | F13: 0.8 | G13: 600 | Q13: System Technique
A14: 38634 | C14: 8 | D14: 585 | E14: 390 | F14: 0.3 | G14: Nil | Q14: System Technique
A15: 38662 | C15: 10 | D15: 1845 | E15: 1230 | F15: 0.8 | G15: 500 | Q15: System Technique
A16: 38722 | C16: 10 | D16: 2175 | E16: 1450 | F16: 0.6 | G16: 700 | H16: Nil | Q16: System Technique
A17: 38739 | C17: 10.1 | D17: 3150 | E17: 2300 | F17: 0.5 | G17: 450 | Q17: System Technique
A18: 38760 | C18: 9.9 | D18: 1675 | E18: 1250 | F18: 0.3 | G18: 600 | H18: Nil | Q18: System Technique
A19: 38767 | C19: 9.7 | D19: 22250 | E19: 1500 | F19: 0.5 | G19: 250 | Q19: System Technique
A20: 38788 | C20: 10.1 | D20: 2475 | E20: 1850 | F20: 0.6 | G20: 1000 | H20: Nil | Q20: System Technique
A21: 38802 | C21: 10.2 | D21: 3000 | E21: 2000 | F21: 0.3 | G21: 650 | Q21: System Technique
A22: 38844 | C22: 10.2 | D22: 2750 | E22: 1800 | F22: 0.5 | G22: 1000 | Q22: System Technique
A23: 38858 | C23: 10.2 | D23: 3750 | E23: 2500 | F23: 0.6 | G23: 1000 | H23: Nil | Q23: System Technique
A24: 38900 | C24: 10.5 | D24: 3000 | E24: 2000 | F24: 0.5 | G24: 1000 | H24: Nil | Q24: System Technique
A25: 38926 | C25: 10.4 | D25: 3000 | E25: 2000 | F25: 0.3 | G25: 700 | H25: Nil | J25: 10.2 | K25: 6000 | L25: 4000 | M25: 0.3 | N25: 2500 | O25: Nil | Q25: System Technique
A26: 38949 | C26: 10.5 | D26: 3000 | E26: 2000 | F26: 0.5 | G26: 1000 | H26: Nil | J26: 9.8 | K26: 7500 | L26: 5000 | M26: 0.6 | N26: 2000 | O26: Nil | Q26: System Technique
A27: 38963 | C27: 10.5 | D27: 1950 | E27: 1300 | F27: 0.3 | G27: 600 | J27: 10.7 | K27: 4500 | L27: 3000 | M27: 0.5 | N27: 2000 | Q27: System Technique
A28: 38977 | C28: 10.5 | D28: 2250 | E28: 1500 | F28: 0.5 | G28: 600 | J28: 9 | K28: 600 | L28: 400 | M28: 3 | N28: Nil | Q28: System Technique
A29: 38998 | C29: 10 | D29: 1950 | E29: 1300 | F29: 0.5 | G29: 600 | H29: Nil | J29: 10.5 | K29: 6000 | L29: 4000 | M29: 0.5 | N29: 1500 | O29: Nil | Q29: System Technique
A30: 39019 | C30: 10.5 | D30: 2700 | E30: 1800 | F30: 0.5 | G30: 600 | H30: Nil | J30: 11 | K30: 6000 | L30: 4000 | M30: 0.5 | N30: 2000 | O30: Nil | Q30: System Technique
A31: 39037 | C31: 10.5 | D31: 2700 | E31: 1800 | F31: 0.7 | G31: 1000 | H31: Nil | J31: 11 | K31: 6000 | L31: 4000 | M31: 0.7 | N31: 3000 | O31: Nil | Q31: System Technique
A32: 39047 | C32: 10.5 | D32: 2700 | E32: 1800 | F32: 0.7 | G32: 1000 | H32: Nil | J32: 11 | K32: 6000 | L32: 4000 | M32: 0.7 | N32: 2500 | O32: Nil | Q32: System Technique
A33: 39096 | C33: 10.6 | D33: 2550 | E33: 1700 | F33: 0.7 | G33: 1000 | H33: Nil | J33: 11 | K33: 5250 | L33: 3500 | M33: 0.7 | N33: 2500 | O33: Nil | Q33: System Technique
A34: 39124 | C34: 10.8 | D34: 3300 | E34: 4500 | F34: 0.6 | G34: 2000 | H34: Nil | J34: 11 | K34: 6750 | L34: 4500 | M34: 0.6 | N34: 2000 | O34: Nil | Q34: System Technique
A35: 39145 | C35: 10.9 | D35: 2700 | E35: 1800 | F35: 0.7 | G35: 600 | H35: Nil | J35: 11 | K35: 5250 | L35: 3500 | M35: 0.7 | N35: 1800 | O35: Nil | Q35: System Technique
A36: 39166 | C36: 10.8 | D36: 2400 | E36: 1600 | F36: 0.6 | G36: 600 | H36: Nil | J36: 10.3 | K36: 4200 | L36: 2800 | M36: 0.4 | N36: 1500 | O36: Nil | Q36: System Technique
A37: 39180 | C37: 10.8 | D37: 2700 | E37: 1800 | F37: 0.7 | G37: 600 | H37: Nil | J37: 10.9 | K37: 5250 | L37: 3500 | M37: 0.6 | N37: 1800 | O37: Nil | Q37: System Technique
A38: 39201 | C38: 10.7 | D38: 2250 | E38: 1700 | F38: 0.7 | H38: 8.2 | J38: 370 | K38: 4500 | L38: 1.2 | M38: 26 | N38: 496 | Q38: System Technique
A39: 39235 | C39: 10.3 | D39: 3000 | E39: 2000 | F39: 0.7 | G39: 1000 | H39: <0.1 | J39: 11 | K39: 5250 | L39: 3500 | M39: 0.7 | N39: 1500 | O39: <0.1 | Q39: System Technique
A40: 39250 | C40: 10.5 | D40: 3000 | E40: 2000 | F40: 0.6 | G40: 800 | H40: <0.1 | J40: 11 | K40: 4500 | L40: 3000 | M40: 0.6 | N40: 1500 | O40: <0.1 | Q40: System Technique
A41: 39264 | C41: 10.5 | D41: 3000 | E41: 2000 | F41: 0.6 | G41: 1000 | J41: 10.6 | K41: 2700 | L41: 1800 | M41: 0.6 | N41: 800 | Q41: System Technique
A42: 39292 | C42: 10.7 | D42: 2700 | E42: 1800 | F42: 0.6 | G42: 600 | H42: <0.1 | J42: 10.5 | K42: 2550 | L42: 1700 | M42: 0.6 | N42: 400 | O42: <0.1 | Q42: System Technique
A43: 39299 | C43: 10.5 | D43: 3000 | E43: 2000 | F43: 0.6 | G43: 1000 | J43: 10.6 | K43: 7500 | L43: 5000 | M43: 0.6 | N43: 3000 | Q43: System Technique
A44: 39327 | C44: 10.2 | D44: 3750 | E44: 2500 | F44: 0.6 | G44: 2000 | H44: Nil | J44: 10.7 | K44: 6000 | L44: 4000 | M44: 0.6 | N44: 3000 | O44: Nil | Q44: System Technique
A45: 39334 | C45: 10.2 | D45: 3750 | E45: 2500 | F45: 0.6 | G45: 2000 | H45: Nil | J45: 10.7 | K45: 6000 | L45: 4000 | M45: 0.6 | N45: 3000 | O45: Nil | Q45: System Technique
A46: 39369 | C46: 10.3 | D46: 3750 | E46: 2500 | F46: 0.6 | G46: 2000 | H46: Nil | J46: 10.8 | K46: 4500 | L46: 3000 | M46: 0.6 | N46: 2500 | O46: Nil | Q46: System Technique
A47: 39390 | C47: 10.5 | D47: 3000 | E47: 2000 | F47: 0.5 | G47: 1000 | H47: Nil | J47: 10.7 | K47: 3750 | L47: 2500 | M47: 0.5 | N47: 2000 | O47: Nil | Q47: System Technique
A48: 39411 | C48: 11 | D48: 3000 | E48: 2000 | F48: 0.5 | G48: 1000 | J48: 11 | K48: 3750 | L48: 2500 | M48: 0.5 | N48: 2000 | Q48: System Technique
A49: 39425 | C49: 10.5 | D49: 3000 | E49: 2000 | F49: 0.5 | G49: 1000 | J49: 10.5 | K49: 4500 | L49: 3000 | M49: 0.5 | N49: 2000 | Q49: System Technique
A50: 39460 | C50: 10 | D50: 3750 | E50: 2500 | F50: 0.5 | G50: 2000 | J50: 9.8 | K50: 3750 | L50: 2500 | M50: 0.5 | N50: 2000 | Q50: System Technique
A51: 39474 | C51: 10.2 | D51: 3750 | E51: 2500 | F51: 0.5 | G51: 2000 | J51: 10.2 | K51: 3750 | L51: 2500 | M51: 0.5 | N51: 2000 | Q51: System Technique
A52: 39488 | C52: 10 | D52: 3750 | E52: 2500 | F52: 0.5 | G52: 2000 | J52: 9.7 | K52: 3225 | L52: 2150 | M52: 0.5 | N52: 1500 | Q52: System Technique
A53: 39537 | C53: 10.8 | D53: 2250 | E53: 1500 | F53: 0.5 | G53: 1000 | J53: 11 | K53: 3750 | L53: 2500 | M53: 0.5 | N53: 1500 | Q53: System Technique
A54: 39544 | C54: 10 | D54: 4500 | E54: 3000 | F54: 0.5 | G54: 1500 | J54: 9.7 | K54: 3000 | L54: 2000 | M54: 0.5 | N54: 1000 | Q54: System Technique
A55: 39562 | C55: 10.6 | D55: 2250 | E55: 1500 | F55: 0.7 | G55: 600 | J55: 11 | K55: 3600 | L55: 2400 | M55: 1 | N55: 1000 | Q55: System Technique
A56: 39564 | C56: 10.6 | D56: 2250 | E56: 1500 | F56: 0.7 | G56: 600 | J56: 11 | K56: 3600 | L56: 2400 | M56: 1 | N56: 1000 | Q56: System Technique
A57: 39578 | C57: 10.9 | D57: 2250 | E57: 1500 | F57: 0.6 | G57: 600 | J57: 11.3 | K57: 3600 | L57: 2400 | M57: 0.7 | N57: 1000 | Q57: System Technique
A58: 39589 | C58: 11 | D58: 2600 | E58: 1400 | F58: 0.5 | G58: 600 | H58: <0.1 | J58: 11 | K58: 3750 | L58: 2500 | M58: 0.5 | N58: 1000 | O58: <0.1 | Q58: System Technique
A59: 39610 | C59: 10 | D59: 3750 | E59: 2500 | F59: 0.5 | G59: 1000 | H59: Nil | J59: 10 | K59: 7500 | L59: 5000 | M59: 0.5 | N59: 2000 | O59: Nil | Q59: System Technique
A60: 39627 | C60: 10.7 | D60: 3750 | E60: 2500 | F60: 0.7 | G60: 1000 | J60: 10.9 | K60: 6450 | L60: 4300 | M60: 0.7 | N60: 2000 | Q60: System Technique
A61: 39637 | C61: 10.4 | D61: 4200 | E61: 2800 | F61: 0.3 | G61: 1200 | J61: 10.2 | K61: 3750 | L61: 2500 | M61: 0.3 | N61: 1200 | Q61: System Technique
A62: 39662 | C62: 10.6 | D62: 3450 | E62: 2300 | F62: 0.7 | G62: 1000 | J62: 10.7 | K62: 5700 | L62: 3800 | M62: 0.7 | N62: 1600 | Q62: System Technique
A63: 39690 | C63: 10.7 | D63: 3600 | E63: 2400 | F63: 0.5 | G63: 1000 | J63: 10.6 | K63: 5400 | L63: 3600 | M63: 0.7 | N63: 1500 | Q63: System Technique
A64: 39711 | C64: 10.4 | E64: 2300 | F64: 0.5 | G64: 1000 | J64: 10.8 | L64: 3400 | M64: 0.5 | N64: 1300 | Q64: System Technique
A65: 39739 | C65: 11 | D65: 3600 | E65: 2400 | F65: 0.5 | G65: 1000 | J65: 11 | K65: 4950 | L65: 3300 | M65: 0.7 | N65: 1300 | Q65: System Technique
A66: 39781 | C66: 10.6 | D66: 3600 | E66: 2400 | F66: 0.5 | G66: 1000 | J66: 10.8 | K66: 4500 | L66: 300 | M66: 0.5 | N66: 1000 | Q66: System Technique
A67: 39816 | C67: 10.7 | D67: 3750 | E67: 2500 | F67: 0.4 | G67: 950 | J67: 11 | K67: 4500 | L67: 3000 | M67: 0.5 | N67: 1200 | Q67: System Technique
A68: 39830 | C68: 10.7 | D68: 3750 | E68: 2500 | F68: 0.4 | G68: 950 | J68: 11 | K68: 4500 | L68: 3000 | M68: 0.5 | N68: 1200 | Q68: System Technique
A69: 39839 | C69: 10.4 | D69: 3750 | E69: 2500 | F69: 0.4 | G69: 950 | J69: 11 | K69: 4500 | L69: 3000 | M69: 0.5 | N69: 1200 | Q69: System Technique
A70: 39908 | C70: 10.5 | D70: 4400 | E70: 2200 | F70: 0.4 | G70: 1000 | J70: 10.6 | K70: 6400 | L70: 3200 | M70: 0.4 | N70: 1200 | Q70: System Technique
A71: 39945 | C71: 10.8 | D71: 4580 | E71: 2519 | F71: 0.2 | G71: 1100 | J71: 10.8 | K71: 4570 | L71: 2519 | M71: 0.2 | N71: 1100 | Q71: System Technique
A72: 39992 | C72: 10.9 | D72: 4500 | E72: 2400 | F72: 0.3 | G72: 1200 | H72: 0.1 | J72: 10.6 | K72: 3900 | L72: 2100 | M72: 0.3 | N72: 1000 | O72: 0.1 | Q72: System Technique
A73: 40001 | C73: 10.4 | D73: 4200 | E73: 2310 | F73: 0.3 | G73: 1000 | J73: 10.4 | K73: 4100 | L73: 2255 | M73: 0.3 | N73: 900 | Q73: System Technique
A74: 40017 | C74: 9.9 | D74: 3150 | E74: 2100 | F74: 0.5 | G74: 1000 | J74: 9.8 | K74: 3800 | L74: 1900 | M74: 0.4 | N74: 900 | Q74: System Technique
A75: 40034 | C75: 11 | D75: 4400 | E75: 2600 | F75: 0.4 | G75: 1000 | J75: 10.6 | K75: 3300 | L75: 1800 | M75: 0.4 | N75: 800 | Q75: System Technique
A76: 40072 | C76: 11 | D76: 3400 | E76: 1800 | F76: 0.3 | G76: 1000 | H76: <0.1 | J76: 11 | K76: 3000 | L76: 1700 | M76: 0.3 | N76: 700 | O76: <0.1 | Q76: System Technique
A77: 40117 | C77: 10.6 | D77: 3700 | E77: 2035 | F77: 0.4 | G77: 1000 | H77: Nil | J77: 10.4 | K77: 2800 | L77: 1540 | M77: 0.3 | N77: 600 | O77: Nil | Q77: System Technique
A78: 40174 | C78: 10.6 | D78: 3700 | E78: 2100 | F78: 0.4 | G78: 1000 | J78: 10.5 | K78: 2500 | L78: 1400 | M78: 0.4 | N78: 800 | Q78: System Technique
A79: 40182 | C79: 10.1 | D79: 3300 | E79: 2200 | F79: 0.3 | G79: 1000 | J79: 9.4 | K79: 2400 | L79: 1600 | M79: 0.4 | N79: 650 | Q79: System Technique
A80: 40216 | C80: 9.8 | D80: 3600 | E80: 1600 | F80: 0.5 | G80: 1000 | H80: Nil | J80: 10.4 | K80: 4000 | L80: 2200 | M80: 0.5 | N80: 1200 | O80: Nil | Q80: System Technique
A81: 40244 | C81: 10.8 | D81: 3600 | E81: 2000 | F81: 0.5 | G81: 800 | H81: <0.1 | J81: 10.6 | K81: 3000 | L81: 1650 | M81: 0.5 | N81: 600 | O81: <0.1 | Q81: System Technique
A82: 40329 | C82: 10.5 | D82: 3600 | E82: 1980 | F82: 0.5 | G82: 1100 | J82: 10.6 | K82: 4000 | L82: 2200 | M82: 0.5 | N82: 1800 | Q82: System Technique
A83: 40343 | C83: 9.9 | D83: 3000 | E83: 1600 | G83: 1000 | H83: <0.1 | J83: 10.7 | K83: 9000 | L83: 5400 | N83: 2000 | O83: <0.1 | Q83: System Technique
A84: 40349 | C84: 10 | D84: 3500 | E84: 1925 | F84: 0.5 | G84: 1200 | J84: 10.5 | K84: 4000 | L84: 2200 | M84: 0.5 | N84: 2000 | Q84: System Technique
A85: 40412 | C85: 10.2 | D85: 4000 | E85: 2200 | F85: 0.5 | G85: 800 | J85: 11 | K85: 8000 | L85: 4400 | M85: 0.4 | N85: 1600 | Q85: System Technique
A86: 40468 | C86: 10.5 | D86: 3400 | E86: 1900 | F86: 0.2 | G86: 650 | J86: 9.3 | K86: 5800 | L86: 3000 | M86: 0.2 | N86: 1200 | Q86: System Technique
A87: 40482 | C87: 10.4 | D87: 3200 | E87: 1260 | F87: 0.5 | G87: 1000 | J87: 9.8 | K87: 5800 | L87: 3000 | M87: 0.5 | N87: 1000 | Q87: System Technique
A88: 40551 | C88: 10.4 | D88: 2500 | E88: 1500 | F88: 0.4 | G88: 800 | J88: 9.8 | K88: 4000 | L88: 2200 | M88: 0.4 | N88: 1000 | Q88: System Technique
A89: 40722 | C89: 10.4 | D89: 2600 | E89: 1400 | F89: 0.6 | G89: 600 | J89: 9.8 | K89: 4000 | L89: 2200 | M89: 0.5 | N89: 1000 | Q89: System Technique
A90: 40762 | C90: 9.2 | D90: 2500 | E90: 1400 | F90: 0.6 | G90: 800 | J90: 10.2 | K90: 4400 | L90: 2440 | M90: 0.4 | N90: 1200 | Q90: System Technique
A91: 40824 | C91: 10.5 | D91: 2000 | E91: 1100 | F91: 0.5 | G91: 800 | J91: 9.5 | K91: 3000 | L91: 1650 | M91: 1.7 | N91: 2000 | Q91: System Technique
A92: 40857 | C92: 10.4 | D92: 1500 | E92: 800 | F92: 1.7 | G92: 600 | J92: 9.1 | K92: 3000 | L92: 1650 | M92: 0.3 | N92: 1200 | Q92: System Technique
A93: 40870 | C93: 9.6 | D93: 2400 | E93: 1320 | F93: 0.6 | G93: 700 | H93: <0.1 | J93: 9 | K93: 3000 | L93: 1650 | M93: 0.3 | N93: 1200 | O93: <0.1 | Q93: System Technique
A94: 40874 | C94: 10 | D94: 3200 | E94: 1760 | F94: 0.6 | G94: 1000 | H94: <0.1 | J94: 9 | K94: 3000 | L94: 1650 | M94: 0.3 | N94: 1200 | O94: <0.1 | Q94: System Technique
A95: 40878 | C95: 10 | D95: 3500 | E95: 2000 | F95: 0.6 | G95: 1000 | H95: <0.1 | J95: 9.8 | K95: 3000 | L95: 1650 | M95: 0.3 | N95: 1200 | O95: <0.1 | Q95: System Technique
A96: 40895 | C96: 10 | D96: 3200 | E96: 1760 | F96: 0.6 | G96: 800 | H96: <0.1 | J96: 10 | K96: 4100 | L96: 2255 | M96: 0.4 | N96: 1000 | Q96: System Technique
A97: 40910 | C97: 10 | D97: 3200 | E97: 1760 | F97: 0.6 | G97: 800 | H97: <0.1 | J97: 9.9 | K97: 4100 | L97: 2255 | M97: 0.4 | N97: 1000 | O97: <0.1 | Q97: System Technique
A98: 40931 | C98: 10 | D98: 3000 | E98: 1650 | F98: 0.6 | G98: 800 | H98: <0.1 | J98: 9.5 | K98: 4000 | L98: 2200 | M98: 0.4 | N98: 1000 | O98: <0.1 | Q98: System Technique
A99: 40948 | C99: 10.2 | D99: 3000 | E99: 1650 | F99: 0.6 | G99: 800 | H99: 0.1 | J99: 10 | K99: 4000 | L99: 2200 | M99: 0.4 | N99: 800 | O99: 0.15 | Q99: System Technique
A100: 40981 | C100: 10.3 | D100: 3000 | E100: 1650 | F100: 0.7 | G100: 800 | H100: 0.1 | J100: 10 | K100: 4000 | L100: 2200 | M100: 0.8 | N100: 800 | O100: 0.2 | Q100: System Technique
A101: 40994 | C101: 10.5 | D101: 2800 | E101: 1500 | F101: 0.5 | G101: 800 | H101: <0.1 | J101: 10.7 | K101: 4100 | L101: 2300 | M101: 1.2 | N101: 1000 | O101: <0.1 | Q101: System Technique
A102: 41010 | C102: 10 | D102: 3200 | E102: 1800 | F102: 0.9 | G102: 800 | H102: <0.1 | J102: 10 | K102: 4800 | L102: 2500 | M102: 1.9 | N102: 1000 | O102: <0.1 | Q102: System Technique
A103: 41025 | C103: 10.1 | D103: 3000 | E103: 1650 | F103: 0.6 | G103: 800 | H103: 0.1 | J103: 10 | K103: 5000 | L103: 2750 | M103: 1.9 | N103: 1000 | O103: 0.1 | Q103: System Technique
A104: 41037 | C104: 10.4 | D104: 3000 | E104: 1600 | F104: 0.5 | G104: 750 | J104: 11 | K104: 4000 | L104: 2200 | M104: 1.6 | N104: 1000 | Q104: System Technique
A105: 41051 | C105: 10.4 | D105: 3000 | E105: 1650 | F105: 0.5 | G105: 800 | J105: 10 | K105: 5000 | L105: 2750 | M105: 1.8 | N105: 1000 | Q105: System Technique
...

Sheet Reading.4.24
A1: 1 | B1: 2 | C1: 3 | D1: 4 | E1: 5 | F1: 6 | G1: 7 | H1: 8 | I1: 9 | J1: 10 | K1: 11 | L1: 12 | M1: 13 | N1: 14 | O1: 15 | P1: 16 | Q1: 17 | R1: 18 | S1: 19 | T1: 20 | U1: 21 | V1: 22 | W1: 23 | X1: 24 | Y1: 25 | Z1: 26 | AA1: 27 | AB1: 28 | AC1: 29 | AD1: 30 | AE1: 31 | AF1: 32 | AG1: 33 | AH1: 34 | AI1: 35 | AJ1: 36 | AK1: 37 | AL1: 38 | AM1: 39 | AN1: 40 | AO1: 41 | AP1: 42 | AQ1: 43 | AR1: 44 | AS1: 45 | AT1: 46 | AU1: 47 | AV1: 48 | AW1: 49 | AX1: 50 | AY1: 51 | AZ1: 52 | BA1: 53 | BB1: 54 | BC1: 55 | BD1: 56 | BE1: 57 | BF1: 58 | BG1: 59 | BH1: 60 | BI1: 61 | BJ1: 62 | BK1: 63 | BL1: 64 | BM1: 65 | BN1: 66 | BO1: 67 | BP1: 68 | BQ1: 69 | BR1: 70 | BS1: 71 | BT1: 72 | BU1: 73 | BV1: 74 | BW1: 75 | BX1: 76 | BY1: 77 | BZ1: 78 | CA1: 79 | CB1: 80 | CC1: 81 | CD1: 82 | CE1: 83 | CF1: 80 | CG1: 81 | CH1: 82 | CI1: 84 | CJ1: 85 | CK1: 86 | CL1: 87 | CM1: 88 | CN1: 89 | CO1: 90 | CP1: 91 | CQ1: 92 | CR1: 93 | CS1: 94 | CT1: 95 | CU1: 96 | CV1: 97 | CW1: 98 | CX1: 99 | CY1: 100 | CZ1: 101 | DA1: 102 | DB1: 103 | DC1: 104 | DD1: 105 | DE1: 106 | DF1: 107 | DG1: 108 | DH1: 109 | DI1: 110 | DJ1: 111 | DK1: 112 | DL1: 113 | DM1: 114 | DN1: 115 | DO1: 116 | DP1: 117 | DQ1: 118 | DR1: 119 | DS1: 120 | DT1: 121 | DU1: 122 | DV1: 123 | DW1: 124 | DX1: 125 | DY1: 126 | DZ1: 127 | EA1: 128 | EB1: 129 | EC1: 130 | ED1: 131 | EE1: 132 | EF1: 133 | EG1: 134 | EH1: 135 | EI1: 136 | EJ1: 137 | EK1: 138 | EL1: 139
B2: WATER | J2: KITCHEN GAS | N2: BOILER GAS | R2: FUEL | W2: ELECTRICITY | AA2: GENERATORS | AE2: TOTAL KWH | AI2: Occupancy % | AM2: Rooms Occupied | AQ2: Max. Demand | AT2: Power Factor | AY2: More Data | BC2: Weather Temperature | BL2: Available Rooms | BN2: Water Sold Last Year | BP2: Kitchen Water | BT2: Laundry Water | BX2: Fountain Water | CB2: S. Pool Water | CF2: Heated Pool Water | CI2: Staff Houses Water | CM2: Total Facilities Cons. | CP2: STP | CV2: Dishwasher | CZ2: Staff Kitchen | DD2: Laundry Electricity | DH2: Kit. Equip. Electricity | DL2: Chiller 1 | DP2: Chiller 2 | DT2: Chiller 3 | DX2: Chilled Pumps KWH | DZ2: Total Chillers | EC2: RO Plant | EF2: Staff Kitchen Gas | EJ2: Rotary Oven Gas
A4: Date | B4: Reading | C4: Product. | D4: Buy | E4: Sold | F4: Tanks Level | G4: Consump. This Year | H4: Last Year | J4: Reading | K4: Consump. This Year | L4: Last Year | N4: Reading | O4: Consump. This Year | P4: Last Year | R4: Reading | S4: Add | T4: Consump. This Year | U4: Last Year | W4: Reading | X4: Consump. This Year | Y4: Consump. Last Year | AA4: Reading | AB4: Consump. This Year | AC4: Consump. Last Year | AE4: This Year | AF4: Last Year | AG4: Budget | AI4: This Year | AJ4: Last Year | AK4: Budget | AM4: This Year | AN4: Last Year | AO4: Budget | AQ4: This Year KW | AR4: Last Year KW | AT4: KVAR Reading | AU4: KVAR Cons. | AV4: Cos Ø | AY4: Last Year January 2021 | BC4: This Year - September 2023 | BG4: Last Year - September 2022 | BP4: Counter Reading | BQ4: Consumption This year | BR4: Consumption Last Year | BT4: Counter Reading | BU4: Consumption | BV4: Consumption Last Year | BX4: Counter Reading | BY4: Consumption | BZ4: Consumption Last Year | CB4: Counter Reading | CC4: Consumption | CD4: Consumption Last Year | CF4: Counter Reading | CG4: Consumption | CH4: Consumption Last Year | CI4: Counter Reading | CJ4: Consumption | CK4: Consumption Last Year | CM4: This Year | CN4: Last Year | CP4: Counter Reading | CQ4: Recycled Water this Year | CR4: % | CS4: Reccycled Water Last Year | CT4: % | CV4: Counter Reading | CW4: Cons. | CX4: Cons. Last Year | CZ4: Counter Reading | DA4: Cons. | DB4: Cons. Last Year | DD4: Counter Reading | DE4: Cons. | DF4: Cons. Last Year | DH4: Counter Reading | DI4: Cons. | DJ4: Cons. Last Year | DL4: Counter Reading | DM4: Cons. | DN4: Cons. Last Year | DP4: Counter Reading | DQ4: Cons. | DR4: Cons. Last Year | DT4: Counter Reading | DU4: Cons. | DV4: Cons. Last Year | DZ4: Cons. | EA4: Cons. Last Year | EC4: KWH This Year | ED4: KWH Last Year | EF4: Counter Reading | EG4: Cons. | EH4: Cons. Last Year | EJ4: Counter Reading | EK4: Cons. | EL4: Cons. Last Year
B5: 277890 | F5: 840 | J5: 206864 | N5: 730976 | R5: 42700 | W5: 45656.55 | AA5: 520030 | AT5: 7138.69 | BP5: 66271 | BT5: 81071 | BX5: 3964 | CB5: 233360 | CF5: 6070 | CI5: 19776 | CP5: 100965 | CV5: 5213 | CZ5: 878 | DD5: 1420698 | DH5: 3314265 | DL5: 2903383 | DP5: 2284888 | DT5: 3046535 | EF5: 59556 | EJ5: 23762
A6: 45383 | B6: 278305 | C6: =B6-B5 -> 415 | E6: 0 | F6: 750 | G6: =C6+D6-E6+F5-F6 -> 505 | H6: ='[1]Reading.4.23'!G6 -> 624 | J6: 206888 | K6: =(J6-J5)*4.668 -> 112.032 | L6: ='[1]Reading.4.23'!K6 -> 149.376 | N6: 731061 | O6: =(N6-N5)*4.61 -> 391.85 | P6: ='[1]Reading.4.23'!O6 -> 419.51 | R6: 42700 | T6: =(R5+S5)-R6 -> 0 | U6: ='[1]Reading.4.23'!T6 -> 0 | W6: 45663.48 | X6: =(W6-W5)*4000 -> 27720 | Y6: ='[1]Reading.4.23'!X6 -> 25200 | AA6: 520030 | AB6: =AA6-AA5 -> 0 | AC6: ='[1]Reading.4.23'!AB6 -> 560 | AE6: =+X6+AB6 -> 27720 | AF6: ='[1]Reading.4.23'!AE6 -> 25760 | AG6: =989409/30 -> 32980.3 | AI6: 0.5209 | AJ6: ='[1]Reading.4.23'!AI6 -> 0.435 | AK6: 0.638 | AM6: 274 | AN6: ='[1]Reading.4.23'!AM6 -> 228 | AO6: =10065/30 -> 335.5 | AQ6: =365*4 -> 1460 | AR6: ='[1]Reading.4.23'!AQ6 -> 1380 | AT6: 7139.41 | AU6: =(AT6-AT5)*4000 -> 2880 | AV6: =+X6/SQRT(((POWER((X6),2)+(POWER((AU6),2))))) -> 0.99464611 | AY6: ='[1]Reading.4.23'!X6 -> 25200 | AZ6: ='[1]Reading.4.23'!AB6 -> 560 | BA6: =AY6+AZ6 -> 25760 | BC6: 19 | BD6: 16.1 | BE6: 12 | BF6: 56 | BG6: 79 | BH6: ='[1]Reading.4.23'!BD6 -> 20.3 | BI6: ='[1]Reading.4.23'!BE6 -> 17 | BJ6: ='[1]Reading.4.23'!BF6 -> 52 | BL6: 526 | BN6: ='[1]Reading.4.23'!E4 -> Sold | BP6: 66301 | BQ6: =BP6-BP5 -> 30 | BR6: ='[1]Reading.4.23'!BQ6 -> 26 | BT6: 81101 | BU6: =BT6-BT5 -> 30 | BV6: ='[1]Reading.4.23'!BU6 -> 29 | BX6: 3975 | BY6: =BX6-BX5 -> 11 | BZ6: ='[1]Reading.4.23'!BY6 -> 0 | CB6: 233390 | CC6: =CB6-CB5 -> 30 | CD6: ='[1]Reading.4.23'!CC6 -> 80 | CF6: 6080 | CG6: =CF6-CF5 -> 10 | CH6: ='[1]Reading.4.23'!CG6 -> 0 | CI6: 19773 | CJ6: =CI6-CI5 -> -3 | CK6: ='[1]Reading.4.23'!CG6 -> 0 | CM6: =BQ6+BU6+BY6+CC6+CJ6 -> 98 | CN6: =BR6+BV6+BZ6+CD6+CK6 -> 135 | CP6: 101308 | CQ6: =CP6-CP5 -> 343 | CR6: =CQ6/G6 -> 0.67920792 | CS6: ='[1]Reading.4.23'!CN6 -> 211 | CT6: ='[1]Reading.4.23'!CO4 -> % | CV6: 5215 | CW6: =CV6-CV5 -> 2 | CX6: ='[1]Reading.4.23'!CT6 -> 1 | CZ6: 881 | DA6: =CZ6-CZ5 -> 3 | DB6: ='[1]Reading.4.23'!CX6 -> 4 | DD6: 1421455 | DE6: =DD6-DD5 -> 757 | DF6: ='[1]Reading.4.23'!DB6 -> 602 | DH6: 3316131 | DI6: =DH6-DH5 -> 1866 | DJ6: ='[1]Reading.4.23'!DF6 -> 1568 | DL6: 2906591 | DM6: =DL6-DL5 -> 3208 | DN6: ='[1]Reading.4.23'!DJ6 -> 1925 | DP6: 2284919 | DQ6: =DP6-DP5 -> 31 | DR6: ='[1]Reading.4.23'!DN6 -> 32 | DT6: 3046566 | DU6: =DT6-DT5 -> 31 | DV6: ='[1]Reading.4.23'!DR6 -> 32 | DX6: 720 | DZ6: =DM6+DQ6+DU6+DX6 -> 3990 | EA6: ='[1]Reading.4.23'!DW6 -> 2709 | EC6: =C6*5.2 -> 2158 | ED6: ='[1]Reading.4.23'!C6*5.2 -> 2828.8 | EF6: 59596 | EG6: =EF6-EF5 -> 40 | EJ6: 23795 | EK6: =EJ6-EJ5 -> 33
A7: 45384 | B7: 278810 | C7: =B7-B6 -> 505 | E7: 0 | F7: 795 | G7: =C7+D7-E7+F6-F7 -> 460 | H7: ='[1]Reading.4.23'!G7 -> 539 | J7: 206914 | K7: =(J7-J6)*4.668 -> 121.368 | L7: ='[1]Reading.4.23'!K7 -> 135.372 | N7: 731150 | O7: =(N7-N6)*4.61 -> 410.29 | P7: ='[1]Reading.4.23'!O7 -> 410.29 | R7: 42700 | T7: =(R6+S6)-R7 -> 0 | U7: ='[1]Reading.4.23'!T7 -> 0 | W7: 45670.63 | X7: =(W7-W6)*4000 -> 28600 | Y7: ='[1]Reading.4.23'!X7 -> 25640 | AA7: 520030 | AB7: =AA7-AA6 -> 0 | AC7: ='[1]Reading.4.23'!AB7 -> 0 | AE7: =+X7+AB7 -> 28600 | AF7: ='[1]Reading.4.23'!AE7 -> 25640 | AG7: =989409/30 -> 32980.3 | AI7: 0.4924 | AJ7: ='[1]Reading.4.23'!AI7 -> 0.4011 | AK7: 0.638 | AM7: 259 | AN7: ='[1]Reading.4.23'!AM7 -> 211 | AO7: =10065/30 -> 335.5 | AQ7: =365*4 -> 1460 | AR7: ='[1]Reading.4.23'!AQ7 -> 1412 | AT7: 7140.23 | AU7: =(AT7-AT6)*4000 -> 3280 | AV7: =+X7/SQRT(((POWER((X7),2)+(POWER((AU7),2))))) -> 0.99348781 | AY7: ='[1]Reading.4.23'!X7 -> 25640 | AZ7: ='[1]Reading.4.23'!AB7 -> 0 | BA7: =AY7+AZ7 -> 25640 | BC7: 19 | BD7: 16.1 | BE7: 12 | BF7: 56 | BG7: 79 | BH7: ='[1]Reading.4.23'!BD7 -> 22.6 | BI7: ='[1]Reading.4.23'!BE7 -> 19 | BJ7: ='[1]Reading.4.23'!BF7 -> 52 | BL7: 526 | BN7: ='[1]Reading.4.23'!E5 -> 0 | BP7: 66319 | BQ7: =BP7-BP6 -> 18 | BR7: ='[1]Reading.4.23'!BQ7 -> 27 | BT7: 81135 | BU7: =BT7-BT6 -> 34 | BV7: ='[1]Reading.4.23'!BU7 -> 31 | BX7: 3975 | BY7: =BX7-BX6 -> 0 | BZ7: ='[1]Reading.4.23'!BY7 -> 0 | CB7: 233410 | CC7: =CB7-CB6 -> 20 | CD7: ='[1]Reading.4.23'!CC7 -> 90 | CF7: 6080 | CG7: =CF7-CF6 -> 0 | CH7: ='[1]Reading.4.23'!CG7 -> 0 | CI7: 19773 | CJ7: =CI7-CI6 -> 0 | CK7: ='[1]Reading.4.23'!CG7 -> 0 | CM7: =BQ7+BU7+BY7+CC7+CJ7 -> 72 | CN7: =BR7+BV7+BZ7+CD7+CK7 -> 148 | CP7: 101658 | CQ7: =CP7-CP6 -> 350 | CR7: =CQ7/G7 -> 0.76086957 | CS7: ='[1]Reading.4.23'!CN7 -> 232 | CT7: ='[1]Reading.4.23'!CO5 -> 0 | CV7: 5217 | CW7: =CV7-CV6 -> 2 | CX7: ='[1]Reading.4.23'!CT7 -> 2 | CZ7: 883 | DA7: =CZ7-CZ6 -> 2 | DB7: ='[1]Reading.4.23'!CX7 -> 5 | DD7: 1422161 | DE7: =DD7-DD6 -> 706 | DF7: ='[1]Reading.4.23'!DB7 -> 593 | DH7: 3317275 | DI7: =DH7-DH6 -> 1144 | DJ7: ='[1]Reading.4.23'!DF7 -> 1953 | DL7: 2910143 | DM7: =DL7-DL6 -> 3552 | DN7: ='[1]Reading.4.23'!DJ7 -> 2345 | DP7: 2284953 | DQ7: =DP7-DP6 -> 34 | DR7: ='[1]Reading.4.23'!DN7 -> 34 | DT7: 3046597 | DU7: =DT7-DT6 -> 31 | DV7: ='[1]Reading.4.23'!DR7 -> 33 | DX7: 720 | DZ7: =DM7+DQ7+DU7+DX7 -> 4337 | EA7: ='[1]Reading.4.23'!DW7 -> 3132 | EC7: =C7*5.2 -> 2626 | ED7: ='[1]Reading.4.23'!C7*5.2 -> 3218.8 | EF7: 59645 | EG7: =EF7-EF6 -> 49 | EJ7: 23812 | EK7: =EJ7-EJ6 -> 17
A8: 45385 | B8: 279392 | C8: =B8-B7 -> 582 | E8: 0 | F8: 825 | G8: =C8+D8-E8+F7-F8 -> 552 | H8: ='[1]Reading.4.23'!G8 -> 526 | J8: 206946 | K8: =(J8-J7)*4.668 -> 149.376 | L8: ='[1]Reading.4.23'!K8 -> 144.708 | N8: 731234 | O8: =(N8-N7)*4.61 -> 387.24 | P8: ='[1]Reading.4.23'!O8 -> 401.07 | R8: 42700 | T8: =(R7+S7)-R8 -> 0 | U8: ='[1]Reading.4.23'!T8 -> 0 | W8: 45677.92 | X8: =(W8-W7)*4000 -> 29160 | Y8: ='[1]Reading.4.23'!X8 -> 25760 | AA8: 520030 | AB8: =AA8-AA7 -> 0 | AC8: ='[1]Reading.4.23'!AB8 -> 0 | AE8: =+X8+AB8 -> 29160 | AF8: ='[1]Reading.4.23'!AE8 -> 25760 | AG8: =989409/30 -> 32980.3 | AI8: 0.4943 | AJ8: ='[1]Reading.4.23'!AI8 -> 0.4449 | AK8: 0.638 | AM8: 260 | AN8: ='[1]Reading.4.23'!AM8 -> 234 | AO8: =10065/30 -> 335.5 | AQ8: =387*4 -> 1548 | AR8: ='[1]Reading.4.23'!AQ8 -> 1488 | AT8: 7141.03 | AU8: =(AT8-AT7)*4000 -> 3200 | AV8: =+X8/SQRT(((POWER((X8),2)+(POWER((AU8),2))))) -> 0.99403248 | AY8: ='[1]Reading.4.23'!X8 -> 25760 | AZ8: ='[1]Reading.4.23'!AB8 -> 0 | BA8: =AY8+AZ8 -> 25760 | BC8: 19 | BD8: 16.1 | BE8: 12 | BF8: 56 | BG8: 79 | BH8: ='[1]Reading.4.23'!BD8 -> 25.2 | BI8: ='[1]Reading.4.23'!BE8 -> 20 | BJ8: ='[1]Reading.4.23'!BF8 -> 64 | BL8: 526 | BN8: ='[1]Reading.4.23'!E6 -> 0 | BP8: 66337 | BQ8: =BP8-BP7 -> 18 | BR8: ='[1]Reading.4.23'!BQ8 -> 26 | BT8: 81171 | BU8: =BT8-BT7 -> 36 | BV8: ='[1]Reading.4.23'!BU8 -> 26 | BX8: 3975 | BY8: =BX8-BX7 -> 0 | BZ8: ='[1]Reading.4.23'!BY8 -> 0 | CB8: 233440 | CC8: =CB8-CB7 -> 30 | CD8: ='[1]Reading.4.23'!CC8 -> 70 | CF8: 6090 | CG8: =CF8-CF7 -> 10 | CH8: ='[1]Reading.4.23'!CG8 -> 0 | CI8: 19773 | CJ8: =CI8-CI7 -> 0 | CK8: ='[1]Reading.4.23'!CG8 -> 0 | CM8: =BQ8+BU8+BY8+CC8+CJ8 -> 84 | CN8: =BR8+BV8+BZ8+CD8+CK8 -> 122 | CP8: 102023 | CQ8: =CP8-CP7 -> 365 | CR8: =CQ8/G8 -> 0.66123188 | CS8: ='[1]Reading.4.23'!CN8 -> 241 | CT8: ='[1]Reading.4.23'!CO6 -> 0.33814103 | CV8: 5219 | CW8: =CV8-CV7 -> 2 | CX8: ='[1]Reading.4.23'!CT8 -> 1 | CZ8: 886 | DA8: =CZ8-CZ7 -> 3 | DB8: ='[1]Reading.4.23'!CX8 -> 4 | DD8: 1422856 | DE8: =DD8-DD7 -> 695 | DF8: ='[1]Reading.4.23'!DB8 -> 704 | DH8: 3318426 | DI8: =DH8-DH7 -> 1151 | DJ8: ='[1]Reading.4.23'!DF8 -> 1739 | DL8: 2913925 | DM8: =DL8-DL7 -> 3782 | DN8: ='[1]Reading.4.23'!DJ8 -> 2679 | DP8: 2284984 | DQ8: =DP8-DP7 -> 31 | DR8: ='[1]Reading.4.23'!DN8 -> 32 | DT8: 3046629 | DU8: =DT8-DT7 -> 32 | DV8: ='[1]Reading.4.23'!DR8 -> 32 | DX8: 720 | DZ8: =DM8+DQ8+DU8+DX8 -> 4565 | EA8: ='[1]Reading.4.23'!DW8 -> 3463 | EC8: =C8*5.2 -> 3026.4 | ED8: ='[1]Reading.4.23'!C8*5.2 -> 2527.2 | EF8: 59690 | EG8: =EF8-EF7 -> 45 | EJ8: 23837 | EK8: =EJ8-EJ7 -> 25
A9: 45386 | B9: 279846 | C9: =B9-B8 -> 454 | E9: 0 | F9: 760 | G9: =C9+D9-E9+F8-F9 -> 519 | H9: ='[1]Reading.4.23'!G9 -> 532 | J9: 206980 | K9: =(J9-J8)*4.668 -> 158.712 | L9: ='[1]Reading.4.23'!K9 -> 149.376 | N9: 731314 | O9: =(N9-N8)*4.61 -> 368.8 | P9: ='[1]Reading.4.23'!O9 -> 391.85 | R9: 42700 | T9: =(R8+S8)-R9 -> 0 | U9: ='[1]Reading.4.23'!T9 -> 0 | W9: 45684.97 | X9: =(W9-W8)*4000 -> 28200 | Y9: ='[1]Reading.4.23'!X9 -> 25480 | AA9: 520030 | AB9: =AA9-AA8 -> 0 | AC9: ='[1]Reading.4.23'!AB9 -> 0 | AE9: =+X9+AB9 -> 28200 | AF9: ='[1]Reading.4.23'!AE9 -> 25480 | AG9: =989409/30 -> 32980.3 | AI9: 0.54 | AJ9: ='[1]Reading.4.23'!AI9 -> 0.4734 | AK9: 0.638 | AM9: 286 | AN9: ='[1]Reading.4.23'!AM9 -> 249 | AO9: =10065/30 -> 335.5 | AQ9: =387*4 -> 1548 | AR9: ='[1]Reading.4.23'!AQ9 -> 1488 | AT9: 7141.77 | AU9: =(AT9-AT8)*4000 -> 2960 | AV9: =+X9/SQRT(((POWER((X9),2)+(POWER((AU9),2))))) -> 0.99453633 | AY9: ='[1]Reading.4.23'!X9 -> 25480 | AZ9: ='[1]Reading.4.23'!AB9 -> 0 | BA9: =AY9+AZ9 -> 25480 | BC9: 19 | BD9: 16.1 | BE9: 12 | BF9: 56 | BG9: 79 | BH9: ='[1]Reading.4.23'!BD9 -> 26.1 | BI9: ='[1]Reading.4.23'!BE9 -> 20 | BJ9: ='[1]Reading.4.23'!BF9 -> 64 | BL9: 526 | BN9: ='[1]Reading.4.23'!E7 -> 0 | BP9: 66385 | BQ9: =BP9-BP8 -> 48 | BR9: ='[1]Reading.4.23'!BQ9 -> 27 | BT9: 81206 | BU9: =BT9-BT8 -> 35 | BV9: ='[1]Reading.4.23'!BU9 -> 26 | BX9: 3975 | BY9: =BX9-BX8 -> 0 | BZ9: ='[1]Reading.4.23'!BY9 -> 0 | CB9: 233480 | CC9: =CB9-CB8 -> 40 | CD9: ='[1]Reading.4.23'!CC9 -> 70 | CF9: 6100 | CG9: =CF9-CF8 -> 10 | CH9: ='[1]Reading.4.23'!CG9 -> 0 | CI9: 19773 | CJ9: =CI9-CI8 -> 0 | CK9: ='[1]Reading.4.23'!CG9 -> 0 | CM9: =BQ9+BU9+BY9+CC9+CJ9 -> 123 | CN9: =BR9+BV9+BZ9+CD9+CK9 -> 123 | CP9: 102368 | CQ9: =CP9-CP8 -> 345 | CR9: =CQ9/G9 -> 0.66473988 | CS9: ='[1]Reading.4.23'!CN9 -> 193 | CT9: ='[1]Reading.4.23'!CO7 -> 0.43042672 | CV9: 5221 | CW9: =CV9-CV8 -> 2 | CX9: ='[1]Reading.4.23'!CT9 -> 1 | CZ9: 887 | DA9: =CZ9-CZ8 -> 1 | DB9: ='[1]Reading.4.23'!CX9 -> 6 | DD9: 1423540 | DE9: =DD9-DD8 -> 684 | DF9: ='[1]Reading.4.23'!DB9 -> 679 | DH9: 3320261 | DI9: =DH9-DH8 -> 1835 | DJ9: ='[1]Reading.4.23'!DF9 -> 1663 | DL9: 2917005 | DM9: =DL9-DL8 -> 3080 | DN9: ='[1]Reading.4.23'!DJ9 -> 3028 | DP9: 2285013 | DQ9: =DP9-DP8 -> 29 | DR9: ='[1]Reading.4.23'!DN9 -> 35 | DT9: 3046657 | DU9: =DT9-DT8 -> 28 | DV9: ='[1]Reading.4.23'!DR9 -> 34 | DX9: 720 | DZ9: =DM9+DQ9+DU9+DX9 -> 3857 | EA9: ='[1]Reading.4.23'!DW9 -> 3817 | EC9: =C9*5.2 -> 2360.8 | ED9: ='[1]Reading.4.23'!C9*5.2 -> 2974.4 | EF9: 59749 | EG9: =EF9-EF8 -> 59 | EJ9: 23863 | EK9: =EJ9-EJ8 -> 26
A10: 45387 | B10: 280445 | C10: =B10-B9 -> 599 | E10: 0 | F10: 810 | G10: =C10+D10-E10+F9-F10 -> 549 | H10: ='[1]Reading.4.23'!G10 -> 490 | J10: 207014 | K10: =(J10-J9)*4.668 -> 158.712 | L10: ='[1]Reading.4.23'!K10 -> 163.38 | N10: 731404 | O10: =(N10-N9)*4.61 -> 414.9 | P10: ='[1]Reading.4.23'!O10 -> 414.9 | R10: 42700 | T10: =(R9+S9)-R10 -> 0 | U10: ='[1]Reading.4.23'!T10 -> 0 | W10: 45692.49 | X10: =(W10-W9)*4000 -> 30080 | Y10: ='[1]Reading.4.23'!X10 -> 27600 | AA10: 520030 | AB10: =AA10-AA9 -> 0 | AC10: ='[1]Reading.4.23'!AB10 -> 0 | AE10: =+X10+AB10 -> 30080 | AF10: ='[1]Reading.4.23'!AE10 -> 27600 | AG10: =989409/30 -> 32980.3 | AI10: 0.481 | AJ10: ='[1]Reading.4.23'!AI10 -> 0.4734 | AK10: 0.638 | AM10: 253 | AN10: ='[1]Reading.4.23'!AM10 -> 249 | AO10: =10065/30 -> 335.5 | AQ10: =401*4 -> 1604 | AR10: ='[1]Reading.4.23'!AQ10 -> 1488 | AT10: 7142.52 | AU10: =(AT10-AT9)*4000 -> 3000 | AV10: =+X10/SQRT(((POWER((X10),2)+(POWER((AU10),2))))) -> 0.99506336 | AY10: ='[1]Reading.4.23'!X10 -> 27600 | AZ10: ='[1]Reading.4.23'!AB10 -> 0 | BA10: =AY10+AZ10 -> 27600 | BC10: 19 | BD10: 16.1 | BE10: 12 | BF10: 56 | BG10: 79 | BH10: ='[1]Reading.4.23'!BD10 -> 24.6 | BI10: ='[1]Reading.4.23'!BE10 -> 18 | BJ10: ='[1]Reading.4.23'!BF10 -> 53 | BL10: 526 | BN10: ='[1]Reading.4.23'!E8 -> 0 | BP10: 66415 | BQ10: =BP10-BP9 -> 30 | BR10: ='[1]Reading.4.23'!BQ10 -> 29 | BT10: 81246 | BU10: =BT10-BT9 -> 40 | BV10: ='[1]Reading.4.23'!BU10 -> 25 | BX10: 3975 | BY10: =BX10-BX9 -> 0 | BZ10: ='[1]Reading.4.23'!BY10 -> 0 | CB10: 233520 | CC10: =CB10-CB9 -> 40 | CD10: ='[1]Reading.4.23'!CC10 -> 90 | CF10: 6110 | CG10: =CF10-CF9 -> 10 | CH10: ='[1]Reading.4.23'!CG10 -> 0 | CI10: 19773 | CJ10: =CI10-CI9 -> 0 | CK10: ='[1]Reading.4.23'!CG10 -> 0 | CM10: =BQ10+BU10+BY10+CC10+CJ10 -> 110 | CN10: =BR10+BV10+BZ10+CD10+CK10 -> 144 | CP10: 102728 | CQ10: =CP10-CP9 -> 360 | CR10: =CQ10/G10 -> 0.6557377 | CS10: ='[1]Reading.4.23'!CN10 -> 220 | CT10: ='[1]Reading.4.23'!CO8 -> 0.4581749 | CV10: 5222 | CW10: =CV10-CV9 -> 1 | CX10: ='[1]Reading.4.23'!CT10 -> 2 | CZ10: 890 | DA10: =CZ10-CZ9 -> 3 | DB10: ='[1]Reading.4.23'!CX10 -> 4 | DD10: 1424336 | DE10: =DD10-DD9 -> 796 | DF10: ='[1]Reading.4.23'!DB10 -> 700 | DH10: 3321769 | DI10: =DH10-DH9 -> 1508 | DJ10: ='[1]Reading.4.23'!DF10 -> 1828 | DL10: 2918370 | DM10: =DL10-DL9 -> 1365 | DN10: ='[1]Reading.4.23'!DJ10 -> 2842 | DP10: 2285046 | DQ10: =DP10-DP9 -> 33 | DR10: ='[1]Reading.4.23'!DN10 -> 32 | DT10: 3048717 | DU10: =DT10-DT9 -> 2060 | DV10: ='[1]Reading.4.23'!DR10 -> 32 | DX10: 720 | DZ10: =DM10+DQ10+DU10+DX10 -> 4178 | EA10: ='[1]Reading.4.23'!DW10 -> 3626 | EC10: =C10*5.2 -> 3114.8 | ED10: ='[1]Reading.4.23'!C10*5.2 -> 2496 | EF10: 59792 | EG10: =EF10-EF9 -> 43 | EJ10: 23887 | EK10: =EJ10-EJ9 -> 24
A11: 45388 | B11: 280990 | C11: =B11-B10 -> 545 | E11: 0 | F11: 830 | G11: =C11+D11-E11+F10-F11 -> 525 | H11: ='[1]Reading.4.23'!G11 -> 582 | J11: 207046 | K11: =(J11-J10)*4.668 -> 149.376 | L11: ='[1]Reading.4.23'!K11 -> 149.376 | N11: 731497 | O11: =(N11-N10)*4.61 -> 428.73 | P11: ='[1]Reading.4.23'!O11 -> 378.02 | R11: 42700 | T11: =(R10+S10)-R11 -> 0 | U11: ='[1]Reading.4.23'!T11 -> 0 | W11: 45700.03 | X11: =(W11-W10)*4000 -> 30160 | Y11: ='[1]Reading.4.23'!X11 -> 27640 | AA11: 520030 | AB11: =AA11-AA10 -> 0 | AC11: ='[1]Reading.4.23'!AB11 -> 0 | AE11: =+X11+AB11 -> 30160 | AF11: ='[1]Reading.4.23'!AE11 -> 27640 | AG11: =989409/30 -> 32980.3 | AI11: 0.519 | AJ11: ='[1]Reading.4.23'!AI11 -> 0.5133 | AK11: 0.638 | AM11: 273 | AN11: ='[1]Reading.4.23'!AM11 -> 270 | AO11: =10065/30 -> 335.5 | AQ11: =413*4 -> 1652 | AR11: ='[1]Reading.4.23'!AQ11 -> 1604 | AT11: 7143.28 | AU11: =(AT11-AT10)*4000 -> 3040 | AV11: =+X11/SQRT(((POWER((X11),2)+(POWER((AU11),2))))) -> 0.99495849 | AY11: ='[1]Reading.4.23'!X11 -> 27640 | AZ11: ='[1]Reading.4.23'!AB11 -> 0 | BA11: =AY11+AZ11 -> 27640 | BC11: 19 | BD11: 16.1 | BE11: 12 | BF11: 56 | BG11: 79 | BH11: ='[1]Reading.4.23'!BD11 -> 24.6 | BI11: ='[1]Reading.4.23'!BE11 -> 20 | BJ11: ='[1]Reading.4.23'!BF11 -> 53 | BL11: 526 | BN11: ='[1]Reading.4.23'!E9 -> 0 | BP11: 66446 | BQ11: =BP11-BP10 -> 31 | BR11: ='[1]Reading.4.23'!BQ11 -> 32 | BT11: 81277 | BU11: =BT11-BT10 -> 31 | BV11: ='[1]Reading.4.23'!BU11 -> 30 | BX11: 3975 | BY11: =BX11-BX10 -> 0 | BZ11: ='[1]Reading.4.23'!BY11 -> 0 | CB11: 233530 | CC11: =CB11-CB10 -> 10 | CD11: ='[1]Reading.4.23'!CC11 -> 80 | CF11: 6120 | CG11: =CF11-CF10 -> 10 | CH11: ='[1]Reading.4.23'!CG11 -> 0 | CI11: 19773 | CJ11: =CI11-CI10 -> 0 | CK11: ='[1]Reading.4.23'!CG11 -> 0 | CM11: =BQ11+BU11+BY11+CC11+CJ11 -> 72 | CN11: =BR11+BV11+BZ11+CD11+CK11 -> 142 | CP11: 103140 | CQ11: =CP11-CP10 -> 412 | CR11: =CQ11/G11 -> 0.7847619 | CS11: ='[1]Reading.4.23'!CN11 -> 200 | CT11: ='[1]Reading.4.23'!CO9 -> 0.36278195 | CV11: 5223 | CW11: =CV11-CV10 -> 1 | CX11: ='[1]Reading.4.23'!CT11 -> 1 | CZ11: 892 | DA11: =CZ11-CZ10 -> 2 | DB11: ='[1]Reading.4.23'!CX11 -> 3 | DD11: 1425184 | DE11: =DD11-DD10 -> 848 | DF11: ='[1]Reading.4.23'!DB11 -> 681 | DH11: 3323683 | DI11: =DH11-DH10 -> 1914 | DJ11: ='[1]Reading.4.23'!DF11 -> 1878 | DL11: 2918404 | DM11: =DL11-DL10 -> 34 | DN11: ='[1]Reading.4.23'!DJ11 -> 2614 | DP11: 2285080 | DQ11: =DP11-DP10 -> 34 | DR11: ='[1]Reading.4.23'!DN11 -> 31 | DT11: 3052211 | DU11: =DT11-DT10 -> 3494 | DV11: ='[1]Reading.4.23'!DR11 -> 30 | DX11: 720 | DZ11: =DM11+DQ11+DU11+DX11 -> 4282 | EA11: ='[1]Reading.4.23'!DW11 -> 3395 | EC11: =C11*5.2 -> 2834 | ED11: ='[1]Reading.4.23'!C11*5.2 -> 2948.4 | EF11: 59845 | EG11: =EF11-EF10 -> 53 | EJ11: 23911 | EK11: =EJ11-EJ10 -> 24
A12: 45389 | B12: 281423 | C12: =B12-B11 -> 433 | E12: 0 | F12: 755 | G12: =C12+D12-E12+F11-F12 -> 508 | H12: ='[1]Reading.4.23'!G12 -> 480 | J12: 207080 | K12: =(J12-J11)*4.668 -> 158.712 | L12: ='[1]Reading.4.23'!K12 -> 177.384 | N12: 731587 | O12: =(N12-N11)*4.61 -> 414.9 | P12: ='[1]Reading.4.23'!O12 -> 405.68 | R12: 42700 | T12: =(R11+S11)-R12 -> 0 | U12: ='[1]Reading.4.23'!T12 -> 0 | W12: 45707.2 | X12: =(W12-W11)*4000 -> 28680 | Y12: ='[1]Reading.4.23'!X12 -> 30040 | AA12: 520050 | AB12: =AA12-AA11 -> 20 | AC12: ='[1]Reading.4.23'!AB12 -> 0 | AE12: =+X12+AB12 -> 28700 | AF12: ='[1]Reading.4.23'!AE12 -> 30040 | AG12: =989409/30 -> 32980.3 | AI12: 0.4753 | AJ12: ='[1]Reading.4.23'!AI12 -> 0.5019 | AK12: 0.638 | AM12: 250 | AN12: ='[1]Reading.4.23'!AM12 -> 264 | AO12: =10065/30 -> 335.5 | AQ12: =413*4 -> 1652 | AR12: ='[1]Reading.4.23'!AQ12 -> 1604 | AT12: 7143.88 | AU12: =(AT12-AT11)*4000 -> 2400 | AV12: =+X12/SQRT(((POWER((X12),2)+(POWER((AU12),2))))) -> 0.99651694 | AY12: ='[1]Reading.4.23'!X12 -> 30040 | AZ12: ='[1]Reading.4.23'!AB12 -> 0 | BA12: =AY12+AZ12 -> 30040 | BC12: 19 | BD12: 16.1 | BE12: 12 | BF12: 56 | BG12: 79 | BH12: ='[1]Reading.4.23'!BD12 -> 27.9 | BI12: ='[1]Reading.4.23'!BE12 -> 22 | BJ12: ='[1]Reading.4.23'!BF12 -> 53 | BL12: 526 | BN12: ='[1]Reading.4.23'!E10 -> 0 | BP12: 66479 | BQ12: =BP12-BP11 -> 33 | BR12: ='[1]Reading.4.23'!BQ12 -> 28 | BT12: 81311 | BU12: =BT12-BT11 -> 34 | BV12: ='[1]Reading.4.23'!BU12 -> 33 | BX12: 3975 | BY12: =BX12-BX11 -> 0 | BZ12: ='[1]Reading.4.23'!BY12 -> 0 | CB12: 233590 | CC12: =CB12-CB11 -> 60 | CD12: ='[1]Reading.4.23'!CC12 -> 50 | CF12: 6130 | CG12: =CF12-CF11 -> 10 | CH12: ='[1]Reading.4.23'!CG12 -> 0 | CI12: 19773 | CJ12: =CI12-CI11 -> 0 | CK12: ='[1]Reading.4.23'!CG12 -> 0 | CM12: =BQ12+BU12+BY12+CC12+CJ12 -> 127 | CN12: =BR12+BV12+BZ12+CD12+CK12 -> 111 | CP12: 103530 | CQ12: =CP12-CP11 -> 390 | CR12: =CQ12/G12 -> 0.76771654 | CS12: ='[1]Reading.4.23'!CN12 -> 240 | CT12: ='[1]Reading.4.23'!CO10 -> 0.44897959 | CV12: 5225 | CW12: =CV12-CV11 -> 2 | CX12: ='[1]Reading.4.23'!CT12 -> 1 | CZ12: 895 | DA12: =CZ12-CZ11 -> 3 | DB12: ='[1]Reading.4.23'!CX12 -> 4 | DD12: 1425999 | DE12: =DD12-DD11 -> 815 | DF12: ='[1]Reading.4.23'!DB12 -> 748 | DH12: 3325200 | DI12: =DH12-DH11 -> 1517 | DJ12: ='[1]Reading.4.23'!DF12 -> 1903 | DL12: 2918435 | DM12: =DL12-DL11 -> 31 | DN12: ='[1]Reading.4.23'!DJ12 -> 3053 | DP12: 2285112 | DQ12: =DP12-DP11 -> 32 | DR12: ='[1]Reading.4.23'!DN12 -> 32 | DT12: 3055092 | DU12: =DT12-DT11 -> 2881 | DV12: ='[1]Reading.4.23'!DR12 -> 31 | DX12: 720 | DZ12: =DM12+DQ12+DU12+DX12 -> 3664 | EA12: ='[1]Reading.4.23'!DW12 -> 3836 | EC12: =C12*5.2 -> 2251.6 | ED12: ='[1]Reading.4.23'!C12*5.2 -> 2626 | EF12: 59910 | EG12: =EF12-EF11 -> 65 | EJ12: 23934 | EK12: =EJ12-EJ11 -> 23
A13: 45390 | B13: 281960 | C13: =B13-B12 -> 537 | E13: 0 | F13: 765 | G13: =C13+D13-E13+F12-F13 -> 527 | H13: ='[1]Reading.4.23'!G13 -> 448 | J13: 207111 | K13: =(J13-J12)*4.668 -> 144.708 | L13: ='[1]Reading.4.23'!K13 -> 144.708 | N13: 731674 | O13: =(N13-N12)*4.61 -> 401.07 | P13: ='[1]Reading.4.23'!O13 -> 424.12 | R13: 42700 | T13: =(R12+S12)-R13 -> 0 | U13: ='[1]Reading.4.23'!T13 -> 0 | W13: 45713.84 | X13: =(W13-W12)*4000 -> 26560 | Y13: ='[1]Reading.4.23'!X13 -> 30120 | AA13: 520050 | AB13: =AA13-AA12 -> 0 | AC13: ='[1]Reading.4.23'!AB13 -> 0 | AE13: =+X13+AB13 -> 26560 | AF13: ='[1]Reading.4.23'!AE13 -> 30120 | AG13: =989409/30 -> 32980.3 | AI13: 0.4848 | AJ13: ='[1]Reading.4.23'!AI13 -> 0.5247 | AK13: 0.638 | AM13: 255 | AN13: ='[1]Reading.4.23'!AM13 -> 276 | AO13: =10065/30 -> 335.5 | AQ13: =413*4 -> 1652 | AR13: ='[1]Reading.4.23'!AQ13 -> 1604 | AT13: 7144.51 | AU13: =(AT13-AT12)*4000 -> 2520 | AV13: =+X13/SQRT(((POWER((X13),2)+(POWER((AU13),2))))) -> 0.9955291 | AY13: ='[1]Reading.4.23'!X13 -> 30120 | AZ13: ='[1]Reading.4.23'!AB13 -> 0 | BA13: =AY13+AZ13 -> 30120 | BC13: 19 | BD13: 16.1 | BE13: 12 | BF13: 56 | BG13: 79 | BH13: ='[1]Reading.4.23'!BD13 -> 29.9 | BI13: ='[1]Reading.4.23'!BE13 -> 24 | BJ13: ='[1]Reading.4.23'!BF13 -> 53 | BL13: 526 | BN13: ='[1]Reading.4.23'!E11 -> 0 | BP13: 66511 | BQ13: =BP13-BP12 -> 32 | BR13: ='[1]Reading.4.23'!BQ13 -> 16 | BT13: 81345 | BU13: =BT13-BT12 -> 34 | BV13: ='[1]Reading.4.23'!BU13 -> 33 | BX13: 3991 | BY13: =BX13-BX12 -> 16 | BZ13: ='[1]Reading.4.23'!BY13 -> 0 | CB13: 233630 | CC13: =CB13-CB12 -> 40 | CD13: ='[1]Reading.4.23'!CC13 -> 30 | CF13: 6130 | CG13: =CF13-CF12 -> 0 | CH13: ='[1]Reading.4.23'!CG13 -> 0 | CI13: 19773 | CJ13: =CI13-CI12 -> 0 | CK13: ='[1]Reading.4.23'!CG13 -> 0 | CM13: =BQ13+BU13+BY13+CC13+CJ13 -> 122 | CN13: =BR13+BV13+BZ13+CD13+CK13 -> 79 | CP13: 103902 | CQ13: =CP13-CP12 -> 372 | CR13: =CQ13/G13 -> 0.70588235 | CS13: ='[1]Reading.4.23'!CN13 -> 254 | CT13: ='[1]Reading.4.23'!CO11 -> 0.34364261 | CV13: 5227 | CW13: =CV13-CV12 -> 2 | CX13: ='[1]Reading.4.23'!CT13 -> 1 | CZ13: 898 | DA13: =CZ13-CZ12 -> 3 | DB13: ='[1]Reading.4.23'!CX13 -> 3 | DD13: 1426464 | DE13: =DD13-DD12 -> 465 | DF13: ='[1]Reading.4.23'!DB13 -> 894 | DH13: 3326804 | DI13: =DH13-DH12 -> 1604 | DJ13: ='[1]Reading.4.23'!DF13 -> 1048 | DL13: 2918466 | DM13: =DL13-DL12 -> 31 | DN13: ='[1]Reading.4.23'!DJ13 -> 3693 | DP13: 2285144 | DQ13: =DP13-DP12 -> 32 | DR13: ='[1]Reading.4.23'!DN13 -> 0 | DT13: 3058080 | DU13: =DT13-DT12 -> 2988 | DV13: ='[1]Reading.4.23'!DR13 -> 32 | DX13: 720 | DZ13: =DM13+DQ13+DU13+DX13 -> 3771 | EA13: ='[1]Reading.4.23'!DW13 -> 4445 | EC13: =C13*5.2 -> 2792.4 | ED13: ='[1]Reading.4.23'!C13*5.2 -> 2407.6 | EF13: 59966 | EG13: =EF13-EF12 -> 56 | EJ13: 23960 | EK13: =EJ13-EJ12 -> 26
A14: 45391 | B14: 282590 | C14: =B14-B13 -> 630 | E14: 0 | F14: 855 | G14: =C14+D14-E14+F13-F14 -> 540 | H14: ='[1]Reading.4.23'!G14 -> 537 | J14: 207144 | K14: =(J14-J13)*4.668 -> 154.044 | L14: ='[1]Reading.4.23'!K14 -> 130.704 | N14: 731765 | O14: =(N14-N13)*4.61 -> 419.51 | P14: ='[1]Reading.4.23'!O14 -> 391.85 | R14: 42700 | T14: =(R13+S13)-R14 -> 0 | U14: ='[1]Reading.4.23'!T14 -> 0 | W14: 45721.33 | X14: =(W14-W13)*4000 -> 29960 | Y14: ='[1]Reading.4.23'!X14 -> 30200 | AA14: 520050 | AB14: =AA14-AA13 -> 0 | AC14: ='[1]Reading.4.23'!AB14 -> 0 | AE14: =+X14+AB14 -> 29960 | AF14: ='[1]Reading.4.23'!AE14 -> 30200 | AG14: =989409/30 -> 32980.3 | AI14: 0.5513 | AJ14: ='[1]Reading.4.23'!AI14 -> 0.4981 | AK14: 0.638 | AM14: 290 | AN14: ='[1]Reading.4.23'!AM14 -> 262 | AO14: =10065/30 -> 335.5 | AQ14: =413*4 -> 1652 | AR14: ='[1]Reading.4.23'!AQ14 -> 1664 | AT14: 7145.3 | AU14: =(AT14-AT13)*4000 -> 3160 | AV14: =+X14/SQRT(((POWER((X14),2)+(POWER((AU14),2))))) -> 0.99448361 | AY14: ='[1]Reading.4.23'!X14 -> 30200 | AZ14: ='[1]Reading.4.23'!AB14 -> 0 | BA14: =AY14+AZ14 -> 30200 | BC14: 19 | BD14: 16.1 | BE14: 12 | BF14: 56 | BG14: 79 | BH14: ='[1]Reading.4.23'!BD14 -> 29.4 | BI14: ='[1]Reading.4.23'!BE14 -> 23 | BJ14: ='[1]Reading.4.23'!BF14 -> 53 | BL14: 526 | BN14: ='[1]Reading.4.23'!E12 -> 0 | BP14: 66541 | BQ14: =BP14-BP13 -> 30 | BR14: ='[1]Reading.4.23'!BQ14 -> 24 | BT14: 81376 | BU14: =BT14-BT13 -> 31 | BV14: ='[1]Reading.4.23'!BU14 -> 28 | BX14: 3991 | BY14: =BX14-BX13 -> 0 | BZ14: ='[1]Reading.4.23'!BY14 -> 0 | CB14: 233680 | CC14: =CB14-CB13 -> 50 | CD14: ='[1]Reading.4.23'!CC14 -> 40 | CF14: 6140 | CG14: =CF14-CF13 -> 10 | CH14: ='[1]Reading.4.23'!CG14 -> 0 | CI14: 19773 | CJ14: =CI14-CI13 -> 0 | CK14: ='[1]Reading.4.23'!CG14 -> 0 | CM14: =BQ14+BU14+BY14+CC14+CJ14 -> 111 | CN14: =BR14+BV14+BZ14+CD14+CK14 -> 92 | CP14: 104287 | CQ14: =CP14-CP13 -> 385 | CR14: =CQ14/G14 -> 0.71296296 | CS14: ='[1]Reading.4.23'!CN14 -> 230 | CT14: ='[1]Reading.4.23'!CO12 -> 0.5 | CV14: 5229 | CW14: =CV14-CV13 -> 2 | CX14: ='[1]Reading.4.23'!CT14 -> 1 | CZ14: 899 | DA14: =CZ14-CZ13 -> 1 | DB14: ='[1]Reading.4.23'!CX14 -> 3 | DD14: 1427004 | DE14: =DD14-DD13 -> 540 | DF14: ='[1]Reading.4.23'!DB14 -> 798 | DH14: 3328745 | DI14: =DH14-DH13 -> 1941 | DJ14: ='[1]Reading.4.23'!DF14 -> 1450 | DL14: 2918498 | DM14: =DL14-DL13 -> 32 | DN14: ='[1]Reading.4.23'!DJ14 -> 3741 | DP14: 2285176 | DQ14: =DP14-DP13 -> 32 | DR14: ='[1]Reading.4.23'!DN14 -> 23 | DT14: 3061371 | DU14: =DT14-DT13 -> 3291 | DV14: ='[1]Reading.4.23'!DR14 -> 31 | DX14: 720 | DZ14: =DM14+DQ14+DU14+DX14 -> 4075 | EA14: ='[1]Reading.4.23'!DW14 -> 4515 | EC14: =C14*5.2 -> 3276 | ED14: ='[1]Reading.4.23'!C14*5.2 -> 2610.4 | EF14: 59989 | EG14: =EF14-EF13 -> 23 | EJ14: 23981 | EK14: =EJ14-EJ13 -> 21
A15: 45392 | B15: 283159 | C15: =B15-B14 -> 569 | E15: 0 | F15: 825 | G15: =C15+D15-E15+F14-F15 -> 599 | H15: ='[1]Reading.4.23'!G15 -> 470 | J15: 207197 | K15: =(J15-J14)*4.668 -> 247.404 | L15: ='[1]Reading.4.23'!K15 -> 149.376 | N15: 731873 | O15: =(N15-N14)*4.61 -> 497.88 | P15: ='[1]Reading.4.23'!O15 -> 414.9 | R15: 42700 | T15: =(R14+S14)-R15 -> 0 | U15: ='[1]Reading.4.23'!T15 -> 0 | W15: 45729.6 | X15: =(W15-W14)*4000 -> 33080 | Y15: ='[1]Reading.4.23'!X15 -> 31640 | AA15: 520050 | AB15: =AA15-AA14 -> 0 | AC15: ='[1]Reading.4.23'!AB15 -> 0 | AE15: =+X15+AB15 -> 33080 | AF15: ='[1]Reading.4.23'!AE15 -> 31640 | AG15: =989409/30 -> 32980.3 | AI15: 0.692 | AJ15: ='[1]Reading.4.23'!AI15 -> 0.4753 | AK15: 0.638 | AM15: 364 | AN15: ='[1]Reading.4.23'!AM15 -> 250 | AO15: =10065/30 -> 335.5 | AQ15: =421*4 -> 1684 | AR15: ='[1]Reading.4.23'!AQ15 -> 1680 | AT15: 7146.14 | AU15: =(AT15-AT14)*4000 -> 3360 | AV15: =+X15/SQRT(((POWER((X15),2)+(POWER((AU15),2))))) -> 0.99488114 | AY15: ='[1]Reading.4.23'!X15 -> 31640 | AZ15: ='[1]Reading.4.23'!AB15 -> 0 | BA15: =AY15+AZ15 -> 31640 | BC15: 19 | BD15: 16.1 | BE15: 12 | BF15: 56 | BG15: 79 | BH15: ='[1]Reading.4.23'!BD15 -> 27.2 | BI15: ='[1]Reading.4.23'!BE15 -> 25 | BJ15: ='[1]Reading.4.23'!BF15 -> 53 | BL15: 526 | BN15: ='[1]Reading.4.23'!E13 -> 0 | BP15: 66574 | BQ15: =BP15-BP14 -> 33 | BR15: ='[1]Reading.4.23'!BQ15 -> 26 | BT15: 81421 | BU15: =BT15-BT14 -> 45 | BV15: ='[1]Reading.4.23'!BU15 -> 35 | BX15: 3991 | BY15: =BX15-BX14 -> 0 | BZ15: ='[1]Reading.4.23'!BY15 -> 0 | CB15: 233730 | CC15: =CB15-CB14 -> 50 | CD15: ='[1]Reading.4.23'!CC15 -> 0 | CF15: 6150 | CG15: =CF15-CF14 -> 10 | CH15: ='[1]Reading.4.23'!CG15 -> 0 | CI15: 19773 | CJ15: =CI15-CI14 -> 0 | CK15: ='[1]Reading.4.23'!CG15 -> 0 | CM15: =BQ15+BU15+BY15+CC15+CJ15 -> 128 | CN15: =BR15+BV15+BZ15+CD15+CK15 -> 61 | CP15: 104647 | CQ15: =CP15-CP14 -> 360 | CR15: =CQ15/G15 -> 0.60100167 | CS15: ='[1]Reading.4.23'!CN15 -> 243 | CT15: ='[1]Reading.4.23'!CO13 -> 0.56696429 | CV15: 5231 | CW15: =CV15-CV14 -> 2 | CX15: ='[1]Reading.4.23'!CT15 -> 1 | CZ15: 901 | DA15: =CZ15-CZ14 -> 2 | DB15: ='[1]Reading.4.23'!CX15 -> 5 | DD15: 1427923 | DE15: =DD15-DD14 -> 919 | DF15: ='[1]Reading.4.23'!DB15 -> 858 | DH15: 3330506 | DI15: =DH15-DH14 -> 1761 | DJ15: ='[1]Reading.4.23'!DF15 -> 1722 | DL15: 2918528 | DM15: =DL15-DL14 -> 30 | DN15: ='[1]Reading.4.23'!DJ15 -> 3686 | DP15: 2285206 | DQ15: =DP15-DP14 -> 30 | DR15: ='[1]Reading.4.23'!DN15 -> 42 | DT15: 3064447 | DU15: =DT15-DT14 -> 3076 | DV15: ='[1]Reading.4.23'!DR15 -> 30 | DX15: 720 | DZ15: =DM15+DQ15+DU15+DX15 -> 3856 | EA15: ='[1]Reading.4.23'!DW15 -> 4478 | EC15: =C15*5.2 -> 2958.8 | ED15: ='[1]Reading.4.23'!C15*5.2 -> 2470 | EF15: 60042 | EG15: =EF15-EF14 -> 53 | EJ15: 24005 | EK15: =EJ15-EJ14 -> 24
A16: 45393 | B16: 283715 | C16: =B16-B15 -> 556 | E16: 0 | F16: 785 | G16: =C16+D16-E16+F15-F16 -> 596 | H16: ='[1]Reading.4.23'!G16 -> 472 | J16: 207239 | K16: =(J16-J15)*4.668 -> 196.056 | L16: ='[1]Reading.4.23'!K16 -> 149.376 | N16: 731987 | O16: =(N16-N15)*4.61 -> 525.54 | P16: ='[1]Reading.4.23'!O16 -> 401.07 | R16: 42700 | T16: =(R15+S15)-R16 -> 0 | U16: ='[1]Reading.4.23'!T16 -> 0 | W16: 45738.16 | X16: =(W16-W15)*4000 -> 34240 | Y16: ='[1]Reading.4.23'!X16 -> 30160 | AA16: 520050 | AB16: =AA16-AA15 -> 0 | AC16: ='[1]Reading.4.23'!AB16 -> 0 | AE16: =+X16+AB16 -> 34240 | AF16: ='[1]Reading.4.23'!AE16 -> 30160 | AG16: =989409/30 -> 32980.3 | AI16: 0.8384 | AJ16: ='[1]Reading.4.23'!AI16 -> 0.4829 | AK16: 0.638 | AM16: 441 | AN16: ='[1]Reading.4.23'!AM16 -> 254 | AO16: =10065/30 -> 335.5 | AQ16: =432*4 -> 1728 | AR16: ='[1]Reading.4.23'!AQ16 -> 1680 | AT16: 7147.05 | AU16: =(AT16-AT15)*4000 -> 3640 | AV16: =+X16/SQRT(((POWER((X16),2)+(POWER((AU16),2))))) -> 0.99439671 | AY16: ='[1]Reading.4.23'!X16 -> 30160 | AZ16: ='[1]Reading.4.23'!AB16 -> 0 | BA16: =AY16+AZ16 -> 30160 | BC16: 19 | BD16: 16.1 | BE16: 12 | BF16: 56 | BG16: 79 | BH16: ='[1]Reading.4.23'!BD16 -> 24.4 | BI16: ='[1]Reading.4.23'!BE16 -> 22 | BJ16: ='[1]Reading.4.23'!BF16 -> 73 | BL16: 526 | BN16: ='[1]Reading.4.23'!E14 -> 0 | BP16: 66603 | BQ16: =BP16-BP15 -> 29 | BR16: ='[1]Reading.4.23'!BQ16 -> 39 | BT16: 81461 | BU16: =BT16-BT15 -> 40 | BV16: ='[1]Reading.4.23'!BU16 -> 27 | BX16: 3991 | BY16: =BX16-BX15 -> 0 | BZ16: ='[1]Reading.4.23'!BY16 -> 0 | CB16: 233780 | CC16: =CB16-CB15 -> 50 | CD16: ='[1]Reading.4.23'!CC16 -> 20 | CF16: 6160 | CG16: =CF16-CF15 -> 10 | CH16: ='[1]Reading.4.23'!CG16 -> 0 | CI16: 19773 | CJ16: =CI16-CI15 -> 0 | CK16: ='[1]Reading.4.23'!CG16 -> 0 | CM16: =BQ16+BU16+BY16+CC16+CJ16 -> 119 | CN16: =BR16+BV16+BZ16+CD16+CK16 -> 86 | CP16: 105101 | CQ16: =CP16-CP15 -> 454 | CR16: =CQ16/G16 -> 0.76174497 | CS16: ='[1]Reading.4.23'!CN16 -> 230 | CT16: ='[1]Reading.4.23'!CO14 -> 0.4283054 | CV16: 5232 | CW16: =CV16-CV15 -> 1 | CX16: ='[1]Reading.4.23'!CT16 -> 2 | CZ16: 905 | DA16: =CZ16-CZ15 -> 4 | DB16: ='[1]Reading.4.23'!CX16 -> 3 | DD16: 1428690 | DE16: =DD16-DD15 -> 767 | DF16: ='[1]Reading.4.23'!DB16 -> 751 | DH16: 3332323 | DI16: =DH16-DH15 -> 1817 | DJ16: ='[1]Reading.4.23'!DF16 -> 2413 | DL16: 2918560 | DM16: =DL16-DL15 -> 32 | DN16: ='[1]Reading.4.23'!DJ16 -> 3657 | DP16: 2285238 | DQ16: =DP16-DP15 -> 32 | DR16: ='[1]Reading.4.23'!DN16 -> 32 | DT16: 3068122 | DU16: =DT16-DT15 -> 3675 | DV16: ='[1]Reading.4.23'!DR16 -> 34 | DX16: 720 | DZ16: =DM16+DQ16+DU16+DX16 -> 4459 | EA16: ='[1]Reading.4.23'!DW16 -> 4443 | EC16: =C16*5.2 -> 2891.2 | ED16: ='[1]Reading.4.23'!C16*5.2 -> 2480.4 | EF16: 60094 | EG16: =EF16-EF15 -> 52 | EJ16: 24028 | EK16: =EJ16-EJ15 -> 23
A17: 45394 | B17: 284378 | C17: =B17-B16 -> 663 | E17: 0 | F17: 765 | G17: =C17+D17-E17+F16-F17 -> 683 | H17: ='[1]Reading.4.23'!G17 -> 513 | J17: 207282 | K17: =(J17-J16)*4.668 -> 200.724 | L17: ='[1]Reading.4.23'!K17 -> 168.048 | N17: 732103 | O17: =(N17-N16)*4.61 -> 534.76 | P17: ='[1]Reading.4.23'!O17 -> 461 | R17: 42700 | T17: =(R16+S16)-R17 -> 0 | U17: ='[1]Reading.4.23'!T17 -> 0 | W17: 45747.05 | X17: =(W17-W16)*4000 -> 35560 | Y17: ='[1]Reading.4.23'!X17 -> 28920 | AA17: 520050 | AB17: =AA17-AA16 -> 0 | AC17: ='[1]Reading.4.23'!AB17 -> 240 | AE17: =+X17+AB17 -> 35560 | AF17: ='[1]Reading.4.23'!AE17 -> 29160 | AG17: =989409/30 -> 32980.3 | AI17: 0.8574 | AJ17: ='[1]Reading.4.23'!AI17 -> 0.4753 | AK17: 0.638 | AM17: 451 | AN17: ='[1]Reading.4.23'!AM17 -> 250 | AO17: =10065/30 -> 335.5 | AQ17: =448*4 -> 1792 | AR17: ='[1]Reading.4.23'!AQ17 -> 1680 | AT17: 7147.99 | AU17: =(AT17-AT16)*4000 -> 3760 | AV17: =+X17/SQRT(((POWER((X17),2)+(POWER((AU17),2))))) -> 0.99445631 | AY17: ='[1]Reading.4.23'!X17 -> 28920 | AZ17: ='[1]Reading.4.23'!AB17 -> 240 | BA17: =AY17+AZ17 -> 29160 | BC17: 19 | BD17: 16.1 | BE17: 12 | BF17: 56 | BG17: 79 | BH17: ='[1]Reading.4.23'!BD17 -> 22.1 | BI17: ='[1]Reading.4.23'!BE17 -> 20 | BJ17: ='[1]Reading.4.23'!BF17 -> 64 | BL17: 526 | BN17: ='[1]Reading.4.23'!E15 -> 0 | BP17: 66647 | BQ17: =BP17-BP16 -> 44 | BR17: ='[1]Reading.4.23'!BQ17 -> 24 | BT17: 81506 | BU17: =BT17-BT16 -> 45 | BV17: ='[1]Reading.4.23'!BU17 -> 39 | BX17: 3991 | BY17: =BX17-BX16 -> 0 | BZ17: ='[1]Reading.4.23'!BY17 -> 5 | CB17: 233820 | CC17: =CB17-CB16 -> 40 | CD17: ='[1]Reading.4.23'!CC17 -> 95 | CF17: 6170 | CG17: =CF17-CF16 -> 10 | CH17: ='[1]Reading.4.23'!CG17 -> 0 | CI17: 19773 | CJ17: =CI17-CI16 -> 0 | CK17: ='[1]Reading.4.23'!CG17 -> 0 | CM17: =BQ17+BU17+BY17+CC17+CJ17 -> 129 | CN17: =BR17+BV17+BZ17+CD17+CK17 -> 163 | CP17: 105570 | CQ17: =CP17-CP16 -> 469 | CR17: =CQ17/G17 -> 0.68667643 | CS17: ='[1]Reading.4.23'!CN17 -> 190 | CT17: ='[1]Reading.4.23'!CO15 -> 0.51702128 | CV17: 5235 | CW17: =CV17-CV16 -> 3 | CX17: ='[1]Reading.4.23'!CT17 -> 1 | CZ17: 909 | DA17: =CZ17-CZ16 -> 4 | DB17: ='[1]Reading.4.23'!CX17 -> 3 | DD17: 1429486 | DE17: =DD17-DD16 -> 796 | DF17: ='[1]Reading.4.23'!DB17 -> 693 | DH17: 3334290 | DI17: =DH17-DH16 -> 1967 | DJ17: ='[1]Reading.4.23'!DF17 -> 1650 | DL17: 2918591 | DM17: =DL17-DL16 -> 31 | DN17: ='[1]Reading.4.23'!DJ17 -> 2379 | DP17: 2285270 | DQ17: =DP17-DP16 -> 32 | DR17: ='[1]Reading.4.23'!DN17 -> 197 | DT17: 3071920 | DU17: =DT17-DT16 -> 3798 | DV17: ='[1]Reading.4.23'!DR17 -> 94 | DX17: 720 | DZ17: =DM17+DQ17+DU17+DX17 -> 4581 | EA17: ='[1]Reading.4.23'!DW17 -> 3390 | EC17: =C17*5.2 -> 3447.6 | ED17: ='[1]Reading.4.23'!C17*5.2 -> 2927.6 | EF17: 60161 | EG17: =EF17-EF16 -> 67 | EJ17: 24057 | EK17: =EJ17-EJ16 -> 29
A18: 45395 | B18: 285100 | C18: =B18-B17 -> 722 | E18: 0 | F18: 820 | G18: =C18+D18-E18+F17-F18 -> 667 | H18: ='[1]Reading.4.23'!G18 -> 484 | J18: 207330 | K18: =(J18-J17)*4.668 -> 224.064 | L18: ='[1]Reading.4.23'!K18 -> 154.044 | N18: 732220 | O18: =(N18-N17)*4.61 -> 539.37 | P18: ='[1]Reading.4.23'!O18 -> 401.07 | R18: 42700 | T18: =(R17+S17)-R18 -> 0 | U18: ='[1]Reading.4.23'!T18 -> 0 | W18: 45756.04 | X18: =(W18-W17)*4000 -> 35960 | Y18: ='[1]Reading.4.23'!X18 -> 28600 | AA18: 520050 | AB18: =AA18-AA17 -> 0 | AC18: ='[1]Reading.4.23'!AB18 -> 0 | AE18: =+X18+AB18 -> 35960 | AF18: ='[1]Reading.4.23'!AE18 -> 28600 | AG18: =989409/30 -> 32980.3 | AI18: 0.8327 | AJ18: ='[1]Reading.4.23'!AI18 -> 0.4886 | AK18: 0.638 | AM18: 438 | AN18: ='[1]Reading.4.23'!AM18 -> 257 | AO18: =10065/30 -> 335.5 | AQ18: =459*4 -> 1836 | AR18: ='[1]Reading.4.23'!AQ18 -> 1680 | AT18: 7149.02 | AU18: =(AT18-AT17)*4000 -> 4120 | AV18: =+X18/SQRT(((POWER((X18),2)+(POWER((AU18),2))))) -> 0.99350057 | AY18: ='[1]Reading.4.23'!X18 -> 28600 | AZ18: ='[1]Reading.4.23'!AB18 -> 0 | BA18: =AY18+AZ18 -> 28600 | BC18: 19 | BD18: 16.1 | BE18: 12 | BF18: 56 | BG18: 79 | BH18: ='[1]Reading.4.23'!BD18 -> 22.2 | BI18: ='[1]Reading.4.23'!BE18 -> 18 | BJ18: ='[1]Reading.4.23'!BF18 -> 60 | BL18: 526 | BN18: ='[1]Reading.4.23'!E16 -> 0 | BP18: 66680 | BQ18: =BP18-BP17 -> 33 | BR18: ='[1]Reading.4.23'!BQ18 -> 29 | BT18: 81548 | BU18: =BT18-BT17 -> 42 | BV18: ='[1]Reading.4.23'!BU18 -> 35 | BX18: 3991 | BY18: =BX18-BX17 -> 0 | BZ18: ='[1]Reading.4.23'!BY18 -> 0 | CB18: 233860 | CC18: =CB18-CB17 -> 40 | CD18: ='[1]Reading.4.23'!CC18 -> 23 | CF18: 6180 | CG18: =CF18-CF17 -> 10 | CH18: ='[1]Reading.4.23'!CG18 -> 0 | CI18: 19773 | CJ18: =CI18-CI17 -> 0 | CK18: ='[1]Reading.4.23'!CG18 -> 0 | CM18: =BQ18+BU18+BY18+CC18+CJ18 -> 115 | CN18: =BR18+BV18+BZ18+CD18+CK18 -> 87 | CP18: 106096 | CQ18: =CP18-CP17 -> 526 | CR18: =CQ18/G18 -> 0.7886057 | CS18: ='[1]Reading.4.23'!CN18 -> 192 | CT18: ='[1]Reading.4.23'!CO16 -> 0.48728814 | CV18: 5237 | CW18: =CV18-CV17 -> 2 | CX18: ='[1]Reading.4.23'!CT18 -> 1 | CZ18: 912 | DA18: =CZ18-CZ17 -> 3 | DB18: ='[1]Reading.4.23'!CX18 -> 4 | DD18: 1430296 | DE18: =DD18-DD17 -> 810 | DF18: ='[1]Reading.4.23'!DB18 -> 703 | DH18: 3336210 | DI18: =DH18-DH17 -> 1920 | DJ18: ='[1]Reading.4.23'!DF18 -> 1498 | DL18: 2918622 | DM18: =DL18-DL17 -> 31 | DN18: ='[1]Reading.4.23'!DJ18 -> 2979 | DP18: 2285302 | DQ18: =DP18-DP17 -> 32 | DR18: ='[1]Reading.4.23'!DN18 -> 31 | DT18: 3075979 | DU18: =DT18-DT17 -> 4059 | DV18: ='[1]Reading.4.23'!DR18 -> 35 | DX18: 720 | DZ18: =DM18+DQ18+DU18+DX18 -> 4842 | EA18: ='[1]Reading.4.23'!DW18 -> 3765 | EC18: =C18*5.2 -> 3754.4 | ED18: ='[1]Reading.4.23'!C18*5.2 -> 2386.8 | EF18: 60220 | EG18: =EF18-EF17 -> 59 | EJ18: 24081 | EK18: =EJ18-EJ17 -> 24
A19: 45396 | B19: 285686 | C19: =B19-B18 -> 586 | E19: 0 | F19: 775 | G19: =C19+D19-E19+F18-F19 -> 631 | H19: ='[1]Reading.4.23'!G19 -> 507 | J19: 207369 | K19: =(J19-J18)*4.668 -> 182.052 | L19: ='[1]Reading.4.23'!K19 -> 163.38 | N19: 732340 | O19: =(N19-N18)*4.61 -> 553.2 | P19: ='[1]Reading.4.23'!O19 -> 424.12 | R19: 42700 | T19: =(R18+S18)-R19 -> 0 | U19: ='[1]Reading.4.23'!T19 -> 0 | W19: 45764.85 | X19: =(W19-W18)*4000 -> 35240 | Y19: ='[1]Reading.4.23'!X19 -> 29320 | AA19: 520050 | AB19: =AA19-AA18 -> 0 | AC19: ='[1]Reading.4.23'!AB19 -> 0 | AE19: =+X19+AB19 -> 35240 | AF19: ='[1]Reading.4.23'!AE19 -> 29320 | AG19: =989409/30 -> 32980.3 | AI19: 0.7452 | AJ19: ='[1]Reading.4.23'!AI19 -> 0.4601 | AK19: 0.638 | AM19: 392 | AN19: ='[1]Reading.4.23'!AM19 -> 242 | AO19: =10065/30 -> 335.5 | AQ19: =467*4 -> 1868 | AR19: ='[1]Reading.4.23'!AQ19 -> 1680 | AT19: 7149.93 | AU19: =(AT19-AT18)*4000 -> 3640 | AV19: =+X19/SQRT(((POWER((X19),2)+(POWER((AU19),2))))) -> 0.99470772 | AY19: ='[1]Reading.4.23'!X19 -> 29320 | AZ19: ='[1]Reading.4.23'!AB19 -> 0 | BA19: =AY19+AZ19 -> 29320 | BC19: 19 | BD19: 16.1 | BE19: 12 | BF19: 56 | BG19: 79 | BH19: ='[1]Reading.4.23'!BD19 -> 23.5 | BI19: ='[1]Reading.4.23'!BE19 -> 18 | BJ19: ='[1]Reading.4.23'!BF19 -> 60 | BL19: 526 | BN19: ='[1]Reading.4.23'!E17 -> 0 | BP19: 66718 | BQ19: =BP19-BP18 -> 38 | BR19: ='[1]Reading.4.23'!BQ19 -> 24 | BT19: 81592 | BU19: =BT19-BT18 -> 44 | BV19: ='[1]Reading.4.23'!BU19 -> 27 | BX19: 3991 | BY19: =BX19-BX18 -> 0 | BZ19: ='[1]Reading.4.23'!BY19 -> 0 | CB19: 233900 | CC19: =CB19-CB18 -> 40 | CD19: ='[1]Reading.4.23'!CC19 -> 57 | CF19: 6190 | CG19: =CF19-CF18 -> 10 | CH19: ='[1]Reading.4.23'!CG19 -> 0 | CI19: 19773 | CJ19: =CI19-CI18 -> 0 | CK19: ='[1]Reading.4.23'!CG19 -> 0 | CM19: =BQ19+BU19+BY19+CC19+CJ19 -> 122 | CN19: =BR19+BV19+BZ19+CD19+CK19 -> 108 | CP19: 106586 | CQ19: =CP19-CP18 -> 490 | CR19: =CQ19/G19 -> 0.77654517 | CS19: ='[1]Reading.4.23'!CN19 -> 191 | CT19: ='[1]Reading.4.23'!CO17 -> 0.37037037 | CV19: 5240 | CW19: =CV19-CV18 -> 3 | CX19: ='[1]Reading.4.23'!CT19 -> 1 | CZ19: 915 | DA19: =CZ19-CZ18 -> 3 | DB19: ='[1]Reading.4.23'!CX19 -> 3 | DD19: 1431096 | DE19: =DD19-DD18 -> 800 | DF19: ='[1]Reading.4.23'!DB19 -> 736 | DH19: 3338087 | DI19: =DH19-DH18 -> 1877 | DJ19: ='[1]Reading.4.23'!DF19 -> 1785 | DL19: 2918654 | DM19: =DL19-DL18 -> 32 | DN19: ='[1]Reading.4.23'!DJ19 -> 2717 | DP19: 2285334 | DQ19: =DP19-DP18 -> 32 | DR19: ='[1]Reading.4.23'!DN19 -> 36 | DT19: 3079922 | DU19: =DT19-DT18 -> 3943 | DV19: ='[1]Reading.4.23'!DR19 -> 34 | DX19: 720 | DZ19: =DM19+DQ19+DU19+DX19 -> 4727 | EA19: ='[1]Reading.4.23'!DW19 -> 3507 | EC19: =C19*5.2 -> 3047.2 | ED19: ='[1]Reading.4.23'!C19*5.2 -> 2766.4 | EF19: 60268 | EG19: =EF19-EF18 -> 48 | EJ19: 24104 | EK19: =EJ19-EJ18 -> 23
A20: 45397 | B20: 286347 | C20: =B20-B19 -> 661 | E20: 0 | F20: 810 | G20: =C20+D20-E20+F19-F20 -> 626 | H20: ='[1]Reading.4.23'!G20 -> 574 | J20: 207403 | K20: =(J20-J19)*4.668 -> 158.712 | L20: ='[1]Reading.4.23'!K20 -> 158.712 | N20: 732458 | O20: =(N20-N19)*4.61 -> 543.98 | P20: ='[1]Reading.4.23'!O20 -> 428.73 | R20: 42700 | T20: =(R19+S19)-R20 -> 0 | U20: ='[1]Reading.4.23'!T20 -> 0 | W20: 45773.41 | X20: =(W20-W19)*4000 -> 34240 | Y20: ='[1]Reading.4.23'!X20 -> 32520 | AA20: 520050 | AB20: =AA20-AA19 -> 0 | AC20: ='[1]Reading.4.23'!AB20 -> 0 | AE20: =+X20+AB20 -> 34240 | AF20: ='[1]Reading.4.23'!AE20 -> 32520 | AG20: =989409/30 -> 32980.3 | AI20: 0.6806 | AJ20: ='[1]Reading.4.23'!AI20 -> 0.5076 | AK20: 0.638 | AM20: 358 | AN20: ='[1]Reading.4.23'!AM20 -> 267 | AO20: =10065/30 -> 335.5 | AQ20: =467*4 -> 1868 | AR20: ='[1]Reading.4.23'!AQ20 -> 1680 | AT20: 7150.7 | AU20: =(AT20-AT19)*4000 -> 3080 | AV20: =+X20/SQRT(((POWER((X20),2)+(POWER((AU20),2))))) -> 0.99597859 | AY20: ='[1]Reading.4.23'!X20 -> 32520 | AZ20: ='[1]Reading.4.23'!AB20 -> 0 | BA20: =AY20+AZ20 -> 32520 | BC20: 19 | BD20: 16.1 | BE20: 12 | BF20: 56 | BG20: 79 | BH20: ='[1]Reading.4.23'!BD20 -> 26.2 | BI20: ='[1]Reading.4.23'!BE20 -> 22 | BJ20: ='[1]Reading.4.23'!BF20 -> 64 | BL20: 526 | BN20: ='[1]Reading.4.23'!E18 -> 0 | BP20: 66749 | BQ20: =BP20-BP19 -> 31 | BR20: ='[1]Reading.4.23'!BQ20 -> 32 | BT20: 81638 | BU20: =BT20-BT19 -> 46 | BV20: ='[1]Reading.4.23'!BU20 -> 33 | BX20: 3991 | BY20: =BX20-BX19 -> 0 | BZ20: ='[1]Reading.4.23'!BY20 -> 0 | CB20: 233920 | CC20: =CB20-CB19 -> 20 | CD20: ='[1]Reading.4.23'!CC20 -> 50 | CF20: 6200 | CG20: =CF20-CF19 -> 10 | CH20: ='[1]Reading.4.23'!CG20 -> 0 | CI20: 19773 | CJ20: =CI20-CI19 -> 0 | CK20: ='[1]Reading.4.23'!CG20 -> 0 | CM20: =BQ20+BU20+BY20+CC20+CJ20 -> 97 | CN20: =BR20+BV20+BZ20+CD20+CK20 -> 115 | CP20: 107020 | CQ20: =CP20-CP19 -> 434 | CR20: =CQ20/G20 -> 0.69329073 | CS20: ='[1]Reading.4.23'!CN20 -> 262 | CT20: ='[1]Reading.4.23'!CO18 -> 0.39669421 | CV20: 5242 | CW20: =CV20-CV19 -> 2 | CX20: ='[1]Reading.4.23'!CT20 -> 1 | CZ20: 919 | DA20: =CZ20-CZ19 -> 4 | DB20: ='[1]Reading.4.23'!CX20 -> 5 | DD20: 1432010 | DE20: =DD20-DD19 -> 914 | DF20: ='[1]Reading.4.23'!DB20 -> 829 | DH20: 3339781 | DI20: =DH20-DH19 -> 1694 | DJ20: ='[1]Reading.4.23'!DF20 -> 1934 | DL20: 2918686 | DM20: =DL20-DL19 -> 32 | DN20: ='[1]Reading.4.23'!DJ20 -> 3356 | DP20: 2285367 | DQ20: =DP20-DP19 -> 33 | DR20: ='[1]Reading.4.23'!DN20 -> 34 | DT20: 3083810 | DU20: =DT20-DT19 -> 3888 | DV20: ='[1]Reading.4.23'!DR20 -> 34 | DX20: 720 | DZ20: =DM20+DQ20+DU20+DX20 -> 4673 | EA20: ='[1]Reading.4.23'!DW20 -> 4144 | EC20: =C20*5.2 -> 3437.2 | ED20: ='[1]Reading.4.23'!C20*5.2 -> 2178.8 | EF20: 60314 | EG20: =EF20-EF19 -> 46 | EJ20: 24124 | EK20: =EJ20-EJ19 -> 20
A21: 45398 | B21: 286856 | C21: =B21-B20 -> 509 | E21: 0 | F21: 765 | G21: =C21+D21-E21+F20-F21 -> 554 | H21: ='[1]Reading.4.23'!G21 -> 474 | J21: 207441 | K21: =(J21-J20)*4.668 -> 177.384 | L21: ='[1]Reading.4.23'!K21 -> 168.048 | N21: 732568 | O21: =(N21-N20)*4.61 -> 507.1 | P21: ='[1]Reading.4.23'!O21 -> 419.51 | R21: 42700 | T21: =(R20+S20)-R21 -> 0 | U21: ='[1]Reading.4.23'!T21 -> 0 | W21: 45781.62 | X21: =(W21-W20)*4000 -> 32840 | Y21: ='[1]Reading.4.23'!X21 -> 26720 | AA21: 520050 | AB21: =AA21-AA20 -> 0 | AC21: ='[1]Reading.4.23'!AB21 -> 0 | AE21: =+X21+AB21 -> 32840 | AF21: ='[1]Reading.4.23'!AE21 -> 26720 | AG21: =989409/30 -> 32980.3 | AI21: 0.6464 | AJ21: ='[1]Reading.4.23'!AI21 -> 0.5057 | AK21: 0.638 | AM21: 340 | AN21: ='[1]Reading.4.23'!AM21 -> 266 | AO21: =10065/30 -> 335.5 | AQ21: =467*4 -> 1868 | AR21: ='[1]Reading.4.23'!AQ21 -> 1680 | AT21: 7151.5 | AU21: =(AT21-AT20)*4000 -> 3200 | AV21: =+X21/SQRT(((POWER((X21),2)+(POWER((AU21),2))))) -> 0.99528606 | AY21: ='[1]Reading.4.23'!X21 -> 26720 | AZ21: ='[1]Reading.4.23'!AB21 -> 0 | BA21: =AY21+AZ21 -> 26720 | BC21: 19 | BD21: 16.1 | BE21: 12 | BF21: 56 | BG21: 79 | BH21: ='[1]Reading.4.23'!BD21 -> 26.5 | BI21: ='[1]Reading.4.23'!BE21 -> 23 | BJ21: ='[1]Reading.4.23'!BF21 -> 57 | BL21: 526 | BN21: ='[1]Reading.4.23'!E19 -> 0 | BP21: 66780 | BQ21: =BP21-BP20 -> 31 | BR21: ='[1]Reading.4.23'!BQ21 -> 32 | BT21: 81678 | BU21: =BT21-BT20 -> 40 | BV21: ='[1]Reading.4.23'!BU21 -> 30 | BX21: 3991 | BY21: =BX21-BX20 -> 0 | BZ21: ='[1]Reading.4.23'!BY21 -> 0 | CB21: 233940 | CC21: =CB21-CB20 -> 20 | CD21: ='[1]Reading.4.23'!CC21 -> 40 | CF21: 6210 | CG21: =CF21-CF20 -> 10 | CH21: ='[1]Reading.4.23'!CG21 -> 0 | CI21: 19773 | CJ21: =CI21-CI20 -> 0 | CK21: ='[1]Reading.4.23'!CG21 -> 0 | CM21: =BQ21+BU21+BY21+CC21+CJ21 -> 91 | CN21: =BR21+BV21+BZ21+CD21+CK21 -> 102 | CP21: 107438 | CQ21: =CP21-CP20 -> 418 | CR21: =CQ21/G21 -> 0.75451264 | CS21: ='[1]Reading.4.23'!CN21 -> 213 | CT21: ='[1]Reading.4.23'!CO19 -> 0.37672584 | CV21: 5244 | CW21: =CV21-CV20 -> 2 | CX21: ='[1]Reading.4.23'!CT21 -> 1 | CZ21: 923 | DA21: =CZ21-CZ20 -> 4 | DB21: ='[1]Reading.4.23'!CX21 -> 4 | DD21: 1432806 | DE21: =DD21-DD20 -> 796 | DF21: ='[1]Reading.4.23'!DB21 -> 802 | DH21: 3341475 | DI21: =DH21-DH20 -> 1694 | DJ21: ='[1]Reading.4.23'!DF21 -> 1974 | DL21: 2918718 | DM21: =DL21-DL20 -> 32 | DN21: ='[1]Reading.4.23'!DJ21 -> 3422 | DP21: 2285400 | DQ21: =DP21-DP20 -> 33 | DR21: ='[1]Reading.4.23'!DN21 -> 33 | DT21: 3088045 | DU21: =DT21-DT20 -> 4235 | DV21: ='[1]Reading.4.23'!DR21 -> 32 | DX21: 720 | DZ21: =DM21+DQ21+DU21+DX21 -> 5020 | EA21: ='[1]Reading.4.23'!DW21 -> 4207 | EC21: =C21*5.2 -> 2646.8 | ED21: ='[1]Reading.4.23'!C21*5.2 -> 2958.8 | EF21: 60360 | EG21: =EF21-EF20 -> 46 | EJ21: 24144 | EK21: =EJ21-EJ20 -> 20
A22: 45399 | B22: 287486 | C22: =B22-B21 -> 630 | E22: 0 | F22: 830 | G22: =C22+D22-E22+F21-F22 -> 565 | H22: ='[1]Reading.4.23'!G22 -> 523 | J22: 207483 | K22: =(J22-J21)*4.668 -> 196.056 | L22: ='[1]Reading.4.23'!K22 -> 182.052 | N22: 732678 | O22: =(N22-N21)*4.61 -> 507.1 | P22: ='[1]Reading.4.23'!O22 -> 456.39 | R22: 42700 | T22: =(R21+S21)-R22 -> 0 | U22: ='[1]Reading.4.23'!T22 -> 0 | W22: 45790.14 | X22: =(W22-W21)*4000 -> 34080 | Y22: ='[1]Reading.4.23'!X22 -> 32920 | AA22: 520050 | AB22: =AA22-AA21 -> 0 | AC22: ='[1]Reading.4.23'!AB22 -> 0 | AE22: =+X22+AB22 -> 34080 | AF22: ='[1]Reading.4.23'!AE22 -> 32920 | AG22: =989409/30 -> 32980.3 | AI22: 0.6426 | AJ22: ='[1]Reading.4.23'!AI22 -> 0.5057 | AK22: 0.638 | AM22: 338 | AN22: ='[1]Reading.4.23'!AM22 -> 266 | AO22: =10065/30 -> 335.5 | AQ22: =467*4 -> 1868 | AR22: ='[1]Reading.4.23'!AQ22 -> 1680 | AT22: 7152.46 | AU22: =(AT22-AT21)*4000 -> 3840 | AV22: =+X22/SQRT(((POWER((X22),2)+(POWER((AU22),2))))) -> 0.99371187 | AY22: ='[1]Reading.4.23'!X22 -> 32920 | AZ22: ='[1]Reading.4.23'!AB22 -> 0 | BA22: =AY22+AZ22 -> 32920 | BC22: 19 | BD22: 16.1 | BE22: 12 | BF22: 56 | BG22: 79 | BH22: ='[1]Reading.4.23'!BD22 -> 27.2 | BI22: ='[1]Reading.4.23'!BE22 -> 22 | BJ22: ='[1]Reading.4.23'!BF22 -> 73 | BL22: 526 | BN22: ='[1]Reading.4.23'!E20 -> 0 | BP22: 66809 | BQ22: =BP22-BP21 -> 29 | BR22: ='[1]Reading.4.23'!BQ22 -> 29 | BT22: 81720 | BU22: =BT22-BT21 -> 42 | BV22: ='[1]Reading.4.23'!BU22 -> 35 | BX22: 3991 | BY22: =BX22-BX21 -> 0 | BZ22: ='[1]Reading.4.23'!BY22 -> 0 | CB22: 233960 | CC22: =CB22-CB21 -> 20 | CD22: ='[1]Reading.4.23'!CC22 -> 63 | CF22: 6220 | CG22: =CF22-CF21 -> 10 | CH22: ='[1]Reading.4.23'!CG22 -> 0 | CI22: 19773 | CJ22: =CI22-CI21 -> 0 | CK22: ='[1]Reading.4.23'!CG22 -> 0 | CM22: =BQ22+BU22+BY22+CC22+CJ22 -> 91 | CN22: =BR22+BV22+BZ22+CD22+CK22 -> 127 | CP22: 107858 | CQ22: =CP22-CP21 -> 420 | CR22: =CQ22/G22 -> 0.74336283 | CS22: ='[1]Reading.4.23'!CN22 -> 128 | CT22: ='[1]Reading.4.23'!CO20 -> 0.45644599 | CV22: 5246 | CW22: =CV22-CV21 -> 2 | CX22: ='[1]Reading.4.23'!CT22 -> 2 | CZ22: 925 | DA22: =CZ22-CZ21 -> 2 | DB22: ='[1]Reading.4.23'!CX22 -> 3 | DD22: 1433713 | DE22: =DD22-DD21 -> 907 | DF22: ='[1]Reading.4.23'!DB22 -> 843 | DH22: 3343044 | DI22: =DH22-DH21 -> 1569 | DJ22: ='[1]Reading.4.23'!DF22 -> 1772 | DL22: 2918748 | DM22: =DL22-DL21 -> 30 | DN22: ='[1]Reading.4.23'!DJ22 -> 3642 | DP22: 2285431 | DQ22: =DP22-DP21 -> 31 | DR22: ='[1]Reading.4.23'!DN22 -> 159 | DT22: 3091939 | DU22: =DT22-DT21 -> 3894 | DV22: ='[1]Reading.4.23'!DR22 -> 30 | DX22: 720 | DZ22: =DM22+DQ22+DU22+DX22 -> 4675 | EA22: ='[1]Reading.4.23'!DW22 -> 4551 | EC22: =C22*5.2 -> 3276 | ED22: ='[1]Reading.4.23'!C22*5.2 -> 2953.6 | EF22: 60433 | EG22: =EF22-EF21 -> 73 | EJ22: 24165 | EK22: =EJ22-EJ21 -> 21
A23: 45400 | B23: 288027 | C23: =B23-B22 -> 541 | E23: 0 | F23: 775 | G23: =C23+D23-E23+F22-F23 -> 596 | H23: ='[1]Reading.4.23'!G23 -> 521 | J23: 207520 | K23: =(J23-J22)*4.668 -> 172.716 | L23: ='[1]Reading.4.23'!K23 -> 186.72 | N23: 732780 | O23: =(N23-N22)*4.61 -> 470.22 | P23: ='[1]Reading.4.23'!O23 -> 433.34 | R23: 42700 | T23: =(R22+S22)-R23 -> 0 | U23: ='[1]Reading.4.23'!T23 -> 0 | W23: 45798.63 | X23: =(W23-W22)*4000 -> 33960 | Y23: ='[1]Reading.4.23'!X23 -> 32880 | AA23: 520050 | AB23: =AA23-AA22 -> 0 | AC23: ='[1]Reading.4.23'!AB23 -> 0 | AE23: =+X23+AB23 -> 33960 | AF23: ='[1]Reading.4.23'!AE23 -> 32880 | AG23: =989409/30 -> 32980.3 | AI23: 0.6426 | AJ23: ='[1]Reading.4.23'!AI23 -> 0.5304 | AK23: 0.638 | AM23: 338 | AN23: ='[1]Reading.4.23'!AM23 -> 279 | AO23: =10065/30 -> 335.5 | AQ23: =467*4 -> 1868 | AR23: ='[1]Reading.4.23'!AQ23 -> 1788 | AT23: 7153.39 | AU23: =(AT23-AT22)*4000 -> 3720 | AV23: =+X23/SQRT(((POWER((X23),2)+(POWER((AU23),2))))) -> 0.99405388 | AY23: ='[1]Reading.4.23'!X23 -> 32880 | AZ23: ='[1]Reading.4.23'!AB23 -> 0 | BA23: =AY23+AZ23 -> 32880 | BC23: 19 | BD23: 16.1 | BE23: 12 | BF23: 56 | BG23: 79 | BH23: ='[1]Reading.4.23'!BD23 -> 29.5 | BI23: ='[1]Reading.4.23'!BE23 -> 20 | BJ23: ='[1]Reading.4.23'!BF23 -> 94 | BL23: 526 | BN23: ='[1]Reading.4.23'!E21 -> 0 | BP23: 66843 | BQ23: =BP23-BP22 -> 34 | BR23: ='[1]Reading.4.23'!BQ23 -> 34 | BT23: 81758 | BU23: =BT23-BT22 -> 38 | BV23: ='[1]Reading.4.23'!BU23 -> 32 | BX23: 4005 | BY23: =BX23-BX22 -> 14 | BZ23: ='[1]Reading.4.23'!BY23 -> 0 | CB23: 233980 | CC23: =CB23-CB22 -> 20 | CD23: ='[1]Reading.4.23'!CC23 -> 32 | CF23: 6225 | CG23: =CF23-CF22 -> 5 | CH23: ='[1]Reading.4.23'!CG23 -> 0 | CI23: 19773 | CJ23: =CI23-CI22 -> 0 | CK23: ='[1]Reading.4.23'!CG23 -> 0 | CM23: =BQ23+BU23+BY23+CC23+CJ23 -> 106 | CN23: =BR23+BV23+BZ23+CD23+CK23 -> 98 | CP23: 108278 | CQ23: =CP23-CP22 -> 420 | CR23: =CQ23/G23 -> 0.70469799 | CS23: ='[1]Reading.4.23'!CN23 -> 257 | CT23: ='[1]Reading.4.23'!CO21 -> 0.44936709 | CV23: 5248 | CW23: =CV23-CV22 -> 2 | CX23: ='[1]Reading.4.23'!CT23 -> 1 | CZ23: 929 | DA23: =CZ23-CZ22 -> 4 | DB23: ='[1]Reading.4.23'!CX23 -> 5 | DD23: 1434478 | DE23: =DD23-DD22 -> 765 | DF23: ='[1]Reading.4.23'!DB23 -> 858 | DH23: 3344871 | DI23: =DH23-DH22 -> 1827 | DJ23: ='[1]Reading.4.23'!DF23 -> 1957 | DL23: 2918782 | DM23: =DL23-DL22 -> 34 | DN23: ='[1]Reading.4.23'!DJ23 -> 3642 | DP23: 2285465 | DQ23: =DP23-DP22 -> 34 | DR23: ='[1]Reading.4.23'!DN23 -> 59 | DT23: 3096574 | DU23: =DT23-DT22 -> 4635 | DV23: ='[1]Reading.4.23'!DR23 -> 30 | DX23: 720 | DZ23: =DM23+DQ23+DU23+DX23 -> 5423 | EA23: ='[1]Reading.4.23'!DW23 -> 4451 | EC23: =C23*5.2 -> 2813.2 | ED23: ='[1]Reading.4.23'!C23*5.2 -> 2709.2 | EF23: 60494 | EG23: =EF23-EF22 -> 61 | EJ23: 24186 | EK23: =EJ23-EJ22 -> 21
A24: 45401 | B24: 288688 | C24: =B24-B23 -> 661 | E24: 0 | F24: 775 | G24: =C24+D24-E24+F23-F24 -> 661 | H24: ='[1]Reading.4.23'!G24 -> 493 | J24: 207556 | K24: =(J24-J23)*4.668 -> 168.048 | L24: ='[1]Reading.4.23'!K24 -> 210.06 | N24: 732888 | O24: =(N24-N23)*4.61 -> 497.88 | P24: ='[1]Reading.4.23'!O24 -> 396.46 | R24: 42700 | T24: =(R23+S23)-R24 -> 0 | U24: ='[1]Reading.4.23'!T24 -> 0 | W24: 45807.54 | X24: =(W24-W23)*4000 -> 35640 | Y24: ='[1]Reading.4.23'!X24 -> 34400 | AA24: 520050 | AB24: =AA24-AA23 -> 0 | AC24: ='[1]Reading.4.23'!AB24 -> 0 | AE24: =+X24+AB24 -> 35640 | AF24: ='[1]Reading.4.23'!AE24 -> 34400 | AG24: =989409/30 -> 32980.3 | AI24: 0.6388 | AJ24: ='[1]Reading.4.23'!AI24 -> 0.5608 | AK24: 1.638 | AM24: 336 | AN24: ='[1]Reading.4.23'!AM24 -> 295 | AO24: =10065/30 -> 335.5 | AQ24: =467*4 -> 1868 | AR24: ='[1]Reading.4.23'!AQ24 -> 1860 | AT24: 7154.49 | AU24: =(AT24-AT23)*4000 -> 4400 | AV24: =+X24/SQRT(((POWER((X24),2)+(POWER((AU24),2))))) -> 0.99246523 | AY24: ='[1]Reading.4.23'!X24 -> 34400 | AZ24: ='[1]Reading.4.23'!AB24 -> 0 | BA24: =AY24+AZ24 -> 34400 | BC24: 23 | BD24: 19 | BE24: 16 | BF24: 49 | BG24: 80 | BH24: ='[1]Reading.4.23'!BD24 -> 30.8 | BI24: ='[1]Reading.4.23'!BE24 -> 25 | BJ24: ='[1]Reading.4.23'!BF24 -> 42 | BL24: 526 | BN24: ='[1]Reading.4.23'!E22 -> 0 | BP24: 66879 | BQ24: =BP24-BP23 -> 36 | BR24: ='[1]Reading.4.23'!BQ24 -> 31 | BT24: 81799 | BU24: =BT24-BT23 -> 41 | BV24: ='[1]Reading.4.23'!BU24 -> 27 | BX24: 4005 | BY24: =BX24-BX23 -> 0 | BZ24: ='[1]Reading.4.23'!BY24 -> 0 | CB24: 234010 | CC24: =CB24-CB23 -> 30 | CD24: ='[1]Reading.4.23'!CC24 -> 36 | CF24: 6230 | CG24: =CF24-CF23 -> 5 | CH24: ='[1]Reading.4.23'!CG24 -> 0 | CI24: 19773 | CJ24: =CI24-CI23 -> 0 | CK24: ='[1]Reading.4.23'!CG24 -> 0 | CM24: =BQ24+BU24+BY24+CC24+CJ24 -> 107 | CN24: =BR24+BV24+BZ24+CD24+CK24 -> 94 | CP24: 108781 | CQ24: =CP24-CP23 -> 503 | CR24: =CQ24/G24 -> 0.76096823 | CS24: ='[1]Reading.4.23'!CN24 -> 200 | CT24: ='[1]Reading.4.23'!CO22 -> 0.24474187 | CV24: 5250 | CW24: =CV24-CV23 -> 2 | CX24: ='[1]Reading.4.23'!CT24 -> 1 | CZ24: 932 | DA24: =CZ24-CZ23 -> 3 | DB24: ='[1]Reading.4.23'!CX24 -> 3 | DD24: 1435268 | DE24: =DD24-DD23 -> 790 | DF24: ='[1]Reading.4.23'!DB24 -> 848 | DH24: 3346977 | DI24: =DH24-DH23 -> 2106 | DJ24: ='[1]Reading.4.23'!DF24 -> 1854 | DL24: 2918815 | DM24: =DL24-DL23 -> 33 | DN24: ='[1]Reading.4.23'!DJ24 -> 4481 | DP24: 2285498 | DQ24: =DP24-DP23 -> 33 | DR24: ='[1]Reading.4.23'!DN24 -> 55 | DT24: 3101124 | DU24: =DT24-DT23 -> 4550 | DV24: ='[1]Reading.4.23'!DR24 -> 32 | DX24: 720 | DZ24: =DM24+DQ24+DU24+DX24 -> 5336 | EA24: ='[1]Reading.4.23'!DW24 -> 5288 | EC24: =C24*5.2 -> 3437.2 | ED24: ='[1]Reading.4.23'!C24*5.2 -> 2641.6 | EF24: 60551 | EG24: =EF24-EF23 -> 57 | EJ24: 24211 | EK24: =EJ24-EJ23 -> 25
A25: 45402 | B25: 289194 | C25: =B25-B24 -> 506 | E25: 0 | F25: 775 | G25: =C25+D25-E25+F24-F25 -> 506 | H25: ='[1]Reading.4.23'!G25 -> 613 | J25: 207595 | K25: =(J25-J24)*4.668 -> 182.052 | L25: ='[1]Reading.4.23'!K25 -> 214.728 | N25: 732987 | O25: =(N25-N24)*4.61 -> 456.39 | P25: ='[1]Reading.4.23'!O25 -> 410.29 | R25: 42700 | T25: =(R24+S24)-R25 -> 0 | U25: ='[1]Reading.4.23'!T25 -> 0 | W25: 45816.2 | X25: =(W25-W24)*4000 -> 34640 | Y25: ='[1]Reading.4.23'!X25 -> 36680 | AA25: 520050 | AB25: =AA25-AA24 -> 0 | AC25: ='[1]Reading.4.23'!AB25 -> 0 | AE25: =+X25+AB25 -> 34640 | AF25: ='[1]Reading.4.23'!AE25 -> 36680 | AG25: =989409/30 -> 32980.3 | AI25: 0.6635 | AJ25: ='[1]Reading.4.23'!AI25 -> 0.6236 | AK25: 2.638 | AM25: 349 | AN25: ='[1]Reading.4.23'!AM25 -> 328 | AO25: =10065/30 -> 335.5 | AQ25: =467*4 -> 1868 | AR25: ='[1]Reading.4.23'!AQ25 -> 1928 | AT25: 7155.47 | AU25: =(AT25-AT24)*4000 -> 3920 | AV25: =+X25/SQRT(((POWER((X25),2)+(POWER((AU25),2))))) -> 0.99365781 | AY25: ='[1]Reading.4.23'!X25 -> 36680 | AZ25: ='[1]Reading.4.23'!AB25 -> 0 | BA25: =AY25+AZ25 -> 36680 | BC25: 24 | BD25: 20 | BE25: 17 | BF25: 84 | BG25: 81 | BH25: ='[1]Reading.4.23'!BD25 -> 28.1 | BI25: ='[1]Reading.4.23'!BE25 -> 24 | BJ25: ='[1]Reading.4.23'!BF25 -> 65 | BL25: 526 | BN25: ='[1]Reading.4.23'!E23 -> 0 | BP25: 66914 | BQ25: =BP25-BP24 -> 35 | BR25: ='[1]Reading.4.23'!BQ25 -> 38 | BT25: 81834 | BU25: =BT25-BT24 -> 35 | BV25: ='[1]Reading.4.23'!BU25 -> 33 | BX25: 4005 | BY25: =BX25-BX24 -> 0 | BZ25: ='[1]Reading.4.23'!BY25 -> 0 | CB25: 234050 | CC25: =CB25-CB24 -> 40 | CD25: ='[1]Reading.4.23'!CC25 -> 35 | CF25: 6235 | CG25: =CF25-CF24 -> 5 | CH25: ='[1]Reading.4.23'!CG25 -> 0 | CI25: 19773 | CJ25: =CI25-CI24 -> 0 | CK25: ='[1]Reading.4.23'!CG25 -> 0 | CM25: =BQ25+BU25+BY25+CC25+CJ25 -> 110 | CN25: =BR25+BV25+BZ25+CD25+CK25 -> 106 | CP25: 109231 | CQ25: =CP25-CP24 -> 450 | CR25: =CQ25/G25 -> 0.88932806 | CS25: ='[1]Reading.4.23'!CN25 -> 219 | CT25: ='[1]Reading.4.23'!CO23 -> 0.49328215 | CV25: 5253 | CW25: =CV25-CV24 -> 3 | CX25: ='[1]Reading.4.23'!CT25 -> 2 | CZ25: 935 | DA25: =CZ25-CZ24 -> 3 | DB25: ='[1]Reading.4.23'!CX25 -> 4 | DD25: 1436138 | DE25: =DD25-DD24 -> 870 | DF25: ='[1]Reading.4.23'!DB25 -> 827 | DH25: 3349115 | DI25: =DH25-DH24 -> 2138 | DJ25: ='[1]Reading.4.23'!DF25 -> 2115 | DL25: 2918847 | DM25: =DL25-DL24 -> 32 | DN25: ='[1]Reading.4.23'!DJ25 -> 2971 | DP25: 2285531 | DQ25: =DP25-DP24 -> 33 | DR25: ='[1]Reading.4.23'!DN25 -> 1514 | DT25: 3105493 | DU25: =DT25-DT24 -> 4369 | DV25: ='[1]Reading.4.23'!DR25 -> 34 | DX25: 720 | DZ25: =DM25+DQ25+DU25+DX25 -> 5154 | EA25: ='[1]Reading.4.23'!DW25 -> 5239 | EC25: =C25*5.2 -> 2631.2 | ED25: ='[1]Reading.4.23'!C25*5.2 -> 2875.6 | EF25: 60611 | EG25: =EF25-EF24 -> 60 | EJ25: 24236 | EK25: =EJ25-EJ24 -> 25
A26: 45403 | B26: 289707 | C26: =B26-B25 -> 513 | E26: 0 | F26: 775 | G26: =C26+D26-E26+F25-F26 -> 513 | H26: ='[1]Reading.4.23'!G26 -> 629 | J26: 207636 | K26: =(J26-J25)*4.668 -> 191.388 | L26: ='[1]Reading.4.23'!K26 -> 210.06 | N26: 733089 | O26: =(N26-N25)*4.61 -> 470.22 | P26: ='[1]Reading.4.23'!O26 -> 543.98 | R26: 42700 | T26: =(R25+S25)-R26 -> 0 | U26: ='[1]Reading.4.23'!T26 -> 0 | W26: 45824.51 | X26: =(W26-W25)*4000 -> 33240 | Y26: ='[1]Reading.4.23'!X26 -> 35360 | AA26: 520050 | AB26: =AA26-AA25 -> 0 | AC26: ='[1]Reading.4.23'!AB26 -> 0 | AE26: =+X26+AB26 -> 33240 | AF26: ='[1]Reading.4.23'!AE26 -> 35360 | AG26: =989409/30 -> 32980.3 | AI26: 0.7091 | AJ26: ='[1]Reading.4.23'!AI26 -> 0.7148 | AK26: 3.638 | AM26: 373 | AN26: ='[1]Reading.4.23'!AM26 -> 376 | AO26: =10065/30 -> 335.5 | AQ26: =467*4 -> 1868 | AR26: ='[1]Reading.4.23'!AQ26 -> 1928 | AT26: 7156.34 | AU26: =(AT26-AT25)*4000 -> 3480 | AV26: =+X26/SQRT(((POWER((X26),2)+(POWER((AU26),2))))) -> 0.99456432 | AY26: ='[1]Reading.4.23'!X26 -> 35360 | AZ26: ='[1]Reading.4.23'!AB26 -> 0 | BA26: =AY26+AZ26 -> 35360 | BC26: 23 | BD26: 21 | BE26: 18 | BF26: 64 | BG26: 82 | BH26: ='[1]Reading.4.23'!BD26 -> 24.6 | BI26: ='[1]Reading.4.23'!BE26 -> 20 | BJ26: ='[1]Reading.4.23'!BF26 -> 65 | BL26: 526 | BN26: ='[1]Reading.4.23'!E24 -> 0 | BP26: 66947 | BQ26: =BP26-BP25 -> 33 | BR26: ='[1]Reading.4.23'!BQ26 -> 30 | BT26: 81872 | BU26: =BT26-BT25 -> 38 | BV26: ='[1]Reading.4.23'!BU26 -> 42 | BX26: 4005 | BY26: =BX26-BX25 -> 0 | BZ26: ='[1]Reading.4.23'!BY26 -> 0 | CB26: 234070 | CC26: =CB26-CB25 -> 20 | CD26: ='[1]Reading.4.23'!CC26 -> 58 | CF26: 6240 | CG26: =CF26-CF25 -> 5 | CH26: ='[1]Reading.4.23'!CG26 -> 0 | CI26: 19770 | CJ26: =CI26-CI25 -> -3 | CK26: ='[1]Reading.4.23'!CG26 -> 0 | CM26: =BQ26+BU26+BY26+CC26+CJ26 -> 88 | CN26: =BR26+BV26+BZ26+CD26+CK26 -> 130 | CP26: 109550 | CQ26: =CP26-CP25 -> 319 | CR26: =CQ26/G26 -> 0.62183236 | CS26: ='[1]Reading.4.23'!CN26 -> 282 | CT26: ='[1]Reading.4.23'!CO24 -> 0.40567951 | CV26: 5255 | CW26: =CV26-CV25 -> 2 | CX26: ='[1]Reading.4.23'!CT26 -> 1 | CZ26: 939 | DA26: =CZ26-CZ25 -> 4 | DB26: ='[1]Reading.4.23'!CX26 -> 4 | DD26: 1436983 | DE26: =DD26-DD25 -> 845 | DF26: ='[1]Reading.4.23'!DB26 -> 1001 | DH26: 3350934 | DI26: =DH26-DH25 -> 1819 | DJ26: ='[1]Reading.4.23'!DF26 -> 1831 | DL26: 2918880 | DM26: =DL26-DL25 -> 33 | DN26: ='[1]Reading.4.23'!DJ26 -> 1865 | DP26: 2285565 | DQ26: =DP26-DP25 -> 34 | DR26: ='[1]Reading.4.23'!DN26 -> 1589 | DT26: 3110115 | DU26: =DT26-DT25 -> 4622 | DV26: ='[1]Reading.4.23'!DR26 -> 29 | DX26: 720 | DZ26: =DM26+DQ26+DU26+DX26 -> 5409 | EA26: ='[1]Reading.4.23'!DW26 -> 4203 | EC26: =C26*5.2 -> 2667.6 | ED26: ='[1]Reading.4.23'!C26*5.2 -> 3556.8 | EF26: 60676 | EG26: =EF26-EF25 -> 65 | EJ26: 24261 | EK26: =EJ26-EJ25 -> 25
A27: 45404 | B27: 290338 | C27: =B27-B26 -> 631 | E27: 0 | F27: 865 | G27: =C27+D27-E27+F26-F27 -> 541 | H27: ='[1]Reading.4.23'!G27 -> 609 | J27: 207675 | K27: =(J27-J26)*4.668 -> 182.052 | L27: ='[1]Reading.4.23'!K27 -> 242.736 | N27: 733196 | O27: =(N27-N26)*4.61 -> 493.27 | P27: ='[1]Reading.4.23'!O27 -> 571.64 | R27: 42700 | T27: =(R26+S26)-R27 -> 0 | U27: ='[1]Reading.4.23'!T27 -> 0 | W27: 45833.68 | X27: =(W27-W26)*4000 -> 36680 | Y27: ='[1]Reading.4.23'!X27 -> 38760 | AA27: 520050 | AB27: =AA27-AA26 -> 0 | AC27: ='[1]Reading.4.23'!AB27 -> 0 | AE27: =+X27+AB27 -> 36680 | AF27: ='[1]Reading.4.23'!AE27 -> 38760 | AG27: =989409/30 -> 32980.3 | AI27: 0.73 | AJ27: ='[1]Reading.4.23'!AI27 -> 0.8099 | AK27: 3.638 | AM27: 384 | AN27: ='[1]Reading.4.23'!AM27 -> 426 | AO27: =10065/30 -> 335.5 | AQ27: =467*4 -> 1868 | AR27: ='[1]Reading.4.23'!AQ27 -> 1968 | AT27: 7157.46 | AU27: =(AT27-AT26)*4000 -> 4480 | AV27: =+X27/SQRT(((POWER((X27),2)+(POWER((AU27),2))))) -> 0.99262365 | AY27: ='[1]Reading.4.23'!X27 -> 38760 | AZ27: ='[1]Reading.4.23'!AB27 -> 0 | BA27: =AY27+AZ27 -> 38760 | BC27: 23 | BD27: 21 | BE27: 18 | BF27: 64 | BG27: 82 | BH27: ='[1]Reading.4.23'!BD27 -> 25.3 | BI27: ='[1]Reading.4.23'!BE27 -> 21 | BJ27: ='[1]Reading.4.23'!BF27 -> 64 | BL27: 526 | BN27: ='[1]Reading.4.23'!E25 -> 0 | BP27: 66982 | BQ27: =BP27-BP26 -> 35 | BR27: ='[1]Reading.4.23'!BQ27 -> 35 | BT27: 81913 | BU27: =BT27-BT26 -> 41 | BV27: ='[1]Reading.4.23'!BU27 -> 43 | BX27: 4005 | BY27: =BX27-BX26 -> 0 | BZ27: ='[1]Reading.4.23'!BY27 -> 0 | CB27: 234100 | CC27: =CB27-CB26 -> 30 | CD27: ='[1]Reading.4.23'!CC27 -> 60 | CF27: 6250 | CG27: =CF27-CF26 -> 10 | CH27: ='[1]Reading.4.23'!CG27 -> 0 | CI27: 19770 | CJ27: =CI27-CI26 -> 0 | CK27: ='[1]Reading.4.23'!CG27 -> 0 | CM27: =BQ27+BU27+BY27+CC27+CJ27 -> 106 | CN27: =BR27+BV27+BZ27+CD27+CK27 -> 138 | CP27: 109920 | CQ27: =CP27-CP26 -> 370 | CR27: =CQ27/G27 -> 0.68391867 | CS27: ='[1]Reading.4.23'!CN27 -> 281 | CT27: ='[1]Reading.4.23'!CO25 -> 0.35725938 | CV27: 5257 | CW27: =CV27-CV26 -> 2 | CX27: ='[1]Reading.4.23'!CT27 -> 1 | CZ27: 942 | DA27: =CZ27-CZ26 -> 3 | DB27: ='[1]Reading.4.23'!CX27 -> 4 | DD27: 1437848 | DE27: =DD27-DD26 -> 865 | DF27: ='[1]Reading.4.23'!DB27 -> 1095 | DH27: 3353210 | DI27: =DH27-DH26 -> 2276 | DJ27: ='[1]Reading.4.23'!DF27 -> 2114 | DL27: 2918912 | DM27: =DL27-DL26 -> 32 | DN27: ='[1]Reading.4.23'!DJ27 -> 2151 | DP27: 2285598 | DQ27: =DP27-DP26 -> 33 | DR27: ='[1]Reading.4.23'!DN27 -> 793 | DT27: 3114681 | DU27: =DT27-DT26 -> 4566 | DV27: ='[1]Reading.4.23'!DR27 -> 32 | DX27: 720 | DZ27: =DM27+DQ27+DU27+DX27 -> 5351 | EA27: ='[1]Reading.4.23'!DW27 -> 3696 | EC27: =C27*5.2 -> 3281.2 | ED27: ='[1]Reading.4.23'!C27*5.2 -> 2646.8 | EF27: 60737 | EG27: =EF27-EF26 -> 61 | EJ27: 24286 | EK27: =EJ27-EJ26 -> 25
A28: 45405 | B28: 290862 | C28: =B28-B27 -> 524 | E28: 0 | F28: 840 | G28: =C28+D28-E28+F27-F28 -> 549 | H28: ='[1]Reading.4.23'!G28 -> 635 | J28: 207709 | K28: =(J28-J27)*4.668 -> 158.712 | L28: ='[1]Reading.4.23'!K28 -> 270.744 | N28: 733282 | O28: =(N28-N27)*4.61 -> 396.46 | P28: ='[1]Reading.4.23'!O28 -> 557.81 | R28: 42700 | T28: =(R27+S27)-R28 -> 0 | U28: ='[1]Reading.4.23'!T28 -> 0 | W28: 45842.4 | X28: =(W28-W27)*4000 -> 34880 | Y28: ='[1]Reading.4.23'!X28 -> 36440 | AA28: 520050 | AB28: =AA28-AA27 -> 0 | AC28: ='[1]Reading.4.23'!AB28 -> 0 | AE28: =+X28+AB28 -> 34880 | AF28: ='[1]Reading.4.23'!AE28 -> 36440 | AG28: =989409/30 -> 32980.3 | AI28: 0.652 | AJ28: ='[1]Reading.4.23'!AI28 -> 0.8498 | AK28: 3.638 | AM28: 342 | AN28: ='[1]Reading.4.23'!AM28 -> 447 | AO28: =10065/30 -> 335.5 | AQ28: =467*4 -> 1868 | AR28: ='[1]Reading.4.23'!AQ28 -> 2008 | AT28: 7158.4 | AU28: =(AT28-AT27)*4000 -> 3760 | AV28: =+X28/SQRT(((POWER((X28),2)+(POWER((AU28),2))))) -> 0.99423993 | AY28: ='[1]Reading.4.23'!X28 -> 36440 | AZ28: ='[1]Reading.4.23'!AB28 -> 0 | BA28: =AY28+AZ28 -> 36440 | BC28: 23 | BD28: 21 | BE28: 18 | BF28: 64 | BG28: 82 | BH28: ='[1]Reading.4.23'!BD28 -> 25.3 | BI28: ='[1]Reading.4.23'!BE28 -> 21 | BJ28: ='[1]Reading.4.23'!BF28 -> 64 | BL28: 526 | BN28: ='[1]Reading.4.23'!E26 -> 0 | BP28: 67017 | BQ28: =BP28-BP27 -> 35 | BR28: ='[1]Reading.4.23'!BQ28 -> 38 | BT28: 81941 | BU28: =BT28-BT27 -> 28 | BV28: ='[1]Reading.4.23'!BU28 -> 40 | BX28: 4005 | BY28: =BX28-BX27 -> 0 | BZ28: ='[1]Reading.4.23'!BY28 -> 0 | CB28: 234130 | CC28: =CB28-CB27 -> 30 | CD28: ='[1]Reading.4.23'!CC28 -> 44 | CF28: 6260 | CG28: =CF28-CF27 -> 10 | CH28: ='[1]Reading.4.23'!CG28 -> 0 | CI28: 19770 | CJ28: =CI28-CI27 -> 0 | CK28: ='[1]Reading.4.23'!CG28 -> 0 | CM28: =BQ28+BU28+BY29+CC28+CJ29 -> 93 | CN28: =BR28+BV28+BZ29+CD28+CK29 -> 122 | CP28: 110270 | CQ28: =CP28-CP27 -> 350 | CR28: =CQ28/G28 -> 0.63752277 | CS28: ='[1]Reading.4.23'!CN28 -> 246 | CT28: ='[1]Reading.4.23'!CO26 -> 0.44833068 | CV28: 5260 | CW28: =CV28-CV27 -> 3 | CX28: ='[1]Reading.4.23'!CT28 -> 2 | CZ28: 946 | DA28: =CZ28-CZ27 -> 4 | DB28: ='[1]Reading.4.23'!CX28 -> 6 | DD28: 1438603 | DE28: =DD28-DD27 -> 755 | DF28: ='[1]Reading.4.23'!DB28 -> 1044 | DH28: 3355165 | DI28: =DH28-DH27 -> 1955 | DJ28: ='[1]Reading.4.23'!DF28 -> 2246 | DL28: 2918942 | DM28: =DL28-DL27 -> 30 | DN28: ='[1]Reading.4.23'!DJ28 -> 2151 | DP28: 2286259 | DQ28: =DP28-DP27 -> 661 | DR28: ='[1]Reading.4.23'!DN28 -> 500 | DT28: 3118457 | DU28: =DT28-DT27 -> 3776 | DV28: ='[1]Reading.4.23'!DR28 -> 32 | DX28: 720 | DZ28: =DM28+DQ28+DU28+DX28 -> 5187 | EA28: ='[1]Reading.4.23'!DW28 -> 3403 | EC28: =C28*5.2 -> 2724.8 | ED28: ='[1]Reading.4.23'!C28*5.2 -> 3536 | EF28: 60785 | EG28: =EF28-EF27 -> 48 | EJ28: 24311 | EK28: =EJ28-EJ27 -> 25
A29: 45406 | B29: 291297 | C29: =B29-B28 -> 435 | E29: 0 | F29: 840 | G29: =C29+D29-E29+F28-F29 -> 435 | H29: ='[1]Reading.4.23'!G29 -> 618 | J29: 207752 | K29: =(J29-J28)*4.668 -> 200.724 | L29: ='[1]Reading.4.23'!K29 -> 219.396 | N29: 733379 | O29: =(N29-N28)*4.61 -> 447.17 | P29: ='[1]Reading.4.23'!O29 -> 594.69 | R29: 42700 | T29: =(R28+S28)-R29 -> 0 | U29: ='[1]Reading.4.23'!T29 -> 0 | W29: 45851.31 | X29: =(W29-W28)*4000 -> 35640 | Y29: ='[1]Reading.4.23'!X29 -> 42120 | AA29: 520050 | AB29: =AA29-AA28 -> 0 | AC29: ='[1]Reading.4.23'!AB29 -> 0 | AE29: =+X29+AB29 -> 35640 | AF29: ='[1]Reading.4.23'!AE29 -> 42120 | AG29: =989409/30 -> 32980.3 | AI29: 0.6483 | AJ29: ='[1]Reading.4.23'!AI29 -> 0.8308 | AK29: 4.638 | AM29: 341 | AN29: ='[1]Reading.4.23'!AM29 -> 437 | AO29: =10065/30 -> 335.5 | AQ29: =467*4 -> 1868 | AR29: ='[1]Reading.4.23'!AQ29 -> 2044 | AT29: 7159.42 | AU29: =(AT29-AT28)*4000 -> 4080 | AV29: =+X29/SQRT(((POWER((X29),2)+(POWER((AU29),2))))) -> 0.99351109 | AY29: ='[1]Reading.4.23'!X29 -> 42120 | AZ29: ='[1]Reading.4.23'!AB29 -> 0 | BA29: =AY29+AZ29 -> 42120 | BC29: 24 | BD29: 21 | BE29: 18 | BF29: 56 | BG29: 83 | BH29: ='[1]Reading.4.23'!BD29 -> 27.6 | BI29: ='[1]Reading.4.23'!BE29 -> 24 | BJ29: ='[1]Reading.4.23'!BF29 -> 53 | BL29: 526 | BN29: ='[1]Reading.4.23'!E27 -> 0 | BP29: 67054 | BQ29: =BP29-BP28 -> 37 | BR29: ='[1]Reading.4.23'!BQ29 -> 34 | BT29: 81981 | BU29: =BT29-BT28 -> 40 | BV29: ='[1]Reading.4.23'!BU29 -> 51 | BX29: 4005 | BY29: =BX28-BX27 -> 0 | BZ29: ='[1]Reading.4.23'!BY28 -> 0 | CB29: 234160 | CC29: =CB29-CB28 -> 30 | CD29: ='[1]Reading.4.23'!CC29 -> 32 | CF29: 6265 | CG29: =CF29-CF28 -> 5 | CH29: ='[1]Reading.4.23'!CG29 -> 0 | CI29: 19770 | CJ29: =CI28-CI27 -> 0 | CK29: ='[1]Reading.4.23'!CG28 -> 0 | CM29: =BQ29+BU29+BY30+CC29+CJ30 -> 107 | CN29: =BR29+BV29+BZ30+CD29+CK30 -> 117 | CP29: 110670 | CQ29: =CP29-CP28 -> 400 | CR29: =CQ29/G29 -> 0.91954023 | CS29: ='[1]Reading.4.23'!CN29 -> 251 | CT29: ='[1]Reading.4.23'!CO27 -> 0.46141215 | CV29: 5262 | CW29: =CV29-CV28 -> 2 | CX29: ='[1]Reading.4.23'!CT29 -> 1 | CZ29: 947 | DA29: =CZ29-CZ28 -> 1 | DB29: ='[1]Reading.4.23'!CX29 -> 6 | DD29: 1439413 | DE29: =DD29-DD28 -> 810 | DF29: ='[1]Reading.4.23'!DB29 -> 1133 | DH29: 3357066 | DI29: =DH29-DH28 -> 1901 | DJ29: ='[1]Reading.4.23'!DF29 -> 2028 | DL29: 2918975 | DM29: =DL29-DL28 -> 33 | DN29: ='[1]Reading.4.23'!DJ29 -> 2892 | DP29: 2288359 | DQ29: =DP29-DP28 -> 2100 | DR29: ='[1]Reading.4.23'!DN29 -> 4255 | DT29: 3121374 | DU29: =DT29-DT28 -> 2917 | DV29: ='[1]Reading.4.23'!DR29 -> 31 | DX29: 720 | DZ29: =DM29+DQ29+DU29+DX29 -> 5770 | EA29: ='[1]Reading.4.23'!DW29 -> 7898 | EC29: =C29*5.2 -> 2262 | ED29: ='[1]Reading.4.23'!C29*5.2 -> 3525.6 | EF29: 60843 | EG29: =EF29-EF28 -> 58 | EJ29: 24334 | EK29: =EJ29-EJ28 -> 23
A30: 45407 | B30: 291927 | C30: =B30-B29 -> 630 | E30: 0 | F30: 615 | G30: =C30+D30-E30+F29-F30 -> 855 | H30: ='[1]Reading.4.23'!G30 -> 694 | J30: 207784 | K30: =(J30-J29)*4.668 -> 149.376 | L30: ='[1]Reading.4.23'!K30 -> 219.396 | N30: 733489 | O30: =(N30-N29)*4.61 -> 507.1 | P30: ='[1]Reading.4.23'!O30 -> 571.64 | R30: 42700 | T30: =(R29+S29)-R30 -> 0 | U30: ='[1]Reading.4.23'!T30 -> 0 | W30: 45860.28 | X30: =(W30-W29)*4000 -> 35880 | Y30: ='[1]Reading.4.23'!X30 -> 37840 | AA30: 520050 | AB30: =AA30-AA29 -> 0 | AC30: ='[1]Reading.4.23'!AB30 -> 0 | AE30: =+X30+AB30 -> 35880 | AF30: ='[1]Reading.4.23'!AE30 -> 37840 | AG30: =989409/30 -> 32980.3 | AI30: 0.73 | AJ30: ='[1]Reading.4.23'!AI30 -> 0.808 | AK30: 4.638 | AM30: 384 | AN30: ='[1]Reading.4.23'!AM30 -> 425 | AO30: =10065/30 -> 335.5 | AQ30: =500*4 -> 2000 | AR30: ='[1]Reading.4.23'!AQ30 -> 2044 | AT30: 7160.42 | AU30: =(AT30-AT29)*4000 -> 4000 | AV30: =+X30/SQRT(((POWER((X30),2)+(POWER((AU30),2))))) -> 0.99384313 | AY30: ='[1]Reading.4.23'!X30 -> 37840 | AZ30: ='[1]Reading.4.23'!AB30 -> 0 | BA30: =AY30+AZ30 -> 37840 | BC30: 24 | BD30: 21 | BE30: 18 | BF30: 56 | BG30: 83 | BH30: ='[1]Reading.4.23'!BD30 -> 26.6 | BI30: ='[1]Reading.4.23'!BE30 -> 22 | BJ30: ='[1]Reading.4.23'!BF30 -> 53 | BL30: 526 | BN30: ='[1]Reading.4.23'!E28 -> 0 | BP30: 67085 | BQ30: =BP30-BP29 -> 31 | BR30: ='[1]Reading.4.23'!BQ30 -> 38 | BT30: 82028 | BU30: =BT30-BT29 -> 47 | BV30: ='[1]Reading.4.23'!BU30 -> 52 | BX30: 4005 | BY30: =BX29-BX28 -> 0 | BZ30: ='[1]Reading.4.23'!BY29 -> 0 | CB30: 234370 | CC30: =CB30-CB29 -> 210 | CD30: ='[1]Reading.4.23'!CC30 -> 75 | CF30: 6270 | CG30: =CF30-CF29 -> 5 | CH30: ='[1]Reading.4.23'!CG30 -> 0 | CI30: 19770 | CJ30: =CI29-CI28 -> 0 | CK30: ='[1]Reading.4.23'!CG29 -> 0 | CM30: =BQ30+BU30+BY31+CC30+CJ31 -> 288 | CN30: =BR30+BV30+BZ31+CD30+CK31 -> 165 | CP30: 111090 | CQ30: =CP30-CP29 -> 420 | CR30: =CQ30/G30 -> 0.49122807 | CS30: ='[1]Reading.4.23'!CN30 -> 269 | CT30: ='[1]Reading.4.23'!CO28 -> 0.38740157 | CV30: 5264 | CW30: =CV30-CV29 -> 2 | CX30: ='[1]Reading.4.23'!CT30 -> 2 | CZ30: 949 | DA30: =CZ30-CZ29 -> 2 | DB30: ='[1]Reading.4.23'!CX30 -> 5 | DD30: 1440364 | DE30: =DD30-DD29 -> 951 | DF30: ='[1]Reading.4.23'!DB30 -> 1116 | DH30: 3359083 | DI30: =DH30-DH29 -> 2017 | DJ30: ='[1]Reading.4.23'!DF30 -> 2251 | DL30: 2919008 | DM30: =DL30-DL29 -> 33 | DN30: ='[1]Reading.4.23'!DJ30 -> 2320 | DP30: 2290476 | DQ30: =DP30-DP29 -> 2117 | DR30: ='[1]Reading.4.23'!DN30 -> 1836 | DT30: 3124326 | DU30: =DT30-DT29 -> 2952 | DV30: ='[1]Reading.4.23'!DR30 -> 32 | DX30: 720 | DZ30: =DM30+DQ30+DU30+DX30 -> 5822 | EA30: ='[1]Reading.4.23'!DW30 -> 4908 | EC30: =C30*5.2 -> 3276 | ED30: ='[1]Reading.4.23'!C30*5.2 -> 2724.8 | EF30: 60898 | EG30: =EF30-EF29 -> 55 | EJ30: 24355 | EK30: =EJ30-EJ29 -> 21
A31: 45408 | B31: 292610 | C31: =B31-B30 -> 683 | E31: 0 | F31: 685 | G31: =C31+D31-E31+F30-F31 -> 613 | H31: ='[1]Reading.4.23'!G31 -> 601 | J31: 207824 | K31: =(J31-J30)*4.668 -> 186.72 | L31: ='[1]Reading.4.23'!K31 -> 233.4 | N31: 733570 | O31: =(N31-N30)*4.61 -> 373.41 | P31: ='[1]Reading.4.23'!O31 -> 567.03 | R31: 42700 | T31: =(R30+S30)-R31 -> 0 | U31: ='[1]Reading.4.23'!T31 -> 0 | W31: 45870.25 | X31: =(W31-W30)*4000 -> 39880 | Y31: ='[1]Reading.4.23'!X31 -> 39320 | AA31: 520050 | AB31: =AA31-AA30 -> 0 | AC31: ='[1]Reading.4.23'!AB31 -> 0 | AE31: =+X31+AB31 -> 39880 | AF31: ='[1]Reading.4.23'!AE31 -> 39320 | AG31: =989409/30 -> 32980.3 | AI31: 0.7129 | AJ31: ='[1]Reading.4.23'!AI31 -> 0.7338 | AK31: 4.638 | AM31: 375 | AN31: ='[1]Reading.4.23'!AM31 -> 386 | AO31: =10065/30 -> 335.5 | AQ31: =517*4 -> 2068 | AR31: ='[1]Reading.4.23'!AQ31 -> 2044 | AT31: 7161.68 | AU31: =(AT31-AT30)*4000 -> 5040 | AV31: =+X31/SQRT(((POWER((X31),2)+(POWER((AU31),2))))) -> 0.99210856 | AY31: ='[1]Reading.4.23'!X31 -> 39320 | AZ31: ='[1]Reading.4.23'!AB31 -> 0 | BA31: =AY31+AZ31 -> 39320 | BC31: 24 | BD31: 21 | BE31: 18 | BF31: 56 | BG31: 83 | BH31: ='[1]Reading.4.23'!BD31 -> 27.5 | BI31: ='[1]Reading.4.23'!BE31 -> 23 | BJ31: ='[1]Reading.4.23'!BF31 -> 41 | BL31: 526 | BN31: ='[1]Reading.4.23'!E29 -> 0 | BP31: 67116 | BQ31: =BP31-BP30 -> 31 | BR31: ='[1]Reading.4.23'!BQ31 -> 41 | BT31: 82057 | BU31: =BT31-BT30 -> 29 | BV31: ='[1]Reading.4.23'!BU31 -> 43 | BX31: 4005 | BY31: =BX30-BX29 -> 0 | BZ31: ='[1]Reading.4.23'!BY30 -> 0 | CB31: 234450 | CC31: =CB31-CB30 -> 80 | CD31: ='[1]Reading.4.23'!CC31 -> 65 | CF31: 6280 | CG31: =CF31-CF30 -> 10 | CH31: ='[1]Reading.4.23'!CG31 -> 0 | CI31: 19770 | CJ31: =CI30-CI29 -> 0 | CK31: ='[1]Reading.4.23'!CG30 -> 0 | CM31: =BQ31+BU31+BY32+CC31+CJ32 -> 140 | CN31: =BR31+BV31+BZ32+CD31+CK32 -> 149 | CP31: 111540 | CQ31: =CP31-CP30 -> 450 | CR31: =CQ31/G31 -> 0.73409462 | CS31: ='[1]Reading.4.23'!CN31 -> 232 | CT31: ='[1]Reading.4.23'!CO29 -> 0.40614887 | CV31: 5267 | CW31: =CV31-CV30 -> 3 | CX31: ='[1]Reading.4.23'!CT31 -> 2 | CZ31: 952 | DA31: =CZ31-CZ30 -> 3 | DB31: ='[1]Reading.4.23'!CX31 -> 4 | DD31: 1441245 | DE31: =DD31-DD30 -> 881 | DF31: ='[1]Reading.4.23'!DB31 -> 1074 | DH31: 3360926 | DI31: =DH31-DH30 -> 1843 | DJ31: ='[1]Reading.4.23'!DF31 -> 2207 | DL31: 2919037 | DM31: =DL31-DL30 -> 29 | DN31: ='[1]Reading.4.23'!DJ31 -> 2203 | DP31: 2292287 | DQ31: =DP31-DP30 -> 1811 | DR31: ='[1]Reading.4.23'!DN31 -> 1757 | DT31: 3126974 | DU31: =DT31-DT30 -> 2648 | DV31: ='[1]Reading.4.23'!DR31 -> 29 | DX31: 720 | DZ31: =DM31+DQ31+DU31+DX31 -> 5208 | EA31: ='[1]Reading.4.23'!DW31 -> 4709 | EC31: =C31*5.2 -> 3551.6 | ED31: ='[1]Reading.4.23'!C31*5.2 -> 3515.2 | EF31: 60947 | EG31: =EF31-EF30 -> 49 | EJ31: 24380 | EK31: =EJ31-EJ30 -> 25
A32: 45409 | B32: 293321 | C32: =B32-B31 -> 711 | E32: 0 | F32: 685 | G32: =C32+D32-E32+F31-F32 -> 711 | H32: ='[1]Reading.4.23'!G32 -> 591 | J32: 207863 | K32: =(J32-J31)*4.668 -> 182.052 | L32: ='[1]Reading.4.23'!K32 -> 186.72 | N32: 733680 | O32: =(N32-N31)*4.61 -> 507.1 | P32: ='[1]Reading.4.23'!O32 -> 525.54 | R32: 42700 | T32: =(R31+S31)-R32 -> 0 | U32: ='[1]Reading.4.23'!T32 -> 0 | W32: 45879.96 | X32: =(W32-W31)*4000 -> 38840 | Y32: ='[1]Reading.4.23'!X32 -> 36240 | AA32: 520050 | AB32: =AA32-AA31 -> 0 | AC32: ='[1]Reading.4.23'!AB32 -> 0 | AE32: =+X32+AB32 -> 38840 | AF32: ='[1]Reading.4.23'!AE32 -> 36240 | AG32: =989409/30 -> 32980.3 | AI32: 0.7414 | AJ32: ='[1]Reading.4.23'!AI32 -> 0.7072 | AK32: 5.638 | AM32: 390 | AN32: ='[1]Reading.4.23'!AM32 -> 372 | AO32: =10065/30 -> 335.5 | AQ32: =517*4 -> 2068 | AR32: ='[1]Reading.4.23'!AQ32 -> 2044 | AT32: 7162.87 | AU32: =(AT32-AT31)*4000 -> 4760 | AV32: =+X32/SQRT(((POWER((X32),2)+(POWER((AU32),2))))) -> 0.9925738 | AY32: ='[1]Reading.4.23'!X32 -> 36240 | AZ32: ='[1]Reading.4.23'!AB32 -> 0 | BA32: =AY32+AZ32 -> 36240 | BC32: 25 | BD32: 20 | BE32: 16 | BF32: 52 | BG32: 84 | BH32: ='[1]Reading.4.23'!BD32 -> 28.1 | BI32: ='[1]Reading.4.23'!BE32 -> 23 | BJ32: ='[1]Reading.4.23'!BF32 -> 47 | BL32: 526 | BN32: ='[1]Reading.4.23'!E30 -> 0 | BP32: 67152 | BQ32: =BP32-BP31 -> 36 | BR32: ='[1]Reading.4.23'!BQ32 -> 35 | BT32: 82099 | BU32: =BT32-BT31 -> 42 | BV32: ='[1]Reading.4.23'!BU32 -> 41 | BX32: 4005 | BY32: =BX31-BX30 -> 0 | BZ32: ='[1]Reading.4.23'!BY31 -> 0 | CB32: 234490 | CC32: =CB32-CB31 -> 40 | CD32: ='[1]Reading.4.23'!CC32 -> 61 | CF32: 6285 | CG32: =CF32-CF31 -> 5 | CH32: ='[1]Reading.4.23'!CG32 -> 0 | CI32: 19770 | CJ32: =CI31-CI30 -> 0 | CK32: ='[1]Reading.4.23'!CG31 -> 0 | CM32: =BQ32+BU32+BY33+CC32+CJ33 -> 118 | CN32: =BR32+BV32+BZ33+CD32+CK33 -> 137 | CP32: 112040 | CQ32: =CP32-CP31 -> 500 | CR32: =CQ32/G32 -> 0.70323488 | CS32: ='[1]Reading.4.23'!CN32 -> 250 | CT32: ='[1]Reading.4.23'!CO30 -> 0.38760807 | CV32: 5269 | CW32: =CV32-CV31 -> 2 | CX32: ='[1]Reading.4.23'!CT32 -> 3 | CZ32: 956 | DA32: =CZ32-CZ31 -> 4 | DB32: ='[1]Reading.4.23'!CX32 -> 5 | DD32: 1442215 | DE32: =DD32-DD31 -> 970 | DF32: ='[1]Reading.4.23'!DB32 -> 1037 | DH32: 3362859 | DI32: =DH32-DH31 -> 1933 | DJ32: ='[1]Reading.4.23'!DF32 -> 1732 | DL32: 2919070 | DM32: =DL32-DL31 -> 33 | DN32: ='[1]Reading.4.23'!DJ32 -> 2516 | DP32: 2293711 | DQ32: =DP32-DP31 -> 1424 | DR32: ='[1]Reading.4.23'!DN32 -> 1942 | DT32: 3130278 | DU32: =DT32-DT31 -> 3304 | DV32: ='[1]Reading.4.23'!DR32 -> 33 | DX32: 720 | DZ32: =DM32+DQ32+DU32+DX32 -> 5481 | EA32: ='[1]Reading.4.23'!DW32 -> 5211 | EC32: =C32*5.2 -> 3697.2 | ED32: ='[1]Reading.4.23'!C32*5.2 -> 3073.2 | EF32: 61005 | EG32: =EF32-EF31 -> 58 | EJ32: 24403 | EK32: =EJ32-EJ31 -> 23
A33: 45410 | B33: 293820 | C33: =B33-B32 -> 499 | E33: 0 | F33: 805 | G33: =C33+D33-E33+F32-F33 -> 379 | H33: ='[1]Reading.4.23'!G33 -> 550 | J33: 207899 | K33: =(J33-J32)*4.668 -> 168.048 | L33: ='[1]Reading.4.23'!K33 -> 177.384 | N33: 733783 | O33: =(N33-N32)*4.61 -> 474.83 | P33: ='[1]Reading.4.23'!O33 -> 511.71 | R33: 42700 | T33: =(R32+S32)-R33 -> 0 | U33: ='[1]Reading.4.23'!T33 -> 0 | W33: 45888.61 | X33: =(W33-W32)*4000 -> 34600 | Y33: ='[1]Reading.4.23'!X33 -> 38560 | AA33: 520050 | AB33: =AA33-AA32 -> 0 | AC33: ='[1]Reading.4.23'!AB33 -> 0 | AE33: =+X33+AB33 -> 34600 | AF33: ='[1]Reading.4.23'!AE33 -> 38560 | AG33: =989409/30 -> 32980.3 | AI33: 0.5989 | AJ33: ='[1]Reading.4.23'!AI33 -> 0.6312 | AK33: 5.638 | AM33: 315 | AN33: ='[1]Reading.4.23'!AM33 -> 332 | AO33: =10065/30 -> 335.5 | AQ33: =517*4 -> 2068 | AR33: ='[1]Reading.4.23'!AQ33 -> 2044 | AT33: 7163.86 | AU33: =(AT33-AT32)*4000 -> 3960 | AV33: =+X33/SQRT(((POWER((X33),2)+(POWER((AU33),2))))) -> 0.99351415 | AY33: ='[1]Reading.4.23'!X33 -> 38560 | AZ33: ='[1]Reading.4.23'!AB33 -> 0 | BA33: =AY33+AZ33 -> 38560 | BC33: 25 | BD33: 20 | BE33: 16 | BF33: 52 | BG33: 84 | BH33: ='[1]Reading.4.23'!BD33 -> 28.1 | BI33: ='[1]Reading.4.23'!BE33 -> 23 | BJ33: ='[1]Reading.4.23'!BF33 -> 69 | BL33: 526 | BN33: ='[1]Reading.4.23'!E31 -> 0 | BP33: 67188 | BQ33: =BP33-BP32 -> 36 | BR33: ='[1]Reading.4.23'!BQ33 -> 44 | BT33: 82140 | BU33: =BT33-BT32 -> 41 | BV33: ='[1]Reading.4.23'!BU33 -> 44 | BX33: 4005 | BY33: =BX32-BX31 -> 0 | BZ33: ='[1]Reading.4.23'!BY32 -> 0 | CB33: 234520 | CC33: =CB33-CB32 -> 30 | CD33: ='[1]Reading.4.23'!CC33 -> 46 | CF33: 6295 | CG33: =CF33-CF32 -> 10 | CH33: ='[1]Reading.4.23'!CG33 -> 0 | CI33: 19770 | CJ33: =CI32-CI31 -> 0 | CK33: ='[1]Reading.4.23'!CG32 -> 0 | CM33: =BQ33+BU33+BY34+CC33+CJ34 -> 107 | CN33: =BR33+BV33+BZ34+CD33+CK34 -> 134 | CP33: 112640 | CQ33: =CP33-CP32 -> 600 | CR33: =CQ33/G33 -> 1.5831135 | CS33: ='[1]Reading.4.23'!CN33 -> 226 | CT33: ='[1]Reading.4.23'!CO31 -> 0.38602329 | CV33: 5271 | CW33: =CV33-CV32 -> 2 | CX33: ='[1]Reading.4.23'!CT33 -> 4 | CZ33: 960 | DA33: =CZ33-CZ32 -> 4 | DB33: ='[1]Reading.4.23'!CX33 -> 6 | DD33: 1443193 | DE33: =DD33-DD32 -> 978 | DF33: ='[1]Reading.4.23'!DB33 -> 1034 | DH33: 3365123 | DI33: =DH33-DH32 -> 2264 | DJ33: ='[1]Reading.4.23'!DF33 -> 2288 | DL33: 2919101 | DM33: =DL33-DL32 -> 31 | DN33: ='[1]Reading.4.23'!DJ33 -> 2422 | DP33: 2295461 | DQ33: =DP33-DP32 -> 1750 | DR33: ='[1]Reading.4.23'!DN33 -> 2451 | DT33: 3132677 | DU33: =DT33-DT32 -> 2399 | DV33: ='[1]Reading.4.23'!DR33 -> 31 | DX33: 720 | DZ33: =DM33+DQ33+DU33+DX33 -> 4900 | EA33: ='[1]Reading.4.23'!DW33 -> 5624 | EC33: =C33*5.2 -> 2594.8 | ED33: ='[1]Reading.4.23'!C33*5.2 -> 3250 | EF33: 61065 | EG33: =EF33-EF32 -> 60 | EJ33: 24429 | EK33: =EJ33-EJ32 -> 26
A34: 45411 | B34: 294460 | C34: =B34-B33 -> 640 | E34: 0 | F34: 820 | G34: =C34+D34-E34+F33-F34 -> 625 | H34: ='[1]Reading.4.23'!G34 -> 512 | J34: 207926 | K34: =(J34-J33)*4.668 -> 126.036 | L34: ='[1]Reading.4.23'!K34 -> 182.052 | N34: 733891 | O34: =(N34-N33)*4.61 -> 497.88 | P34: ='[1]Reading.4.23'!O34 -> 534.76 | R34: 42700 | T34: =(R33+S33)-R34 -> 0 | U34: ='[1]Reading.4.23'!T34 -> 0 | W34: 45897.72 | X34: =(W34-W33)*4000 -> 36440 | Y34: ='[1]Reading.4.23'!X34 -> 32440 | AA34: 520050 | AB34: =AA34-AA33 -> 0 | AC34: ='[1]Reading.4.23'!AB34 -> 0 | AE34: =+X34+AB34 -> 36440 | AF34: ='[1]Reading.4.23'!AE34 -> 32440 | AG34: =989409/30 -> 32980.3 | AI34: 0.5817 | AJ34: ='[1]Reading.4.23'!AI34 -> 0.5741 | AK34: 5.638 | AM34: 306 | AN34: ='[1]Reading.4.23'!AM34 -> 302 | AO34: =10065/30 -> 335.5 | AQ34: =517*4 -> 2068 | AR34: ='[1]Reading.4.23'!AQ34 -> 2044 | AT34: 7165.01 | AU34: =(AT34-AT33)*4000 -> 4600 | AV34: =+X34/SQRT(((POWER((X34),2)+(POWER((AU34),2))))) -> 0.99212635 | AY34: ='[1]Reading.4.23'!X34 -> 32440 | AZ34: ='[1]Reading.4.23'!AB34 -> 0 | BA34: =AY34+AZ34 -> 32440 | BC34: 25 | BD34: 20 | BE34: 16 | BF34: 52 | BG34: 84 | BH34: ='[1]Reading.4.23'!BD34 -> 23.5 | BI34: ='[1]Reading.4.23'!BE34 -> 20 | BJ34: ='[1]Reading.4.23'!BF34 -> 60 | BL34: 526 | BN34: ='[1]Reading.4.23'!E32 -> 0 | BP34: 67215 | BQ34: =BP34-BP33 -> 27 | BR34: ='[1]Reading.4.23'!BQ34 -> 37 | BT34: 82179 | BU34: =BT34-BT33 -> 39 | BV34: ='[1]Reading.4.23'!BU34 -> 41 | BX34: 4005 | BY34: =BX33-BX32 -> 0 | BZ34: ='[1]Reading.4.23'!BY33 -> 0 | CB34: 234590 | CC34: =CB34-CB33 -> 70 | CD34: ='[1]Reading.4.23'!CC34 -> 38 | CF34: 6305 | CG34: =CF34-CF33 -> 10 | CH34: ='[1]Reading.4.23'!CG34 -> 0 | CI34: 19770 | CJ34: =CI33-CI32 -> 0 | CK34: ='[1]Reading.4.23'!CG33 -> 0 | CM34: =BQ34+BU34+BY35+CC34+CJ35 -> 176 | CN34: =BR34+BV34+BZ35+CD34+CK35 -> 116 | CP34: 113182 | CQ34: =CP34-CP33 -> 542 | CR34: =CQ34/G34 -> 0.8672 | CS34: ='[1]Reading.4.23'!CN34 -> 213 | CT34: ='[1]Reading.4.23'!CO32 -> 0.42301184 | CV34: 5273 | CW34: =CV34-CV33 -> 2 | CX34: ='[1]Reading.4.23'!CT34 -> 2 | CZ34: 963 | DA34: =CZ34-CZ33 -> 3 | DB34: ='[1]Reading.4.23'!CX34 -> 5 | DD34: 1444191 | DE34: =DD34-DD33 -> 998 | DF34: ='[1]Reading.4.23'!DB34 -> 977 | DH34: 3366689 | DI34: =DH34-DH33 -> 1566 | DJ34: ='[1]Reading.4.23'!DF34 -> 1906 | DL34: 2919134 | DM34: =DL34-DL33 -> 33 | DN34: ='[1]Reading.4.23'!DJ34 -> 1606 | DP34: 2297480 | DQ34: =DP34-DP33 -> 2019 | DR34: ='[1]Reading.4.23'!DN34 -> 1522 | DT34: 3135167 | DU34: =DT34-DT33 -> 2490 | DV34: ='[1]Reading.4.23'!DR34 -> 32 | DX34: 720 | DZ34: =DM34+DQ34+DU34+DX34 -> 5262 | EA34: ='[1]Reading.4.23'!DW34 -> 3880 | EC34: =C34*5.2 -> 3328 | ED34: ='[1]Reading.4.23'!C34*5.2 -> 2324.4 | EF34: 61118 | EG34: =EF34-EF33 -> 53 | EJ34: 24451 | EK34: =EJ34-EJ33 -> 22
A35: 45412 | B35: 294932 | C35: =B35-B34 -> 472 | E35: 0 | F35: 780 | G35: =C35+D35-E35+F34-F35 -> 512 | H35: ='[1]Reading.4.23'!G35 -> 417 | J35: 207959 | K35: =(J35-J34)*4.668 -> 154.044 | L35: ='[1]Reading.4.23'!K35 -> 168.048 | N35: 733991 | O35: =(N35-N34)*4.61 -> 461 | P35: ='[1]Reading.4.23'!O35 -> 516.32 | R35: 42700 | T35: =(R34+S34)-R35 -> 0 | U35: ='[1]Reading.4.23'!T35 -> 0 | W35: 45905.86 | X35: =(W35-W34)*4000 -> 32560 | Y35: ='[1]Reading.4.23'!X35 -> 32040 | AA35: 520050 | AB35: =AA35-AA34 -> 0 | AC35: ='[1]Reading.4.23'!AB35 -> 0 | AE35: =+X35+AB35 -> 32560 | AF35: ='[1]Reading.4.23'!AE35 -> 32040 | AG35: =989409/30 -> 32980.3 | AI35: 0.5551 | AJ35: ='[1]Reading.4.23'!AI35 -> 0.5456 | AK35: 5.638 | AM35: 291 | AN35: ='[1]Reading.4.23'!AM35 -> 287 | AO35: =10065/30 -> 335.5 | AQ35: =436*4 -> 1744 | AR35: ='[1]Reading.4.23'!AQ35 -> 1588 | AT35: 7165.9 | AU35: =(AT35-AT34)*4000 -> 3560 | AV35: =+X35/SQRT(((POWER((X35),2)+(POWER((AU35),2))))) -> 0.99407582 | AY35: ='[1]Reading.4.23'!X35 -> 32040 | AZ35: ='[1]Reading.4.23'!AB35 -> 0 | BA35: =AY35+AZ35 -> 32040 | BC35: 25 | BD35: 20 | BE35: 16 | BF35: 52 | BG35: 84 | BH35: ='[1]Reading.4.23'!BD35 -> 23.5 | BI35: ='[1]Reading.4.23'!BE35 -> 20 | BJ35: ='[1]Reading.4.23'!BF35 -> 60 | BL35: 526 | BN35: ='[1]Reading.4.23'!E33 -> 0 | BP35: 67249 | BQ35: =BP35-BP34 -> 34 | BR35: ='[1]Reading.4.23'!BQ35 -> 39 | BT35: 82221 | BU35: =BT35-BT34 -> 42 | BV35: ='[1]Reading.4.23'!BU35 -> 50 | BX35: 4045 | BY35: =BX35-BX34 -> 40 | BZ35: ='[1]Reading.4.23'!BY34 -> 0 | CB35: 234620 | CC35: =CB35-CB34 -> 30 | CD35: ='[1]Reading.4.23'!CC35 -> 34 | CF35: 6310 | CG35: =CF35-CF34 -> 5 | CH35: ='[1]Reading.4.23'!CG35 -> 0 | CI35: 19770 | CJ35: =CI34-CI33 -> 0 | CK35: ='[1]Reading.4.23'!CG34 -> 0 | CM35: =BQ35+BU35+BY36+CC35+CJ36 -> 106 | CN35: =BR35+BV35+BZ36+CD35+CK36 -> 123 | CP35: 113578 | CQ35: =CP35-CP34 -> 396 | CR35: =CQ35/G35 -> 0.7734375 | CS35: ='[1]Reading.4.23'!CN35 -> 221 | CT35: ='[1]Reading.4.23'!CO33 -> 0.41090909 | CV35: 5276 | CW35: =CV35-CV34 -> 3 | CX35: ='[1]Reading.4.23'!CT35 -> 4 | CZ35: 966 | DA35: =CZ35-CZ34 -> 3 | DB35: ='[1]Reading.4.23'!CX35 -> 5 | DD35: 1445259 | DE35: =DD35-DD34 -> 1068 | DF35: ='[1]Reading.4.23'!DB35 -> 957 | DH35: 3368645 | DI35: =DH35-DH34 -> 1956 | DJ35: ='[1]Reading.4.23'!DF35 -> 2061 | DL35: 2919166 | DM35: =DL35-DL34 -> 32 | DN35: ='[1]Reading.4.23'!DJ35 -> 32 | DP35: 2299326 | DQ35: =DP35-DP34 -> 1846 | DR35: ='[1]Reading.4.23'!DN35 -> 3395 | DT35: 3137289 | DU35: =DT35-DT34 -> 2122 | DV35: ='[1]Reading.4.23'!DR35 -> 33 | DX35: 720 | DZ35: =DM35+DQ35+DU35+DX35 -> 4720 | EA35: ='[1]Reading.4.23'!DW35 -> 4180 | EC35: =C35*5.2 -> 2454.4 | ED35: ='[1]Reading.4.23'!C35*5.2 -> 2402.4 | EF35: 61166 | EG35: =EF35-EF34 -> 48 | EJ35: 24472 | EK35: =EJ35-EJ34 -> 21
C37: =AVERAGE(C6:C36) -> 568.06667 | E37: =SUM(E6:E36) -> 0 | G37: =SUM(G6:G36) -> 17102 | H37: =SUM(H6:H36) -> 16258 | K37: =SUM(K6:K36) -> 5111.46 | L37: =SUM(L6:L36) -> 5358.864 | O37: =SUM(O6:O36) -> 13899.15 | P37: =SUM(P6:P36) -> 13779.29 | S37: =SUM(S6:S36) -> 0 | T37: =SUM(T6:T36) -> 0 | U37: =SUM(U6:U36) -> 0 | X37: =SUM(X6:X36) -> 997240 | Y37: =SUM(Y6:Y36) -> 961560 | AB37: =SUM(AB6:AB36) -> 20 | AC37: =SUM(AC6:AC36) -> 800 | AE37: =SUM(AE6:AE36) -> 997260 | AF37: =SUM(AF6:AF36) -> 962360 | AG37: =SUM(AG6:AG36) -> 989409 | AI37: =AVERAGE(AI6:AI36) -> 0.63662 | AJ37: =AVERAGE(AJ6:AJ36) -> 0.56956667 | AK37: =AVERAGE(AK6:AK36) -> 2.1046667 | AM37: =SUM(AM6:AM36) -> 10046 | AN37: =SUM(AN6:AN36) -> 8987 | AO37: =SUM(AO6:AO36) -> 10065 | AQ37: =MAX(AQ6:AQ36) -> 2068 | AR37: =MAX(AR6:AR36) -> 2044 | AV37: =AVERAGE(AV6:AV36) -> 0.9941177 | AY37: =SUM(AY6:AY36) -> 961560 | AZ37: =SUM(AZ6:AZ36) -> 800 | BA37: =SUM(BA6:BA36) -> 962360 | BC37: =AVERAGE(BC6:BC36) -> 21 | BD37: =AVERAGE(BD6:BD36) -> 17.826667 | BE37: =AVERAGE(BE6:BE36) -> 14.033333 | BF37: =AVERAGE(BF6:BF36) -> 56.966667 | BG37: =AVERAGE(BG6:BG36) -> 80.466667 | BH37: =AVERAGE(BH6:BH36) -> 25.946667 | BI37: =AVERAGE(BI6:BI36) -> 21.3 | BJ37: =AVERAGE(BJ6:BJ36) -> 59.266667 | BL37: =SUM(BL6:BL36) -> 15780 | BN37: =SUM(BN6:BN36) -> 0 | BQ37: =SUM(BQ6:BQ36) -> 978 | BR37: =SUM(BR6:BR36) -> 944 | BU37: =SUM(BU6:BU36) -> 1150 | BV37: =SUM(BV6:BV36) -> 1061 | BY37: =SUM(BY6:BY36) -> 81 | BZ37: =SUM(BZ6:BZ36) -> 5 | CC37: =SUM(CC6:CC36) -> 1260 | CD37: =SUM(CD6:CD36) -> 1564 | CG37: =SUM(CG6:CG36) -> 240 | CH37: =SUM(CH6:CH36) -> 0 | CJ37: =SUM(CJ6:CJ36) -> -6 | CK37: =SUM(CK6:CK36) -> 0 | CM37: =SUM(CM6:CM36) -> 3463 | CN37: =SUM(CN6:CN36) -> 3574 | CQ37: =SUM(CQ6:CQ36) -> 12613 | CR37: =AVERAGE(CR6:CR36) -> 0.75229892 | CS37: =SUM(CS6:CS35) -> 6817 | CT37: ='[1]Reading.4.23'!CO35 -> 0.52997602 | CW37: =SUM(CW6:CW36) -> 63 | CX37: =SUM(CX6:CX36) -> 47 | DA37: =SUM(DA6:DA36) -> 88 | DB37: =SUM(DB6:DB36) -> 128 | DE37: =SUM(DE6:DE36) -> 24561 | DF37: =SUM(DF6:DF36) -> 25615 | DI37: =SUM(DI6:DI36) -> 54380 | DJ37: =SUM(DJ6:DJ36) -> 56368 | DM37: =SUM(DM6:DM36) -> 15783 | DN37: =SUM(DN6:DN36) -> 83010 | DQ37: =SUM(DQ6:DQ36) -> 14438 | DR37: =SUM(DR6:DR36) -> 22483 | DU37: =SUM(DU6:DU36) -> 90754 | DV37: =SUM(DV6:DV36) -> 1020 | DZ37: =SUM(DZ6:DZ36) -> 142575 | EA37: =SUM(EA6:EA36) -> 128113 | EC37: =SUM(EC6:EC36) -> 88618.4 | ED37: =SUM(ED6:ED36) -> 84541.6 | EG37: =SUM(EG6:EG36) -> 1610 | EH37: =SUM(EH6:EH36) -> 0 | EK37: =SUM(EK6:EK36) -> 710 | EL37: =SUM(EL6:EL36) -> 0
C38: Average/Day | AP38: Last Period Max. Demand: | AQ38: 2216 | CQ38: 0
C39: =SUM(C6:C36) -> 17042 | AP39: This Period Max. Demand: | AQ39: 2160
U40: ENERGY COST / OCCUPIED ROOM - LAST YEAR = | AB40: ='[1]Cost.4.24'!BG39 -> 155.41202 | AC40: L.E. | AF40: OCCUPANCY - LAST YEAR = | AJ40: =AJ37 -> 0.56956667 | AM40: KWH / OCCUPIED ROOM - LAST YEAR | AR40: =AF37/AN37 -> 107.08357 | AY40: https://www.wunderground.com/history/monthly/eg/sharm-el-sheikh/HESH/date/2024-02
U41: ENERGY COST / OCCUPIED ROOM - THIS YEAR = | AB41: ='[1]Cost.4.24'!BI39 -> 155.63659 | AC41: L.E. | AF41: OCCUPANCY - THIS YEAR = | AJ41: =AI37 -> 0.63662 | AM41: KWH / OCCU[PIED ROOM - THIS YEAR | AR41: =AE37/AM37 -> 99.269361
U42: ENERGY COST / OCCUPIED ROOM - BUDGET = | AB42: ='[1]Cost.4.24'!BH39 -> 145.70114 | AC42: L.E. | AF42: OCCUPANCY - BUDGET= | AJ42: =AK37 -> 2.1046667 | AM42: KWH / OCCUPIED ROOM - BUDGET | AR42: =AG37/AO37 -> 98.301937 | CC42: =229975+25 -> 230000
AM44: KWH / AVAILABLE ROOM - LAST YEAR | AR44: =AF37/BL37 -> 60.986058
AM45: KWH / AVAILABLE ROOM - THIS YEAR | AR45: =AE37/BL37 -> 63.197719
AM46: KWH / AVAILABLE ROOM - BUDGET | AR46: =AG37/BL37 -> 62.70019
BQ151: .

Sheet Cost.4.24
H1: =H8*31 -> 10400.5 | K1: =K8*31 -> 1349554 | P1: =P8*31 -> 2290.9 | R1: =R8*31 -> 14983.333 | W1: =W8*31 -> 18547.3 | X1: =X8*31 -> 90137.667 | AD1: =AD8*31 -> 12041.95 | AJ1: =AJ8*31 -> 4013.9833 | AP1: =AP8*31 -> 16055.933 | AQ1: =AQ8*31 -> 60689.733
A2: Energy Cost April 2024 | AV2: Energy Cost - October 2023
B3: 1 | C3: 2 | D3: 3 | E3: 4 | F3: 5 | G3: 6 | H3: 7 | I3: 8 | J3: 9 | K3: 10 | L3: 11 | M3: 12 | N3: 13 | O3: 14 | P3: 15 | Q3: 16 | R3: 17 | S3: 18 | T3: 19 | U3: 20 | V3: 21 | W3: 22 | X3: 23 | Y3: 24 | Z3: 25 | AA3: 26 | AB3: 27 | AC3: 28 | AD3: 29 | AE3: 30 | AF3: 31 | AG3: 32 | AH3: 33 | AI3: 34 | AJ3: 35 | AK3: 36 | AL3: 37 | AM3: 38 | AN3: 39 | AO3: 40 | AP3: 41 | AQ3: 42 | AR3: 43 | AS3: 44 | AT3: 45 | AU3: 46 | AV3: 47 | AW3: 48 | AX3: 49 | AY3: 50 | AZ3: 51 | BA3: 52 | BB3: 53 | BC3: 54 | BD3: 55 | BE3: 56 | BF3: 57 | BG3: 58 | BH3: 59 | BI3: 60
J5: ELECTRICITY | O5: FUEL | V5: WATER | AB5: NATURAL GAS | AV5: ELECTRICITY | AX5: WATER | AZ5: NATURAL GAS | BC5: LAST YEAR TOTAL ENERGY L.E. | BD5: BUDGET TOTAL ENERGY L.E. | BE5: ACTUAL TOTAL ENERGY L.E. | BG5: ENERGY LAST YEAR / OCCUPIED ROOM | BH5: ENERGY BUDGET / OCCUPIED ROOM | BI5: ENERGY ACTUAL / OCCUPIED ROOM
B6: DATE | D6: Occ. | F6: Occupied Rooms | H6: Occupied Rooms Budget | J6: CONSUMP. KWH | K6: BUDGET L.E. | L6: LAST YEAR ACTUAL L.E. | M6: ACTUAL L.E. | O6: CONSUMP. LITRE | P6: BUDGET LITRE | Q6: GENERATOR KWH | R6: BUDGET L.E. | S6: LAST YEAR ACTUAL L.E. | T6: ACTUAL L.E. | V6: CONSUMP. M³ | W6: BUDGET M³ | X6: BUDGET L.E. | Y6: LAST YEAR ACTUAL L.E. | Z6: ACTUAL L.E. | AB6: BOILER CONSUMP. M³ | AC6: BOILER COST L.E. | AD6: BOILER BUDGET CONSUMP. M³ | AE6: BOILER BUDGET COST L.E. | AF6: BOILER CONSUMP. LAST YEAR M³ | AG6: BOILER COST LAST YEAR L.E. | AH6: KITCHEN CONSUMP. M³ | AI6: KITCHEN COST L.E. | AJ6: KITCHEN BUDGET CONSUMP. M³ | AK6: KITCHEN BUDGET COST L.E. | AL6: KITCHEN CONSUMP. LAST YEAR M³ | AM6: KITCHEN COST LAST YEAR L.E. | AN6: TOTAL CONSUMP. M³ | AO6: TOTAL CONSUMP. LAST YEAR M³ | AP6: BUDGET TOTAL CONSUMP. M³ | AQ6: BUDGET L.E. | AR6: LAST YEAR ACTUAL L.E. | AS6: ACTUAL L.E. | AV6: KWH / Occupied Room | AW6: L.E. / Occupied Room | AX6: Cu.Mt. / Occupied Room | AY6: L.E. / Occupied Room | AZ6: Cu.Mt. / Occupied Room | BA6: L.E. / Occupied Room
B8: 45383 | D8: ='[1]Reading.4.24'!AI6 -> 0.5209 | F8: ='[1]Reading.4.24'!AM6 -> 274 | H8: ='[1]Reading.4.24'!AO6 -> 335.5 | J8: ='[1]Reading.4.24'!X6 -> 27720 | K8: =1306020/30 -> 43534 | L8: ='[1]Cost.4.23'!M8 -> 32760 | M8: =J8*1.39 -> 38530.8 | O8: ='[1]Reading.4.24'!T6 -> 0 | P8: =2217/30 -> 73.9 | Q8: ='[1]Reading.4.24'!AB6 -> 0 | R8: =14500/30 -> 483.33333 | S8: ='[1]Cost.4.23'!T8 -> 0 | T8: =O8*5.86 -> 0 | V8: ='[1]Reading.4.24'!G6 -> 505 | W8: =17949/30 -> 598.3 | X8: =87230/30 -> 2907.6667 | Y8: ='[1]Cost.4.23'!Z8 -> 2889.12 | Z8: ='[1]Reading.4.24'!G6*4.86 -> 2454.3 | AB8: ='[1]Reading.4.24'!O6 -> 391.85 | AC8: =AB8*3.73 -> 1461.6005 | AD8: =((15538/4)*3)/30 -> 388.45 | AE8: =((58732/4)*3)/30 -> 1468.3 | AF8: ='[1]Cost.4.23'!AB8 -> 419.51 | AG8: ='[1]Cost.4.23'!AC8 -> 1564.7723 | AH8: ='[1]Reading.4.24'!K6 -> 112.032 | AI8: =AH8*3.73 -> 417.87936 | AJ8: =(15538/4)/30 -> 129.48333 | AK8: =(58732/4)/30 -> 489.43333 | AL8: ='[1]Cost.4.23'!AH8 -> 149.376 | AM8: ='[1]Cost.4.23'!AI8 -> 557.17248 | AN8: =AB8+AH8 -> 503.882 | AO8: =AF8+AL8 -> 568.886 | AP8: =AD8+AJ8 -> 517.93333 | AQ8: =58732/30 -> 1957.7333 | AR8: ='[1]Cost.4.23'!AS8 -> 2121.9448 | AS8: =AC8+AI8 -> 1879.4799 | AV8: ='[1]Reading.4.24'!AE6/'[1]Cost.4.24'!F8 -> 101.16788 | AW8: =(M8+T8)/F8 -> 140.62336 | AX8: =V8/F8 -> 1.8430657 | AY8: =Z8/F8 -> 8.9572993 | AZ8: =AN8/F8 -> 1.8389854 | BA8: =AS8/F8 -> 6.8594155 | BC8: ='[1]Cost.4.23'!BE8 -> 37771.065 | BD8: =K8+R8+X8+AQ8 -> 48882.733 | BE8: =M8+T8+Z8+AS8 -> 42864.58 | BG8: ='[1]Cost.4.23'!BI8 -> 165.66256 | BH8: =BD8/H8 -> 145.70114 | BI8: =BE8/F8 -> 156.44007
B9: 45384 | D9: ='[1]Reading.4.24'!AI7 -> 0.4924 | F9: ='[1]Reading.4.24'!AM7 -> 259 | H9: ='[1]Reading.4.24'!AO7 -> 335.5 | J9: ='[1]Reading.4.24'!X7 -> 28600 | K9: =1306020/30 -> 43534 | L9: ='[1]Cost.4.23'!M9 -> 33332 | M9: =J9*1.39 -> 39754 | O9: ='[1]Reading.4.24'!T7 -> 0 | P9: =2217/30 -> 73.9 | Q9: ='[1]Reading.4.24'!AB7 -> 0 | R9: =14500/30 -> 483.33333 | S9: ='[1]Cost.4.23'!T9 -> 0 | T9: =O9*5.86 -> 0 | V9: ='[1]Reading.4.24'!G7 -> 460 | W9: =17949/30 -> 598.3 | X9: =87230/30 -> 2907.6667 | Y9: ='[1]Cost.4.23'!Z9 -> 2495.57 | Z9: ='[1]Reading.4.24'!G7*4.86 -> 2235.6 | AB9: ='[1]Reading.4.24'!O7 -> 410.29 | AC9: =AB9*3.73 -> 1530.3817 | AD9: =((15538/4)*3)/30 -> 388.45 | AE9: =((58732/4)*3)/30 -> 1468.3 | AF9: ='[1]Cost.4.23'!AB9 -> 410.29 | AG9: ='[1]Cost.4.23'!AC9 -> 1530.3817 | AH9: ='[1]Reading.4.24'!K7 -> 121.368 | AI9: =AH9*3.73 -> 452.70264 | AJ9: =(15538/4)/30 -> 129.48333 | AK9: =(58732/4)/30 -> 489.43333 | AL9: ='[1]Cost.4.23'!AH9 -> 135.372 | AM9: ='[1]Cost.4.23'!AI9 -> 504.93756 | AN9: =AB9+AH9 -> 531.658 | AO9: =AF9+AL9 -> 545.662 | AP9: =AD9+AJ9 -> 517.93333 | AQ9: =58732/30 -> 1957.7333 | AR9: ='[1]Cost.4.23'!AS9 -> 2035.3193 | AS9: =AC9+AI9 -> 1983.0843 | AV9: ='[1]Reading.4.24'!AE7/'[1]Cost.4.24'!F9 -> 110.42471 | AW9: =(M9+T9)/F9 -> 153.49035 | AX9: =V9/F9 -> 1.7760618 | AY9: =Z9/F9 -> 8.6316602 | AZ9: =AN9/F9 -> 2.0527336 | BA9: =AS9/F9 -> 7.6566963 | BC9: ='[1]Cost.4.23'!BE9 -> 37862.889 | BD9: =K9+R9+X9+AQ9 -> 48882.733 | BE9: =M9+T9+Z9+AS9 -> 43972.684 | BG9: ='[1]Cost.4.23'!BI9 -> 179.44497 | BH9: =BD9/H9 -> 145.70114 | BI9: =BE9/F9 -> 169.7787
B10: 45385 | D10: ='[1]Reading.4.24'!AI8 -> 0.4943 | F10: ='[1]Reading.4.24'!AM8 -> 260 | H10: ='[1]Reading.4.24'!AO8 -> 335.5 | J10: ='[1]Reading.4.24'!X8 -> 29160 | K10: =1306020/30 -> 43534 | L10: ='[1]Cost.4.23'!M10 -> 33488 | M10: =J10*1.39 -> 40532.4 | O10: ='[1]Reading.4.24'!T8 -> 0 | P10: =2217/30 -> 73.9 | Q10: ='[1]Reading.4.24'!AB8 -> 0 | R10: =14500/30 -> 483.33333 | S10: ='[1]Cost.4.23'!T10 -> 0 | T10: =O10*5.86 -> 0 | V10: ='[1]Reading.4.24'!G8 -> 552 | W10: =17949/30 -> 598.3 | X10: =87230/30 -> 2907.6667 | Y10: ='[1]Cost.4.23'!Z10 -> 2435.38 | Z10: ='[1]Reading.4.24'!G8*4.86 -> 2682.72 | AB10: ='[1]Reading.4.24'!O8 -> 387.24 | AC10: =AB10*3.73 -> 1444.4052 | AD10: =((15538/4)*3)/30 -> 388.45 | AE10: =((58732/4)*3)/30 -> 1468.3 | AF10: ='[1]Cost.4.23'!AB10 -> 401.07 | AG10: ='[1]Cost.4.23'!AC10 -> 1495.9911 | AH10: ='[1]Reading.4.24'!K8 -> 149.376 | AI10: =AH10*3.73 -> 557.17248 | AJ10: =(15538/4)/30 -> 129.48333 | AK10: =(58732/4)/30 -> 489.43333 | AL10: ='[1]Cost.4.23'!AH10 -> 144.708 | AM10: ='[1]Cost.4.23'!AI10 -> 539.76084 | AN10: =AB10+AH10 -> 536.616 | AO10: =AF10+AL10 -> 545.778 | AP10: =AD10+AJ10 -> 517.93333 | AQ10: =58732/30 -> 1957.7333 | AR10: ='[1]Cost.4.23'!AS10 -> 2035.7519 | AS10: =AC10+AI10 -> 2001.5777 | AV10: ='[1]Reading.4.24'!AE8/'[1]Cost.4.24'!F10 -> 112.15385 | AW10: =(M10+T10)/F10 -> 155.89385 | AX10: =V10/F10 -> 2.1230769 | AY10: =Z10/F10 -> 10.318154 | AZ10: =AN10/F10 -> 2.0639077 | BA10: =AS10/F10 -> 7.6983757 | BC10: ='[1]Cost.4.23'!BE10 -> 37959.132 | BD10: =K10+R10+X10+AQ10 -> 48882.733 | BE10: =M10+T10+Z10+AS10 -> 45216.698 | BG10: ='[1]Cost.4.23'!BI10 -> 162.21851 | BH10: =BD10/H10 -> 145.70114 | BI10: =BE10/F10 -> 173.91038
B11: 45386 | D11: ='[1]Reading.4.24'!AI9 -> 0.54 | F11: ='[1]Reading.4.24'!AM9 -> 286 | H11: ='[1]Reading.4.24'!AO9 -> 335.5 | J11: ='[1]Reading.4.24'!X9 -> 28200 | K11: =1306020/30 -> 43534 | L11: ='[1]Cost.4.23'!M11 -> 33124 | M11: =J11*1.39 -> 39198 | O11: ='[1]Reading.4.24'!T9 -> 0 | P11: =2217/30 -> 73.9 | Q11: ='[1]Reading.4.24'!AB9 -> 0 | R11: =14500/30 -> 483.33333 | S11: ='[1]Cost.4.23'!T11 -> 0 | T11: =O11*5.86 -> 0 | V11: ='[1]Reading.4.24'!G9 -> 519 | W11: =17949/30 -> 598.3 | X11: =87230/30 -> 2907.6667 | Y11: ='[1]Cost.4.23'!Z11 -> 2463.16 | Z11: ='[1]Reading.4.24'!G9*4.86 -> 2522.34 | AB11: ='[1]Reading.4.24'!O9 -> 368.8 | AC11: =AB11*3.73 -> 1375.624 | AD11: =((15538/4)*3)/30 -> 388.45 | AE11: =((58732/4)*3)/30 -> 1468.3 | AF11: ='[1]Cost.4.23'!AB11 -> 391.85 | AG11: ='[1]Cost.4.23'!AC11 -> 1461.6005 | AH11: ='[1]Reading.4.24'!K9 -> 158.712 | AI11: =AH11*3.73 -> 591.99576 | AJ11: =(15538/4)/30 -> 129.48333 | AK11: =(58732/4)/30 -> 489.43333 | AL11: ='[1]Cost.4.23'!AH11 -> 149.376 | AM11: ='[1]Cost.4.23'!AI11 -> 557.17248 | AN11: =AB11+AH11 -> 527.512 | AO11: =AF11+AL11 -> 541.226 | AP11: =AD11+AJ11 -> 517.93333 | AQ11: =58732/30 -> 1957.7333 | AR11: ='[1]Cost.4.23'!AS11 -> 2018.773 | AS11: =AC11+AI11 -> 1967.6198 | AV11: ='[1]Reading.4.24'!AE9/'[1]Cost.4.24'!F11 -> 98.601399 | AW11: =(M11+T11)/F11 -> 137.05594 | AX11: =V11/F11 -> 1.8146853 | AY11: =Z11/F11 -> 8.8193706 | AZ11: =AN11/F11 -> 1.8444476 | BA11: =AS11/F11 -> 6.8797894 | BC11: ='[1]Cost.4.23'!BE11 -> 37605.933 | BD11: =K11+R11+X11+AQ11 -> 48882.733 | BE11: =M11+T11+Z11+AS11 -> 43687.96 | BG11: ='[1]Cost.4.23'!BI11 -> 151.02784 | BH11: =BD11/H11 -> 145.70114 | BI11: =BE11/F11 -> 152.7551
B12: 45387 | D12: ='[1]Reading.4.24'!AI10 -> 0.481 | F12: ='[1]Reading.4.24'!AM10 -> 253 | H12: ='[1]Reading.4.24'!AO10 -> 335.5 | J12: ='[1]Reading.4.24'!X10 -> 30080 | K12: =1306020/30 -> 43534 | L12: ='[1]Cost.4.23'!M12 -> 35880 | M12: =J12*1.39 -> 41811.2 | O12: ='[1]Reading.4.24'!T10 -> 0 | P12: =2217/30 -> 73.9 | Q12: ='[1]Reading.4.24'!AB10 -> 0 | R12: =14500/30 -> 483.33333 | S12: ='[1]Cost.4.23'!T12 -> 0 | T12: =O12*5.86 -> 0 | V12: ='[1]Reading.4.24'!G10 -> 549 | W12: =17949/30 -> 598.3 | X12: =87230/30 -> 2907.6667 | Y12: ='[1]Cost.4.23'!Z12 -> 2268.7 | Z12: ='[1]Reading.4.24'!G10*4.86 -> 2668.14 | AB12: ='[1]Reading.4.24'!O10 -> 414.9 | AC12: =AB12*3.73 -> 1547.577 | AD12: =((15538/4)*3)/30 -> 388.45 | AE12: =((58732/4)*3)/30 -> 1468.3 | AF12: ='[1]Cost.4.23'!AB12 -> 414.9 | AG12: ='[1]Cost.4.23'!AC12 -> 1547.577 | AH12: ='[1]Reading.4.24'!K10 -> 158.712 | AI12: =AH12*3.73 -> 591.99576 | AJ12: =(15538/4)/30 -> 129.48333 | AK12: =(58732/4)/30 -> 489.43333 | AL12: ='[1]Cost.4.23'!AH12 -> 163.38 | AM12: ='[1]Cost.4.23'!AI12 -> 609.4074 | AN12: =AB12+AH12 -> 573.612 | AO12: =AF12+AL12 -> 578.28 | AP12: =AD12+AJ12 -> 517.93333 | AQ12: =58732/30 -> 1957.7333 | AR12: ='[1]Cost.4.23'!AS12 -> 2156.9844 | AS12: =AC12+AI12 -> 2139.5728 | AV12: ='[1]Reading.4.24'!AE10/'[1]Cost.4.24'!F12 -> 118.89328 | AW12: =(M12+T12)/F12 -> 165.26166 | AX12: =V12/F12 -> 2.1699605 | AY12: =Z12/F12 -> 10.546008 | AZ12: =AN12/F12 -> 2.2672411 | BA12: =AS12/F12 -> 8.4568093 | BC12: ='[1]Cost.4.23'!BE12 -> 40305.684 | BD12: =K12+R12+X12+AQ12 -> 48882.733 | BE12: =M12+T12+Z12+AS12 -> 46618.913 | BG12: ='[1]Cost.4.23'!BI12 -> 161.87022 | BH12: =BD12/H12 -> 145.70114 | BI12: =BE12/F12 -> 184.26448
B13: 45388 | D13: ='[1]Reading.4.24'!AI11 -> 0.519 | F13: ='[1]Reading.4.24'!AM11 -> 273 | H13: ='[1]Reading.4.24'!AO11 -> 335.5 | J13: ='[1]Reading.4.24'!X11 -> 30160 | K13: =1306020/30 -> 43534 | L13: ='[1]Cost.4.23'!M13 -> 35932 | M13: =J13*1.39 -> 41922.4 | O13: ='[1]Reading.4.24'!T11 -> 0 | P13: =2217/30 -> 73.9 | Q13: ='[1]Reading.4.24'!AB11 -> 0 | R13: =14500/30 -> 483.33333 | S13: ='[1]Cost.4.23'!T13 -> 0 | T13: =O13*5.86 -> 0 | V13: ='[1]Reading.4.24'!G11 -> 525 | W13: =17949/30 -> 598.3 | X13: =87230/30 -> 2907.6667 | Y13: ='[1]Cost.4.23'!Z13 -> 2694.66 | Z13: ='[1]Reading.4.24'!G11*4.86 -> 2551.5 | AB13: ='[1]Reading.4.24'!O11 -> 428.73 | AC13: =AB13*3.73 -> 1599.1629 | AD13: =((15538/4)*3)/30 -> 388.45 | AE13: =((58732/4)*3)/30 -> 1468.3 | AF13: ='[1]Cost.4.23'!AB13 -> 378.02 | AG13: ='[1]Cost.4.23'!AC13 -> 1410.0146 | AH13: ='[1]Reading.4.24'!K11 -> 149.376 | AI13: =AH13*3.73 -> 557.17248 | AJ13: =(15538/4)/30 -> 129.48333 | AK13: =(58732/4)/30 -> 489.43333 | AL13: ='[1]Cost.4.23'!AH13 -> 149.376 | AM13: ='[1]Cost.4.23'!AI13 -> 557.17248 | AN13: =AB13+AH13 -> 578.106 | AO13: =AF13+AL13 -> 527.396 | AP13: =AD13+AJ13 -> 517.93333 | AQ13: =58732/30 -> 1957.7333 | AR13: ='[1]Cost.4.23'!AS13 -> 1967.1871 | AS13: =AC13+AI13 -> 2156.3354 | AV13: ='[1]Reading.4.24'!AE11/'[1]Cost.4.24'!F13 -> 110.47619 | AW13: =(M13+T13)/F13 -> 153.5619 | AX13: =V13/F13 -> 1.9230769 | AY13: =Z13/F13 -> 9.3461538 | AZ13: =AN13/F13 -> 2.1176044 | BA13: =AS13/F13 -> 7.8986644 | BC13: ='[1]Cost.4.23'!BE13 -> 40593.847 | BD13: =K13+R13+X13+AQ13 -> 48882.733 | BE13: =M13+T13+Z13+AS13 -> 46630.235 | BG13: ='[1]Cost.4.23'!BI13 -> 150.34758 | BH13: =BD13/H13 -> 145.70114 | BI13: =BE13/F13 -> 170.80672
B14: 45389 | D14: ='[1]Reading.4.24'!AI12 -> 0.4753 | F14: ='[1]Reading.4.24'!AM12 -> 250 | H14: ='[1]Reading.4.24'!AO12 -> 335.5 | J14: ='[1]Reading.4.24'!X12 -> 28680 | K14: =1306020/30 -> 43534 | L14: ='[1]Cost.4.23'!M14 -> 39052 | M14: =J14*1.39 -> 39865.2 | O14: ='[1]Reading.4.24'!T12 -> 0 | P14: =2217/30 -> 73.9 | Q14: ='[1]Reading.4.24'!AB12 -> 20 | R14: =14500/30 -> 483.33333 | S14: ='[1]Cost.4.23'!T14 -> 0 | T14: =O14*5.86 -> 0 | V14: ='[1]Reading.4.24'!G12 -> 508 | W14: =17949/30 -> 598.3 | X14: =87230/30 -> 2907.6667 | Y14: ='[1]Cost.4.23'!Z14 -> 2222.4 | Z14: ='[1]Reading.4.24'!G12*4.86 -> 2468.88 | AB14: ='[1]Reading.4.24'!O12 -> 414.9 | AC14: =AB14*3.73 -> 1547.577 | AD14: =((15538/4)*3)/30 -> 388.45 | AE14: =((58732/4)*3)/30 -> 1468.3 | AF14: ='[1]Cost.4.23'!AB14 -> 405.68 | AG14: ='[1]Cost.4.23'!AC14 -> 1513.1864 | AH14: ='[1]Reading.4.24'!K12 -> 158.712 | AI14: =AH14*3.73 -> 591.99576 | AJ14: =(15538/4)/30 -> 129.48333 | AK14: =(58732/4)/30 -> 489.43333 | AL14: ='[1]Cost.4.23'!AH14 -> 177.384 | AM14: ='[1]Cost.4.23'!AI14 -> 661.64232 | AN14: =AB14+AH14 -> 573.612 | AO14: =AF14+AL14 -> 583.064 | AP14: =AD14+AJ14 -> 517.93333 | AQ14: =58732/30 -> 1957.7333 | AR14: ='[1]Cost.4.23'!AS14 -> 2174.8287 | AS14: =AC14+AI14 -> 2139.5728 | AV14: ='[1]Reading.4.24'!AE12/'[1]Cost.4.24'!F14 -> 114.8 | AW14: =(M14+T14)/F14 -> 159.4608 | AX14: =V14/F14 -> 2.032 | AY14: =Z14/F14 -> 9.87552 | AZ14: =AN14/F14 -> 2.294448 | BA14: =AS14/F14 -> 8.558291 | BC14: ='[1]Cost.4.23'!BE14 -> 43449.229 | BD14: =K14+R14+X14+AQ14 -> 48882.733 | BE14: =M14+T14+Z14+AS14 -> 44473.653 | BG14: ='[1]Cost.4.23'!BI14 -> 164.58041 | BH14: =BD14/H14 -> 145.70114 | BI14: =BE14/F14 -> 177.89461
B15: 45390 | D15: ='[1]Reading.4.24'!AI13 -> 0.4848 | F15: ='[1]Reading.4.24'!AM13 -> 255 | H15: ='[1]Reading.4.24'!AO13 -> 335.5 | J15: ='[1]Reading.4.24'!X13 -> 26560 | K15: =1306020/30 -> 43534 | L15: ='[1]Cost.4.23'!M15 -> 39156 | M15: =J15*1.39 -> 36918.4 | O15: ='[1]Reading.4.24'!T13 -> 0 | P15: =2217/30 -> 73.9 | Q15: ='[1]Reading.4.24'!AB13 -> 0 | R15: =14500/30 -> 483.33333 | S15: ='[1]Cost.4.23'!T15 -> 0 | T15: =O15*5.86 -> 0 | V15: ='[1]Reading.4.24'!G13 -> 527 | W15: =17949/30 -> 598.3 | X15: =87230/30 -> 2907.6667 | Y15: ='[1]Cost.4.23'!Z15 -> 2074.24 | Z15: ='[1]Reading.4.24'!G13*4.86 -> 2561.22 | AB15: ='[1]Reading.4.24'!O13 -> 401.07 | AC15: =AB15*3.73 -> 1495.9911 | AD15: =((15538/4)*3)/30 -> 388.45 | AE15: =((58732/4)*3)/30 -> 1468.3 | AF15: ='[1]Cost.4.23'!AB15 -> 424.12 | AG15: ='[1]Cost.4.23'!AC15 -> 1581.9676 | AH15: ='[1]Reading.4.24'!K13 -> 144.708 | AI15: =AH15*3.73 -> 539.76084 | AJ15: =(15538/4)/30 -> 129.48333 | AK15: =(58732/4)/30 -> 489.43333 | AL15: ='[1]Cost.4.23'!AH15 -> 144.708 | AM15: ='[1]Cost.4.23'!AI15 -> 539.76084 | AN15: =AB15+AH15 -> 545.778 | AO15: =AF15+AL15 -> 568.828 | AP15: =AD15+AJ15 -> 517.93333 | AQ15: =58732/30 -> 1957.7333 | AR15: ='[1]Cost.4.23'!AS15 -> 2121.7284 | AS15: =AC15+AI15 -> 2035.7519 | AV15: ='[1]Reading.4.24'!AE13/'[1]Cost.4.24'!F15 -> 104.15686 | AW15: =(M15+T15)/F15 -> 144.77804 | AX15: =V15/F15 -> 2.0666667 | AY15: =Z15/F15 -> 10.044 | AZ15: =AN15/F15 -> 2.1403059 | BA15: =AS15/F15 -> 7.9833409 | BC15: ='[1]Cost.4.23'!BE15 -> 43351.968 | BD15: =K15+R15+X15+AQ15 -> 48882.733 | BE15: =M15+T15+Z15+AS15 -> 41515.372 | BG15: ='[1]Cost.4.23'!BI15 -> 157.07235 | BH15: =BD15/H15 -> 145.70114 | BI15: =BE15/F15 -> 162.80538
B16: 45391 | D16: ='[1]Reading.4.24'!AI14 -> 0.5513 | F16: ='[1]Reading.4.24'!AM14 -> 290 | H16: ='[1]Reading.4.24'!AO14 -> 335.5 | J16: ='[1]Reading.4.24'!X14 -> 29960 | K16: =1306020/30 -> 43534 | L16: ='[1]Cost.4.23'!M16 -> 39260 | M16: =J16*1.39 -> 41644.4 | O16: ='[1]Reading.4.24'!T14 -> 0 | P16: =2217/30 -> 73.9 | Q16: ='[1]Reading.4.24'!AB14 -> 0 | R16: =14500/30 -> 483.33333 | S16: ='[1]Cost.4.23'!T16 -> 0 | T16: =O16*5.86 -> 0 | V16: ='[1]Reading.4.24'!G14 -> 540 | W16: =17949/30 -> 598.3 | X16: =87230/30 -> 2907.6667 | Y16: ='[1]Cost.4.23'!Z16 -> 2486.31 | Z16: ='[1]Reading.4.24'!G14*4.86 -> 2624.4 | AB16: ='[1]Reading.4.24'!O14 -> 419.51 | AC16: =AB16*3.73 -> 1564.7723 | AD16: =((15538/4)*3)/30 -> 388.45 | AE16: =((58732/4)*3)/30 -> 1468.3 | AF16: ='[1]Cost.4.23'!AB16 -> 391.85 | AG16: ='[1]Cost.4.23'!AC16 -> 1461.6005 | AH16: ='[1]Reading.4.24'!K14 -> 154.044 | AI16: =AH16*3.73 -> 574.58412 | AJ16: =(15538/4)/30 -> 129.48333 | AK16: =(58732/4)/30 -> 489.43333 | AL16: ='[1]Cost.4.23'!AH16 -> 130.704 | AM16: ='[1]Cost.4.23'!AI16 -> 487.52592 | AN16: =AB16+AH16 -> 573.554 | AO16: =AF16+AL16 -> 522.554 | AP16: =AD16+AJ16 -> 517.93333 | AQ16: =58732/30 -> 1957.7333 | AR16: ='[1]Cost.4.23'!AS16 -> 1949.1264 | AS16: =AC16+AI16 -> 2139.3564 | AV16: ='[1]Reading.4.24'!AE14/'[1]Cost.4.24'!F16 -> 103.31034 | AW16: =(M16+T16)/F16 -> 143.60138 | AX16: =V16/F16 -> 1.862069 | AY16: =Z16/F16 -> 9.0496552 | AZ16: =AN16/F16 -> 1.9777724 | BA16: =AS16/F16 -> 7.3770911 | BC16: ='[1]Cost.4.23'!BE16 -> 43695.436 | BD16: =K16+R16+X16+AQ16 -> 48882.733 | BE16: =M16+T16+Z16+AS16 -> 46408.156 | BG16: ='[1]Cost.4.23'!BI16 -> 166.77647 | BH16: =BD16/H16 -> 145.70114 | BI16: =BE16/F16 -> 160.02813
B17: 45392 | D17: ='[1]Reading.4.24'!AI15 -> 0.692 | F17: ='[1]Reading.4.24'!AM15 -> 364 | H17: ='[1]Reading.4.24'!AO15 -> 335.5 | J17: ='[1]Reading.4.24'!X15 -> 33080 | K17: =1306020/30 -> 43534 | L17: ='[1]Cost.4.23'!M17 -> 41132 | M17: =J17*1.39 -> 45981.2 | O17: ='[1]Reading.4.24'!T15 -> 0 | P17: =2217/30 -> 73.9 | Q17: ='[1]Reading.4.24'!AB15 -> 0 | R17: =14500/30 -> 483.33333 | S17: ='[1]Cost.4.23'!T17 -> 0 | T17: =O17*5.86 -> 0 | V17: ='[1]Reading.4.24'!G15 -> 599 | W17: =17949/30 -> 598.3 | X17: =87230/30 -> 2907.6667 | Y17: ='[1]Cost.4.23'!Z17 -> 2176.1 | Z17: ='[1]Reading.4.24'!G15*4.86 -> 2911.14 | AB17: ='[1]Reading.4.24'!O15 -> 497.88 | AC17: =AB17*3.73 -> 1857.0924 | AD17: =((15538/4)*3)/30 -> 388.45 | AE17: =((58732/4)*3)/30 -> 1468.3 | AF17: ='[1]Cost.4.23'!AB17 -> 414.9 | AG17: ='[1]Cost.4.23'!AC17 -> 1547.577 | AH17: ='[1]Reading.4.24'!K15 -> 247.404 | AI17: =AH17*3.73 -> 922.81692 | AJ17: =(15538/4)/30 -> 129.48333 | AK17: =(58732/4)/30 -> 489.43333 | AL17: ='[1]Cost.4.23'!AH17 -> 149.376 | AM17: ='[1]Cost.4.23'!AI17 -> 557.17248 | AN17: =AB17+AH17 -> 745.284 | AO17: =AF17+AL17 -> 564.276 | AP17: =AD17+AJ17 -> 517.93333 | AQ17: =58732/30 -> 1957.7333 | AR17: ='[1]Cost.4.23'!AS17 -> 2104.7495 | AS17: =AC17+AI17 -> 2779.9093 | AV17: ='[1]Reading.4.24'!AE15/'[1]Cost.4.24'!F17 -> 90.879121 | AW17: =(M17+T17)/F17 -> 126.32198 | AX17: =V17/F17 -> 1.6456044 | AY17: =Z17/F17 -> 7.9976374 | AZ17: =AN17/F17 -> 2.0474835 | BA17: =AS17/F17 -> 7.6371135 | BC17: ='[1]Cost.4.23'!BE17 -> 45412.849 | BD17: =K17+R17+X17+AQ17 -> 48882.733 | BE17: =M17+T17+Z17+AS17 -> 51672.249 | BG17: ='[1]Cost.4.23'!BI17 -> 181.6514 | BH17: =BD17/H17 -> 145.70114 | BI17: =BE17/F17 -> 141.95673
B18: 45393 | D18: ='[1]Reading.4.24'!AI16 -> 0.8384 | F18: ='[1]Reading.4.24'!AM16 -> 441 | H18: ='[1]Reading.4.24'!AO16 -> 335.5 | J18: ='[1]Reading.4.24'!X16 -> 34240 | K18: =1306020/30 -> 43534 | L18: ='[1]Cost.4.23'!M18 -> 39208 | M18: =J18*1.39 -> 47593.6 | O18: ='[1]Reading.4.24'!T16 -> 0 | P18: =2217/30 -> 73.9 | Q18: ='[1]Reading.4.24'!AB16 -> 0 | R18: =14500/30 -> 483.33333 | S18: ='[1]Cost.4.23'!T18 -> 0 | T18: =O18*5.86 -> 0 | V18: ='[1]Reading.4.24'!G16 -> 596 | W18: =17949/30 -> 598.3 | X18: =87230/30 -> 2907.6667 | Y18: ='[1]Cost.4.23'!Z18 -> 2185.36 | Z18: ='[1]Reading.4.24'!G16*4.86 -> 2896.56 | AB18: ='[1]Reading.4.24'!O16 -> 525.54 | AC18: =AB18*3.73 -> 1960.2642 | AD18: =((15538/4)*3)/30 -> 388.45 | AE18: =((58732/4)*3)/30 -> 1468.3 | AF18: ='[1]Cost.4.23'!AB18 -> 401.07 | AG18: ='[1]Cost.4.23'!AC18 -> 1495.9911 | AH18: ='[1]Reading.4.24'!K16 -> 196.056 | AI18: =AH18*3.73 -> 731.28888 | AJ18: =(15538/4)/30 -> 129.48333 | AK18: =(58732/4)/30 -> 489.43333 | AL18: ='[1]Cost.4.23'!AH18 -> 149.376 | AM18: ='[1]Cost.4.23'!AI18 -> 557.17248 | AN18: =AB18+AH18 -> 721.596 | AO18: =AF18+AL18 -> 550.446 | AP18: =AD18+AJ18 -> 517.93333 | AQ18: =58732/30 -> 1957.7333 | AR18: ='[1]Cost.4.23'!AS18 -> 2053.1636 | AS18: =AC18+AI18 -> 2691.5531 | AV18: ='[1]Reading.4.24'!AE16/'[1]Cost.4.24'!F18 -> 77.641723 | AW18: =(M18+T18)/F18 -> 107.922 | AX18: =V18/F18 -> 1.3514739 | AY18: =Z18/F18 -> 6.5681633 | AZ18: =AN18/F18 -> 1.6362721 | BA18: =AS18/F18 -> 6.103295 | BC18: ='[1]Cost.4.23'!BE18 -> 43446.524 | BD18: =K18+R18+X18+AQ18 -> 48882.733 | BE18: =M18+T18+Z18+AS18 -> 53181.713 | BG18: ='[1]Cost.4.23'!BI18 -> 171.04931 | BH18: =BD18/H18 -> 145.70114 | BI18: =BE18/F18 -> 120.59345
B19: 45394 | D19: ='[1]Reading.4.24'!AI17 -> 0.8574 | F19: ='[1]Reading.4.24'!AM17 -> 451 | H19: ='[1]Reading.4.24'!AO17 -> 335.5 | J19: ='[1]Reading.4.24'!X17 -> 35560 | K19: =1306020/30 -> 43534 | L19: ='[1]Cost.4.23'!M19 -> 37596 | M19: =J19*1.39 -> 49428.4 | O19: ='[1]Reading.4.24'!T17 -> 0 | P19: =2217/30 -> 73.9 | Q19: ='[1]Reading.4.24'!AB17 -> 0 | R19: =14500/30 -> 483.33333 | S19: ='[1]Cost.4.23'!T19 -> 0 | T19: =O19*5.86 -> 0 | V19: ='[1]Reading.4.24'!G17 -> 683 | W19: =17949/30 -> 598.3 | X19: =87230/30 -> 2907.6667 | Y19: ='[1]Cost.4.23'!Z19 -> 2375.19 | Z19: ='[1]Reading.4.24'!G17*4.86 -> 3319.38 | AB19: ='[1]Reading.4.24'!O17 -> 534.76 | AC19: =AB19*3.73 -> 1994.6548 | AD19: =((15538/4)*3)/30 -> 388.45 | AE19: =((58732/4)*3)/30 -> 1468.3 | AF19: ='[1]Cost.4.23'!AB19 -> 461 | AG19: ='[1]Cost.4.23'!AC19 -> 1719.53 | AH19: ='[1]Reading.4.24'!K17 -> 200.724 | AI19: =AH19*3.73 -> 748.70052 | AJ19: =(15538/4)/30 -> 129.48333 | AK19: =(58732/4)/30 -> 489.43333 | AL19: ='[1]Cost.4.23'!AH19 -> 168.048 | AM19: ='[1]Cost.4.23'!AI19 -> 626.81904 | AN19: =AB19+AH19 -> 735.484 | AO19: =AF19+AL19 -> 629.048 | AP19: =AD19+AJ19 -> 517.93333 | AQ19: =58732/30 -> 1957.7333 | AR19: ='[1]Cost.4.23'!AS19 -> 2346.349 | AS19: =AC19+AI19 -> 2743.3553 | AV19: ='[1]Reading.4.24'!AE17/'[1]Cost.4.24'!F19 -> 78.847007 | AW19: =(M19+T19)/F19 -> 109.59734 | AX19: =V19/F19 -> 1.5144124 | AY19: =Z19/F19 -> 7.3600443 | AZ19: =AN19/F19 -> 1.6307849 | BA19: =AS19/F19 -> 6.0828278 | BC19: ='[1]Cost.4.23'!BE19 -> 42317.539 | BD19: =K19+R19+X19+AQ19 -> 48882.733 | BE19: =M19+T19+Z19+AS19 -> 55491.135 | BG19: ='[1]Cost.4.23'!BI19 -> 169.27016 | BH19: =BD19/H19 -> 145.70114 | BI19: =BE19/F19 -> 123.04021
... B37: 45412 | D37: ='[1]Reading.4.24'!AI35 -> 0.5551 | F37: ='[1]Reading.4.24'!AM35 -> 291 | H37: ='[1]Reading.4.24'!AO35 -> 335.5 | J37: ='[1]Reading.4.24'!X35 -> 32560 | K37: =1306020/30 -> 43534 | L37: ='[1]Cost.4.23'!M37 -> 41652 | M37: =J37*1.39 -> 45258.4 | O37: ='[1]Reading.4.24'!T35 -> 0 | P37: =2217/30 -> 73.9 | Q37: ='[1]Reading.4.24'!AB35 -> 0 | R37: =14500/30 -> 483.33333 | S37: ='[1]Cost.4.23'!T37 -> 0 | T37: =O37*5.86 -> 0 | V37: ='[1]Reading.4.24'!G35 -> 512 | W37: =17949/30 -> 598.3 | X37: =87230/30 -> 2907.6667 | Y37: ='[1]Cost.4.23'!Z37 -> 1930.71 | Z37: ='[1]Reading.4.24'!G35*4.86 -> 2488.32 | AB37: ='[1]Reading.4.24'!O35 -> 461 | AC37: =AB37*3.73 -> 1719.53 | AD37: =((15538/4)*3)/30 -> 388.45 | AE37: =((58732/4)*3)/30 -> 1468.3 | AF37: ='[1]Cost.4.23'!AB37 -> 516.32 | AG37: ='[1]Cost.4.23'!AC37 -> 1925.8736 | AH37: ='[1]Reading.4.24'!K35 -> 154.044 | AI37: =AH37*3.73 -> 574.58412 | AJ37: =(15538/4)/30 -> 129.48333 | AK37: =(58732/4)/30 -> 489.43333 | AL37: ='[1]Cost.4.23'!AH37 -> 168.048 | AM37: ='[1]Cost.4.23'!AI37 -> 626.81904 | AN37: =AB37+AH37 -> 615.044 | AO37: =AF37+AL37 -> 684.368 | AP37: =AD37+AJ37 -> 517.93333 | AQ37: =58732/30 -> 1957.7333 | AR37: ='[1]Cost.4.23'!AS37 -> 2552.6926 | AS37: =AC37+AI37 -> 2294.1141 | AV37: ='[1]Reading.4.24'!AE35/'[1]Cost.4.24'!F37 -> 111.89003 | AW37: =(M37+T37)/F37 -> 155.52715 | AX37: =V37/F37 -> 1.7594502 | AY37: =Z37/F37 -> 8.5509278 | AZ37: =AN37/F37 -> 2.1135533 | BA37: =AS37/F37 -> 7.8835537 | BC37: ='[1]Cost.4.23'!BE37 -> 46135.403 | BD37: =K37+R37+X37+AQ37 -> 48882.733 | BE37: =M37+T37+Z37+AS37 -> 50040.834 | BG37: ='[1]Cost.4.23'!BI37 -> 160.75053 | BH37: =BD37/H37 -> 145.70114 | BI37: =BE37/F37 -> 171.96163
B39: TOTAL | D39: =AVERAGE(D8:D38) -> 0.63662 | F39: =SUM(F8:F38) -> 10046 | H39: =SUM(H8:H38) -> 10065 | J39: =SUM(J8:J38) -> 997240 | K39: =SUM(K8:K38) -> 1306020 | L39: =SUM(L8:L38) -> 1250028 | M39: =SUM(M8:M38) -> 1386163.6 | O39: =SUM(O8:O38) -> 0 | P39: =SUM(P8:P38) -> 2217 | Q39: =SUM(Q8:Q38) -> 20 | R39: =SUM(R8:R38) -> 14500 | S39: =SUM(S8:S38) -> 0 | T39: =SUM(T8:T38) -> 0 | V39: =SUM(V8:V38) -> 17102 | W39: =SUM(W8:W38) -> 17949 | X39: =SUM(X8:X38) -> 87230 | Y39: =SUM(Y8:Y38) -> 75274.54 | Z39: =SUM(Z8:Z38) -> 83115.72 | AB39: =SUM(AB8:AB38) -> 13899.15 | AC39: =SUM(AC8:AC38) -> 51843.829 | AD39: =SUM(AD8:AD38) -> 11653.5 | AE39: =SUM(AE8:AE38) -> 44049 | AF39: =SUM(AF8:AF38) -> 13779.29 | AG39: =SUM(AG8:AG38) -> 51396.752 | AH39: =SUM(AH8:AH38) -> 5111.46 | AI39: =SUM(AI8:AI38) -> 19065.746 | ... AS39: =SUM(AS8:AS38) -> 70909.575 | AV39: =AVERAGE(AV8:AV38) -> 100.78468 | AW39: =AVERAGE(AW8:AW38) -> 140.087 | AX39: =AVERAGE(AX8:AX38) -> 1.727975 | AY39: =AVERAGE(AY8:AY38) -> 8.3979585 | AZ39: =AVERAGE(AZ8:AZ38) -> 1.9173273 | BA39: =AVERAGE(BA8:BA38) -> 7.1516307 | BC39: =SUM(BC8:BC38) -> 1396687.9 | BD39: =SUM(BD8:BD38) -> 1466482 | BE39: =SUM(BE8:BE38) -> 1540188.9 | BG39: =BC39/'[1]Reading.4.24'!AN37 -> 155.41202 | BH39: =AVERAGE(BH8:BH38) -> 145.70114 | BI39: =AVERAGE(BI8:BI38) -> 155.63659
J42: =+J39/30 -> 33241.333 | K42: 0.64
J43: =+J42*K43 -> 27257.893 | K43: 0.82
J44: =+J43/K42 -> 42590.458 | L44: =+J44*30 -> 1277713.7
L46: =+L44*1.94 -> 2478764.7

Sheet Sheet1
B5: Daily Observations
B6: Time | C6: Temperature (° C) | F6: Dew Point (° C) | I6: Humidity (%) | L6: Wind Speed (mph) | O6: Pressure (Hg) | R6: Precipitation (in)
B7: Jun | C7: Max | D7: Avg | E7: Min | F7: Max | G7: Avg | H7: Min | I7: Max | J7: Avg | K7: Min | L7: Max | M7: Avg | N7: Min | O7: Max | P7: Avg | Q7: Min
B8: 1 | C8: 35 | D8: 29.8 | E8: 25 | F8: 14 | G8: 10.3 | H8: 7 | I8: 50 | J8: 31 | K8: 20 | L8: 37 | M8: 23.4 | N8: 4 | O8: 1003.9 | P8: 1002.9 | Q8: 1001.9
B9: 2 | C9: 39 | D9: 33.4 | E9: 26 | F9: 12 | G9: 8.6 | H9: 4 | I9: 42 | J9: 22.9 | K9: 14 | L9: 33 | M9: 13.8 | N9: 0 | O9: 1001.9 | P9: 1000.2 | Q9: 998.9
B10: 3 | C10: 33 | D10: 28.9 | E10: 24 | F10: 17 | G10: 12.1 | H10: 7 | I10: 65 | J10: 37.2 | K10: 20 | L10: 30 | M10: 16.3 | N10: 0 | O10: 1005.9 | P10: 1003.7 | Q10: 1001.9
B11: 4 | C11: 36 | D11: 31.1 | E11: 26 | F11: 15 | G11: 11.7 | H11: 10 | I11: 51 | J11: 31.3 | K11: 20 | L11: 30 | M11: 16.1 | N11: 6 | O11: 1004.9 | P11: 1003.4 | Q11: 1001.9
B12: 5 | C12: 36 | D12: 30.8 | E12: 26 | F12: 18 | G12: 15.1 | H12: 12 | I12: 61 | J12: 39.5 | K12: 28 | L12: 35 | M12: 25.1 | N12: 11 | O12: 1004.9 | P12: 1002.9 | Q12: 1000.9
B13: 6 | C13: 37 | D13: 31.4 | E13: 27 | F13: 17 | G13: 14.7 | H13: 11 | I13: 54 | J13: 37.6 | K13: 21 | L13: 28 | M13: 14.5 | N13: 0 | O13: 1004.9 | P13: 1002.6 | Q13: 1000.9
B14: 7 | C14: 39 | D14: 32.2 | E14: 28 | F14: 18 | G14: 15.3 | H14: 13 | I14: 48 | J14: 36.9 | K14: 22 | L14: 22 | M14: 9.2 | N14: 0 | O14: 1002.9 | P14: 1001 | Q14: 999.9
B15: 8 | C15: 39 | D15: 33.7 | E15: 26 | F15: 21 | G15: 15.5 | H15: 12 | I15: 51 | J15: 34.5 | K15: 20 | L15: 19 | M15: 8.4 | N15: 0 | O15: 1000.9 | P15: 999.3 | Q15: 997.9
B16: 9 | C16: 38 | D16: 33 | E16: 29 | F16: 16 | G16: 14.1 | H16: 12 | I16: 45 | J16: 32.3 | K16: 21 | L16: 28 | M16: 15.9 | N16: 6 | O16: 1001.9 | P16: 1000.1 | Q16: 998.9
B17: 10 | C17: 38 | D17: 33 | E17: 28 | F17: 17 | G17: 13.5 | H17: 9 | I17: 51 | J17: 32 | K17: 18 | L17: 37 | M17: 22.5 | N17: 9 | O17: 1002.9 | P17: 1001.9 | Q17: 1000.9
B18: 11 | C18: 38 | D18: 33.5 | E18: 29 | F18: 17 | G18: 14.2 | H18: 12 | I18: 45 | J18: 31.5 | K18: 22 | L18: 31 | M18: 23.9 | N18: 19 | O18: 1003.9 | P18: 1002.1 | Q18: 1000.9
B19: 12 | C19: 37 | D19: 31.9 | E19: 26 | F19: 17 | G19: 15.6 | H19: 14 | I19: 51 | J19: 37.9 | K19: 29 | L19: 44 | M19: 32.5 | N19: 20 | O19: 1002.9 | P19: 1001.6 | Q19: 1000.9
... B37: 30 | C37: 37 | D37: 33.7 | E37: 29 | F37: 15 | G37: 11.5 | H37: 8 | I37: 40 | J37: 26.3 | K37: 19 | L37: 26 | M37: 17.1 | N37: 7 | O37: 998.9 | P37: 997 | Q37: 996

Sheet Daily Consumption new
A2: Date: | B2: =TODAY()-1 -> 45752
A4: Energy Consumption
I5: Month To Date Energy Cost per Occupied Room
B6: Today | E6: Month To Date
B7: Actual | C7: Budget | D7: Last Year | E7: Actual | F7: Budget | G7: Last Year
A9: Occupied Rooms | B9: 274 | C9: ='Reading.4.25'!AO6 -> 341.9 | D9: 225 | E9: ='Reading.4.25'!AM36 -> 1366.1272 | F9: ='cost.4.25'!H38 -> 640.28571 | G9: ='Reading.4.25'!AN36 -> 793
A10: Occupancy | B10: 0.58 | C10: ='Reading.4.25'!AK6 -> 0.65 | D10: 0.43 | E10: ='Reading.4.25'!AI36 -> 0.86573333 | F10: ='Reading.4.25'!AK36:AK36 -> 0.65 | G10: ='Reading.4.25'!AJ36 -> 0.50253333
A12: Electricity - KWH | B12: ='Reading.4.25'!AE30 -> 0 | C12: ='Reading.4.25'!AG6 -> 26554.533 | D12: ='Reading.4.25'!AF30 -> 0 | E12: ='Reading.4.25'!AE36 -> 103620 | F12: ='Reading.4.25'!AG36 -> 79663.6 | G12: ='Reading.4.25'!AF36 -> 85480
A13: Fuel - Liter | B13: 0 | C13: ='cost.4.25'!P8 -> 83.967742 | D13: 0 | E13: ='Reading.4.25'!T36 -> 0 | F13: ='cost.4.25'!P38 -> 251.90323 | G13: ='Reading.4.25'!U36 -> 0
A15: Boilers Gas - Cu.Mt. | B15: ='Reading.4.25'!O30 -> 0 | C15: ='cost.4.25'!AD8 -> 487.5 | D15: ='Reading.4.25'!P30 -> 0 | E15: ='Reading.4.25'!O36 -> 2000.74 | F15: ='cost.4.25'!AD38 -> 1462.5 | G15: ='Reading.4.25'!P36 -> 1189.38
A16: Kitchens Gas - Cu. Mt. | B16: ='Reading.4.25'!K30 -> 0 | C16: ='cost.4.25'!AJ8 -> 162.5 | D16: ='Reading.4.25'!L30 -> 0 | E16: ='Reading.4.25'!K36 -> 830.904 | F16: ='cost.4.25'!AJ38 -> 487.5 | G16: ='Reading.4.25'!L36 -> 382.776
A18: Water To Staff House - Cu.Mt. | B18: ='Reading.4.25'!CJ30 -> 0 | C18: 0 | D18: 0 | E18: ='Reading.4.25'!#REF! -> #REF! | F18: 0 | G18: ='Reading.4.25'!BN36 -> 0
A19: Hotel Water - Cu.Mt. | B19: 493 | C19: 496 | D19: 529 | E19: ='Reading.4.25'!G36 -> 2284 | F19: ='cost.4.25'!W38 -> 1480.4516 | G19: ='Reading.4.25'!H36 -> 1517
A21: Total Energy Cost - L.E. | B21: ='cost.4.25'!BE32 -> 0 | C21: ='cost.4.25'!BD8 -> 71443.809 | D21: ='cost.4.25'!BC32 -> 0 | E21: ='cost.4.25'!BE38 -> 223030.78 | F21: ='cost.4.25'!BD38 -> 214331.43 | G21: ='cost.4.25'!BC38 -> 86837.264
A22: Energy Cost per Occupied Room | B22: =B21/B9 -> 0 | C22: =C21/C9 -> 208.96112 | D22: =D21/D9 -> 0 | E22: ='cost.4.25'!BI38 -> 163.33877 | F22: =F21/F9 -> 334.74341 | G22: =G21/G9 -> 109.50475
A23: Energy Cost per Available Room | B23: =B21/526 -> 0 | C23: =C21/526 -> 135.82473 | D23: =D22/D10 -> 0 | E23: =E21/(526*25) -> 16.960515 | F23: =F21/11572 -> 18.521554 | G23: =G22/G10 -> 217.90544
A24: Energy Forcast per Occupied Room | B24: =B22 -> 0 | C24: 213 | D24: =D23/D11 -> #DIV/0! | E24: =E22 -> 163.33877 | F24: =C24 -> 213 | G24: =G23/G11 -> #DIV/0!
A25: Energy Forcast per Available Room | B25: =B23 -> 0 | C25: 76.82 | D25: =D23/D11 -> #DIV/0! | E25: =E23 -> 16.960515 | F25: =C25 -> 76.82 | G25: =G23/G11 -> #DIV/0!
A46: Month To Date Electricity Consumption | D46: Month To Date Boilers' Gas Consumption | I46: Month To Date Kitchens' Gas Consumption
D47: Laundry Performance | I47: Kitchens Performance
A48: Electricity Maximum Demand KW | B48: Today | D48: Target | E48: Last Year
B49: Actual | C49: Last Period | D49: This Period | E49: This Period
B50: ='Reading.4.25'!AQ36 -> 1332 | C50: ='Reading.4.25'!AQ37 -> 2216 | D50: 2180 | E50: 2120
A52: Weather Temperature ⁰C | B52: Today | D52: Month To Date
B53: Actual | C53: Last year | D53: Actual | E53: Last Year
B54: 36 | C54: 31 | D54: ='Reading.4.25'!BC36 -> 16 | E54: ='Reading.4.25'!BG36 -> 80
A55: Humidity % | B55: 50 | C55: 60 | D55: ='Reading.4.25'!BF36 -> 25 | E55: ='Reading.4.25'!BJ36 -> 56
A57: Comments:

Sheet Sheet2

Sheet Sheet3
