Workbook
Name شت8: 'cost.5.25'!$H$18

Sheet Total
A1: Site Name | B1: Day | C1: Month | D1: Year | E1: Total Electricity Kwh | F1: Electricity Tariff ($/Kwh) | G1: LPG (Liters) | H1: LPG $/Liters | I1: Total Fuel Oil (Liter) | J1: Fuel Oil $/Liter | K1: Water Utility Supply (m3) m3 | L1: Water Utility Supply (m3) $/m3 | M1: Room Nights | N1: Total Guests
A2: Grand Rotana Sharm El Sheikh | B2: 1 | C2: 5 | D2: 2025 | E2: ='cost.5.25'!J8 -> 37560 | F2: 1.49 | G2: ='cost.5.25'!AN8 -> 934.352 | H2: ='cost.5.25'!AS8/'cost.5.25'!AN8 -> 3.8028413 | I2: ='cost.5.25'!O8 -> 0 | J2: ='cost.5.25'!T8/'cost.5.25'!O8 -> #DIV/0! | K2: ='cost.5.25'!V8 -> 704 | L2: ='cost.5.25'!Z8/'cost.5.25'!V8 -> 5.1 | M2: ='cost.5.25'!F8 -> 453.9906
A3: Grand Rotana Sharm El Sheikh | B3: =B2+1 -> 2 | C3: 5 | D3: 2025 | E3: ='cost.5.25'!J9 -> 37720 | F3: 1.49 | G3: ='cost.5.25'!AN9 -> 1097.848 | H3: ='cost.5.25'!AS9/'cost.5.25'!AN9 -> 3.8344705 | I3: ='cost.5.25'!O9 -> 0 | J3: ='cost.5.25'!T9/'cost.5.25'!O9 -> #DIV/0! | K3: ='cost.5.25'!V9 -> 712 | L3: ='cost.5.25'!Z9/'cost.5.25'!V9 -> 5.1 | M3: ='cost.5.25'!F9 -> 453.9906
A4: Grand Rotana Sharm El Sheikh | B4: =B3+1 -> 3 | C4: 5 | D4: 2025 | E4: ='cost.5.25'!J10 -> 37240 | F4: 1.49 | G4: ='cost.5.25'!AN10 -> 808.316 | H4: ='cost.5.25'!AS10/'cost.5.25'!AN10 -> 3.7720995 | I4: ='cost.5.25'!O10 -> 0 | J4: ='cost.5.25'!T10/'cost.5.25'!O10 -> #DIV/0! | K4: ='cost.5.25'!V10 -> 576 | L4: ='cost.5.25'!Z10/'cost.5.25'!V10 -> 5.1 | M4: ='cost.5.25'!F10 -> 453.9906
A5: Grand Rotana Sharm El Sheikh | B5: =B4+1 -> 4 | C5: 5 | D5: 2025 | E5: ='cost.5.25'!J11 -> 37240 | F5: 1.49 | G5: ='cost.5.25'!AN11 -> 892.514 | H5: ='cost.5.25'!AS11/'cost.5.25'!AN11 -> 3.797783 | I5: ='cost.5.25'!O11 -> 0 | J5: ='cost.5.25'!T11/'cost.5.25'!O11 -> #DIV/0! | K5: ='cost.5.25'!V11 -> 719 | L5: ='cost.5.25'!Z11/'cost.5.25'!V11 -> 5.1 | M5: ='cost.5.25'!F11 -> 390.9758
A6: Grand Rotana Sharm El Sheikh | B6: =B5+1 -> 5 | C6: 5 | D6: 2025 | E6: ='cost.5.25'!J12 -> 32320 | F6: 1.49 | G6: ='cost.5.25'!AN12 -> 915.97 | H6: ='cost.5.25'!AS12/'cost.5.25'!AN12 -> 3.8056791 | I6: ='cost.5.25'!O12 -> 0 | J6: ='cost.5.25'!T12/'cost.5.25'!O12 -> #DIV/0! | K6: ='cost.5.25'!V12 -> 688 | L6: ='cost.5.25'!Z12/'cost.5.25'!V12 -> 5.1 | M6: ='cost.5.25'!F12 -> 377.9836
A7: Grand Rotana Sharm El Sheikh | B7: =B6+1 -> 6 | C7: 5 | D7: 2025 | E7: ='cost.5.25'!J13 -> 35720 | F7: 1.49 | G7: ='cost.5.25'!AN13 -> 851.256 | H7: ='cost.5.25'!AS13/'cost.5.25'!AN13 -> 3.8069906 | I7: ='cost.5.25'!O13 -> 0 | J7: ='cost.5.25'!T13/'cost.5.25'!O13 -> #DIV/0! | K7: ='cost.5.25'!V13 -> 644 | L7: ='cost.5.25'!Z13/'cost.5.25'!V13 -> 5.1 | M7: ='cost.5.25'!F13 -> 347.0022
A8: Grand Rotana Sharm El Sheikh | B8: =B7+1 -> 7 | C8: 5 | D8: 2025 | E8: ='cost.5.25'!J14 -> 39120 | F8: 1.49 | G8: ='cost.5.25'!AN14 -> 893.094 | H8: ='cost.5.25'!AS14/'cost.5.25'!AN14 -> 3.8118513 | I8: ='cost.5.25'!O14 -> 0 | J8: ='cost.5.25'!T14/'cost.5.25'!O14 -> #DIV/0! | K8: ='cost.5.25'!V14 -> 707 | L8: ='cost.5.25'!Z14/'cost.5.25'!V14 -> 5.1 | M8: ='cost.5.25'!F14 -> 442.103
A9: Grand Rotana Sharm El Sheikh | B9: =B8+1 -> 8 | C9: 5 | D9: 2025 | E9: ='cost.5.25'!J15 -> 38960 | F9: 1.49 | G9: ='cost.5.25'!AN15 -> 980.684 | H9: ='cost.5.25'!AS15/'cost.5.25'!AN15 -> 3.8045407 | I9: ='cost.5.25'!O15 -> 0 | J9: ='cost.5.25'!T15/'cost.5.25'!O15 -> #DIV/0! | K9: ='cost.5.25'!V15 -> 692 | L9: ='cost.5.25'!Z15/'cost.5.25'!V15 -> 5.1 | M9: ='cost.5.25'!F15 -> 417.0128
A10: Grand Rotana Sharm El Sheikh | B10: =B9+1 -> 9 | C10: 5 | D10: 2025 | E10: ='cost.5.25'!J16 -> 0 | F10: 1.49 | G10: ='cost.5.25'!AN16 -> 0 | H10: ='cost.5.25'!AS16/'cost.5.25'!AN16 -> #DIV/0! | I10: ='cost.5.25'!O16 -> 0 | J10: ='cost.5.25'!T16/'cost.5.25'!O16 -> #DIV/0! | K10: ='cost.5.25'!V16 -> 0 | L10: ='cost.5.25'!Z16/'cost.5.25'!V16 -> #DIV/0! | M10: ='cost.5.25'!F16 -> 0
A11: Grand Rotana Sharm El Sheikh | B11: =B10+1 -> 10 | C11: 5 | D11: 2025 | E11: ='cost.5.25'!J17 -> 0 | F11: 1.49 | G11: ='cost.5.25'!AN17 -> 0 | H11: ='cost.5.25'!AS17/'cost.5.25'!AN17 -> #DIV/0! | I11: ='cost.5.25'!O17 -> 0 | J11: ='cost.5.25'!T17/'cost.5.25'!O17 -> #DIV/0! | K11: ='cost.5.25'!V17 -> 0 | L11: ='cost.5.25'!Z17/'cost.5.25'!V17 -> #DIV/0! | M11: ='cost.5.25'!F17 -> 0
A12: Grand Rotana Sharm El Sheikh | B12: =B11+1 -> 11 | C12: 5 | D12: 2025 | E12: ='cost.5.25'!J18 -> 0 | F12: 1.49 | G12: ='cost.5.25'!AN18 -> 0 | H12: ='cost.5.25'!AS18/'cost.5.25'!AN18 -> #DIV/0! | I12: ='cost.5.25'!O18 -> 0 | J12: ='cost.5.25'!T18/'cost.5.25'!O18 -> #DIV/0! | K12: ='cost.5.25'!V18 -> 0 | L12: ='cost.5.25'!Z18/'cost.5.25'!V18 -> #DIV/0! | M12: ='cost.5.25'!F18 -> 0
A13: Grand Rotana Sharm El Sheikh | B13: =B12+1 -> 12 | C13: 5 | D13: 2025 | E13: ='cost.5.25'!J19 -> 0 | F13: 1.49 | G13: ='cost.5.25'!AN19 -> 0 | H13: ='cost.5.25'!AS19/'cost.5.25'!AN19 -> #DIV/0! | I13: ='cost.5.25'!O19 -> 0 | J13: ='cost.5.25'!T19/'cost.5.25'!O19 -> #DIV/0! | K13: ='cost.5.25'!V19 -> 0 | L13: ='cost.5.25'!Z19/'cost.5.25'!V19 -> #DIV/0! | M13: ='cost.5.25'!F19 -> 0
A14: Grand Rotana Sharm El Sheikh | B14: =B13+1 -> 13 | C14: 5 | D14: 2025 | E14: ='cost.5.25'!J20 -> 0 | F14: 1.49 | G14: ='cost.5.25'!AN20 -> 0 | H14: ='cost.5.25'!AS20/'cost.5.25'!AN20 -> #DIV/0! | I14: ='cost.5.25'!O20 -> 0 | J14: ='cost.5.25'!T20/'cost.5.25'!O20 -> #DIV/0! | K14: ='cost.5.25'!V20 -> 0 | L14: ='cost.5.25'!Z20/'cost.5.25'!V20 -> #DIV/0! | M14: ='cost.5.25'!F20 -> 0
... A31: Grand Rotana Sharm El Sheikh | B31: =B30+1 -> 30 | C31: 5 | D31: 2025 | E31: ='cost.5.25'!J37 -> 0 | F31: 1.49 | G31: ='cost.5.25'!AN37 -> 0 | H31: ='cost.5.25'!AS37/'cost.5.25'!AN37 -> #DIV/0! | I31: ='cost.5.25'!O37 -> 0 | J31: ='cost.5.25'!T37/'cost.5.25'!O37 -> #DIV/0! | K31: ='cost.5.25'!V37 -> 0 | L31: ='cost.5.25'!Z37/'cost.5.25'!V37 -> #DIV/0! | M31: ='cost.5.25'!F37 -> 0
A32: Grand Rotana Sharm El Sheikh | B32: =B31+1 -> 31 | C32: 5 | D32: 2025 | I32: ='cost.5.25'!O39 -> 0 | J32: ='cost.5.25'!T39/'cost.5.25'!O39 -> #DIV/0!

Sheet Daily Consumption
A1: Date: | B1: =TODAY()-1 -> 45786
A2: Energy Consumption
L3: Month To Date Energy Cost per Occupied Room
B4: Today | F4: Month To Date
B5: Actual | C5: Budget | D5: Act Vs Bdgt | E5: Forecast | F5: Actual | G5: Budget | H5: Act Vs Bdgt | I5: Act Vs Forcast | J5: Forecast
A7: Occupied Rooms | B7: =VLOOKUP(B1,'Reading.5.25'!A5:EL36,39,FALSE) -> 0 | C7: 286 | D7: =B7-C7 -> -286 | E7: 399.48 | F7: ='Reading.5.25'!AM37 -> 3337.0492 | G7: =C7*DAY(B1) -> 2574 | H7: =(F7-G7)/F7 -> 0.22865986 | I7: =(F7-J7)/F7 -> -0.077394963 | J7: =E7*DAY(B1) -> 3595.32
A8: Occupancy | B8: =VLOOKUP(B1,'Reading.5.25'!A5:EL36,35,FALSE) -> 0 | C8: 0.545 | D8: =B8-C8 -> -0.545 | E8: 0.759 | F8: ='Reading.5.25'!AI37 -> 0.793025 | G8: =C8 -> 0.545 | H8: =F8-G8 -> 0.248025 | I8: =F8-J8 -> 0.034025 | J8: 0.759
A10: Electricity - KWH | B10: =VLOOKUP(B1,'Reading.5.25'!A5:EL36,31,FALSE) -> 0 | C10: ='Reading.5.25'!AG6 -> 38659.097 | D10: =B10-C10 -> -38659.097 | E10: 39000 | F10: ='Reading.5.25'!AE37 -> 295880 | G10: =C10*DAY(B1) -> 347931.87 | H10: =(F10-G10)/F10 -> -0.17592224 | I10: =(F10-J10)/F10 -> -0.18629174 | J10: =+E10*DAY(B1) -> 351000
A11: Fuel - Liter | B11: =VLOOKUP(B1,'Reading.5.25'!A5:EL36,20,FALSE) -> 0 | C11: ='cost.5.25'!P8 -> 0 | D11: =B11-C11 -> 0 | E11: 0 | F11: ='Reading.5.25'!T37 -> 0 | G11: =C11*DAY(B1) -> 0 | H11: =F11-G11 -> 0 | I11: =F11-J11 -> 0 | J11: 0
A13: Boilers Gas - Cu.Mt. | B13: =VLOOKUP(B1,'Reading.5.25'!A5:EL36,15,FALSE) -> 0 | C13: ='cost.5.25'!AD8 -> 522.72581 | D13: =B13-C13 -> -522.72581 | E13: 722 | F13: ='Reading.5.25'!O37 -> 5306.11 | G13: =C13*DAY(B1) -> 4704.5323 | H13: =(F13-G13)/F13 -> 0.11337453 | I13: =(F13-J13)/F13 -> -0.22462595 | J13: =E13*DAY(B1) -> 6498
A14: Kitchens Gas - Cu. Mt. | B14: =VLOOKUP(B1,'Reading.5.25'!A5:EL36,11,FALSE) -> 0 | C14: ='cost.5.25'!AJ8 -> 174.24194 | D14: =B14-C14 -> -174.24194 | E14: 240 | F14: ='Reading.5.25'!K37 -> 2067.924 | G14: =C14*DAY(B1) -> 1568.1774 | H14: =(F14-G14)/F14 -> 0.24166584 | I14: =(F14-J14)/F14 -> -0.044525814 | J14: =E14*DAY(B1) -> 2160
H15: =F15-G15 -> 0
A16: Water To Staff House - Cu.Mt. | B16: =VLOOKUP(B1,'Reading.5.25'!A2:EL36,88,FALSE) -> 0 | C16: 0 | D16: =B16-C16 -> 0 | E16: 0 | F16: 0 | G16: 0 | H16: =F16-G16 -> 0 | J16: 0
A17: Laundry Water - Cu.Mt. | B17: =VLOOKUP(B1,'Reading.5.25'!A5:EL36,73,FALSE) -> 0 | C17: 0 | D17: =-B17-C17 -> 0 | E17: 0 | F17: ='Reading.5.25'!BU37 -> 453 | G17: 0 | H17: =F17-G17 -> 453 | J17: 0
A18: Kitchen Water - Cu.Mt. | B18: =VLOOKUP(B1,'Reading.5.25'!A5:EL36,69,FALSE) -> 0 | C18: 0 | D18: =B18-C18 -> 0 | E18: 0 | F18: ='Reading.5.25'!BQ37 -> 328 | G18: 0 | H18: =F18-G18 -> 328 | J18: 0
A19: Hotel Water - Cu.Mt. | B19: =VLOOKUP(B1,'Reading.5.25'!A5:EL36,6,FALSE) -> 0 | C19: ='cost.5.25'!W8 -> 607.90323 | D19: =B19-C19 -> -607.90323 | E19: 660 | F19: ='cost.5.25'!V39 -> 5442 | G19: ='cost.5.25'!W39 -> 4863.2258 | H19: =(F19-G19)/F19 -> 0.10635321 | I19: =(F19-J19)/F19 -> -0.091510474 | J19: =E19*DAY(B1) -> 5940
A21: Total Energy Cost - L.E. | B21: =VLOOKUP(B1,'cost.5.25'!B8:BI37,56,FALSE) -> 0 | C21: ='cost.5.25'!BD8 -> 86204.29 | D21: =B21-C21 -> -86204.29 | E21: =(E10*1.94)+(E19*5.1)+((E13+E14)*5) -> 83836 | F21: =+(F10*1.94)+((F13+F14)*5)+(F19*5.1) -> 638631.57 | G21: =C21*DAY(B1) -> 775838.61 | H21: =(F21-G21)/F21 -> -0.21484538 | I21: =(F21-J21)/F21 -> -0.18146994 | J21: =+(J10*1.94)+((J13+J14)*5)+(J19*5.1) -> 754524
A22: Energy Cost per Occupied Room | B22: =B21/B7 -> #DIV/0! | C22: =C21/C7 -> 301.4136 | D22: =B22-C22 -> #DIV/0! | E22: =E21/E7 -> 209.86282 | F22: =F21/F7 -> 191.37613 | G22: =G21/G7 -> 301.4136 | H22: =(F22-G22)/F22 -> -0.57498011 | I22: =(F22-J22)/F22 -> -0.096598718 | J22: =J21/J7 -> 209.86282
A23: Energy Cost per Available Room | B23: =B21/526 -> 0 | C23: =C21/526 -> 163.88648 | D23: =B23-C23 -> -163.88648 | E23: =E21/526 -> 159.38403 | F23: =F21/(526*DAY(B1)) -> 134.90316 | G23: =G21/(DAY(B1)*526) -> 163.88648 | H23: =(F23-G23)/F23 -> -0.21484538 | I23: =(F23-J23)/F23 -> -0.18146994 | J23: =J21/(526*DAY(B1)) -> 159.38403
A45: Month To Date Electricity Consumption | E45: Month To Date Energy Consumption | L45: Month To Date Kitchens' Gas Consumption
E46: Laundry Performance | L46: Kitchens Performance
A47: Electricity Maximum Demand KW | B47: Today | E47: Target | F47: Last Year | H47: Elec.(Kw)/Room | I47: Today | J47: MTD | K47: Budgeted | L47: Act. LE | M47: Budget LE | N47: Act Vs Bdg | O47: % Budget | P47: forcast | Q47: Act Vs Fos | R47: %forcast
B48: Actual | C48: Last Period | E48: This Period | F48: This Period | I48: =B10/B7 -> #DIV/0! | J48: =F10/F7 -> 88.66516 | K48: =C10/C7 -> 135.17167 | L48: ='cost.5.25'!M39 -> 574007.2 | M48: ='cost.5.25'!K39 -> 643545.29 | N48: =L48-M48 -> -69538.09 | O48: =(L48/M48)-1 -> -0.1080547 | P48: =J10*1.94 -> 680940 | Q48: =L48-P48 -> -106932.8 | R48: =(L48/P48)-1 -> -0.15703704
B49: ='Reading.5.25'!AQ37 -> 2056 | C49: ='Reading.5.25'!AQ38 -> 2216 | E49: 2180 | F49: 2120
A51: Weather Temperature ⁰C | B51: Today | E51: Month To Date | H51: Water(l)/Room | I51: Today | J51: MTD | K51: Budgeted | L51: Act. LE | M51: Budget LE | N51: Diff | O51: % | P51: forcast | Q51: Act Vs Fos | R51: % forcast
B52: Actual | C52: Last year | E52: Actual | F52: Last Year | I52: =B19/B7 -> #DIV/0! | J52: =F19/F7 -> 1.6307821 | K52: =C19/C7 -> 2.1255358 | L52: ='cost.5.25'!Z39 -> 27754.2 | M52: ='cost.5.25'!X39 -> 24803.097 | N52: =L52-M52 -> 2951.1032 | O52: =(L52/M52)-1 -> 0.11898124 | P52: =J19*5.1 -> 30294 | Q52: =L52-P52 -> -2539.8 | R52: =(L52/P52)-1 -> -0.083838384
B53: =VLOOKUP(B1,'Reading.5.25'!A5:EL36,55,FALSE) -> 0 | C53: =VLOOKUP(B1,'Reading.5.25'!A5:EL36,59,FALSE) -> 0 | E53: ='Reading.5.25'!BC37 -> 28.375 | F53: ='Reading.5.25'!BG37 -> 80
A54: Humidity % | B54: =VLOOKUP(B1,'Reading.5.25'!A5:EL36,58,FALSE) -> 0 | C54: 60 | E54: ='Reading.5.25'!BF37 -> 23.75 | F54: =VLOOKUP(B1,'Reading.5.25'!A5:EL36,62,FALSE) -> 0 | H54: Energy - MTD | I54: Energy - forcast | J54: Diff | K54: % | P54: Ro. Production | R54: =VLOOKUP(B1,'Reading.5.25'!A5:EL36,3,FALSE) -> 0
H55: =+F21 -> 638631.57 | I55: =+J21 -> 754524 | J55: =+H55-I55 -> -115892.43 | K55: =+(H55/I55)-1 -> -0.15359674 | P55: Hotel consumption | R55: =+B19 -> 0
A56: Comments: | P56: Diff. | R56: =+R54-R55 -> 0

Sheet Reading.5.25
A1: 1 | B1: 2 | C1: 3 | D1: 4 | E1: 5 | F1: 6 | G1: 7 | H1: 8 | I1: 9 | J1: 10 | K1: 11 | L1: 12 | M1: 13 | N1: 14 | O1: 15 | P1: 16 | Q1: 17 | R1: 18 | S1: 19 | T1: 20 | U1: 21 | V1: 22 | W1: 23 | X1: 24 | Y1: 25 | Z1: 26 | AA1: 27 | AB1: 28 | AC1: 29 | AD1: 30 | AE1: 31 | AF1: 32 | AG1: 33 | AH1: 34 | AI1: 35 | AJ1: 36 | AK1: 37 | AL1: 38 | AM1: 39 | AN1: 40 | AO1: 41 | AP1: 42 | AQ1: 43 | AR1: 44 | AS1: 45 | AT1: 46 | AU1: 47 | AV1: 48 | AW1: 49 | AX1: 50 | AY1: 51 | AZ1: 52 | BA1: 53 | BB1: 54 | BC1: 55 | BD1: 56 | BE1: 57 | BF1: 58 | BG1: 59 | BH1: 60 | BI1: 61 | BJ1: 62 | BK1: 63 | BL1: 64 | BM1: 65 | BN1: 66 | BO1: 67 | BP1: 68 | BQ1: 69 | BR1: 70 | BS1: 71 | BT1: 72 | BU1: 73 | BV1: 74 | BW1: 75 | BX1: 76 | BY1: 77 | BZ1: 78 | CA1: 79 | CB1: 80 | CC1: 81 | CD1: 82 | CE1: 83 | CF1: 84 | CG1: 85 | CH1: 86 | CI1: 87 | CJ1: 88 | CK1: 89 | CL1: 90 | CM1: 91 | CN1: 92 | CO1: 93 | CP1: 94 | CQ1: 95 | CR1: 96 | CS1: 97 | CT1: 98 | CU1: 99 | CV1: 100 | CW1: 101 | CX1: 102 | CY1: 103 | CZ1: 104 | DA1: 105 | DB1: 106 | DC1: 107 | DD1: 108 | DE1: 109 | DF1: 110 | DG1: 111 | DH1: 112 | DI1: 113 | DJ1: 114 | DK1: 115 | DL1: 116 | DM1: 117 | DN1: 118 | DO1: 119 | DP1: 120 | DQ1: 121 | DR1: 122 | DS1: 123 | DT1: 124 | DU1: 125 | DV1: 126 | DW1: 127 | DX1: 128 | DY1: 129 | DZ1: 130 | EA1: 131 | EB1: 132 | EC1: 133 | ED1: 134 | EE1: 135 | EF1: 136 | EG1: 137 | EH1: 138 | EI1: 139 | EJ1: 140 | EK1: 141 | EL1: 142
B2: WATER | J2: KITCHEN GAS | N2: BOILER GAS | R2: FUEL | W2: ELECTRICITY | AA2: GENERATORS | AE2: TOTAL KWH | AI2: Occupancy % | AM2: Rooms Occupied | AQ2: Max. Demand | AT2: Power Factor | AY2: More Data | BC2: Weather Temperature | BL2: Available Rooms | BN2: Water Sold Last Year | BP2: Kitchen Water | BT2: Laundry Water | BX2: Fountain Water | CB2: S. Pool Water | CF2: Heated Pool Water | CI2: Staff Houses Water | CM2: Total Facilities Cons. | CP2: STP | CV2: Dishwasher | CZ2: Staff Kitchen | DD2: Laundry Electricity | DH2: Kit. Equip. Electricity | DL2: Chiller 1 | DP2: Chiller 2 | DT2: Chiller 3 | DX2: Chilled Pumps KWH | DZ2: Total Chillers | EC2: RO Plant | EF2: Staff Kitchen Gas | EJ2: Rotary Oven Gas | EN2: Water Counter Reading | ES2: Jockey Pump | ET2: Consumption
A4: Date | B4: Reading | C4: Product. | D4: Sold | E4: Tanks Level | F4: Counters reading | G4: Consump. This Year | H4: Last Year | J4: Reading | K4: Consump. This Year | L4: Last Year | N4: Reading | O4: Consump. This Year | P4: Last Year | R4: Reading | S4: Add | T4: Consump. This Year | U4: Last Year | W4: Reading | X4: Consump. This Year | Y4: Consump. Last Year | AA4: Reading | AB4: Consump. This Year | AC4: Consump. Last Year | AE4: This Year | AF4: Last Year | AG4: Budget | AI4: This Year | AJ4: Last Year | AK4: Budget | AM4: This Year | AN4: Last Year | AO4: Budget | AQ4: This Year KW | AR4: Last Year KW | AT4: KVAR Reading | AU4: KVAR Cons. | AV4: Cos Ø | AY4: Last Year OCT 2023 | BC4: This Year - May 2025 | BG4: Last Year - May 2024 | BP4: Counter Reading | BQ4: Consumption This year | BR4: Consumption Last Year | BT4: Counter Reading | BU4: Consumption | BV4: Consumption Last Year | BX4: Counter Reading | BY4: Consumption | BZ4: Consumption Last Year | CB4: Counter Reading | CC4: Consumption | CD4: Consumption Last Year | CF4: Counter Reading | CG4: Consumption | CH4: Consumption Last Year | CI4: Counter Reading | CJ4: Consumption | CK4: Consumption Last Year | CM4: This Year | CN4: Last Year | CP4: Counter Reading | CQ4: Recycled Water this Year | CR4: % | CS4: Reccycled Water Last Year | CT4: % | CV4: Counter Reading | CW4: Cons. | CX4: Cons. Last Year | CZ4: Counter Reading | DA4: Cons. | DB4: Cons. Last Year | DD4: Counter Reading | DE4: Cons. | DF4: Cons. Last Year | DH4: Counter Reading | DI4: Cons. | DJ4: Cons. Last Year | DL4: Counter Reading | DM4: Cons. | DN4: Cons. Last Year | DP4: Counter Reading | DQ4: Cons. | DR4: Cons. Last Year | DT4: Counter Reading | DU4: Cons. | DV4: Cons. Last Year | DZ4: Cons. | EA4: Cons. Last Year | EC4: KWH This Year | ED4: KWH Last Year | EF4: Counter Reading | EG4: Cons. | EH4: Cons. Last Year | EJ4: Counter Reading | EK4: Cons. | EL4: Cons. Last Year | EN4: C1 | EO4: C2 | EP4: C3 | EQ4: Total
B5: 522960 | E5: 740 | G5: =F5+ET5 -> 0 | J5: 225832 | N5: 774830 | R5: 65800 | W5: 49176.42 | AA5: 536130 | AT5: 7598.27 | BL5: 526 | BP5: 81741 | BT5: 97835 | BX5: 4317 | CB5: 250320 | CF5: 9535 | CI5: 19771 | CP5: 100020 | CV5: 465 | CZ5: 2547 | DD5: 1768697 | DH5: 4002500 | DL5: 3419475 | DP5: 2948741 | DT5: 3592467 | DX5: 720 | EF5: 71926 | EJ5: 33433 | EN5: 41654 | EO5: 42689 | EP5: 40428 | ES5: 7950
A6: 45778 | B6: 523691 | C6: =B6-B5 -> 731 | E6: 785 | F6: =EQ6 -> 670 | G6: =F6+ET6 -> 704 | H6: ='[1]Reading.4.24'!G6 -> 505 | J6: 225886 | K6: =(J6-J5)*4.668 -> 252.072 | L6: ='[1]Reading.4.24'!K6 -> 112.032 | N6: 774978 | O6: =(N6-N5)*4.61 -> 682.28 | P6: ='[1]Reading.4.24'!O6 -> 391.85 | R6: 65800 | T6: =(R5+S5)-R6 -> 0 | U6: ='[1]Reading.4.24'!T6 -> 0 | W6: 49185.81 | X6: =(W6-W5)*4000 -> 37560 | Y6: ='[1]Reading.4.24'!X6 -> 27720 | AA6: 536130 | AB6: =AA6-AA5 -> 0 | AC6: ='[1]Reading.4.24'!AB6 -> 0 | AE6: =+X6+AB6 -> 37560 | AF6: ='[1]Reading.4.24'!AE6 -> 27720 | AG6: =1198432/31 -> 38659.097 | AI6: 0.8631 | AJ6: ='[1]Reading.4.24'!AI6 -> 0.5209 | AK6: 0.545 | AM6: =AI6*526 -> 453.9906 | AN6: ='[1]Reading.4.24'!AM6 -> 274 | AO6: =8880/31 -> 286.45161 | AQ6: =514*4 -> 2056 | AR6: ='[1]Reading.4.24'!AQ6 -> 1460 | AT6: 7599.69 | AU6: =(AT6-AT5)*4000 -> 5680 | AV6: =+X6/SQRT(((POWER((X6),2)+(POWER((AU6),2))))) -> 0.988758 | AY6: ='[1]Reading.4.24'!X6 -> 27720 | AZ6: ='[1]Reading.4.24'!Y6 -> 25200 | BA6: =AY6+AZ6 -> 52920 | BC6: 27 | BD6: 38 | BE6: 50 | BF6: 25 | BG6: 80 | BH6: ='[1]Reading.4.24'!BD6 -> 16.1 | BI6: ='[1]Reading.4.24'!BE6 -> 12 | BJ6: ='[1]Reading.4.24'!BF6 -> 56 | BL6: 526 | BN6: ='Reading.5.24'!BN4 -> 0 | BP6: 81780 | BQ6: =BP6-BP5 -> 39 | BR6: ='[1]Reading.4.24'!BQ6 -> 30 | BT6: 97888 | BU6: =BT6-BT5 -> 53 | BV6: ='[1]Reading.4.24'!BU6 -> 30 | BX6: 4317 | BY6: =BX6-BX5 -> 0 | BZ6: ='[1]Reading.4.24'!BY6 -> 11 | CB6: 250360 | CC6: =CB6-CB5 -> 40 | CD6: ='[1]Reading.4.24'!CC6 -> 30 | CF6: 9545 | CG6: =CF6-CF5 -> 10 | CH6: ='[1]Reading.4.24'!CG6 -> 10 | CI6: 19771 | CJ6: =CI6-CI5 -> 0 | CK6: ='[1]Reading.4.24'!CJ6 -> -3 | CM6: =BQ6+BU6+BY6+CC6+CJ6 -> 132 | CN6: =BR6+BV6+BZ6+CD6+CK6 -> 98 | CP6: 100570 | CQ6: =CP6-CP5 -> 550 | CR6: =CQ6/G6 -> 0.78125 | CS6: ='[1]Reading.4.24'!CN6 -> 135 | CT6: ='[1]Reading.4.24'!CR6 -> 0.67920792 | CV6: 466 | CW6: =CV6-CV5 -> 1 | CX6: ='[1]Reading.4.24'!CW6 -> 2 | CZ6: 2550 | DA6: =CZ6-CZ5 -> 3 | DB6: ='[1]Reading.4.24'!DA6 -> 3 | DD6: 1769802 | DE6: =DD6-DD5 -> 1105 | DF6: ='[1]Reading.4.24'!DE6 -> 757 | DH6: 4004282 | DI6: =DH6-DH5 -> 1782 | DJ6: ='[1]Reading.4.24'!DI6 -> 1866 | DL6: 3421750 | DM6: =DL6-DL5 -> 2275 | DN6: ='[1]Reading.4.24'!DM6 -> 3208 | DP6: 2951324 | DQ6: =DP6-DP5 -> 2583 | DR6: ='[1]Reading.4.24'!DQ6 -> 31 | DT6: 3593676 | DU6: =DT6-DT5 -> 1209 | DV6: ='[1]Reading.4.24'!DU6 -> 31 | DX6: 720 | DZ6: =DM6+DQ6+DU6+DX6 -> 6787 | EA6: ='Reading.5.24'!DZ6 -> 4474 | EC6: =C6*5.2 -> 3801.2 | ED6: ='[1]Reading.4.24'!EC6 -> 2158 | EF6: 72006 | EG6: =EF6-EF5 -> 80 | EH6: ='[1]Reading.4.24'!EG6 -> 40 | EJ6: 33464 | EK6: =EJ6-EJ5 -> 31 | EL6: ='[1]Reading.4.24'!EK6 -> 33 | EN6: 41654 | EO6: 43359 | EP6: 40428 | EQ6: =(EN6-EN5)+(EO6-EO5)+(EP6-EP5) -> 670 | ES6: 7984 | ET6: =+ES6-ES5 -> 34
A7: 45779 | B7: 524424 | C7: =B7-B6 -> 733 | E7: 785 | F7: =EQ7 -> 677 | G7: =F7+ET7 -> 712 | H7: ='Reading.5.24'!G7 -> 552 | J7: 225977 | K7: =(J7-J6)*4.668 -> 424.788 | L7: ='Reading.5.24'!K7 -> 177.384 | N7: 775124 | O7: =(N7-N6)*4.61 -> 673.06 | P7: ='Reading.5.24'!O7 -> 461 | R7: 65800 | T7: =(R6+S6)-R7 -> 0 | U7: ='Reading.5.24'!T7 -> 0 | W7: 49195.24 | X7: =(W7-W6)*4000 -> 37720 | Y7: ='Reading.5.24'!X7 -> 37120 | AA7: 536130 | AB7: =AA7-AA6 -> 0 | AC7: ='Reading.5.24'!AB7 -> 0 | AE7: =+X7+AB7 -> 37720 | AF7: ='Reading.5.24'!AE7 -> 37120 | AG7: =1198432/31 -> 38659.097 | AI7: 0.8631 | AJ7: ='Reading.5.24'!AI7 -> 0.7351 | AK7: 0.545 | AM7: =AI7*526 -> 453.9906 | AN7: ='Reading.5.24'!AM7 -> 371 | AO7: =8880/31 -> 286.45161 | AQ7: =514*4 -> 2056 | AR7: ='Reading.5.24'!AQ7 -> 1804 | AT7: 7601 | AU7: =(AT7-AT6)*4000 -> 5240 | AV7: =+X7/SQRT(((POWER((X7),2)+(POWER((AU7),2))))) -> 0.9904883 | AY7: ='Reading.5.24'!X7 -> 37120 | AZ7: ='Reading.5.24'!Y7 -> 32920 | BA7: =AY7+AZ7 -> 70040 | BC7: 27 | BD7: 38 | BE7: 50 | BF7: 25 | BG7: 80 | BH7: ='Reading.5.24'!BD7 -> 16.1 | BI7: ='Reading.5.24'!BE7 -> 12 | BJ7: ='Reading.5.24'!BF7 -> 56 | BL7: 526 | BN7: ='Reading.5.24'!BN5 -> 0 | BP7: 81822 | BQ7: =BP7-BP6 -> 42 | BR7: ='Reading.5.24'!BQ7 -> 32 | BT7: 97947 | BU7: =BT7-BT6 -> 59 | BV7: ='Reading.5.24'!BU7 -> 38 | BX7: 4317 | BY7: =BX7-BX6 -> 0 | BZ7: ='Reading.5.24'!BY7 -> 0 | CB7: 250400 | CC7: =CB7-CB6 -> 40 | CD7: ='Reading.5.24'!CC7 -> 40 | CF7: 9560 | CG7: =CF7-CF6 -> 15 | CH7: ='Reading.5.24'!CG7 -> 10 | CI7: 19771 | CJ7: =CI7-CI6 -> 0 | CK7: ='Reading.5.24'!CJ7 -> 0 | CM7: =BQ7+BU7+BY7+CC7+CJ7 -> 141 | CN7: =BR7+BV7+BZ7+CD7+CK7 -> 110 | CP7: 101100 | CQ7: =CP7-CP6 -> 530 | CR7: =CQ7/G7 -> 0.74438202 | CS7: ='Reading.5.24'!CN7 -> 131 | CT7: ='Reading.5.24'!CO7 -> 0 | CV7: 468 | CW7: =CV7-CV6 -> 2 | CX7: ='Reading.5.24'!CW7 -> 1 | CZ7: 2555 | DA7: =CZ7-CZ6 -> 5 | DB7: ='Reading.5.24'!DA7 -> 3 | DD7: 1770749 | DE7: =DD7-DD6 -> 947 | DF7: ='Reading.5.24'!DE7 -> 744 | DH7: 4006293 | DI7: =DH7-DH6 -> 2011 | DJ7: ='Reading.5.24'!DI7 -> 1936 | DL7: 3423324 | DM7: =DL7-DL6 -> 1574 | DN7: ='Reading.5.24'!DM7 -> 34 | DP7: 2952552 | DQ7: =DP7-DP6 -> 1228 | DR7: ='Reading.5.24'!DQ7 -> 1988 | DT7: 3594869 | DU7: =DT7-DT6 -> 1193 | DV7: ='Reading.5.24'!DU7 -> 2463 | DX7: 720 | DZ7: =DM7+DQ7+DU7+DX7 -> 4715 | EA7: ='Reading.5.24'!DZ7 -> 5205 | EC7: =C7*5.2 -> 3811.6 | ED7: ='Reading.5.24'!EC7 -> 2584.4 | EF7: 72084 | EG7: =EF7-EF6 -> 78 | EH7: ='Reading.5.24'!EG7 -> 54 | EJ7: 33492 | EK7: =EJ7-EJ6 -> 28 | EL7: ='Reading.5.24'!EK7 -> 22 | EN7: 41886 | EO7: 43394 | EP7: 40838 | EQ7: =(EN7-EN6)+(EO7-EO6)+(EP7-EP6) -> 677 | ES7: 8019 | ET7: =+ES7-ES6 -> 35
A8: 45780 | B8: 525157 | C8: =B8-B7 -> 733 | E8: 785 | F8: =EQ8 -> 544 | G8: =F8+ET8 -> 576 | H8: ='Reading.5.24'!G8 -> 591 | J8: 226004 | K8: =(J8-J7)*4.668 -> 126.036 | L8: ='Reading.5.24'!K8 -> 214.728 | N8: 775272 | O8: =(N8-N7)*4.61 -> 682.28 | P8: ='Reading.5.24'!O8 -> 451.78 | R8: 65800 | T8: =(R7+S7)-R8 -> 0 | U8: ='Reading.5.24'!T8 -> 0 | W8: 49204.55 | X8: =(W8-W7)*4000 -> 37240 | Y8: ='Reading.5.24'!X8 -> 36800 | AA8: 536130 | AB8: =AA8-AA7 -> 0 | AC8: ='Reading.5.24'!AB8 -> 0 | AE8: =+X8+AB8 -> 37240 | AF8: ='Reading.5.24'!AE8 -> 36800 | AG8: =1198432/31 -> 38659.097 | AI8: 0.8631 | AJ8: ='Reading.5.24'!AI8 -> 0.7529 | AK8: 0.545 | AM8: =AI8*526 -> 453.9906 | AN8: ='Reading.5.24'!AM8 -> 396 | AO8: =8880/31 -> 286.45161 | AQ8: =514*4 -> 2056 | AR8: ='Reading.5.24'!AQ8 -> 1900 | AT8: 7602.51 | AU8: =(AT8-AT7)*4000 -> 6040 | AV8: =+X8/SQRT(((POWER((X8),2)+(POWER((AU8),2))))) -> 0.98710095 | AY8: ='Reading.5.24'!X8 -> 36800 | AZ8: ='Reading.5.24'!Y8 -> 37280 | BA8: =AY8+AZ8 -> 74080 | BC8: 27 | BD8: 38 | BE8: 50 | BF8: 25 | BG8: 80 | BH8: ='Reading.5.24'!BD8 -> 17 | BI8: ='Reading.5.24'!BE8 -> 14 | BJ8: ='Reading.5.24'!BF8 -> 48 | BL8: 526 | BN8: ='Reading.5.24'!BN6 -> Sold | BP8: 81863 | BQ8: =BP8-BP7 -> 41 | BR8: ='Reading.5.24'!BQ8 -> 35 | BT8: 98000 | BU8: =BT8-BT7 -> 53 | BV8: ='Reading.5.24'!BU8 -> 40 | BX8: 4317 | BY8: =BX8-BX7 -> 0 | BZ8: ='Reading.5.24'!BY8 -> 0 | CB8: 250440 | CC8: =CB8-CB7 -> 40 | CD8: ='Reading.5.24'!CC8 -> 30 | CF8: 9575 | CG8: =CF8-CF7 -> 15 | CH8: ='Reading.5.24'!CG8 -> 5 | CI8: 19771 | CJ8: =CI8-CI7 -> 0 | CK8: ='Reading.5.24'!CJ8 -> 0 | CM8: =BQ8+BU8+BY8+CC8+CJ8 -> 134 | CN8: =BR8+BV8+BZ8+CD8+CK8 -> 105 | CP8: 101690 | CQ8: =CP8-CP7 -> 590 | CR8: =CQ8/G8 -> 1.0243056 | CS8: ='Reading.5.24'!CN8 -> 157 | CT8: ='Reading.5.24'!CO8 -> 0 | CV8: 470 | CW8: =CV8-CV7 -> 2 | CX8: ='Reading.5.24'!CW8 -> 2 | CZ8: 2559 | DA8: =CZ8-CZ7 -> 4 | DB8: ='Reading.5.24'!DA8 -> 5 | DD8: 1771665 | DE8: =DD8-DD7 -> 916 | DF8: ='Reading.5.24'!DE8 -> 810 | DH8: 4008224 | DI8: =DH8-DH7 -> 1931 | DJ8: ='Reading.5.24'!DI8 -> 1903 | DL8: 3424919 | DM8: =DL8-DL7 -> 1595 | DN8: ='Reading.5.24'!DM8 -> 33 | DP8: 2954025 | DQ8: =DP8-DP7 -> 1473 | DR8: ='Reading.5.24'!DQ8 -> 1973 | DT8: 3596112 | DU8: =DT8-DT7 -> 1243 | DV8: ='Reading.5.24'!DU8 -> 2614 | DX8: 720 | DZ8: =DM8+DQ8+DU8+DX8 -> 5031 | EA8: ='Reading.5.24'!DZ8 -> 5340 | EC8: =C8*5.2 -> 3811.6 | ED8: ='Reading.5.24'!EC8 -> 3073.2 | EF8: 72174 | EG8: =EF8-EF7 -> 90 | EH8: ='Reading.5.24'!EG8 -> 61 | EJ8: 33518 | EK8: =EJ8-EJ7 -> 26 | EL8: ='Reading.5.24'!EK8 -> 24 | EN8: 42123 | EO8: 43395 | EP8: 41144 | EQ8: =(EN8-EN7)+(EO8-EO7)+(EP8-EP7) -> 544 | ES8: 8051 | ET8: =+ES8-ES7 -> 32
A9: 45781 | B9: 525696 | C9: =B9-B8 -> 539 | E9: 825 | F9: =EQ9 -> 685 | G9: =F9+ET9 -> 719 | H9: ='Reading.5.24'!G9 -> 617 | J9: 226052 | K9: =(J9-J8)*4.668 -> 224.064 | L9: ='Reading.5.24'!K9 -> 186.72 | N9: 775417 | O9: =(N9-N8)*4.61 -> 668.45 | P9: ='Reading.5.24'!O9 -> 553.2 | R9: 65800 | T9: =(R8+S8)-R9 -> 0 | U9: ='Reading.5.24'!T9 -> 0 | W9: 49213.86 | X9: =(W9-W8)*4000 -> 37240 | Y9: ='Reading.5.24'!X9 -> 34880 | AA9: 536130 | AB9: =AA9-AA8 -> 0 | AC9: ='Reading.5.24'!AB9 -> 0 | AE9: =+X9+AB9 -> 37240 | AF9: ='Reading.5.24'!AE9 -> 34880 | AG9: =1198432/31 -> 38659.097 | AI9: 0.7433 | AJ9: ='Reading.5.24'!AI9 -> 0.6179 | AK9: 0.545 | AM9: =AI9*526 -> 390.9758 | AN9: ='Reading.5.24'!AM9 -> 325 | AO9: =8880/31 -> 286.45161 | AQ9: =514*4 -> 2056 | AR9: ='Reading.5.24'!AQ9 -> 1900 | AT9: 7603.86 | AU9: =(AT9-AT8)*4000 -> 5400 | AV9: =+X9/SQRT(((POWER((X9),2)+(POWER((AU9),2))))) -> 0.98964966 | AY9: ='Reading.5.24'!X9 -> 34880 | AZ9: ='Reading.5.24'!Y9 -> 34080 | BA9: =AY9+AZ9 -> 68960 | BC9: 27 | BD9: 38 | BE9: 50 | BF9: 25 | BG9: 80 | BH9: ='Reading.5.24'!BD9 -> 18 | BI9: ='Reading.5.24'!BE9 -> 14 | BJ9: ='Reading.5.24'!BF9 -> 52 | BL9: 526 | BN9: ='Reading.5.24'!BN7 -> 0 | BP9: 81899 | BQ9: =BP9-BP8 -> 36 | BR9: ='Reading.5.24'!BQ9 -> 31 | BT9: 98066 | BU9: =BT9-BT8 -> 66 | BV9: ='Reading.5.24'!BU9 -> 33 | BX9: 4317 | BY9: =BX9-BX8 -> 0 | BZ9: ='Reading.5.24'!BY9 -> 0 | CB9: 250480 | CC9: =CB9-CB8 -> 40 | CD9: ='Reading.5.24'!CC9 -> 40 | CF9: 9585 | CG9: =CF9-CF8 -> 10 | CH9: ='Reading.5.24'!CG9 -> 5 | CI9: 19771 | CJ9: =CI9-CI8 -> 0 | CK9: ='Reading.5.24'!CJ9 -> 0 | CM9: =BQ9+BU9+BY9+CC9+CJ9 -> 142 | CN9: =BR9+BV9+BZ9+CD9+CK9 -> 104 | CP9: 102230 | CQ9: =CP9-CP8 -> 540 | CR9: =CQ9/G9 -> 0.75104312 | CS9: ='Reading.5.24'!CN9 -> 312 | CT9: ='Reading.5.24'!CO9 -> 0 | CV9: 471 | CW9: =CV9-CV8 -> 1 | CX9: ='Reading.5.24'!CW9 -> 2 | CZ9: 2563 | DA9: =CZ9-CZ8 -> 4 | DB9: ='Reading.5.24'!DA9 -> 5 | DD9: 1772567 | DE9: =DD9-DD8 -> 902 | DF9: ='Reading.5.24'!DE9 -> 1116 | DH9: 4010194 | DI9: =DH9-DH8 -> 1970 | DJ9: ='Reading.5.24'!DI9 -> 1821 | DL9: 3426463 | DM9: =DL9-DL8 -> 1544 | DN9: ='Reading.5.24'!DM9 -> 15 | DP9: 2955419 | DQ9: =DP9-DP8 -> 1394 | DR9: ='Reading.5.24'!DQ9 -> 1907 | DT9: 3597401 | DU9: =DT9-DT8 -> 1289 | DV9: ='Reading.5.24'!DU9 -> 2409 | DX9: 720 | DZ9: =DM9+DQ9+DU9+DX9 -> 4947 | EA9: ='Reading.5.24'!DZ9 -> 5051 | EC9: =C9*5.2 -> 2802.8 | ED9: ='Reading.5.24'!EC9 -> 3208.4 | EF9: 72248 | EG9: =EF9-EF8 -> 74 | EH9: ='Reading.5.24'!EG9 -> 60 | EJ9: 33543 | EK9: =EJ9-EJ8 -> 25 | EL9: ='Reading.5.24'!EK9 -> 23 | EN9: 42595 | EO9: 43400 | EP9: 41352 | EQ9: =(EN9-EN8)+(EO9-EO8)+(EP9-EP8) -> 685 | ES9: 8085 | ET9: =+ES9-ES8 -> 34
A10: 45782 | B10: 526432 | C10: =B10-B9 -> 736 | E10: 880 | F10: =EQ10 -> 655 | G10: =F10+ET10 -> 688 | H10: ='Reading.5.24'!G10 -> 506 | J10: 226107 | K10: =(J10-J9)*4.668 -> 256.74 | L10: ='Reading.5.24'!K10 -> 196.056 | N10: 775560 | O10: =(N10-N9)*4.61 -> 659.23 | P10: ='Reading.5.24'!O10 -> 534.76 | R10: 65800 | T10: =(R9+S9)-R10 -> 0 | U10: ='Reading.5.24'!T10 -> 0 | W10: 49221.94 | X10: =(W10-W9)*4000 -> 32320 | Y10: ='Reading.5.24'!X10 -> 36240 | AA10: 536130 | AB10: =AA10-AA9 -> 0 | AC10: ='Reading.5.24'!AB10 -> 0 | AE10: =+X10+AB10 -> 32320 | AF10: ='Reading.5.24'!AE10 -> 36240 | AG10: =1198432/31 -> 38659.097 | AI10: 0.7186 | AJ10: ='Reading.5.24'!AI10 -> 0.557 | AK10: 0.545 | AM10: =AI10*526 -> 377.9836 | AN10: ='Reading.5.24'!AM10 -> 293 | AO10: =8880/31 -> 286.45161 | AQ10: =514*4 -> 2056 | AR10: ='Reading.5.24'!AQ10 -> 1900 | AT10: 7605.27 | AU10: =(AT10-AT9)*4000 -> 5640 | AV10: =+X10/SQRT(((POWER((X10),2)+(POWER((AU10),2))))) -> 0.98511316 | AY10: ='Reading.5.24'!X10 -> 36240 | AZ10: ='Reading.5.24'!Y10 -> 37760 | BA10: =AY10+AZ10 -> 74000 | BC10: 27 | BD10: 38 | BE10: 50 | BF10: 25 | BG10: 80 | BH10: ='Reading.5.24'!BD10 -> 17 | BI10: ='Reading.5.24'!BE10 -> 14 | BJ10: ='Reading.5.24'!BF10 -> 50 | BL10: 526 | BN10: ='Reading.5.24'!BN8 -> 0 | BP10: 81944 | BQ10: =BP10-BP9 -> 45 | BR10: ='Reading.5.24'!BQ10 -> 33 | BT10: 98125 | BU10: =BT10-BT9 -> 59 | BV10: ='Reading.5.24'!BU10 -> 43 | BX10: 4317 | BY10: =BX10-BX9 -> 0 | BZ10: ='Reading.5.24'!BY10 -> 0 | CB10: 250580 | CC10: =CB10-CB9 -> 100 | CD10: ='Reading.5.24'!CC10 -> 40 | CF10: 9595 | CG10: =CF10-CF9 -> 10 | CH10: ='Reading.5.24'!CG10 -> 5 | CI10: 19771 | CJ10: =CI10-CI9 -> 0 | CK10: ='Reading.5.24'!CJ10 -> 0 | CM10: =BQ10+BU10+BY10+CC10+CJ10 -> 204 | CN10: =BR10+BV10+BZ10+CD10+CK10 -> 116 | CP10: 102770 | CQ10: =CP10-CP9 -> 540 | CR10: =CQ10/G10 -> 0.78488372 | CS10: ='Reading.5.24'!CN10 -> 184 | CT10: ='Reading.5.24'!CO10 -> 0 | CV10: 473 | CW10: =CV10-CV9 -> 2 | CX10: ='Reading.5.24'!CW10 -> 1 | CZ10: 2568 | DA10: =CZ10-CZ9 -> 5 | DB10: ='Reading.5.24'!DA10 -> 4 | DD10: 1773398 | DE10: =DD10-DD9 -> 831 | DF10: ='Reading.5.24'!DE10 -> 1106 | DH10: 4012159 | DI10: =DH10-DH9 -> 1965 | DJ10: ='Reading.5.24'!DI10 -> 1915 | DL10: 3428012 | DM10: =DL10-DL9 -> 1549 | DN10: ='Reading.5.24'!DM10 -> 29 | DP10: 2956718 | DQ10: =DP10-DP9 -> 1299 | DR10: ='Reading.5.24'!DQ10 -> 709 | DT10: 3598590 | DU10: =DT10-DT9 -> 1189 | DV10: ='Reading.5.24'!DU10 -> 3500 | DX10: 720 | DZ10: =DM10+DQ10+DU10+DX10 -> 4757 | EA10: ='Reading.5.24'!DZ10 -> 4958 | EC10: =C10*5.2 -> 3827.2 | ED10: ='Reading.5.24'!EC10 -> 2631.2 | EF10: 72324 | EG10: =EF10-EF9 -> 76 | EH10: ='Reading.5.24'!EG10 -> 46 | EJ10: 33570 | EK10: =EJ10-EJ9 -> 27 | EL10: ='Reading.5.24'!EK10 -> 26 | EN10: 42918 | EO10: 43401 | EP10: 41683 | EQ10: =(EN10-EN9)+(EO10-EO9)+(EP10-EP9) -> 655 | ES10: 8118 | ET10: =+ES10-ES9 -> 33
A11: 45783 | B11: 527024 | C11: =B11-B10 -> 592 | E11: 860 | F11: =EQ11 -> 610 | G11: =F11+ET11 -> 644 | H11: ='Reading.5.24'!G11 -> 570 | J11: 226159 | K11: =(J11-J10)*4.668 -> 242.736 | L11: ='Reading.5.24'!K11 -> 154.044 | N11: 775692 | O11: =(N11-N10)*4.61 -> 608.52 | P11: ='Reading.5.24'!O11 -> 507.1 | R11: 65800 | T11: =(R10+S10)-R11 -> 0 | U11: ='Reading.5.24'!T11 -> 0 | W11: 49230.87 | X11: =(W11-W10)*4000 -> 35720 | Y11: ='Reading.5.24'!X11 -> 32200 | AA11: 536130 | AB11: =AA11-AA10 -> 0 | AC11: ='Reading.5.24'!AB11 -> 0 | AE11: =+X11+AB11 -> 35720 | AF11: ='Reading.5.24'!AE11 -> 32200 | AG11: =1198432/31 -> 38659.097 | AI11: 0.6597 | AJ11: ='Reading.5.24'!AI11 -> 0.4468 | AK11: 0.545 | AM11: =AI11*526 -> 347.0022 | AN11: ='Reading.5.24'!AM11 -> 235 | AO11: =8880/31 -> 286.45161 | AQ11: =514*4 -> 2056 | AR11: ='Reading.5.24'!AQ11 -> 1900 | AT11: 7606.71 | AU11: =(AT11-AT10)*4000 -> 5760 | AV11: =+X11/SQRT(((POWER((X11),2)+(POWER((AU11),2))))) -> 0.98724673 | AY11: ='Reading.5.24'!X11 -> 32200 | AZ11: ='Reading.5.24'!Y11 -> 37840 | BA11: =AY11+AZ11 -> 70040 | BC11: 27 | BD11: 38 | BE11: 50 | BF11: 25 | BG11: 80 | BH11: ='Reading.5.24'!BD11 -> 17 | BI11: ='Reading.5.24'!BE11 -> 14 | BJ11: ='Reading.5.24'!BF11 -> 50 | BL11: 526 | BN11: ='Reading.5.24'!BN9 -> 0 | BP11: 81989 | BQ11: =BP11-BP10 -> 45 | BR11: ='Reading.5.24'!BQ11 -> 33 | BT11: 98177 | BU11: =BT11-BT10 -> 52 | BV11: ='Reading.5.24'!BU11 -> 42 | BX11: 4317 | BY11: =BX11-BX10 -> 0 | BZ11: ='Reading.5.24'!BY11 -> 8 | CB11: 250620 | CC11: =CB11-CB10 -> 40 | CD11: ='Reading.5.24'!CC11 -> 30 | CF11: 9605 | CG11: =CF11-CF10 -> 10 | CH11: ='Reading.5.24'!CG11 -> 10 | CI11: 19771 | CJ11: =CI11-CI10 -> 0 | CK11: ='Reading.5.24'!CJ11 -> 0 | CM11: =BQ11+BU11+BY11+CC11+CJ11 -> 137 | CN11: =BR11+BV11+BZ11+CD11+CK11 -> 113 | CP11: 103330 | CQ11: =CP11-CP10 -> 560 | CR11: =CQ11/G11 -> 0.86956522 | CS11: ='Reading.5.24'!CN11 -> 121 | CT11: ='Reading.5.24'!CO11 -> 0 | CV11: 475 | CW11: =CV11-CV10 -> 2 | CX11: ='Reading.5.24'!CW11 -> 0 | CZ11: 2573 | DA11: =CZ11-CZ10 -> 5 | DB11: ='Reading.5.24'!DA11 -> 5 | DD11: 1774287 | DE11: =DD11-DD10 -> 889 | DF11: ='Reading.5.24'!DE11 -> 848 | DH11: 4014124 | DI11: =DH11-DH10 -> 1965 | DJ11: ='Reading.5.24'!DI11 -> 1724 | DL11: 3429523 | DM11: =DL11-DL10 -> 1511 | DN11: ='Reading.5.24'!DM11 -> 2756 | DP11: 2958102 | DQ11: =DP11-DP10 -> 1384 | DR11: ='Reading.5.24'!DQ11 -> -34 | DT11: 3599710 | DU11: =DT11-DT10 -> 1120 | DV11: ='Reading.5.24'!DU11 -> 1064 | DX11: 720 | DZ11: =DM11+DQ11+DU11+DX11 -> 4735 | EA11: ='Reading.5.24'!DZ11 -> 4506 | EC11: =C11*5.2 -> 3078.4 | ED11: ='Reading.5.24'!EC11 -> 3094 | EF11: 72400 | EG11: =EF11-EF10 -> 76 | EH11: ='Reading.5.24'!EG11 -> 24 | EJ11: 33597 | EK11: =EJ11-EJ10 -> 27 | EL11: ='Reading.5.24'!EK11 -> 22 | EN11: 43209 | EO11: 43401 | EP11: 42002 | EQ11: =(EN11-EN10)+(EO11-EO10)+(EP11-EP10) -> 610 | ES11: 8152 | ET11: =+ES11-ES10 -> 34
A12: 45784 | B12: 527698 | C12: =B12-B11 -> 674 | E12: 860 | F12: =EQ12 -> 674 | G12: =F12+ET12 -> 707 | H12: ='Reading.5.24'!G12 -> 620 | J12: 226217 | K12: =(J12-J11)*4.668 -> 270.744 | L12: ='Reading.5.24'!K12 -> 177.384 | N12: 775827 | O12: =(N12-N11)*4.61 -> 622.35 | P12: ='Reading.5.24'!O12 -> 525.54 | R12: 65800 | T12: =(R11+S11)-R12 -> 0 | U12: ='Reading.5.24'!T12 -> 0 | W12: 49240.65 | X12: =(W12-W11)*4000 -> 39120 | Y12: ='Reading.5.24'!X12 -> 30880 | AA12: 536130 | AB12: =AA12-AA11 -> 0 | AC12: ='Reading.5.24'!AB12 -> 0 | AE12: =+X12+AB12 -> 39120 | AF12: ='Reading.5.24'!AE12 -> 30880 | AG12: =1198432/31 -> 38659.097 | AI12: 0.8405 | AJ12: ='Reading.5.24'!AI12 -> 0.4373 | AK12: 0.545 | AM12: =AI12*526 -> 442.103 | AN12: ='Reading.5.24'!AM12 -> 230 | AO12: =8880/31 -> 286.45161 | AQ12: =514*4 -> 2056 | AR12: ='Reading.5.24'!AQ12 -> 1900 | AT12: 7608.1 | AU12: =(AT12-AT11)*4000 -> 5560 | AV12: =+X12/SQRT(((POWER((X12),2)+(POWER((AU12),2))))) -> 0.99005047 | AY12: ='Reading.5.24'!X12 -> 30880 | AZ12: ='Reading.5.24'!Y12 -> 35840 | BA12: =AY12+AZ12 -> 66720 | BC12: 32 | BD12: 22 | BE12: 50 | BF12: 20 | BG12: 80 | BH12: ='Reading.5.24'!BD12 -> 21 | BI12: ='Reading.5.24'!BE12 -> 17 | BJ12: ='Reading.5.24'!BF12 -> 50 | BL12: 526 | BN12: ='Reading.5.24'!BN10 -> 0 | BP12: 82026 | BQ12: =BP12-BP11 -> 37 | BR12: ='Reading.5.24'!BQ12 -> 32 | BT12: 98233 | BU12: =BT12-BT11 -> 56 | BV12: ='Reading.5.24'!BU12 -> 43 | BX12: 4317 | BY12: =BX12-BX11 -> 0 | BZ12: ='Reading.5.24'!BY12 -> 0 | CB12: 250660 | CC12: =CB12-CB11 -> 40 | CD12: ='Reading.5.24'!CC12 -> 100 | CF12: 9620 | CG12: =CF12-CF11 -> 15 | CH12: ='Reading.5.24'!CG12 -> 5 | CI12: 19771 | CJ12: =CI12-CI11 -> 0 | CK12: ='Reading.5.24'!CJ12 -> 0 | CM12: =BQ12+BU12+BY12+CC12+CJ12 -> 133 | CN12: =BR12+BV12+BZ12+CD12+CK12 -> 175 | CP12: 103850 | CQ12: =CP12-CP11 -> 520 | CR12: =CQ12/G12 -> 0.73550212 | CS12: ='Reading.5.24'!CN12 -> 138 | CT12: ='Reading.5.24'!CO12 -> 0 | CV12: 477 | CW12: =CV12-CV11 -> 2 | CX12: ='Reading.5.24'!CW12 -> 1 | CZ12: 2576 | DA12: =CZ12-CZ11 -> 3 | DB12: ='Reading.5.24'!DA12 -> 6 | DD12: 1775170 | DE12: =DD12-DD11 -> 883 | DF12: ='Reading.5.24'!DE12 -> 890 | DH12: 4015584 | DI12: =DH12-DH11 -> 1460 | DJ12: ='Reading.5.24'!DI12 -> 1910 | DL12: 3431546 | DM12: =DL12-DL11 -> 2023 | DN12: ='Reading.5.24'!DM12 -> 3592 | DP12: 2959770 | DQ12: =DP12-DP11 -> 1668 | DR12: ='Reading.5.24'!DQ12 -> 33 | DT12: 3600982 | DU12: =DT12-DT11 -> 1272 | DV12: ='Reading.5.24'!DU12 -> 32 | DX12: 720 | DZ12: =DM12+DQ12+DU12+DX12 -> 5683 | EA12: ='Reading.5.24'!DZ12 -> 4377 | EC12: =C12*5.2 -> 3504.8 | ED12: ='Reading.5.24'!EC12 -> 3224 | EF12: 72483 | EG12: =EF12-EF11 -> 83 | EH12: ='Reading.5.24'!EG12 -> 49 | EJ12: 33622 | EK12: =EJ12-EJ11 -> 25 | EL12: ='Reading.5.24'!EK12 -> 24 | EN12: 43209 | EO12: 43732 | EP12: 42345 | EQ12: =(EN12-EN11)+(EO12-EO11)+(EP12-EP11) -> 674 | ES12: 8185 | ET12: =+ES12-ES11 -> 33
A13: 45785 | B13: 528333 | C13: =B13-B12 -> 635 | E13: 860 | F13: =EQ13 -> 659 | G13: =F13+ET13 -> 692 | H13: ='Reading.5.24'!G13 -> 489 | J13: 226275 | K13: =(J13-J12)*4.668 -> 270.744 | L13: ='Reading.5.24'!K13 -> 205.392 | N13: 775981 | O13: =(N13-N12)*4.61 -> 709.94 | P13: ='Reading.5.24'!O13 -> 456.39 | R13: 65800 | T13: =(R12+S12)-R13 -> 0 | U13: ='Reading.5.24'!T13 -> 0 | W13: 49250.39 | X13: =(W13-W12)*4000 -> 38960 | Y13: ='Reading.5.24'!X13 -> 31680 | AA13: 536130 | AB13: =AA13-AA12 -> 0 | AC13: ='Reading.5.24'!AB13 -> 0 | AE13: =+X13+AB13 -> 38960 | AF13: ='Reading.5.24'!AE13 -> 31680 | AG13: =1198432/31 -> 38659.097 | AI13: 0.7928 | AJ13: ='Reading.5.24'!AI13 -> 0.4696 | AK13: 0.545 | AM13: =AI13*526 -> 417.0128 | AN13: ='Reading.5.24'!AM13 -> 247 | AO13: =8880/31 -> 286.45161 | AQ13: =514*4 -> 2056 | AR13: ='Reading.5.24'!AQ13 -> 1900 | AT13: 7609.44 | AU13: =(AT13-AT12)*4000 -> 5360 | AV13: =+X13/SQRT(((POWER((X13),2)+(POWER((AU13),2))))) -> 0.99066854 | AY13: ='Reading.5.24'!X13 -> 31680 | AZ13: ='Reading.5.24'!Y13 -> 34360 | BA13: =AY13+AZ13 -> 66040 | BC13: 33 | BD13: 23 | BE13: 50 | BF13: 20 | BG13: 80 | BH13: ='Reading.5.24'!BD13 -> 21 | BI13: ='Reading.5.24'!BE13 -> 17 | BJ13: ='Reading.5.24'!BF13 -> 49 | BL13: 526 | BN13: ='Reading.5.24'!BN11 -> 0 | BP13: 82069 | BQ13: =BP13-BP12 -> 43 | BR13: ='Reading.5.24'!BQ13 -> 30 | BT13: 98288 | BU13: =BT13-BT12 -> 55 | BV13: ='Reading.5.24'!BU13 -> 35 | BX13: 4317 | BY13: =BX13-BX12 -> 0 | BZ13: ='Reading.5.24'!BY13 -> 0 | CB13: 250710 | CC13: =CB13-CB12 -> 50 | CD13: ='Reading.5.24'!CC13 -> 40 | CF13: 9635 | CG13: =CF13-CF12 -> 15 | CH13: ='Reading.5.24'!CG13 -> 5 | CI13: 19771 | CJ13: =CI13-CI12 -> 0 | CK13: ='Reading.5.24'!CJ13 -> 0 | CM13: =BQ13+BU13+BY13+CC13+CJ13 -> 148 | CN13: =BR13+BV13+BZ13+CD13+CK13 -> 105 | CP13: 104440 | CQ13: =CP13-CP12 -> 590 | CR13: =CQ13/G13 -> 0.85260116 | CS13: ='Reading.5.24'!CN13 -> 118 | CT13: ='Reading.5.24'!CO13 -> 0 | CV13: 478 | CW13: =CV13-CV12 -> 1 | CX13: ='Reading.5.24'!CW13 -> 0 | CZ13: 2581 | DA13: =CZ13-CZ12 -> 5 | DB13: ='Reading.5.24'!DA13 -> 4 | DD13: 1776274 | DE13: =DD13-DD12 -> 1104 | DF13: ='Reading.5.24'!DE13 -> 702 | DH13: 4017364 | DI13: =DH13-DH12 -> 1780 | DJ13: ='Reading.5.24'!DI13 -> 1710 | DL13: 3433112 | DM13: =DL13-DL12 -> 1566 | DN13: ='Reading.5.24'!DM13 -> 3912 | DP13: 2961865 | DQ13: =DP13-DP12 -> 2095 | DR13: ='Reading.5.24'!DQ13 -> 34 | DT13: 3602097 | DU13: =DT13-DT12 -> 1115 | DV13: ='Reading.5.24'!DU13 -> 33 | DX13: 720 | DZ13: =DM13+DQ13+DU13+DX13 -> 5496 | EA13: ='Reading.5.24'!DZ13 -> 4699 | EC13: =C13*5.2 -> 3302 | ED13: ='Reading.5.24'!EC13 -> 2542.8 | EF13: 72557 | EG13: =EF13-EF12 -> 74 | EH13: ='Reading.5.24'!EG13 -> 51 | EJ13: 33648 | EK13: =EJ13-EJ12 -> 26 | EL13: ='Reading.5.24'!EK13 -> 21 | EN13: 43209 | EO13: 44391 | EP13: 42345 | EQ13: =(EN13-EN12)+(EO13-EO12)+(EP13-EP12) -> 659 | ES13: 8218 | ET13: =+ES13-ES12 -> 33
A14: 45786
A15: 45787
A16: 45788
A17: 45789
A18: 45790
A19: 45791
A20: 45792
A21: 45793
A22: 45794
A23: 45795
A24: 45796
A25: 45797
... A36: 45808
C37: =AVERAGE(C6:C36) -> 671.625 | G37: =SUM(G6:G36) -> 5442 | H37: =SUM(H6:H36) -> 4450 | K37: =SUM(K6:K36) -> 2067.924 | L37: =SUM(L6:L36) -> 1423.74 | O37: =SUM(O6:O36) -> 5306.11 | P37: =SUM(P6:P36) -> 3881.62 | S37: =SUM(S6:S36) -> 0 | T37: =SUM(T6:T36) -> 0 | U37: =SUM(U6:U36) -> 0 | X37: =SUM(X6:X36) -> 295880 | Y37: =SUM(Y6:Y36) -> 267520 | AB37: =SUM(AB6:AB36) -> 0 | AC37: =SUM(AC6:AC36) -> 0 | AE37: =SUM(AE6:AE36) -> 295880 | AF37: =SUM(AF6:AF36) -> 267520 | AG37: =SUM(AG6:AG36) -> 309272.77 | AI37: =AVERAGE(AI6:AI36) -> 0.793025 | AJ37: =AVERAGE(AJ6:AJ36) -> 0.5671875 | AK37: =AVERAGE(AK6:AK36) -> 0.545 | AM37: =SUM(AM6:AM36) -> 3337.0492 | AN37: =SUM(AN6:AN36) -> 2371 | AO37: =SUM(AO6:AO36) -> 2291.6129 | AQ37: =MAX(AQ6:AQ36) -> 2056 | AR37: =MAX(AR6:AR36) -> 1900 | AV37: =AVERAGE(AV6:AV36) -> 0.98863448 | AY37: =SUM(AY6:AY36) -> 267520 | AZ37: =SUM(AZ6:AZ36) -> 275280 | BA37: =SUM(BA6:BA36) -> 542800 | BC37: =AVERAGE(BC6:BC36) -> 28.375 | BD37: =AVERAGE(BD6:BD36) -> 34.125 | BE37: =AVERAGE(BE6:BE36) -> 50 | BF37: =AVERAGE(BF6:BF36) -> 23.75 | BG37: =AVERAGE(BG6:BG36) -> 80 | BH37: =AVERAGE(BH6:BH36) -> 17.9 | BI37: =AVERAGE(BI6:BI36) -> 14.25 | BJ37: =AVERAGE(BJ6:BJ36) -> 51.375 | BL37: =SUM(BL6:BL36) -> 4208 | BN37: =SUM(BN6:BN36) -> 0 | BQ37: =SUM(BQ6:BQ36) -> 328 | BR37: =SUM(BR6:BR36) -> 256 | BU37: =SUM(BU6:BU36) -> 453 | BV37: =SUM(BV6:BV36) -> 304 | BY37: =SUM(BY6:BY36) -> 0 | BZ37: =SUM(BZ6:BZ36) -> 19 | CC37: =SUM(CC6:CC36) -> 390 | CD37: =SUM(CD6:CD36) -> 350 | CG37: =SUM(CG6:CG36) -> 100 | CH37: =SUM(CH6:CH36) -> 55 | CJ37: =SUM(CJ6:CJ36) -> 0 | CK37: =SUM(CK6:CK36) -> -3 | CM37: =SUM(CM6:CM36) -> 1171 | CN37: =SUM(CN6:CN36) -> 926 | CQ37: =SUM(CQ6:CQ36) -> 4420 | CR37: =AVERAGE(CR13:CR36) -> 0.85260116 | CS37: ='[1]Reading.4.24'!CN35 -> 123 | CT37: ='[1]Reading.4.24'!CO35 -> #REF! | CW37: =SUM(CW6:CW36) -> 13 | CX37: ='[1]Reading.4.24'!CT37 -> 0.52997602 | DA37: =SUM(DA6:DA36) -> 34 | DB37: =SUM(DB6:DB36) -> 35 | DE37: =SUM(DE6:DE36) -> 7577 | DF37: =SUM(DF6:DF36) -> 6973 | DI37: =SUM(DI6:DI36) -> 14864 | DJ37: =SUM(DJ6:DJ36) -> 14785 | DM37: =SUM(DM6:DM36) -> 13637 | DN37: =SUM(DN6:DN36) -> 13579 | DQ37: =SUM(DQ6:DQ36) -> 13124 | DR37: =SUM(DR6:DR36) -> 6641 | DU37: =SUM(DU6:DU36) -> 9630 | DV37: =SUM(DV6:DV36) -> 12146 | DZ37: =SUM(DZ6:DZ36) -> 42151 | EA37: =SUM(EA6:EA36) -> 38610 | EC37: =SUM(EC6:EC36) -> 27939.6 | ED37: =SUM(ED6:ED36) -> 22516 | EG37: =SUM(EG6:EG36) -> 631 | EH37: =SUM(EH6:EH36) -> 385 | EK37: =SUM(EK6:EK36) -> 215 | EL37: =SUM(EL6:EL36) -> 195
C38: Average/Day | AP38: Last Period Max. Demand: | AQ38: 2216 | CQ38: 0
C39: =SUM(C6:C36) -> 5373 | AP39: This Period Max. Demand: | AQ39: 2160
B40: =+B31-B30 -> 0 | U40: ENERGY COST / OCCUPIED ROOM - LAST YEAR = | AB40: ='[1]cost.4.25'!BG38 -> 131.93838 | AC40: L.E. | AF40: OCCUPANCY - LAST YEAR = | AJ40: =AJ37 -> 0.5671875 | AM40: KWH / OCCUPIED ROOM - LAST YEAR | AR40: =AF37/AN37 -> 112.83003 | AY40: https://www.wunderground.com/history/monthly/eg/sharm-el-shiekh/HESH/date/2024-10
U41: ENERGY COST / OCCUPIED ROOM - THIS YEAR = | AB41: ='[1]cost.4.25'!BI38 -> 168.59449 | AC41: L.E. | AF41: OCCUPANCY - THIS YEAR = | AJ41: =AI37 -> 0.793025 | AM41: KWH / OCCU[PIED ROOM - THIS YEAR | AR41: =AE37/AM37 -> 88.66516 | BA41: 7598.27
N42: =X37*2 -> 591760 | U42: ENERGY COST / OCCUPIED ROOM - BUDGET = | AB42: ='[1]cost.4.25'!BH38 -> 334.74341 | AC42: L.E. | AF42: OCCUPANCY - BUDGET= | AJ42: =AK37 -> 0.545 | AM42: KWH / OCCUPIED ROOM - BUDGET | AR42: =AG37/AO37 -> 134.95856 | CC42: =229975+25 -> 230000
AM44: KWH / AVAILABLE ROOM - LAST YEAR | AR44: =AF37/BL37 -> 63.574144
AM45: KWH / AVAILABLE ROOM - THIS YEAR | AR45: =AE37/BL37 -> 70.313688
AM46: KWH / AVAILABLE ROOM - BUDGET | AR46: =AG37/BL37 -> 73.496382
DM81: .
BQ151: .

Sheet Sheet4

Sheet cost.5.25
H1: =H8*31 -> 6616.2857 | K1: =K8*31 -> 2493738 | P1: =P8*31 -> 0 | R1: =R8*31 -> 0 | W1: =W8*31 -> 18845 | X1: =X8*31 -> 96112 | AD1: =AD8*31 -> 16204.5 | AJ1: =AJ8*31 -> 5401.5 | AP1: =AP8*31 -> 21606 | AQ1: =AQ8*31 -> 82483
A2: Energy Cost May 2025 | AV2: Energy Cost - May 2024
B3: 1 | C3: 2 | D3: 3 | E3: 4 | F3: 5 | G3: 6 | H3: 7 | I3: 8 | J3: 9 | K3: 10 | L3: 11 | M3: 12 | N3: 13 | O3: 14 | P3: 15 | Q3: 16 | R3: 17 | S3: 18 | T3: 19 | U3: 20 | V3: 21 | W3: 22 | X3: 23 | Y3: 24 | Z3: 25 | AA3: 26 | AB3: 27 | AC3: 28 | AD3: 29 | AE3: 30 | AF3: 31 | AG3: 32 | AH3: 33 | AI3: 34 | AJ3: 35 | AK3: 36 | AL3: 37 | AM3: 38 | AN3: 39 | AO3: 40 | AP3: 41 | AQ3: 42 | AR3: 43 | AS3: 44 | AT3: 45 | AU3: 46 | AV3: 47 | AW3: 48 | AX3: 49 | AY3: 50 | AZ3: 51 | BA3: 52 | BB3: 53 | BC3: 54 | BD3: 55 | BE3: 56 | BF3: 57 | BG3: 58 | BH3: 59 | BI3: 60
J5: ELECTRICITY | O5: FUEL | V5: WATER | AB5: NATURAL GAS | AV5: ELECTRICITY | AX5: WATER | AZ5: NATURAL GAS | BC5: LAST YEAR TOTAL ENERGY L.E. | BD5: BUDGET TOTAL ENERGY L.E. | BE5: ACTUAL TOTAL ENERGY L.E. | BG5: ENERGY LAST YEAR / OCCUPIED ROOM | BH5: ENERGY BUDGET / OCCUPIED ROOM | BI5: ENERGY ACTUAL / OCCUPIED ROOM
B6: DATE | D6: Occ. | F6: Occupied Rooms | H6: Occupied Rooms Budget | J6: CONSUMP. KWH | K6: BUDGET L.E. | L6: LAST YEAR ACTUAL L.E. | M6: ACTUAL L.E. | O6: CONSUMP. LITRE | P6: BUDGET LITRE | Q6: GENERATOR KWH | R6: BUDGET L.E. | S6: LAST YEAR ACTUAL L.E. | T6: ACTUAL L.E. | V6: CONSUMP. M³ | W6: BUDGET M³ | X6: BUDGET L.E. | Y6: LAST YEAR ACTUAL L.E. | Z6: ACTUAL L.E. | AB6: BOILER CONSUMP. M³ | AC6: BOILER COST L.E. | AD6: BOILER BUDGET CONSUMP. M³ | AE6: BOILER BUDGET COST L.E. | AF6: BOILER CONSUMP. LAST YEAR M³ | AG6: BOILER COST LAST YEAR L.E. | AH6: KITCHEN CONSUMP. M³ | AI6: KITCHEN COST L.E. | AJ6: KITCHEN BUDGET CONSUMP. M³ | AK6: KITCHEN BUDGET COST L.E. | AL6: KITCHEN CONSUMP. LAST YEAR M³ | AM6: KITCHEN COST LAST YEAR L.E. | AN6: TOTAL CONSUMP. M³ | AO6: TOTAL CONSUMP. LAST YEAR M³ | AP6: BUDGET TOTAL CONSUMP. M³ | AQ6: BUDGET L.E. | AR6: LAST YEAR ACTUAL L.E. | AS6: ACTUAL L.E. | AV6: KWH / Occupied Room | AW6: L.E. / Occupied Room | AX6: Cu.Mt. / Occupied Room | AY6: L.E. / Occupied Room | AZ6: Cu.Mt. / Occupied Room | BA6: L.E. / Occupied Room
B8: 45778 | D8: ='Reading.5.25'!AI6 -> 0.8631 | F8: ='Reading.5.25'!AM6 -> 453.9906 | H8: =5976/28 -> 213.42857 | J8: ='Reading.5.25'!X6 -> 37560 | K8: =2493738/31 -> 80443.161 | L8: ='Cost.4.24'!M7 -> 0 | M8: =J8*1.94 -> 72866.4 | O8: ='Reading.5.25'!T6 -> 0 | P8: =0/31 -> 0 | Q8: ='Reading.5.25'!AB6 -> 0 | R8: =0/30 -> 0 | S8: ='Cost.4.24'!T7 -> 0 | T8: =O8*7.55 -> 0 | V8: ='Reading.5.25'!G6 -> 704 | W8: =18845/31 -> 607.90323 | X8: =96112/31 -> 3100.3871 | Y8: ='Cost.4.24'!Z7 -> 0 | Z8: ='Reading.5.25'!G6*5.1 -> 3590.4 | AB8: ='Reading.5.25'!O6 -> 682.28 | AC8: =AB8*3.73 -> 2544.9044 | AD8: =((21606/4)*3)/31 -> 522.72581 | AE8: =((92472/4)*3)/31 -> 2237.2258 | AF8: ='Cost.4.24'!AB7 -> 0 | AG8: ='Cost.4.24'!AC7 -> 0 | AH8: ='Reading.5.25'!K6 -> 252.072 | AI8: =AH8*4 -> 1008.288 | AJ8: =(21606/4)/31 -> 174.24194 | AK8: =(96112/4)/31 -> 775.09677 | AL8: ='Cost.4.24'!AH7 -> 0 | AM8: ='Cost.4.24'!AI7 -> 0 | AN8: =AB8+AH8 -> 934.352 | AO8: =AF8+AL8 -> 0 | AP8: =AD8+AJ8 -> 696.96774 | AQ8: =82483/31 -> 2660.7419 | AR8: ='Cost.4.24'!AS7 -> 0 | AS8: =AC8+AI8 -> 3553.1924 | AV8: ='Reading.5.25'!AE6/'cost.5.25'!F8 -> 82.732991 | AW8: =(M8+T8)/F8 -> 160.502 | AX8: =V8/F8 -> 1.5506929 | AY8: =Z8/F8 -> 7.9085338 | AZ8: =AN8/F8 -> 2.0580867 | BA8: =AS8/F8 -> 7.826577 | BC8: ='Cost.4.24'!BE7 -> 0 | BD8: =K8+R8+X8+AQ8 -> 86204.29 | BE8: =M8+T8+Z8+AS8 -> 80009.992 | BG8: ='Cost.4.24'!BI7 -> 0 | BH8: =BD8/H8 -> 403.9023 | BI8: =BE8/F8 -> 176.23711
B9: 45779 | D9: ='Reading.5.25'!AI7 -> 0.8631 | F9: ='Reading.5.25'!AM7 -> 453.9906 | H9: =5976/28 -> 213.42857 | J9: ='Reading.5.25'!X7 -> 37720 | K9: =2493738/31 -> 80443.161 | L9: ='Cost.4.24'!M8 -> 38530.8 | M9: =J9*1.94 -> 73176.8 | O9: ='Reading.5.25'!T7 -> 0 | P9: =0/31 -> 0 | Q9: ='Reading.5.25'!AB7 -> 0 | R9: =0/30 -> 0 | S9: ='Cost.4.24'!T8 -> 0 | T9: =O9*7.55 -> 0 | V9: ='Reading.5.25'!G7 -> 712 | W9: =18845/31 -> 607.90323 | X9: =96112/31 -> 3100.3871 | Y9: ='Cost.4.24'!Z8 -> 2454.3 | Z9: ='Reading.5.25'!G7*5.1 -> 3631.2 | AB9: ='Reading.5.25'!O7 -> 673.06 | AC9: =AB9*3.73 -> 2510.5138 | AD9: =((21606/4)*3)/31 -> 522.72581 | AE9: =((92472/4)*3)/31 -> 2237.2258 | AF9: ='Cost.4.24'!AB8 -> 391.85 | AG9: ='Cost.4.24'!AC8 -> 1461.6005 | AH9: ='Reading.5.25'!K7 -> 424.788 | AI9: =AH9*4 -> 1699.152 | AJ9: =(21606/4)/31 -> 174.24194 | AK9: =(96112/4)/31 -> 775.09677 | AL9: ='Cost.4.24'!AH8 -> 112.032 | AM9: ='Cost.4.24'!AI8 -> 417.87936 | AN9: =AB9+AH9 -> 1097.848 | AO9: =AF9+AL9 -> 503.882 | AP9: =AD9+AJ9 -> 696.96774 | AQ9: =82483/31 -> 2660.7419 | AR9: ='Cost.4.24'!AS8 -> 1879.4799 | AS9: =AC9+AI9 -> 4209.6658 | AV9: ='Reading.5.25'!AE7/'cost.5.25'!F9 -> 83.085421 | AW9: =(M9+T9)/F9 -> 161.18572 | AX9: =V9/F9 -> 1.5683144 | AY9: =Z9/F9 -> 7.9984035 | AZ9: =AN9/F9 -> 2.4182175 | BA9: =AS9/F9 -> 9.2725836 | BC9: ='Cost.4.24'!BE8 -> 42864.58 | BD9: =K9+R9+X9+AQ9 -> 86204.29 | BE9: =M9+T9+Z9+AS9 -> 81017.666 | BG9: ='Cost.4.24'!BI8 -> 156.44007 | BH9: =BD9/H9 -> 403.9023 | BI9: =BE9/F9 -> 178.4567
B10: 45780 | D10: ='Reading.5.25'!AI8 -> 0.8631 | F10: ='Reading.5.25'!AM8 -> 453.9906 | H10: =5976/28 -> 213.42857 | J10: ='Reading.5.25'!X8 -> 37240 | K10: =2493738/31 -> 80443.161 | L10: ='Cost.4.24'!M9 -> 39754 | M10: =J10*1.94 -> 72245.6 | O10: ='Reading.5.25'!T8 -> 0 | P10: =0/31 -> 0 | Q10: ='Reading.5.25'!AB8 -> 0 | R10: =0/30 -> 0 | S10: ='Cost.4.24'!T9 -> 0 | T10: =O10*7.55 -> 0 | V10: ='Reading.5.25'!G8 -> 576 | W10: =18845/31 -> 607.90323 | X10: =96112/31 -> 3100.3871 | Y10: ='Cost.4.24'!Z9 -> 2235.6 | Z10: ='Reading.5.25'!G8*5.1 -> 2937.6 | AB10: ='Reading.5.25'!O8 -> 682.28 | AC10: =AB10*3.73 -> 2544.9044 | AD10: =((21606/4)*3)/31 -> 522.72581 | AE10: =((92472/4)*3)/31 -> 2237.2258 | AF10: ='Cost.4.24'!AB9 -> 410.29 | AG10: ='Cost.4.24'!AC9 -> 1530.3817 | AH10: ='Reading.5.25'!K8 -> 126.036 | AI10: =AH10*4 -> 504.144 | AJ10: =(21606/4)/31 -> 174.24194 | AK10: =(96112/4)/31 -> 775.09677 | AL10: ='Cost.4.24'!AH9 -> 121.368 | AM10: ='Cost.4.24'!AI9 -> 452.70264 | AN10: =AB10+AH10 -> 808.316 | AO10: =AF10+AL10 -> 531.658 | AP10: =AD10+AJ10 -> 696.96774 | AQ10: =82483/31 -> 2660.7419 | AR10: ='Cost.4.24'!AS9 -> 1983.0843 | AS10: =AC10+AI10 -> 3049.0484 | AV10: ='Reading.5.25'!AE8/'cost.5.25'!F10 -> 82.02813 | AW10: =(M10+T10)/F10 -> 159.13457 | AX10: =V10/F10 -> 1.2687487 | AY10: =Z10/F10 -> 6.4706186 | AZ10: =AN10/F10 -> 1.7804686 | BA10: =AS10/F10 -> 6.7161047 | BC10: ='Cost.4.24'!BE9 -> 43972.684 | BD10: =K10+R10+X10+AQ10 -> 86204.29 | BE10: =M10+T10+Z10+AS10 -> 78232.248 | BG10: ='Cost.4.24'!BI9 -> 169.7787 | BH10: =BD10/H10 -> 403.9023 | BI10: =BE10/F10 -> 172.3213
B11: 45781 | D11: ='Reading.5.25'!AI9 -> 0.7433 | F11: ='Reading.5.25'!AM9 -> 390.9758 | H11: =5976/28 -> 213.42857 | J11: ='Reading.5.25'!X9 -> 37240 | K11: =2493738/31 -> 80443.161 | L11: ='Cost.4.24'!M10 -> 40532.4 | M11: =J11*1.94 -> 72245.6 | O11: ='Reading.5.25'!T9 -> 0 | P11: =0/31 -> 0 | Q11: ='Reading.5.25'!AB9 -> 0 | R11: =0/30 -> 0 | S11: ='Cost.4.24'!T10 -> 0 | T11: =O11*7.55 -> 0 | V11: ='Reading.5.25'!G9 -> 719 | W11: =18845/31 -> 607.90323 | X11: =96112/31 -> 3100.3871 | Y11: ='Cost.4.24'!Z10 -> 2682.72 | Z11: ='Reading.5.25'!G9*5.1 -> 3666.9 | AB11: ='Reading.5.25'!O9 -> 668.45 | AC11: =AB11*3.73 -> 2493.3185 | AD11: =((21606/4)*3)/31 -> 522.72581 | AE11: =((92472/4)*3)/31 -> 2237.2258 | AF11: ='Cost.4.24'!AB10 -> 387.24 | AG11: ='Cost.4.24'!AC10 -> 1444.4052 | AH11: ='Reading.5.25'!K9 -> 224.064 | AI11: =AH11*4 -> 896.256 | AJ11: =(21606/4)/31 -> 174.24194 | AK11: =(96112/4)/31 -> 775.09677 | AL11: ='Cost.4.24'!AH10 -> 149.376 | AM11: ='Cost.4.24'!AI10 -> 557.17248 | AN11: =AB11+AH11 -> 892.514 | AO11: =AF11+AL11 -> 536.616 | AP11: =AD11+AJ11 -> 696.96774 | AQ11: =82483/31 -> 2660.7419 | AR11: ='Cost.4.24'!AS10 -> 2001.5777 | AS11: =AC11+AI11 -> 3389.5745 | AV11: ='Reading.5.25'!AE9/'cost.5.25'!F11 -> 95.248862 | AW11: =(M11+T11)/F11 -> 184.78279 | AX11: =V11/F11 -> 1.8389885 | AY11: =Z11/F11 -> 9.3788414 | AZ11: =AN11/F11 -> 2.2827858 | BA11: =AS11/F11 -> 8.6695251 | BC11: ='Cost.4.24'!BE10 -> 45216.698 | BD11: =K11+R11+X11+AQ11 -> 86204.29 | BE11: =M11+T11+Z11+AS11 -> 79302.074 | BG11: ='Cost.4.24'!BI10 -> 173.91038 | BH11: =BD11/H11 -> 403.9023 | BI11: =BE11/F11 -> 202.83116
B12: 45782 | D12: ='Reading.5.25'!AI10 -> 0.7186 | F12: ='Reading.5.25'!AM10 -> 377.9836 | H12: =5976/28 -> 213.42857 | J12: ='Reading.5.25'!X10 -> 32320 | K12: =2493738/31 -> 80443.161 | L12: ='Cost.4.24'!M11 -> 39198 | M12: =J12*1.94 -> 62700.8 | O12: ='Reading.5.25'!T10 -> 0 | P12: =0/31 -> 0 | Q12: ='Reading.5.25'!AB10 -> 0 | R12: =0/30 -> 0 | S12: ='Cost.4.24'!T11 -> 0 | T12: =O12*7.55 -> 0 | V12: ='Reading.5.25'!G10 -> 688 | W12: =18845/31 -> 607.90323 | X12: =96112/31 -> 3100.3871 | Y12: ='Cost.4.24'!Z11 -> 2522.34 | Z12: ='Reading.5.25'!G10*5.1 -> 3508.8 | AB12: ='Reading.5.25'!O10 -> 659.23 | AC12: =AB12*3.73 -> 2458.9279 | AD12: =((21606/4)*3)/31 -> 522.72581 | AE12: =((92472/4)*3)/31 -> 2237.2258 | AF12: ='Cost.4.24'!AB11 -> 368.8 | AG12: ='Cost.4.24'!AC11 -> 1375.624 | AH12: ='Reading.5.25'!K10 -> 256.74 | AI12: =AH12*4 -> 1026.96 | AJ12: =(21606/4)/31 -> 174.24194 | AK12: =(96112/4)/31 -> 775.09677 | AL12: ='Cost.4.24'!AH11 -> 158.712 | AM12: ='Cost.4.24'!AI11 -> 591.99576 | AN12: =AB12+AH12 -> 915.97 | AO12: =AF12+AL12 -> 527.512 | AP12: =AD12+AJ12 -> 696.96774 | AQ12: =82483/31 -> 2660.7419 | AR12: ='Cost.4.24'!AS11 -> 1967.6198 | AS12: =AC12+AI12 -> 3485.8879 | AV12: ='Reading.5.25'!AE10/'cost.5.25'!F12 -> 85.506355 | AW12: =(M12+T12)/F12 -> 165.88233 | AX12: =V12/F12 -> 1.8201848 | AY12: =Z12/F12 -> 9.2829424 | AZ12: =AN12/F12 -> 2.4233062 | BA12: =AS12/F12 -> 9.2223258 | BC12: ='Cost.4.24'!BE11 -> 43687.96 | BD12: =K12+R12+X12+AQ12 -> 86204.29 | BE12: =M12+T12+Z12+AS12 -> 69695.488 | BG12: ='Cost.4.24'!BI11 -> 152.7551 | BH12: =BD12/H12 -> 403.9023 | BI12: =BE12/F12 -> 184.3876
B13: 45783 | D13: ='Reading.5.25'!AI11 -> 0.6597 | F13: ='Reading.5.25'!AM11 -> 347.0022 | H13: =5976/28 -> 213.42857 | J13: ='Reading.5.25'!X11 -> 35720 | K13: =2493738/31 -> 80443.161 | L13: ='Cost.4.24'!M12 -> 41811.2 | M13: =J13*1.94 -> 69296.8 | O13: ='Reading.5.25'!T11 -> 0 | P13: =0/31 -> 0 | Q13: ='Reading.5.25'!AB11 -> 0 | R13: =0/30 -> 0 | S13: ='Cost.4.24'!T12 -> 0 | T13: =O13*7.55 -> 0 | V13: ='Reading.5.25'!G11 -> 644 | W13: =18845/31 -> 607.90323 | X13: =96112/31 -> 3100.3871 | Y13: ='Cost.4.24'!Z12 -> 2668.14 | Z13: ='Reading.5.25'!G11*5.1 -> 3284.4 | AB13: ='Reading.5.25'!O11 -> 608.52 | AC13: =AB13*3.73 -> 2269.7796 | AD13: =((21606/4)*3)/31 -> 522.72581 | AE13: =((92472/4)*3)/31 -> 2237.2258 | AF13: ='Cost.4.24'!AB12 -> 414.9 | AG13: ='Cost.4.24'!AC12 -> 1547.577 | AH13: ='Reading.5.25'!K11 -> 242.736 | AI13: =AH13*4 -> 970.944 | AJ13: =(21606/4)/31 -> 174.24194 | AK13: =(96112/4)/31 -> 775.09677 | AL13: ='Cost.4.24'!AH12 -> 158.712 | AM13: ='Cost.4.24'!AI12 -> 591.99576 | AN13: =AB13+AH13 -> 851.256 | AO13: =AF13+AL13 -> 573.612 | AP13: =AD13+AJ13 -> 696.96774 | AQ13: =82483/31 -> 2660.7419 | AR13: ='Cost.4.24'!AS12 -> 2139.5728 | AS13: =AC13+AI13 -> 3240.7236 | AV13: ='Reading.5.25'!AE11/'cost.5.25'!F13 -> 102.93883 | AW13: =(M13+T13)/F13 -> 199.70133 | AX13: =V13/F13 -> 1.855896 | AY13: =Z13/F13 -> 9.4650697 | AZ13: =AN13/F13 -> 2.4531718 | BA13: =AS13/F13 -> 9.3392019 | BC13: ='Cost.4.24'!BE12 -> 46618.913 | BD13: =K13+R13+X13+AQ13 -> 86204.29 | BE13: =M13+T13+Z13+AS13 -> 75821.924 | BG13: ='Cost.4.24'!BI12 -> 184.26448 | BH13: =BD13/H13 -> 403.9023 | BI13: =BE13/F13 -> 218.5056
B14: 45784 | D14: ='Reading.5.25'!AI12 -> 0.8405 | F14: ='Reading.5.25'!AM12 -> 442.103 | H14: =5976/28 -> 213.42857 | J14: ='Reading.5.25'!X12 -> 39120 | K14: =2493738/31 -> 80443.161 | L14: ='Cost.4.24'!M13 -> 41922.4 | M14: =J14*1.94 -> 75892.8 | O14: ='Reading.5.25'!T12 -> 0 | P14: =0/31 -> 0 | Q14: ='Reading.5.25'!AB12 -> 0 | R14: =0/30 -> 0 | S14: ='Cost.4.24'!T13 -> 0 | T14: =O14*7.55 -> 0 | V14: ='Reading.5.25'!G12 -> 707 | W14: =18845/31 -> 607.90323 | X14: =96112/31 -> 3100.3871 | Y14: ='Cost.4.24'!Z13 -> 2551.5 | Z14: ='Reading.5.25'!G12*5.1 -> 3605.7 | AB14: ='Reading.5.25'!O12 -> 622.35 | AC14: =AB14*3.73 -> 2321.3655 | AD14: =((21606/4)*3)/31 -> 522.72581 | AE14: =((92472/4)*3)/31 -> 2237.2258 | AF14: ='Cost.4.24'!AB13 -> 428.73 | AG14: ='Cost.4.24'!AC13 -> 1599.1629 | AH14: ='Reading.5.25'!K12 -> 270.744 | AI14: =AH14*4 -> 1082.976 | AJ14: =(21606/4)/31 -> 174.24194 | AK14: =(96112/4)/31 -> 775.09677 | AL14: ='Cost.4.24'!AH13 -> 149.376 | AM14: ='Cost.4.24'!AI13 -> 557.17248 | AN14: =AB14+AH14 -> 893.094 | AO14: =AF14+AL14 -> 578.106 | AP14: =AD14+AJ14 -> 696.96774 | AQ14: =82483/31 -> 2660.7419 | AR14: ='Cost.4.24'!AS13 -> 2156.3354 | AS14: =AC14+AI14 -> 3404.3415 | AV14: ='Reading.5.25'!AE12/'cost.5.25'!F14 -> 88.486167 | AW14: =(M14+T14)/F14 -> 171.66316 | AX14: =V14/F14 -> 1.5991749 | AY14: =Z14/F14 -> 8.1557917 | AZ14: =AN14/F14 -> 2.0201039 | BA14: =AS14/F14 -> 7.7003357 | BC14: ='Cost.4.24'!BE13 -> 46630.235 | BD14: =K14+R14+X14+AQ14 -> 86204.29 | BE14: =M14+T14+Z14+AS14 -> 82902.841 | BG14: ='Cost.4.24'!BI13 -> 170.80672 | BH14: =BD14/H14 -> 403.9023 | BI14: =BE14/F14 -> 187.51929
B15: 45785 | D15: ='Reading.5.25'!AI13 -> 0.7928 | F15: ='Reading.5.25'!AM13 -> 417.0128 | H15: =5976/28 -> 213.42857 | J15: ='Reading.5.25'!X13 -> 38960 | K15: =2493738/31 -> 80443.161 | L15: ='Cost.4.24'!M14 -> 39865.2 | M15: =J15*1.94 -> 75582.4 | O15: ='Reading.5.25'!T13 -> 0 | P15: =0/31 -> 0 | Q15: ='Reading.5.25'!AB13 -> 0 | R15: =0/30 -> 0 | S15: ='Cost.4.24'!T14 -> 0 | T15: =O15*7.55 -> 0 | V15: ='Reading.5.25'!G13 -> 692 | W15: =18845/31 -> 607.90323 | X15: =96112/31 -> 3100.3871 | Y15: ='Cost.4.24'!Z14 -> 2468.88 | Z15: ='Reading.5.25'!G13*5.1 -> 3529.2 | AB15: ='Reading.5.25'!O13 -> 709.94 | AC15: =AB15*3.73 -> 2648.0762 | AD15: =((21606/4)*3)/31 -> 522.72581 | AE15: =((92472/4)*3)/31 -> 2237.2258 | AF15: ='Cost.4.24'!AB14 -> 414.9 | AG15: ='Cost.4.24'!AC14 -> 1547.577 | AH15: ='Reading.5.25'!K13 -> 270.744 | AI15: =AH15*4 -> 1082.976 | AJ15: =(21606/4)/31 -> 174.24194 | AK15: =(96112/4)/31 -> 775.09677 | AL15: ='Cost.4.24'!AH14 -> 158.712 | AM15: ='Cost.4.24'!AI14 -> 591.99576 | AN15: =AB15+AH15 -> 980.684 | AO15: =AF15+AL15 -> 573.612 | AP15: =AD15+AJ15 -> 696.96774 | AQ15: =82483/31 -> 2660.7419 | AR15: ='Cost.4.24'!AS14 -> 2139.5728 | AS15: =AC15+AI15 -> 3731.0522 | AV15: ='Reading.5.25'!AE13/'cost.5.25'!F15 -> 93.426389 | AW15: =(M15+T15)/F15 -> 181.24719 | AX15: =V15/F15 -> 1.6594215 | AY15: =Z15/F15 -> 8.4630496 | AZ15: =AN15/F15 -> 2.351688 | BA15: =AS15/F15 -> 8.9470928 | BC15: ='Cost.4.24'!BE14 -> 44473.653 | BD15: =K15+R15+X15+AQ15 -> 86204.29 | BE15: =M15+T15+Z15+AS15 -> 82842.652 | BG15: ='Cost.4.24'!BI14 -> 177.89461 | BH15: =BD15/H15 -> 403.9023 | BI15: =BE15/F15 -> 198.65734
B16: 45786
B17: 45787
B18: 45788
B19: 45789
B20: 45790
B21: 45791
B22: 45792
B23: 45793
B24: 45794
B25: 45795
B26: 45796
B27: 45797
... B38: 45808
B39: TOTAL | D39: =AVERAGE(D8:D37) -> 0.793025 | F39: =SUM(F8:F37) -> 3337.0492 | H39: =+SUM(H8:H37) -> 1707.4286 | J39: =SUM(J8:J37) -> 295880 | K39: =SUM(K8:K37) -> 643545.29 | L39: =SUM(L8:L37) -> 281614 | M39: =SUM(M8:M37) -> 574007.2 | O39: =SUM(O8:O37) -> 0 | P39: =SUM(P8:P37) -> 0 | Q39: =SUM(Q8:Q37) -> 0 | R39: =SUM(R8:R37) -> 0 | S39: =SUM(S8:S37) -> 0 | T39: =SUM(T8:T37) -> 0 | V39: =SUM(V8:V37) -> 5442 | W39: =SUM(W8:W37) -> 4863.2258 | X39: =SUM(X8:X37) -> 24803.097 | Y39: =SUM(Y8:Y37) -> 17583.48 | Z39: =SUM(Z8:Z37) -> 27754.2 | AB39: =SUM(AB8:AB37) -> 5306.11 | AC39: =SUM(AC8:AC37) -> 19791.79 | AD39: =SUM(AD8:AD37) -> 4181.8065 | AE39: =SUM(AE8:AE37) -> 17897.806 | AF39: =SUM(AF8:AF37) -> 2816.71 | AG39: =SUM(AG8:AG37) -> 10506.328 | AH39: =SUM(AH8:AH37) -> 2067.924 | AI39: =SUM(AI8:AI37) -> 8271.696 | ... AS39: =SUM(AS8:AS37) -> 28063.486 | AV39: =AVERAGE(AV8:AV37) -> 89.181643 | AW39: =AVERAGE(AW8:AW37) -> 173.01239 | AX39: =AVERAGE(AX8:AX37) -> 1.6451777 | AY39: =AVERAGE(AY8:AY37) -> 8.3904063 | AZ39: =AVERAGE(AZ8:AZ37) -> 2.2234785 | BA39: =AVERAGE(BA8:BA37) -> 8.4617183 | BC39: =SUM(BC8:BC37) -> 313464.72 | BD39: =SUM(BD8:BD37) -> 689634.32 | BE39: =SUM(BE8:BE37) -> 629824.89 | BG39: =BC39/'Reading.5.25'!AN37 -> 132.20781 | BH39: =AVERAGE(BH8:BH37) -> 403.9023 | BI39: =AVERAGE(BI8:BI37) -> 189.86451

Sheet Domestic Water
A5: Engineering Department
A6: Domestic Water Parameters | L6: Month : | M6: May | N6: 2025
A8: Day | B8: Hardness | D8: Alkalinity | G8: Chloride | H8: PH | I8: Conductivity | J8: TDS | K8: Fe | L8: CL | M8: T ºc | N8: Production
B9: CAL | C9: Total | D9: P | E9: M | F9: CH | G9: CL/NaCL
A10: 1
A11: 2
A12: 3
A13: 4
A14: 5
A15: 6
A16: 7
A17: 8
A18: 9
A19: 10
A20: 11
A21: 12
... A40: 31
H41: =AVERAGE(H10:H40) -> #DIV/0! | J41: =AVERAGE(J10:J40) -> #DIV/0! | L41: =AVERAGE(L10:L40) -> #DIV/0! | M41: =AVERAGE(M10:M40) -> #DIV/0! | N41: =SUM(N10:N40) -> 0

Sheet Main Pool
A5: Engineering Department
A6: Main Swimming Pool | M6: Month : | N6: April | O6: 2025
A8: Pool Parameters | I8: Fresh Water Add (M³) | J8: Chemicals | O8: Backwash
A9: Day | B9: Calcium Hardness | C9: Total Alkalinity | D9: PH | E9: TDS | F9: Cyan. Acid | G9: CL | H9: T ºc | J9: Chlorine 65% (Kg) | K9: Chlorine 90% (Kg) | L9: Soda Ash PH+ (Kg) | M9: HCL PH- (Lit) | N9: Other Chemicals
A10: 1
A11: 2
A12: 3
A13: 4
A14: 5
A15: 6
A16: 7
A17: 8
A18: 9
A19: 10
A20: 11
A21: 12
... A40: 31
D41: =AVERAGE(D10:D40) -> #DIV/0! | G41: =AVERAGE(G10:G40) -> #DIV/0! | H41: =AVERAGE(H10:H40) -> #DIV/0! | I41: =SUM(I10:I40) -> 0 | J41: =SUM(J10:J40) -> 0 | K41: =SUM(K10:K40) -> 0

Sheet Heated Pool
A5: Engineering Department
A6: Heated Pool | M6: Month : | N6: April | O6: 2025
A8: Pool Parameters | I8: Fresh Water Add (M³) | J8: Chemicals | O8: Backwash
A9: Day | B9: Calcium Hardness | C9: Total Alkalinity | D9: PH | E9: TDS | F9: Cyan. Acid | G9: CL | H9: T ºc | J9: Chlorine 65% (Kg) | K9: Chlorine 90% (Kg) | L9: Sda Ash PH+ (Kg) | M9: HCL PH- (Lit) | N9: Other Chemicals
A10: 1
A11: 2
A12: 3
A13: 4
A14: 5
A15: 6
A16: 7
A17: 8
A18: 9
A19: 10
A20: 11
A21: 12
... A40: 31
D41: =AVERAGE(D10:D40) -> #DIV/0! | G41: =AVERAGE(G10:G40) -> #DIV/0! | H41: =AVERAGE(H10:H40) -> #DIV/0! | I41: =AVERAGE(I10:I40) -> #DIV/0! | J41: =SUM(J10:J40) -> 0 | K41: =SUM(K10:K40) -> 0

Sheet Kids pool 
A5: Engineering Department
A6: Kids Pool | M6: Month : | N6: April | O6: 2025
A8: Pool Parameters | I8: Fresh Water Add (M³) | J8: Chemicals | O8: Backwash
A9: Day | B9: Calcium Hardness | C9: Total Alkalinity | D9: PH | E9: TDS | F9: Cyan. Acid | G9: CL | H9: T ºc | J9: Chlorine 65% (Kg) | K9: Chlorine 90% (Kg) | L9: Sda Ash PH+ (Kg) | M9: HCL PH- (Lit) | N9: Other Chemicals
A10: 1
A11: 2
A12: 3
A13: 4
A14: 5
A15: 6
A16: 7
A17: 8
A18: 9
A19: 10
A20: 11
A21: 12
... A40: 31
D41: =AVERAGE(D10:D40) -> #DIV/0! | G41: =AVERAGE(G10:G40) -> #DIV/0! | H41: =AVERAGE(H10:H40) -> #DIV/0! | I41: =AVERAGE(I10:I40) -> #DIV/0! | J41: =SUM(J10:J40) -> 0 | K41: =SUM(K10:K40) -> 0

Sheet Jacuzzi
A5: Engineering Department
A6: Infinity Pool | M6: Month : | N6: April | O6: 2025
A8: Pool Parameters | I8: Fresh Water Add (M³) | J8: Chemicals | O8: Backwash
A9: Day | B9: Calcium Hardness | C9: Total Alkalinity | D9: PH | E9: TDS | F9: Cyan. Acid | G9: CL | H9: T ºc | J9: Chlorine 65% (Kg) | K9: Chlorine 90% (Kg) | L9: Sda Ash PH+ (Kg) | M9: HCL PH- (Lit) | N9: Other Chemicals
A10: 1
A11: 2
A12: 3
A13: 4
A14: 5
A15: 6
A16: 7
A17: 8
A18: 9
A19: 10
A20: 11
A21: 12
... A40: 31
D41: =AVERAGE(D10:D40) -> #DIV/0! | G41: =AVERAGE(G10:G40) -> #DIV/0! | H41: =AVERAGE(H10:H40) -> #DIV/0! | J41: =SUM(J10:J40) -> 0 | K41: =SUM(K10:K40) -> 0

Sheet Fountains & Lagoons
A5: Engineering Department
A6: Fountains, Water Falls and Lagoons | I6: Month : | M6: April | N6: 2021 | O6: 2025
B8: Lagoons | E8: Water Falls | H8: Entrance Fountain | J8: Shops Fountain | M8: Main Tank | O8: Irrigation Tank
A9: Day | B9: PH | C9: CL | D9: Backwash | E9: PH | F9: CL | G9: Backwash | H9: PH | I9: CL | J9: PH | K9: CL | L9: Backwash | M9: PH | N9: CL | O9: PH | P9: CL
A10: 1
A11: 2
A12: 3
A13: 4
A14: 5
A15: 6
A16: 7
A17: 8
A18: 9
A19: 10
A20: 11
A21: 12
... A40: 31

Sheet Boilers
A5: Engineering Department
A6: Boilers Water Parameters | V6: Month : | X6: April | Y6: 2025
A8: Day | B8: Feed Tank | M8: Boiler Water
B9: Alkalinity | E9: Chloride | F9: PH | G9: Conduc- tivity | H9: TDS | I9: Fe | J9: TH | K9: TºC | M9: Alkalinity | P9: Chloride | Q9: PH | R9: Conduc- tivity | S9: TDS | T9: Fe | U9: Po4 | V9: Na2 So3 | W9: TH | X9: Boiler No. | Y9: Company
B10: P | C10: M | D10: OH | E10: CL/NaCL | M10: P | N10: M | O10: OH | P10: CL/NaCL
A11: 1
A12: 2
A13: 3
A14: 4
A15: 5
A16: 6
A17: 7
A18: 8
A19: 9
A20: 10
A21: 11
A22: 12
... A41: 31
H42: =AVERAGE(H11:H41) -> #DIV/0! | I42: =AVERAGE(I11:I41) -> #DIV/0! | J42: =AVERAGE(J11:J41) -> #DIV/0! | K42: =AVERAGE(K11:K41) -> #DIV/0! | Q42: =AVERAGE(Q11:Q41) -> #DIV/0! | S42: =AVERAGE(S11:S41) -> #DIV/0! | T42: =AVERAGE(T11:T41) -> #DIV/0!

Sheet Chillers
A5: Engineering Department
A6: Chilled Water Parameters | L6: HISTORY
A8: Date | C8: Main Chillers | J8: Gym & Spa Chillers | Q8: Company
C9: PH | D9: Conduc- tivity | E9: TDS | F9: Fe | G9: INH | H9: Cu. | J9: PH | K9: Conduc- tivity | L9: TDS | M9: Fe | N9: INH | O9: Cu.
A10: 38591 | C10: 10.5 | D10: 2550 | E10: 1700 | F10: 0.8 | G10: 600 | Q10: System Technique
A11: 38599 | C11: 9.7 | D11: 2055 | E11: 1370 | F11: 0.8 | G11: 600 | Q11: System Technique
A12: 38606 | C12: 9.8 | D12: 2160 | E12: 1440 | F12: 0.7 | G12: 650 | Q12: System Technique
A13: 38613 | C13: 9.7 | D13: 2250 | E13: 1500 | F13: 0.8 | G13: 600 | Q13: System Technique
A14: 38634 | C14: 8 | D14: 585 | E14: 390 | F14: 0.3 | G14: Nil | Q14: System Technique
A15: 38662 | C15: 10 | D15: 1845 | E15: 1230 | F15: 0.8 | G15: 500 | Q15: System Technique
A16: 38722 | C16: 10 | D16: 2175 | E16: 1450 | F16: 0.6 | G16: 700 | H16: Nil | Q16: System Technique
A17: 38739 | C17: 10.1 | D17: 3150 | E17: 2300 | F17: 0.5 | G17: 450 | Q17: System Technique
A18: 38760 | C18: 9.9 | D18: 1675 | E18: 1250 | F18: 0.3 | G18: 600 | H18: Nil | Q18: System Technique
A19: 38767 | C19: 9.7 | D19: 22250 | E19: 1500 | F19: 0.5 | G19: 250 | Q19: System Technique
A20: 38788 | C20: 10.1 | D20: 2475 | E20: 1850 | F20: 0.6 | G20: 1000 | H20: Nil | Q20: System Technique
A21: 38802 | C21: 10.2 | D21: 3000 | E21: 2000 | F21: 0.3 | G21: 650 | Q21: System Technique
A22: 38844 | C22: 10.2 | D22: 2750 | E22: 1800 | F22: 0.5 | G22: 1000 | Q22: System Technique
A23: 38858 | C23: 10.2 | D23: 3750 | E23: 2500 | F23: 0.6 | G23: 1000 | H23: Nil | Q23: System Technique
A24: 38900 | C24: 10.5 | D24: 3000 | E24: 2000 | F24: 0.5 | G24: 1000 | H24: Nil | Q24: System Technique
A25: 38926 | C25: 10.4 | D25: 3000 | E25: 2000 | F25: 0.3 | G25: 700 | H25: Nil | J25: 10.2 | K25: 6000 | L25: 4000 | M25: 0.3 | N25: 2500 | O25: Nil | Q25: System Technique
A26: 38949 | C26: 10.5 | D26: 3000 | E26: 2000 | F26: 0.5 | G26: 1000 | H26: Nil | J26: 9.8 | K26: 7500 | L26: 5000 | M26: 0.6 | N26: 2000 | O26: Nil | Q26: System Technique
A27: 38963 | C27: 10.5 | D27: 1950 | E27: 1300 | F27: 0.3 | G27: 600 | J27: 10.7 | K27: 4500 | L27: 3000 | M27: 0.5 | N27: 2000 | Q27: System Technique
A28: 38977 | C28: 10.5 | D28: 2250 | E28: 1500 | F28: 0.5 | G28: 600 | J28: 9 | K28: 600 | L28: 400 | M28: 3 | N28: Nil | Q28: System Technique
A29: 38998 | C29: 10 | D29: 1950 | E29: 1300 | F29: 0.5 | G29: 600 | H29: Nil | J29: 10.5 | K29: 6000 | L29: 4000 | M29: 0.5 | N29: 1500 | O29: Nil | Q29: System Technique
A30: 39019 | C30: 10.5 | D30: 2700 | E30: 1800 | F30: 0.5 | G30: 600 | H30: Nil | J30: 11 | K30: 6000 | L30: 4000 | M30: 0.5 | N30: 2000 | O30: Nil | Q30: System Technique
A31: 39037 | C31: 10.5 | D31: 2700 | E31: 1800 | F31: 0.7 | G31: 1000 | H31: Nil | J31: 11 | K31: 6000 | L31: 4000 | M31: 0.7 | N31: 3000 | O31: Nil | Q31: System Technique
A32: 39047 | C32: 10.5 | D32: 2700 | E32: 1800 | F32: 0.7 | G32: 1000 | H32: Nil | J32: 11 | K32: 6000 | L32: 4000 | M32: 0.7 | N32: 2500 | O32: Nil | Q32: System Technique
A33: 39096 | C33: 10.6 | D33: 2550 | E33: 1700 | F33: 0.7 | G33: 1000 | H33: Nil | J33: 11 | K33: 5250 | L33: 3500 | M33: 0.7 | N33: 2500 | O33: Nil | Q33: System Technique
A34: 39124 | C34: 10.8 | D34: 3300 | E34: 4500 | F34: 0.6 | G34: 2000 | H34: Nil | J34: 11 | K34: 6750 | L34: 4500 | M34: 0.6 | N34: 2000 | O34: Nil | Q34: System Technique
A35: 39145 | C35: 10.9 | D35: 2700 | E35: 1800 | F35: 0.7 | G35: 600 | H35: Nil | J35: 11 | K35: 5250 | L35: 3500 | M35: 0.7 | N35: 1800 | O35: Nil | Q35: System Technique
A36: 39166 | C36: 10.8 | D36: 2400 | E36: 1600 | F36: 0.6 | G36: 600 | H36: Nil | J36: 10.3 | K36: 4200 | L36: 2800 | M36: 0.4 | N36: 1500 | O36: Nil | Q36: System Technique
A37: 39180 | C37: 10.8 | D37: 2700 | E37: 1800 | F37: 0.7 | G37: 600 | H37: Nil | J37: 10.9 | K37: 5250 | L37: 3500 | M37: 0.6 | N37: 1800 | O37: Nil | Q37: System Technique
A38: 39201 | C38: 10.7 | D38: 2250 | E38: 1700 | F38: 0.7 | H38: 8.2 | J38: 370 | K38: 4500 | L38: 1.2 | M38: 26 | N38: 496 | Q38: System Technique
A39: 39235 | C39: 10.3 | D39: 3000 | E39: 2000 | F39: 0.7 | G39: 1000 | H39: <0.1 | J39: 11 | K39: 5250 | L39: 3500 | M39: 0.7 | N39: 1500 | O39: <0.1 | Q39: System Technique
A40: 39250 | C40: 10.5 | D40: 3000 | E40: 2000 | F40: 0.6 | G40: 800 | H40: <0.1 | J40: 11 | K40: 4500 | L40: 3000 | M40: 0.6 | N40: 1500 | O40: <0.1 | Q40: System Technique
A41: 39264 | C41: 10.5 | D41: 3000 | E41: 2000 | F41: 0.6 | G41: 1000 | J41: 10.6 | K41: 2700 | L41: 1800 | M41: 0.6 | N41: 800 | Q41: System Technique
A42: 39292 | C42: 10.7 | D42: 2700 | E42: 1800 | F42: 0.6 | G42: 600 | H42: <0.1 | J42: 10.5 | K42: 2550 | L42: 1700 | M42: 0.6 | N42: 400 | O42: <0.1 | Q42: System Technique
A43: 39299 | C43: 10.5 | D43: 3000 | E43: 2000 | F43: 0.6 | G43: 1000 | J43: 10.6 | K43: 7500 | L43: 5000 | M43: 0.6 | N43: 3000 | Q43: System Technique
A44: 39327 | C44: 10.2 | D44: 3750 | E44: 2500 | F44: 0.6 | G44: 2000 | H44: Nil | J44: 10.7 | K44: 6000 | L44: 4000 | M44: 0.6 | N44: 3000 | O44: Nil | Q44: System Technique
A45: 39334 | C45: 10.2 | D45: 3750 | E45: 2500 | F45: 0.6 | G45: 2000 | H45: Nil | J45: 10.7 | K45: 6000 | L45: 4000 | M45: 0.6 | N45: 3000 | O45: Nil | Q45: System Technique
A46: 39369 | C46: 10.3 | D46: 3750 | E46: 2500 | F46: 0.6 | G46: 2000 | H46: Nil | J46: 10.8 | K46: 4500 | L46: 3000 | M46: 0.6 | N46: 2500 | O46: Nil | Q46: System Technique
A47: 39390 | C47: 10.5 | D47: 3000 | E47: 2000 | F47: 0.5 | G47: 1000 | H47: Nil | J47: 10.7 | K47: 3750 | L47: 2500 | M47: 0.5 | N47: 2000 | O47: Nil | Q47: System Technique
A48: 39411 | C48: 11 | D48: 3000 | E48: 2000 | F48: 0.5 | G48: 1000 | J48: 11 | K48: 3750 | L48: 2500 | M48: 0.5 | N48: 2000 | Q48: System Technique
A49: 39425 | C49: 10.5 | D49: 3000 | E49: 2000 | F49: 0.5 | G49: 1000 | J49: 10.5 | K49: 4500 | L49: 3000 | M49: 0.5 | N49: 2000 | Q49: System Technique
A50: 39460 | C50: 10 | D50: 3750 | E50: 2500 | F50: 0.5 | G50: 2000 | J50: 9.8 | K50: 3750 | L50: 2500 | M50: 0.5 | N50: 2000 | Q50: System Technique
A51: 39474 | C51: 10.2 | D51: 3750 | E51: 2500 | F51: 0.5 | G51: 2000 | J51: 10.2 | K51: 3750 | L51: 2500 | M51: 0.5 | N51: 2000 | Q51: System Technique
A52: 39488 | C52: 10 | D52: 3750 | E52: 2500 | F52: 0.5 | G52: 2000 | J52: 9.7 | K52: 3225 | L52: 2150 | M52: 0.5 | N52: 1500 | Q52: System Technique
A53: 39537 | C53: 10.8 | D53: 2250 | E53: 1500 | F53: 0.5 | G53: 1000 | J53: 11 | K53: 3750 | L53: 2500 | M53: 0.5 | N53: 1500 | Q53: System Technique
A54: 39544 | C54: 10 | D54: 4500 | E54: 3000 | F54: 0.5 | G54: 1500 | J54: 9.7 | K54: 3000 | L54: 2000 | M54: 0.5 | N54: 1000 | Q54: System Technique
A55: 39562 | C55: 10.6 | D55: 2250 | E55: 1500 | F55: 0.7 | G55: 600 | J55: 11 | K55: 3600 | L55: 2400 | M55: 1 | N55: 1000 | Q55: System Technique
A56: 39564 | C56: 10.6 | D56: 2250 | E56: 1500 | F56: 0.7 | G56: 600 | J56: 11 | K56: 3600 | L56: 2400 | M56: 1 | N56: 1000 | Q56: System Technique
A57: 39578 | C57: 10.9 | D57: 2250 | E57: 1500 | F57: 0.6 | G57: 600 | J57: 11.3 | K57: 3600 | L57: 2400 | M57: 0.7 | N57: 1000 | Q57: System Technique
A58: 39589 | C58: 11 | D58: 2600 | E58: 1400 | F58: 0.5 | G58: 600 | H58: <0.1 | J58: 11 | K58: 3750 | L58: 2500 | M58: 0.5 | N58: 1000 | O58: <0.1 | Q58: System Technique
A59: 39610 | C59: 10 | D59: 3750 | E59: 2500 | F59: 0.5 | G59: 1000 | H59: Nil | J59: 10 | K59: 7500 | L59: 5000 | M59: 0.5 | N59: 2000 | O59: Nil | Q59: System Technique
A60: 39627 | C60: 10.7 | D60: 3750 | E60: 2500 | F60: 0.7 | G60: 1000 | J60: 10.9 | K60: 6450 | L60: 4300 | M60: 0.7 | N60: 2000 | Q60: System Technique
A61: 39637 | C61: 10.4 | D61: 4200 | E61: 2800 | F61: 0.3 | G61: 1200 | J61: 10.2 | K61: 3750 | L61: 2500 | M61: 0.3 | N61: 1200 | Q61: System Technique
A62: 39662 | C62: 10.6 | D62: 3450 | E62: 2300 | F62: 0.7 | G62: 1000 | J62: 10.7 | K62: 5700 | L62: 3800 | M62: 0.7 | N62: 1600 | Q62: System Technique
A63: 39690 | C63: 10.7 | D63: 3600 | E63: 2400 | F63: 0.5 | G63: 1000 | J63: 10.6 | K63: 5400 | L63: 3600 | M63: 0.7 | N63: 1500 | Q63: System Technique
A64: 39711 | C64: 10.4 | E64: 2300 | F64: 0.5 | G64: 1000 | J64: 10.8 | L64: 3400 | M64: 0.5 | N64: 1300 | Q64: System Technique
A65: 39739 | C65: 11 | D65: 3600 | E65: 2400 | F65: 0.5 | G65: 1000 | J65: 11 | K65: 4950 | L65: 3300 | M65: 0.7 | N65: 1300 | Q65: System Technique
A66: 39781 | C66: 10.6 | D66: 3600 | E66: 2400 | F66: 0.5 | G66: 1000 | J66: 10.8 | K66: 4500 | L66: 300 | M66: 0.5 | N66: 1000 | Q66: System Technique
A67: 39816 | C67: 10.7 | D67: 3750 | E67: 2500 | F67: 0.4 | G67: 950 | J67: 11 | K67: 4500 | L67: 3000 | M67: 0.5 | N67: 1200 | Q67: System Technique
A68: 39830 | C68: 10.7 | D68: 3750 | E68: 2500 | F68: 0.4 | G68: 950 | J68: 11 | K68: 4500 | L68: 3000 | M68: 0.5 | N68: 1200 | Q68: System Technique
A69: 39839 | C69: 10.4 | D69: 3750 | E69: 2500 | F69: 0.4 | G69: 950 | J69: 11 | K69: 4500 | L69: 3000 | M69: 0.5 | N69: 1200 | Q69: System Technique
A70: 39908 | C70: 10.5 | D70: 4400 | E70: 2200 | F70: 0.4 | G70: 1000 | J70: 10.6 | K70: 6400 | L70: 3200 | M70: 0.4 | N70: 1200 | Q70: System Technique
A71: 39945 | C71: 10.8 | D71: 4580 | E71: 2519 | F71: 0.2 | G71: 1100 | J71: 10.8 | K71: 4570 | L71: 2519 | M71: 0.2 | N71: 1100 | Q71: System Technique
A72: 39992 | C72: 10.9 | D72: 4500 | E72: 2400 | F72: 0.3 | G72: 1200 | H72: 0.1 | J72: 10.6 | K72: 3900 | L72: 2100 | M72: 0.3 | N72: 1000 | O72: 0.1 | Q72: System Technique
A73: 40001 | C73: 10.4 | D73: 4200 | E73: 2310 | F73: 0.3 | G73: 1000 | J73: 10.4 | K73: 4100 | L73: 2255 | M73: 0.3 | N73: 900 | Q73: System Technique
A74: 40017 | C74: 9.9 | D74: 3150 | E74: 2100 | F74: 0.5 | G74: 1000 | J74: 9.8 | K74: 3800 | L74: 1900 | M74: 0.4 | N74: 900 | Q74: System Technique
A75: 40034 | C75: 11 | D75: 4400 | E75: 2600 | F75: 0.4 | G75: 1000 | J75: 10.6 | K75: 3300 | L75: 1800 | M75: 0.4 | N75: 800 | Q75: System Technique
A76: 40072 | C76: 11 | D76: 3400 | E76: 1800 | F76: 0.3 | G76: 1000 | H76: <0.1 | J76: 11 | K76: 3000 | L76: 1700 | M76: 0.3 | N76: 700 | O76: <0.1 | Q76: System Technique
A77: 40117 | C77: 10.6 | D77: 3700 | E77: 2035 | F77: 0.4 | G77: 1000 | H77: Nil | J77: 10.4 | K77: 2800 | L77: 1540 | M77: 0.3 | N77: 600 | O77: Nil | Q77: System Technique
A78: 40174 | C78: 10.6 | D78: 3700 | E78: 2100 | F78: 0.4 | G78: 1000 | J78: 10.5 | K78: 2500 | L78: 1400 | M78: 0.4 | N78: 800 | Q78: System Technique
A79: 40182 | C79: 10.1 | D79: 3300 | E79: 2200 | F79: 0.3 | G79: 1000 | J79: 9.4 | K79: 2400 | L79: 1600 | M79: 0.4 | N79: 650 | Q79: System Technique
A80: 40216 | C80: 9.8 | D80: 3600 | E80: 1600 | F80: 0.5 | G80: 1000 | H80: Nil | J80: 10.4 | K80: 4000 | L80: 2200 | M80: 0.5 | N80: 1200 | O80: Nil | Q80: System Technique
A81: 40244 | C81: 10.8 | D81: 3600 | E81: 2000 | F81: 0.5 | G81: 800 | H81: <0.1 | J81: 10.6 | K81: 3000 | L81: 1650 | M81: 0.5 | N81: 600 | O81: <0.1 | Q81: System Technique
A82: 40329 | C82: 10.5 | D82: 3600 | E82: 1980 | F82: 0.5 | G82: 1100 | J82: 10.6 | K82: 4000 | L82: 2200 | M82: 0.5 | N82: 1800 | Q82: System Technique
A83: 40343 | C83: 9.9 | D83: 3000 | E83: 1600 | G83: 1000 | H83: <0.1 | J83: 10.7 | K83: 9000 | L83: 5400 | N83: 2000 | O83: <0.1 | Q83: System Technique
A84: 40349 | C84: 10 | D84: 3500 | E84: 1925 | F84: 0.5 | G84: 1200 | J84: 10.5 | K84: 4000 | L84: 2200 | M84: 0.5 | N84: 2000 | Q84: System Technique
A85: 40412 | C85: 10.2 | D85: 4000 | E85: 2200 | F85: 0.5 | G85: 800 | J85: 11 | K85: 8000 | L85: 4400 | M85: 0.4 | N85: 1600 | Q85: System Technique
A86: 40468 | C86: 10.5 | D86: 3400 | E86: 1900 | F86: 0.2 | G86: 650 | J86: 9.3 | K86: 5800 | L86: 3000 | M86: 0.2 | N86: 1200 | Q86: System Technique
A87: 40482 | C87: 10.4 | D87: 3200 | E87: 1260 | F87: 0.5 | G87: 1000 | J87: 9.8 | K87: 5800 | L87: 3000 | M87: 0.5 | N87: 1000 | Q87: System Technique
A88: 40551 | C88: 10.4 | D88: 2500 | E88: 1500 | F88: 0.4 | G88: 800 | J88: 9.8 | K88: 4000 | L88: 2200 | M88: 0.4 | N88: 1000 | Q88: System Technique
A89: 40722 | C89: 10.4 | D89: 2600 | E89: 1400 | F89: 0.6 | G89: 600 | J89: 9.8 | K89: 4000 | L89: 2200 | M89: 0.5 | N89: 1000 | Q89: System Technique
A90: 40762 | C90: 9.2 | D90: 2500 | E90: 1400 | F90: 0.6 | G90: 800 | J90: 10.2 | K90: 4400 | L90: 2440 | M90: 0.4 | N90: 1200 | Q90: System Technique
A91: 40824 | C91: 10.5 | D91: 2000 | E91: 1100 | F91: 0.5 | G91: 800 | J91: 9.5 | K91: 3000 | L91: 1650 | M91: 1.7 | N91: 2000 | Q91: System Technique
A92: 40857 | C92: 10.4 | D92: 1500 | E92: 800 | F92: 1.7 | G92: 600 | J92: 9.1 | K92: 3000 | L92: 1650 | M92: 0.3 | N92: 1200 | Q92: System Technique
A93: 40870 | C93: 9.6 | D93: 2400 | E93: 1320 | F93: 0.6 | G93: 700 | H93: <0.1 | J93: 9 | K93: 3000 | L93: 1650 | M93: 0.3 | N93: 1200 | O93: <0.1 | Q93: System Technique
A94: 40874 | C94: 10 | D94: 3200 | E94: 1760 | F94: 0.6 | G94: 1000 | H94: <0.1 | J94: 9 | K94: 3000 | L94: 1650 | M94: 0.3 | N94: 1200 | O94: <0.1 | Q94: System Technique
A95: 40878 | C95: 10 | D95: 3500 | E95: 2000 | F95: 0.6 | G95: 1000 | H95: <0.1 | J95: 9.8 | K95: 3000 | L95: 1650 | M95: 0.3 | N95: 1200 | O95: <0.1 | Q95: System Technique
A96: 40895 | C96: 10 | D96: 3200 | E96: 1760 | F96: 0.6 | G96: 800 | H96: <0.1 | J96: 10 | K96: 4100 | L96: 2255 | M96: 0.4 | N96: 1000 | Q96: System Technique
A97: 40910 | C97: 10 | D97: 3200 | E97: 1760 | F97: 0.6 | G97: 800 | H97: <0.1 | J97: 9.9 | K97: 4100 | L97: 2255 | M97: 0.4 | N97: 1000 | O97: <0.1 | Q97: System Technique
A98: 40931 | C98: 10 | D98: 3000 | E98: 1650 | F98: 0.6 | G98: 800 | H98: <0.1 | J98: 9.5 | K98: 4000 | L98: 2200 | M98: 0.4 | N98: 1000 | O98: <0.1 | Q98: System Technique
A99: 40948 | C99: 10.2 | D99: 3000 | E99: 1650 | F99: 0.6 | G99: 800 | H99: 0.1 | J99: 10 | K99: 4000 | L99: 2200 | M99: 0.4 | N99: 800 | O99: 0.15 | Q99: System Technique
A100: 40981 | C100: 10.3 | D100: 3000 | E100: 1650 | F100: 0.7 | G100: 800 | H100: 0.1 | J100: 10 | K100: 4000 | L100: 2200 | M100: 0.8 | N100: 800 | O100: 0.2 | Q100: System Technique
A101: 40994 | C101: 10.5 | D101: 2800 | E101: 1500 | F101: 0.5 | G101: 800 | H101: <0.1 | J101: 10.7 | K101: 4100 | L101: 2300 | M101: 1.2 | N101: 1000 | O101: <0.1 | Q101: System Technique
A102: 41010 | C102: 10 | D102: 3200 | E102: 1800 | F102: 0.9 | G102: 800 | H102: <0.1 | J102: 10 | K102: 4800 | L102: 2500 | M102: 1.9 | N102: 1000 | O102: <0.1 | Q102: System Technique
A103: 41025 | C103: 10.1 | D103: 3000 | E103: 1650 | F103: 0.6 | G103: 800 | H103: 0.1 | J103: 10 | K103: 5000 | L103: 2750 | M103: 1.9 | N103: 1000 | O103: 0.1 | Q103: System Technique
A104: 41037 | C104: 10.4 | D104: 3000 | E104: 1600 | F104: 0.5 | G104: 750 | J104: 11 | K104: 4000 | L104: 2200 | M104: 1.6 | N104: 1000 | Q104: System Technique
A105: 41051 | C105: 10.4 | D105: 3000 | E105: 1650 | F105: 0.5 | G105: 800 | J105: 10 | K105: 5000 | L105: 2750 | M105: 1.8 | N105: 1000 | Q105: System Technique
...

Sheet Reading.5.24
A1: 1 | B1: 2 | C1: 3 | D1: 4 | E1: 5 | F1: 6 | G1: 7 | H1: 8 | I1: 9 | J1: 10 | K1: 11 | L1: 12 | M1: 13 | N1: 14 | O1: 15 | P1: 16 | Q1: 17 | R1: 18 | S1: 19 | T1: 20 | U1: 21 | V1: 22 | W1: 23 | X1: 24 | Y1: 25 | Z1: 26 | AA1: 27 | AB1: 28 | AC1: 29 | AD1: 30 | AE1: 31 | AF1: 32 | AG1: 33 | AH1: 34 | AI1: 35 | AJ1: 36 | AK1: 37 | AL1: 38 | AM1: 39 | AN1: 40 | AO1: 41 | AP1: 42 | AQ1: 43 | AR1: 44 | AS1: 45 | AT1: 46 | AU1: 47 | AV1: 48 | AW1: 49 | AX1: 50 | AY1: 51 | AZ1: 52 | BA1: 53 | BB1: 54 | BC1: 55 | BD1: 56 | BE1: 57 | BF1: 58 | BG1: 59 | BH1: 60 | BI1: 61 | BJ1: 62 | BK1: 63 | BL1: 64 | BM1: 65 | BN1: 66 | BO1: 67 | BP1: 68 | BQ1: 69 | BR1: 70 | BS1: 71 | BT1: 72 | BU1: 73 | BV1: 74 | BW1: 75 | BX1: 76 | BY1: 77 | BZ1: 78 | CA1: 79 | CB1: 80 | CC1: 81 | CD1: 82 | CE1: 83 | CF1: 80 | CG1: 81 | CH1: 82 | CI1: 84 | CJ1: 85 | CK1: 86 | CL1: 87 | CM1: 88 | CN1: 89 | CO1: 90 | CP1: 91 | CQ1: 92 | CR1: 93 | CS1: 94 | CT1: 95 | CU1: 96 | CV1: 97 | CW1: 98 | CX1: 99 | CY1: 100 | CZ1: 101 | DA1: 102 | DB1: 103 | DC1: 104 | DD1: 105 | DE1: 106 | DF1: 107 | DG1: 108 | DH1: 109 | DI1: 110 | DJ1: 111 | DK1: 112 | DL1: 113 | DM1: 114 | DN1: 115 | DO1: 116 | DP1: 117 | DQ1: 118 | DR1: 119 | DS1: 120 | DT1: 121 | DU1: 122 | DV1: 123 | DW1: 124 | DX1: 125 | DY1: 126 | DZ1: 127 | EA1: 128 | EB1: 129 | EC1: 130 | ED1: 131 | EE1: 132 | EF1: 133 | EG1: 134 | EH1: 135 | EI1: 136 | EJ1: 137 | EK1: 138 | EL1: 139
B2: WATER | J2: KITCHEN GAS | N2: BOILER GAS | R2: FUEL | W2: ELECTRICITY | AA2: GENERATORS | AE2: TOTAL KWH | AI2: Occupancy % | AM2: Rooms Occupied | AQ2: Max. Demand | AT2: Power Factor | AY2: More Data | BC2: Weather Temperature | BL2: Available Rooms | BN2: Water Sold Last Year | BP2: Kitchen Water | BT2: Laundry Water | BX2: Fountain Water | CB2: S. Pool Water | CF2: Heated Pool Water | CI2: Staff Houses Water | CM2: Total Facilities Cons. | CP2: STP | CV2: Dishwasher | CZ2: Staff Kitchen | DD2: Laundry Electricity | DH2: Kit. Equip. Electricity | DL2: Chiller 1 | DP2: Chiller 2 | DT2: Chiller 3 | DX2: Chilled Pumps KWH | DZ2: Total Chillers | EC2: RO Plant | EF2: Staff Kitchen Gas | EJ2: Rotary Oven Gas
A4: Date | B4: Reading | C4: Product. | D4: Buy | E4: Sold | F4: Tanks Level | G4: Consump. This Year | H4: Last Year | J4: Reading | K4: Consump. This Year | L4: Last Year | N4: Reading | O4: Consump. This Year | P4: Last Year | R4: Reading | S4: Add | T4: Consump. This Year | U4: Last Year | W4: Reading | X4: Consump. This Year | Y4: Consump. Last Year | AA4: Reading | AB4: Consump. This Year | AC4: Consump. Last Year | AE4: This Year | AF4: Last Year | AG4: Budget | AI4: This Year | AJ4: Last Year | AK4: Budget | AM4: This Year | AN4: Last Year | AO4: Budget | AQ4: This Year KW | AR4: Last Year KW | AT4: KVAR Reading | AU4: KVAR Cons. | AV4: Cos Ø | AY4: Last Year January 2021 | BC4: This Year - May 2024 | BG4: Last Year - May 2023 | BP4: Counter Reading | BQ4: Consumption This year | BR4: Consumption Last Year | BT4: Counter Reading | BU4: Consumption | BV4: Consumption Last Year | BX4: Counter Reading | BY4: Consumption | BZ4: Consumption Last Year | CB4: Counter Reading | CC4: Consumption | CD4: Consumption Last Year | CF4: Counter Reading | CG4: Consumption | CH4: Consumption Last Year | CI4: Counter Reading | CJ4: Consumption | CK4: Consumption Last Year | CM4: This Year | CN4: Last Year | CP4: Counter Reading | CQ4: Recycled Water this Year | CR4: % | CS4: Reccycled Water Last Year | CT4: % | CV4: Counter Reading | CW4: Cons. | CX4: Cons. Last Year | CZ4: Counter Reading | DA4: Cons. | DB4: Cons. Last Year | DD4: Counter Reading | DE4: Cons. | DF4: Cons. Last Year | DH4: Counter Reading | DI4: Cons. | DJ4: Cons. Last Year | DL4: Counter Reading | DM4: Cons. | DN4: Cons. Last Year | DP4: Counter Reading | DQ4: Cons. | DR4: Cons. Last Year | DT4: Counter Reading | DU4: Cons. | DV4: Cons. Last Year | DZ4: Cons. | EA4: Cons. Last Year | EC4: KWH This Year | ED4: KWH Last Year | EF4: Counter Reading | EG4: Cons. | EH4: Cons. Last Year | EJ4: Counter Reading | EK4: Cons. | EL4: Cons. Last Year
B5: 294932 | F5: 780 | J5: 207959 | N5: 733991 | R5: 42700 | W5: 45905.86 | AA5: 520050 | AT5: 7165.9 | BP5: 67249 | BT5: 82221 | BX5: 4045 | CB5: 234620 | CF5: 6310 | CI5: 19770 | CP5: 113578 | CV5: 5276 | CZ5: 966 | DD5: 1445259 | DH5: 3368645 | DL5: 2919166 | DP5: 2299326 | DT5: 3137289 | EF5: 61166 | EJ5: 24472
A6: 45413 | B6: 295577 | C6: =B6-B5 -> 645 | E6: 0 | F6: 840 | G6: =C6+D6-E6+F5-F6 -> 585 | H6: ='[2]Reading.5.23'!G6 -> 660 | J6: 208003 | K6: =(J6-J5)*4.668 -> 205.392 | L6: ='[2]Reading.5.23'!K6 -> 168.048 | N6: 734095 | O6: =(N6-N5)*4.61 -> 479.44 | P6: ='[2]Reading.5.23'!O6 -> 488.66 | R6: 42700 | T6: =(R5+S5)-R6 -> 0 | U6: ='[2]Reading.5.23'!T6 -> 0 | W6: 45914 | X6: =(W6-W5)*4000 -> 32560 | Y6: ='[2]Reading.5.23'!X6 -> 32040 | AA6: 520030 | AB6: =AA6-AA5 -> -20 | AC6: ='[2]Reading.5.23'!AB6 -> 0 | AE6: =+X6+AB6 -> 32540 | AF6: ='[2]Reading.5.23'!AE6 -> 32040 | AG6: =1090308/30 -> 36343.6 | AI6: 0.5494 | AJ6: ='[2]Reading.5.23'!AI6 -> 0.5323 | AK6: 0.687 | AM6: 289 | AN6: ='[2]Reading.5.23'!AM6 -> 280 | AO6: =11205/30 -> 373.5 | AQ6: =449*4 -> 1796 | AR6: ='[2]Reading.5.23'!AQ6 -> 1612 | AT6: 7167.06 | AU6: =(AT6-AT5)*4000 -> 4640 | AV6: =+X6/SQRT(((POWER((X6),2)+(POWER((AU6),2))))) -> 0.98999808 | AY6: ='[2]Reading.5.23'!X6 -> 32040 | AZ6: ='[2]Reading.5.23'!AB6 -> 0 | BA6: =AY6+AZ6 -> 32040 | BC6: 19 | BD6: 16.1 | BE6: 12 | BF6: 56 | BG6: 79 | BH6: ='[2]Reading.5.23'!BD6 -> 23.8 | BI6: ='[2]Reading.5.23'!BE6 -> 20 | BJ6: ='[2]Reading.5.23'!BF6 -> 60 | BL6: 526 | BN6: ='[2]Reading.5.23'!E4 -> Sold | BP6: 67284 | BQ6: =BP6-BP5 -> 35 | BR6: ='[2]Reading.5.23'!BQ6 -> 35 | BT6: 82261 | BU6: =BT6-BT5 -> 40 | BV6: ='[2]Reading.5.23'!BU6 -> 33 | BX6: 4045 | BY6: =BX6-BX5 -> 0 | BZ6: ='[2]Reading.5.23'!BY6 -> 70 | CB6: 234670 | CC6: =CB6-CB5 -> 50 | CD6: ='[2]Reading.5.23'!CC6 -> 68 | CF6: 6320 | CG6: =CF6-CF5 -> 10 | CH6: ='[2]Reading.5.23'!CG6 -> 0 | CI6: 19770 | CJ6: =CI6-CI5 -> 0 | CK6: ='[2]Reading.5.23'!CG6 -> 0 | CM6: =BQ6+BU6+BY6+CC6+CJ6 -> 125 | CN6: =BR6+BV6+BZ6+CD6+CK6 -> 206 | CP6: 113998 | CQ6: =CP6-CP5 -> 420 | CR6: =CQ6/G6 -> 0.71794872 | CS6: ='[2]Reading.5.23'!CN6 -> 207 | CT6: ='[2]Reading.5.23'!CO4 -> % | CV6: 5278 | CW6: =CV6-CV5 -> 2 | CX6: ='[2]Reading.5.23'!CT6 -> 2 | CZ6: 970 | DA6: =CZ6-CZ5 -> 4 | DB6: ='[2]Reading.5.23'!CX6 -> 6 | DD6: 1446269 | DE6: =DD6-DD5 -> 1010 | DF6: ='[2]Reading.5.23'!DB6 -> 988 | DH6: 3370241 | DI6: =DH6-DH5 -> 1596 | DJ6: ='[2]Reading.5.23'!DF6 -> 2146 | DL6: 2919196 | DM6: =DL6-DL5 -> 30 | DN6: ='[2]Reading.5.23'!DJ6 -> 33 | DP6: 2300998 | DQ6: =DP6-DP5 -> 1672 | DR6: ='[2]Reading.5.23'!DN6 -> 3224 | DT6: 3139341 | DU6: =DT6-DT5 -> 2052 | DV6: ='[2]Reading.5.23'!DR6 -> 32 | DX6: 720 | DZ6: =DM6+DQ6+DU6+DX6 -> 4474 | EA6: ='[2]Reading.5.23'!DW6 -> 4009 | EC6: =C6*5.2 -> 3354 | ED6: ='[2]Reading.5.23'!C6*5.2 -> 3328 | EF6: 61216 | EG6: =EF6-EF5 -> 50 | EJ6: 24493 | EK6: =EJ6-EJ5 -> 21
A7: 45414 | B7: 296074 | C7: =B7-B6 -> 497 | E7: 0 | F7: 785 | G7: =C7+D7-E7+F6-F7 -> 552 | H7: ='[2]Reading.5.23'!G7 -> 549 | J7: 208041 | K7: =(J7-J6)*4.668 -> 177.384 | L7: ='[2]Reading.5.23'!K7 -> 200.724 | N7: 734195 | O7: =(N7-N6)*4.61 -> 461 | P7: ='[2]Reading.5.23'!O7 -> 461 | R7: 42700 | T7: =(R6+S6)-R7 -> 0 | U7: ='[2]Reading.5.23'!T7 -> 0 | W7: 45923.28 | X7: =(W7-W6)*4000 -> 37120 | Y7: ='[2]Reading.5.23'!X7 -> 32920 | AA7: 520030 | AB7: =AA7-AA6 -> 0 | AC7: ='[2]Reading.5.23'!AB7 -> 0 | AE7: =+X7+AB7 -> 37120 | AF7: ='[2]Reading.5.23'!AE7 -> 32920 | AG7: =1090308/30 -> 36343.6 | AI7: 0.7351 | AJ7: ='[2]Reading.5.23'!AI7 -> 0.6454 | AK7: 0.687 | AM7: 371 | AN7: ='[2]Reading.5.23'!AM7 -> 339 | AO7: =11205/30 -> 373.5 | AQ7: =451*4 -> 1804 | AR7: ='[2]Reading.5.23'!AQ7 -> 1796 | AT7: 7168.11 | AU7: =(AT7-AT6)*4000 -> 4200 | AV7: =+X7/SQRT(((POWER((X7),2)+(POWER((AU7),2))))) -> 0.99365974 | AY7: ='[2]Reading.5.23'!X7 -> 32920 | AZ7: ='[2]Reading.5.23'!AB7 -> 0 | BA7: =AY7+AZ7 -> 32920 | BC7: 19 | BD7: 16.1 | BE7: 12 | BF7: 56 | BG7: 79 | BH7: ='[2]Reading.5.23'!BD7 -> 26.6 | BI7: ='[2]Reading.5.23'!BE7 -> 22 | BJ7: ='[2]Reading.5.23'!BF7 -> 57 | BL7: 526 | BN7: ='[2]Reading.5.23'!E5 -> 0 | BP7: 67316 | BQ7: =BP7-BP6 -> 32 | BR7: ='[2]Reading.5.23'!BQ7 -> 35 | BT7: 82299 | BU7: =BT7-BT6 -> 38 | BV7: ='[2]Reading.5.23'!BU7 -> 30 | BX7: 4045 | BY7: =BX7-BX6 -> 0 | BZ7: ='[2]Reading.5.23'!BY7 -> 0 | CB7: 234710 | CC7: =CB7-CB6 -> 40 | CD7: ='[2]Reading.5.23'!CC7 -> 66 | CF7: 6330 | CG7: =CF7-CF6 -> 10 | CH7: ='[2]Reading.5.23'!CG7 -> 0 | CI7: 19770 | CJ7: =CI7-CI6 -> 0 | CK7: ='[2]Reading.5.23'!CG7 -> 0 | CM7: =BQ7+BU7+BY7+CC7+CJ7 -> 110 | CN7: =BR7+BV7+BZ7+CD7+CK7 -> 131 | CP7: 114528 | CQ7: =CP7-CP6 -> 530 | CR7: =CQ7/G7 -> 0.96014493 | CS7: ='[2]Reading.5.23'!CN7 -> 201 | CT7: ='[2]Reading.5.23'!CO5 -> 0 | CV7: 5279 | CW7: =CV7-CV6 -> 1 | CX7: ='[2]Reading.5.23'!CT7 -> 2 | CZ7: 973 | DA7: =CZ7-CZ6 -> 3 | DB7: ='[2]Reading.5.23'!CX7 -> 7 | DD7: 1447013 | DE7: =DD7-DD6 -> 744 | DF7: ='[2]Reading.5.23'!DB7 -> 933 | DH7: 3372177 | DI7: =DH7-DH6 -> 1936 | DJ7: ='[2]Reading.5.23'!DF7 -> 2056 | DL7: 2919230 | DM7: =DL7-DL6 -> 34 | DN7: ='[2]Reading.5.23'!DJ7 -> 32 | DP7: 2302986 | DQ7: =DP7-DP6 -> 1988 | DR7: ='[2]Reading.5.23'!DN7 -> 3672 | DT7: 3141804 | DU7: =DT7-DT6 -> 2463 | DV7: ='[2]Reading.5.23'!DR7 -> 32 | DX7: 720 | DZ7: =DM7+DQ7+DU7+DX7 -> 5205 | EA7: ='[2]Reading.5.23'!DW7 -> 4456 | EC7: =C7*5.2 -> 2584.4 | ED7: ='[2]Reading.5.23'!C7*5.2 -> 2958.8 | EF7: 61270 | EG7: =EF7-EF6 -> 54 | EJ7: 24515 | EK7: =EJ7-EJ6 -> 22
A8: 45415 | B8: 296665 | C8: =B8-B7 -> 591 | E8: 0 | F8: 785 | G8: =C8+D8-E8+F7-F8 -> 591 | H8: ='[2]Reading.5.23'!G8 -> 620 | J8: 208087 | K8: =(J8-J7)*4.668 -> 214.728 | L8: ='[2]Reading.5.23'!K8 -> 196.056 | N8: 734293 | O8: =(N8-N7)*4.61 -> 451.78 | P8: ='[2]Reading.5.23'!O8 -> 530.15 | R8: 42700 | T8: =(R7+S7)-R8 -> 0 | U8: ='[2]Reading.5.23'!T8 -> 0 | W8: 45932.48 | X8: =(W8-W7)*4000 -> 36800 | Y8: ='[2]Reading.5.23'!X8 -> 37280 | AA8: 520030 | AB8: =AA8-AA7 -> 0 | AC8: ='[2]Reading.5.23'!AB8 -> 1500 | AE8: =+X8+AB8 -> 36800 | AF8: ='[2]Reading.5.23'!AE8 -> 38780 | AG8: =1090308/30 -> 36343.6 | AI8: 0.7529 | AJ8: ='[2]Reading.5.23'!AI8 -> 0.6502 | AK8: 0.687 | AM8: 396 | AN8: ='[2]Reading.5.23'!AM8 -> 342 | AO8: =11205/30 -> 373.5 | AQ8: =475*4 -> 1900 | AR8: ='[2]Reading.5.23'!AQ8 -> 1892 | AT8: 7170.34 | AU8: =(AT8-AT7)*4000 -> 8920 | AV8: =+X8/SQRT(((POWER((X8),2)+(POWER((AU8),2))))) -> 0.97185743 | AY8: ='[2]Reading.5.23'!X8 -> 37280 | AZ8: ='[2]Reading.5.23'!AB8 -> 1500 | BA8: =AY8+AZ8 -> 38780 | BC8: 22 | BD8: 17 | BE8: 14 | BF8: 48 | BG8: 80 | BH8: ='[2]Reading.5.23'!BD8 -> 26.6 | BI8: ='[2]Reading.5.23'!BE8 -> 22 | BJ8: ='[2]Reading.5.23'!BF8 -> 57 | BL8: 526 | BN8: ='[2]Reading.5.23'!E6 -> 0 | BP8: 67351 | BQ8: =BP8-BP7 -> 35 | BR8: ='[2]Reading.5.23'!BQ8 -> 36 | BT8: 82339 | BU8: =BT8-BT7 -> 40 | BV8: ='[2]Reading.5.23'!BU8 -> 53 | BX8: 4045 | BY8: =BX8-BX7 -> 0 | BZ8: ='[2]Reading.5.23'!BY8 -> 0 | CB8: 234740 | CC8: =CB8-CB7 -> 30 | CD8: ='[2]Reading.5.23'!CC8 -> 68 | CF8: 6335 | CG8: =CF8-CF7 -> 5 | CH8: ='[2]Reading.5.23'!CG8 -> 0 | CI8: 19770 | CJ8: =CI8-CI7 -> 0 | CK8: ='[2]Reading.5.23'!CG8 -> 0 | CM8: =BQ8+BU8+BY8+CC8+CJ8 -> 105 | CN8: =BR8+BV8+BZ8+CD8+CK8 -> 157 | CP8: 114998 | CQ8: =CP8-CP7 -> 470 | CR8: =CQ8/G8 -> 0.79526227 | CS8: ='[2]Reading.5.23'!CN8 -> 277 | CT8: ='[2]Reading.5.23'!CO6 -> 0.31363636 | CV8: 5281 | CW8: =CV8-CV7 -> 2 | CX8: ='[2]Reading.5.23'!CT8 -> 4 | CZ8: 978 | DA8: =CZ8-CZ7 -> 5 | DB8: ='[2]Reading.5.23'!CX8 -> 5 | DD8: 1447823 | DE8: =DD8-DD7 -> 810 | DF8: ='[2]Reading.5.23'!DB8 -> 1038 | DH8: 3374080 | DI8: =DH8-DH7 -> 1903 | DJ8: ='[2]Reading.5.23'!DF8 -> 1907 | DL8: 2919263 | DM8: =DL8-DL7 -> 33 | DN8: ='[2]Reading.5.23'!DJ8 -> 32 | DP8: 2304959 | DQ8: =DP8-DP7 -> 1973 | DR8: ='[2]Reading.5.23'!DN8 -> 4229 | DT8: 3144418 | DU8: =DT8-DT7 -> 2614 | DV8: ='[2]Reading.5.23'!DR8 -> 32 | DX8: 720 | DZ8: =DM8+DQ8+DU8+DX8 -> 5340 | EA8: ='[2]Reading.5.23'!DW8 -> 5013 | EC8: =C8*5.2 -> 3073.2 | ED8: ='[2]Reading.5.23'!C8*5.2 -> 3276 | EF8: 61331 | EG8: =EF8-EF7 -> 61 | EJ8: 24539 | EK8: =EJ8-EJ7 -> 24
A9: 45416 | B9: 297282 | C9: =B9-B8 -> 617 | E9: 0 | F9: 785 | G9: =C9+D9-E9+F8-F9 -> 617 | H9: ='[2]Reading.5.23'!G9 -> 738 | J9: 208127 | K9: =(J9-J8)*4.668 -> 186.72 | L9: ='[2]Reading.5.23'!K9 -> 168.048 | N9: 734413 | O9: =(N9-N8)*4.61 -> 553.2 | P9: ='[2]Reading.5.23'!O9 -> 511.71 | R9: 42700 | T9: =(R8+S8)-R9 -> 0 | U9: ='[2]Reading.5.23'!T9 -> 0 | W9: 45941.2 | X9: =(W9-W8)*4000 -> 34880 | Y9: ='[2]Reading.5.23'!X9 -> 34080 | AA9: 520030 | AB9: =AA9-AA8 -> 0 | AC9: ='[2]Reading.5.23'!AB9 -> 2370 | AE9: =+X9+AB9 -> 34880 | AF9: ='[2]Reading.5.23'!AE9 -> 36450 | AG9: =1090308/30 -> 36343.6 | AI9: 0.6179 | AJ9: ='[2]Reading.5.23'!AI9 -> 0.6559 | AK9: 0.687 | AM9: 325 | AN9: ='[2]Reading.5.23'!AM9 -> 345 | AO9: =11205/30 -> 373.5 | AQ9: =475*4 -> 1900 | AR9: ='[2]Reading.5.23'!AQ9 -> 1892 | AT9: 7171.94 | AU9: =(AT9-AT8)*4000 -> 6400 | AV9: =+X9/SQRT(((POWER((X9),2)+(POWER((AU9),2))))) -> 0.98357987 | AY9: ='[2]Reading.5.23'!X9 -> 34080 | AZ9: ='[2]Reading.5.23'!AB9 -> 2370 | BA9: =AY9+AZ9 -> 36450 | BC9: 22 | BD9: 18 | BE9: 14 | BF9: 52 | BG9: 81 | BH9: ='[2]Reading.5.23'!BD9 -> 26.6 | BI9: ='[2]Reading.5.23'!BE9 -> 22 | BJ9: ='[2]Reading.5.23'!BF9 -> 57 | BL9: 526 | BN9: ='[2]Reading.5.23'!E7 -> 0 | BP9: 67382 | BQ9: =BP9-BP8 -> 31 | BR9: ='[2]Reading.5.23'!BQ9 -> 31 | BT9: 82372 | BU9: =BT9-BT8 -> 33 | BV9: ='[2]Reading.5.23'!BU9 -> 37 | BX9: 4045 | BY9: =BX9-BX8 -> 0 | BZ9: ='[2]Reading.5.23'!BY9 -> 0 | CB9: 234780 | CC9: =CB9-CB8 -> 40 | CD9: ='[2]Reading.5.23'!CC9 -> 244 | CF9: 6340 | CG9: =CF9-CF8 -> 5 | CH9: ='[2]Reading.5.23'!CG9 -> 0 | CI9: 19770 | CJ9: =CI9-CI8 -> 0 | CK9: ='[2]Reading.5.23'!CG9 -> 0 | CM9: =BQ9+BU9+BY9+CC9+CJ9 -> 104 | CN9: =BR9+BV9+BZ9+CD9+CK9 -> 312 | CP9: 115433 | CQ9: =CP9-CP8 -> 435 | CR9: =CQ9/G9 -> 0.70502431 | CS9: ='[2]Reading.5.23'!CN9 -> 261 | CT9: ='[2]Reading.5.23'!CO7 -> 0.36612022 | CV9: 5283 | CW9: =CV9-CV8 -> 2 | CX9: ='[2]Reading.5.23'!CT9 -> 2 | CZ9: 983 | DA9: =CZ9-CZ8 -> 5 | DB9: ='[2]Reading.5.23'!CX9 -> 5 | DD9: 1448939 | DE9: =DD9-DD8 -> 1116 | DF9: ='[2]Reading.5.23'!DB9 -> 1033 | DH9: 3375901 | DI9: =DH9-DH8 -> 1821 | DJ9: ='[2]Reading.5.23'!DF9 -> 1971 | DL9: 2919278 | DM9: =DL9-DL8 -> 15 | DN9: ='[2]Reading.5.23'!DJ9 -> 30 | DP9: 2306866 | DQ9: =DP9-DP8 -> 1907 | DR9: ='[2]Reading.5.23'!DN9 -> 4055 | DT9: 3146827 | DU9: =DT9-DT8 -> 2409 | DV9: ='[2]Reading.5.23'!DR9 -> 29 | DX9: 720 | DZ9: =DM9+DQ9+DU9+DX9 -> 5051 | EA9: ='[2]Reading.5.23'!DW9 -> 4834 | EC9: =C9*5.2 -> 3208.4 | ED9: ='[2]Reading.5.23'!C9*5.2 -> 3083.6 | EF9: 61391 | EG9: =EF9-EF8 -> 60 | EJ9: 24562 | EK9: =EJ9-EJ8 -> 23
A10: 45417 | B10: 297788 | C10: =B10-B9 -> 506 | E10: 0 | F10: 785 | G10: =C10+D10-E10+F9-F10 -> 506 | H10: ='[2]Reading.5.23'!G10 -> 598 | J10: 208169 | K10: =(J10-J9)*4.668 -> 196.056 | L10: ='[2]Reading.5.23'!K10 -> 182.052 | N10: 734529 | O10: =(N10-N9)*4.61 -> 534.76 | P10: ='[2]Reading.5.23'!O10 -> 474.83 | R10: 42700 | T10: =(R9+S9)-R10 -> 0 | U10: ='[2]Reading.5.23'!T10 -> 0 | W10: 45950.26 | X10: =(W10-W9)*4000 -> 36240 | Y10: ='[2]Reading.5.23'!X10 -> 37760 | AA10: 520030 | AB10: =AA10-AA9 -> 0 | AC10: ='[2]Reading.5.23'!AB10 -> 0 | AE10: =+X10+AB10 -> 36240 | AF10: ='[2]Reading.5.23'!AE10 -> 37760 | AG10: =1090308/30 -> 36343.6 | AI10: 0.557 | AJ10: ='[2]Reading.5.23'!AI10 -> 0.6559 | AK10: 0.687 | AM10: 293 | AN10: ='[2]Reading.5.23'!AM10 -> 345 | AO10: =11205/30 -> 373.5 | AQ10: =475*4 -> 1900 | AR10: ='[2]Reading.5.23'!AQ10 -> 1952 | AT10: 7173.62 | AU10: =(AT10-AT9)*4000 -> 6720 | AV10: =+X10/SQRT(((POWER((X10),2)+(POWER((AU10),2))))) -> 0.9832388 | AY10: ='[2]Reading.5.23'!X10 -> 37760 | AZ10: ='[2]Reading.5.23'!AB10 -> 0 | BA10: =AY10+AZ10 -> 37760 | BC10: 21 | BD10: 17 | BE10: 14 | BF10: 50 | BG10: 81 | BH10: ='[2]Reading.5.23'!BD10 -> 26 | BI10: ='[2]Reading.5.23'!BE10 -> 23 | BJ10: ='[2]Reading.5.23'!BF10 -> 57 | BL10: 526 | BN10: ='[2]Reading.5.23'!E8 -> 0 | BP10: 67415 | BQ10: =BP10-BP9 -> 33 | BR10: ='[2]Reading.5.23'!BQ10 -> 38 | BT10: 82415 | BU10: =BT10-BT9 -> 43 | BV10: ='[2]Reading.5.23'!BU10 -> 36 | BX10: 4045 | BY10: =BX10-BX9 -> 0 | BZ10: ='[2]Reading.5.23'!BY10 -> 0 | CB10: 234820 | CC10: =CB10-CB9 -> 40 | CD10: ='[2]Reading.5.23'!CC10 -> 110 | CF10: 6345 | CG10: =CF10-CF9 -> 5 | CH10: ='[2]Reading.5.23'!CG10 -> 0 | CI10: 19770 | CJ10: =CI10-CI9 -> 0 | CK10: ='[2]Reading.5.23'!CG10 -> 0 | CM10: =BQ10+BU10+BY10+CC10+CJ10 -> 116 | CN10: =BR10+BV10+BZ10+CD10+CK10 -> 184 | CP10: 115841 | CQ10: =CP10-CP9 -> 408 | CR10: =CQ10/G10 -> 0.80632411 | CS10: ='[2]Reading.5.23'!CN10 -> 249 | CT10: ='[2]Reading.5.23'!CO8 -> 0.44677419 | CV10: 5284 | CW10: =CV10-CV9 -> 1 | CX10: ='[2]Reading.5.23'!CT10 -> 3 | CZ10: 987 | DA10: =CZ10-CZ9 -> 4 | DB10: ='[2]Reading.5.23'!CX10 -> 4 | DD10: 1450045 | DE10: =DD10-DD9 -> 1106 | DF10: ='[2]Reading.5.23'!DB10 -> 1002 | DH10: 3377816 | DI10: =DH10-DH9 -> 1915 | DJ10: ='[2]Reading.5.23'!DF10 -> 1812 | DL10: 2919307 | DM10: =DL10-DL9 -> 29 | DN10: ='[2]Reading.5.23'!DJ10 -> 32 | DP10: 2307575 | DQ10: =DP10-DP9 -> 709 | DR10: ='[2]Reading.5.23'!DN10 -> 4042 | DT10: 3150327 | DU10: =DT10-DT9 -> 3500 | DV10: ='[2]Reading.5.23'!DR10 -> 957 | DX10: 720 | DZ10: =DM10+DQ10+DU10+DX10 -> 4958 | EA10: ='[2]Reading.5.23'!DW10 -> 5751 | EC10: =C10*5.2 -> 2631.2 | ED10: ='[2]Reading.5.23'!C10*5.2 -> 3525.6 | EF10: 61437 | EG10: =EF10-EF9 -> 46 | EJ10: 24588 | EK10: =EJ10-EJ9 -> 26
A11: 45418 | B11: 298383 | C11: =B11-B10 -> 595 | E11: 0 | F11: 810 | G11: =C11+D11-E11+F10-F11 -> 570 | H11: ='[2]Reading.5.23'!G11 -> 527 | J11: 208202 | K11: =(J11-J10)*4.668 -> 154.044 | L11: ='[2]Reading.5.23'!K11 -> 149.376 | N11: 734639 | O11: =(N11-N10)*4.61 -> 507.1 | P11: ='[2]Reading.5.23'!O11 -> 479.44 | R11: 42700 | T11: =(R10+S10)-R11 -> 0 | U11: ='[2]Reading.5.23'!T11 -> 0 | W11: 45958.31 | X11: =(W11-W10)*4000 -> 32200 | Y11: ='[2]Reading.5.23'!X11 -> 37840 | AA11: 520030 | AB11: =AA11-AA10 -> 0 | AC11: ='[2]Reading.5.23'!AB11 -> 0 | AE11: =+X11+AB11 -> 32200 | AF11: ='[2]Reading.5.23'!AE11 -> 37840 | AG11: =1090308/30 -> 36343.6 | AI11: 0.4468 | AJ11: ='[2]Reading.5.23'!AI11 -> 0.5342 | AK11: 0.687 | AM11: 235 | AN11: ='[2]Reading.5.23'!AM11 -> 281 | AO11: =11205/30 -> 373.5 | AQ11: =475*4 -> 1900 | AR11: ='[2]Reading.5.23'!AQ11 -> 1956 | AT11: 7174.9 | AU11: =(AT11-AT10)*4000 -> 5120 | AV11: =+X11/SQRT(((POWER((X11),2)+(POWER((AU11),2))))) -> 0.98759328 | AY11: ='[2]Reading.5.23'!X11 -> 37840 | AZ11: ='[2]Reading.5.23'!AB11 -> 0 | BA11: =AY11+AZ11 -> 37840 | BC11: 24 | BD11: 17 | BE11: 14 | BF11: 50 | BG11: 81 | BH11: ='[2]Reading.5.23'!BD11 -> 29.7 | BI11: ='[2]Reading.5.23'!BE11 -> 24 | BJ11: ='[2]Reading.5.23'!BF11 -> 57 | BL11: 526 | BN11: ='[2]Reading.5.23'!E9 -> 0 | BP11: 67448 | BQ11: =BP11-BP10 -> 33 | BR11: ='[2]Reading.5.23'!BQ11 -> 36 | BT11: 82457 | BU11: =BT11-BT10 -> 42 | BV11: ='[2]Reading.5.23'!BU11 -> 35 | BX11: 4053 | BY11: =BX11-BX10 -> 8 | BZ11: ='[2]Reading.5.23'!BY11 -> 0 | CB11: 234850 | CC11: =CB11-CB10 -> 30 | CD11: ='[2]Reading.5.23'!CC11 -> 50 | CF11: 6355 | CG11: =CF11-CF10 -> 10 | CH11: ='[2]Reading.5.23'!CG11 -> 0 | CI11: 19770 | CJ11: =CI11-CI10 -> 0 | CK11: ='[2]Reading.5.23'!CG11 -> 0 | CM11: =BQ11+BU11+BY11+CC11+CJ11 -> 113 | CN11: =BR11+BV11+BZ11+CD11+CK11 -> 121 | CP11: 116258 | CQ11: =CP11-CP10 -> 417 | CR11: =CQ11/G11 -> 0.73157895 | CS11: ='[2]Reading.5.23'!CN11 -> 260 | CT11: ='[2]Reading.5.23'!CO9 -> 0.35365854 | CV11: 5284 | CW11: =CV11-CV10 -> 0 | CX11: ='[2]Reading.5.23'!CT11 -> 3 | CZ11: 992 | DA11: =CZ11-CZ10 -> 5 | DB11: ='[2]Reading.5.23'!CX11 -> 6 | DD11: 1450893 | DE11: =DD11-DD10 -> 848 | DF11: ='[2]Reading.5.23'!DB11 -> 1061 | DH11: 3379540 | DI11: =DH11-DH10 -> 1724 | DJ11: ='[2]Reading.5.23'!DF11 -> 1962 | DL11: 2922063 | DM11: =DL11-DL10 -> 2756 | DN11: ='[2]Reading.5.23'!DJ11 -> 33 | DP11: 2307541 | DQ11: =DP11-DP10 -> -34 | DR11: ='[2]Reading.5.23'!DN11 -> 3364 | DT11: 3151391 | DU11: =DT11-DT10 -> 1064 | DV11: ='[2]Reading.5.23'!DR11 -> 1395 | DX11: 720 | DZ11: =DM11+DQ11+DU11+DX11 -> 4506 | EA11: ='[2]Reading.5.23'!DW11 -> 5512 | EC11: =C11*5.2 -> 3094 | ED11: ='[2]Reading.5.23'!C11*5.2 -> 2948.4 | EF11: 61461 | EG11: =EF11-EF10 -> 24 | EJ11: 24610 | EK11: =EJ11-EJ10 -> 22
A12: 45419 | B12: 299003 | C12: =B12-B11 -> 620 | E12: 0 | F12: 810 | G12: =C12+D12-E12+F11-F12 -> 620 | H12: ='[2]Reading.5.23'!G12 -> 540 | J12: 208240 | K12: =(J12-J11)*4.668 -> 177.384 | L12: ='[2]Reading.5.23'!K12 -> 172.716 | N12: 734753 | O12: =(N12-N11)*4.61 -> 525.54 | P12: ='[2]Reading.5.23'!O12 -> 530.15 | R12: 42700 | T12: =(R11+S11)-R12 -> 0 | U12: ='[2]Reading.5.23'!T12 -> 0 | W12: 45966.03 | X12: =(W12-W11)*4000 -> 30880 | Y12: ='[2]Reading.5.23'!X12 -> 35840 | AA12: 520030 | AB12: =AA12-AA11 -> 0 | AC12: ='[2]Reading.5.23'!AB12 -> 0 | AE12: =+X12+AB12 -> 30880 | AF12: ='[2]Reading.5.23'!AE12 -> 35840 | AG12: =1090308/30 -> 36343.6 | AI12: 0.4373 | AJ12: ='[2]Reading.5.23'!AI12 -> 0.5059 | AK12: 0.687 | AM12: 230 | AN12: ='[2]Reading.5.23'!AM12 -> 268 | AO12: =11205/30 -> 373.5 | AQ12: =475*4 -> 1900 | AR12: ='[2]Reading.5.23'!AQ12 -> 1956 | AT12: 7176.03 | AU12: =(AT12-AT11)*4000 -> 4520 | AV12: =+X12/SQRT(((POWER((X12),2)+(POWER((AU12),2))))) -> 0.98945658 | AY12: ='[2]Reading.5.23'!X12 -> 35840 | AZ12: ='[2]Reading.5.23'!AB12 -> 0 | BA12: =AY12+AZ12 -> 35840 | BC12: 26 | BD12: 21 | BE12: 17 | BF12: 50 | BG12: 81 | BH12: ='[2]Reading.5.23'!BD12 -> 29.8 | BI12: ='[2]Reading.5.23'!BE12 -> 24 | BJ12: ='[2]Reading.5.23'!BF12 -> 41 | BL12: 526 | BN12: ='[2]Reading.5.23'!E10 -> 0 | BP12: 67480 | BQ12: =BP12-BP11 -> 32 | BR12: ='[2]Reading.5.23'!BQ12 -> 39 | BT12: 82500 | BU12: =BT12-BT11 -> 43 | BV12: ='[2]Reading.5.23'!BU12 -> 39 | BX12: 4053 | BY12: =BX12-BX11 -> 0 | BZ12: ='[2]Reading.5.23'!BY12 -> 5 | CB12: 234950 | CC12: =CB12-CB11 -> 100 | CD12: ='[2]Reading.5.23'!CC12 -> 55 | CF12: 6360 | CG12: =CF12-CF11 -> 5 | CH12: ='[2]Reading.5.23'!CG12 -> 0 | CI12: 19770 | CJ12: =CI12-CI11 -> 0 | CK12: ='[2]Reading.5.23'!CG12 -> 0 | CM12: =BQ12+BU12+BY12+CC12+CJ12 -> 175 | CN12: =BR12+BV12+BZ12+CD12+CK12 -> 138 | CP12: 116710 | CQ12: =CP12-CP11 -> 452 | CR12: =CQ12/G12 -> 0.72903226 | CS12: ='[2]Reading.5.23'!CN12 -> 254 | CT12: ='[2]Reading.5.23'!CO10 -> 0.41638796 | CV12: 5285 | CW12: =CV12-CV11 -> 1 | CX12: ='[2]Reading.5.23'!CT12 -> 3 | CZ12: 998 | DA12: =CZ12-CZ11 -> 6 | DB12: ='[2]Reading.5.23'!CX12 -> 6 | DD12: 1451783 | DE12: =DD12-DD11 -> 890 | DF12: ='[2]Reading.5.23'!DB12 -> 1030 | DH12: 3381450 | DI12: =DH12-DH11 -> 1910 | DJ12: ='[2]Reading.5.23'!DF12 -> 2182 | DL12: 2925655 | DM12: =DL12-DL11 -> 3592 | DN12: ='[2]Reading.5.23'!DJ12 -> 33 | DP12: 2307574 | DQ12: =DP12-DP11 -> 33 | DR12: ='[2]Reading.5.23'!DN12 -> 3215 | DT12: 3151423 | DU12: =DT12-DT11 -> 32 | DV12: ='[2]Reading.5.23'!DR12 -> 1541 | DX12: 720 | DZ12: =DM12+DQ12+DU12+DX12 -> 4377 | EA12: ='[2]Reading.5.23'!DW12 -> 5509 | EC12: =C12*5.2 -> 3224 | ED12: ='[2]Reading.5.23'!C12*5.2 -> 2990 | EF12: 61510 | EG12: =EF12-EF11 -> 49 | EJ12: 24634 | EK12: =EJ12-EJ11 -> 24
A13: 45420 | B13: 299492 | C13: =B13-B12 -> 489 | E13: 0 | F13: 810 | G13: =C13+D13-E13+F12-F13 -> 489 | H13: ='[2]Reading.5.23'!G13 -> 535 | J13: 208284 | K13: =(J13-J12)*4.668 -> 205.392 | L13: ='[2]Reading.5.23'!K13 -> 163.38 | N13: 734852 | O13: =(N13-N12)*4.61 -> 456.39 | P13: ='[2]Reading.5.23'!O13 -> 507.1 | R13: 42700 | T13: =(R12+S12)-R13 -> 0 | U13: ='[2]Reading.5.23'!T13 -> 0 | W13: 45973.95 | X13: =(W13-W12)*4000 -> 31680 | Y13: ='[2]Reading.5.23'!X13 -> 34360 | AA13: 520030 | AB13: =AA13-AA12 -> 0 | AC13: ='[2]Reading.5.23'!AB13 -> 0 | AE13: =+X13+AB13 -> 31680 | AF13: ='[2]Reading.5.23'!AE13 -> 34360 | AG13: =1090308/30 -> 36343.6 | AI13: 0.4696 | AJ13: ='[2]Reading.5.23'!AI13 -> 0.5418 | AK13: 0.687 | AM13: 247 | AN13: ='[2]Reading.5.23'!AM13 -> 285 | AO13: =11205/30 -> 373.5 | AQ13: =475*4 -> 1900 | AR13: ='[2]Reading.5.23'!AQ13 -> 1956 | AT13: 7177 | AU13: =(AT13-AT12)*4000 -> 3880 | AV13: =+X13/SQRT(((POWER((X13),2)+(POWER((AU13),2))))) -> 0.9925833 | AY13: ='[2]Reading.5.23'!X13 -> 34360 | AZ13: ='[2]Reading.5.23'!AB13 -> 0 | BA13: =AY13+AZ13 -> 34360 | BC13: 25 | BD13: 21 | BE13: 17 | BF13: 49 | BG13: 82 | BH13: ='[2]Reading.5.23'!BD13 -> 26.6 | BI13: ='[2]Reading.5.23'!BE13 -> 23 | BJ13: ='[2]Reading.5.23'!BF13 -> 54 | BL13: 526 | BN13: ='[2]Reading.5.23'!E11 -> 0 | BP13: 67510 | BQ13: =BP13-BP12 -> 30 | BR13: ='[2]Reading.5.23'!BQ13 -> 33 | BT13: 82535 | BU13: =BT13-BT12 -> 35 | BV13: ='[2]Reading.5.23'!BU13 -> 40 | BX13: 4053 | BY13: =BX13-BX12 -> 0 | BZ13: ='[2]Reading.5.23'!BY13 -> 0 | CB13: 234990 | CC13: =CB13-CB12 -> 40 | CD13: ='[2]Reading.5.23'!CC13 -> 45 | CF13: 6365 | CG13: =CF13-CF12 -> 5 | CH13: ='[2]Reading.5.23'!CG13 -> 0 | CI13: 19770 | CJ13: =CI13-CI12 -> 0 | CK13: ='[2]Reading.5.23'!CG13 -> 0 | CM13: =BQ13+BU13+BY13+CC13+CJ13 -> 105 | CN13: =BR13+BV13+BZ13+CD13+CK13 -> 118 | CP13: 117152 | CQ13: =CP13-CP12 -> 442 | CR13: =CQ13/G13 -> 0.90388548 | CS13: ='[2]Reading.5.23'!CN13 -> 169 | CT13: ='[2]Reading.5.23'!CO11 -> 0.49335863 | CV13: 5285 | CW13: =CV13-CV12 -> 0 | CX13: ='[2]Reading.5.23'!CT13 -> 3 | CZ13: 1002 | DA13: =CZ13-CZ12 -> 4 | DB13: ='[2]Reading.5.23'!CX13 -> 6 | DD13: 1452485 | DE13: =DD13-DD12 -> 702 | DF13: ='[2]Reading.5.23'!DB13 -> 1078 | DH13: 3383160 | DI13: =DH13-DH12 -> 1710 | DJ13: ='[2]Reading.5.23'!DF13 -> 1945 | DL13: 2929567 | DM13: =DL13-DL12 -> 3912 | DN13: ='[2]Reading.5.23'!DJ13 -> 33 | DP13: 2307608 | DQ13: =DP13-DP12 -> 34 | DR13: ='[2]Reading.5.23'!DN13 -> 3038 | DT13: 3151456 | DU13: =DT13-DT12 -> 33 | DV13: ='[2]Reading.5.23'!DR13 -> 1432 | DX13: 720 | DZ13: =DM13+DQ13+DU13+DX13 -> 4699 | EA13: ='[2]Reading.5.23'!DW13 -> 5223 | EC13: =C13*5.2 -> 2542.8 | ED13: ='[2]Reading.5.23'!C13*5.2 -> 2288 | EF13: 61561 | EG13: =EF13-EF12 -> 51 | EJ13: 24655 | EK13: =EJ13-EJ12 -> 21
A14: 45421 | B14: 300053 | C14: =B14-B13 -> 561 | E14: 0 | F14: 795 | G14: =C14+D14-E14+F13-F14 -> 576 | H14: ='[2]Reading.5.23'!G14 -> 513 | J14: 208326 | K14: =(J14-J13)*4.668 -> 196.056 | L14: ='[2]Reading.5.23'!K14 -> 154.044 | N14: 734953 | O14: =(N14-N13)*4.61 -> 465.61 | P14: ='[2]Reading.5.23'!O14 -> 474.83 | R14: 42700 | T14: =(R13+S13)-R14 -> 0 | U14: ='[2]Reading.5.23'!T14 -> 0 | W14: 45982.38 | X14: =(W14-W13)*4000 -> 33720 | Y14: ='[2]Reading.5.23'!X14 -> 36280 | AA14: 520030 | AB14: =AA14-AA13 -> 0 | AC14: ='[2]Reading.5.23'!AB14 -> 0 | AE14: =+X14+AB14 -> 33720 | AF14: ='[2]Reading.5.23'!AE14 -> 36280 | AG14: =1090308/30 -> 36343.6 | AI14: 0.4601 | AJ14: ='[2]Reading.5.23'!AI14 -> 0.5304 | AK14: 0.687 | AM14: 246 | AN14: ='[2]Reading.5.23'!AM14 -> 279 | AO14: =11205/30 -> 373.5 | AQ14: =475*4 -> 1900 | AR14: ='[2]Reading.5.23'!AQ14 -> 1956 | AT14: 7178.46 | AU14: =(AT14-AT13)*4000 -> 5840 | AV14: =+X14/SQRT(((POWER((X14),2)+(POWER((AU14),2))))) -> 0.98533161 | AY14: ='[2]Reading.5.23'!X14 -> 36280 | AZ14: ='[2]Reading.5.23'!AB14 -> 0 | BA14: =AY14+AZ14 -> 36280 | BC14: 25 | BD14: 21 | BE14: 17 | BF14: 49 | BG14: 82 | BH14: ='[2]Reading.5.23'!BD14 -> 29 | BI14: ='[2]Reading.5.23'!BE14 -> 25 | BJ14: ='[2]Reading.5.23'!BF14 -> 54 | BL14: 526 | BN14: ='[2]Reading.5.23'!E12 -> 0 | BP14: 67540 | BQ14: =BP14-BP13 -> 30 | BR14: ='[2]Reading.5.23'!BQ14 -> 41 | BT14: 82581 | BU14: =BT14-BT13 -> 46 | BV14: ='[2]Reading.5.23'!BU14 -> 38 | BX14: 4053 | BY14: =BX14-BX13 -> 0 | BZ14: ='[2]Reading.5.23'!BY14 -> 0 | CB14: 235040 | CC14: =CB14-CB13 -> 50 | CD14: ='[2]Reading.5.23'!CC14 -> 55 | CF14: 6375 | CG14: =CF14-CF13 -> 10 | CH14: ='[2]Reading.5.23'!CG14 -> 0 | CI14: 19770 | CJ14: =CI14-CI13 -> 0 | CK14: ='[2]Reading.5.23'!CG14 -> 0 | CM14: =BQ14+BU14+BY14+CC14+CJ14 -> 126 | CN14: =BR14+BV14+BZ14+CD14+CK14 -> 134 | CP14: 117495 | CQ14: =CP14-CP13 -> 343 | CR14: =CQ14/G14 -> 0.59548611 | CS14: ='[2]Reading.5.23'!CN14 -> 199 | CT14: ='[2]Reading.5.23'!CO12 -> 0.47037037 | CV14: 5285 | CW14: =CV14-CV13 -> 0 | CX14: ='[2]Reading.5.23'!CT14 -> 3 | CZ14: 1008 | DA14: =CZ14-CZ13 -> 6 | DB14: ='[2]Reading.5.23'!CX14 -> 6 | DD14: 1453438 | DE14: =DD14-DD13 -> 953 | DF14: ='[2]Reading.5.23'!DB14 -> 989 | DH14: 3384981 | DI14: =DH14-DH13 -> 1821 | DJ14: ='[2]Reading.5.23'!DF14 -> 2272 | DL14: 2933590 | DM14: =DL14-DL13 -> 4023 | DN14: ='[2]Reading.5.23'!DJ14 -> 33 | DP14: 2307640 | DQ14: =DP14-DP13 -> 32 | DR14: ='[2]Reading.5.23'!DN14 -> 3068 | DT14: 3151487 | DU14: =DT14-DT13 -> 31 | DV14: ='[2]Reading.5.23'!DR14 -> 1251 | DX14: 720 | DZ14: =DM14+DQ14+DU14+DX14 -> 4806 | EA14: ='[2]Reading.5.23'!DW14 -> 5072 | EC14: =C14*5.2 -> 2917.2 | ED14: ='[2]Reading.5.23'!C14*5.2 -> 2875.6 | EF14: 61611 | EG14: =EF14-EF13 -> 50 | EJ14: 24675 | EK14: =EJ14-EJ13 -> 20
A15: 45422 | B15: 300666 | C15: =B15-B14 -> 613 | E15: 0 | F15: 835 | G15: =C15+D15-E15+F14-F15 -> 573 | H15: ='[2]Reading.5.23'!G15 -> 543 | J15: 208359 | K15: =(J15-J14)*4.668 -> 154.044 | L15: ='[2]Reading.5.23'!K15 -> 172.716 | N15: 735056 | O15: =(N15-N14)*4.61 -> 474.83 | P15: ='[2]Reading.5.23'!O15 -> 465.61 | R15: 42700 | T15: =(R14+S14)-R15 -> 0 | U15: ='[2]Reading.5.23'!T15 -> 0 | W15: 45990.69 | X15: =(W15-W14)*4000 -> 33240 | Y15: ='[2]Reading.5.23'!X15 -> 33600 | AA15: 520040 | AB15: =AA15-AA14 -> 10 | AC15: ='[2]Reading.5.23'!AB15 -> 0 | AE15: =+X15+AB15 -> 33250 | AF15: ='[2]Reading.5.23'!AE15 -> 33600 | AG15: =1090308/30 -> 36343.6 | AI15: 0.4316 | AJ15: ='[2]Reading.5.23'!AI15 -> 0.6198 | AK15: 0.687 | AM15: 227 | AN15: ='[2]Reading.5.23'!AM15 -> 326 | AO15: =11205/30 -> 373.5 | AQ15: =475*4 -> 1900 | AR15: ='[2]Reading.5.23'!AQ15 -> 1956 | AT15: 7179.63 | AU15: =(AT15-AT14)*4000 -> 4680 | AV15: =+X15/SQRT(((POWER((X15),2)+(POWER((AU15),2))))) -> 0.99023346 | AY15: ='[2]Reading.5.23'!X15 -> 33600 | AZ15: ='[2]Reading.5.23'!AB15 -> 0 | BA15: =AY15+AZ15 -> 33600 | BC15: 25 | BD15: 21 | BE15: 17 | BF15: 49 | BG15: 82 | BH15: ='[2]Reading.5.23'!BD15 -> 29 | BI15: ='[2]Reading.5.23'!BE15 -> 26 | BJ15: ='[2]Reading.5.23'!BF15 -> 65 | BL15: 526 | BN15: ='[2]Reading.5.23'!E13 -> 0 | BP15: 67573 | BQ15: =BP15-BP14 -> 33 | BR15: ='[2]Reading.5.23'!BQ15 -> 45 | BT15: 82619 | BU15: =BT15-BT14 -> 38 | BV15: ='[2]Reading.5.23'!BU15 -> 38 | BX15: 4053 | BY15: =BX15-BX14 -> 0 | BZ15: ='[2]Reading.5.23'!BY15 -> 0 | CB15: 235070 | CC15: =CB15-CB14 -> 30 | CD15: ='[2]Reading.5.23'!CC15 -> 45 | CF15: 6380 | CG15: =CF15-CF14 -> 5 | CH15: ='[2]Reading.5.23'!CG15 -> 0 | CI15: 19770 | CJ15: =CI15-CI14 -> 0 | CK15: ='[2]Reading.5.23'!CG15 -> 0 | CM15: =BQ15+BU15+BY15+CC15+CJ15 -> 101 | CN15: =BR15+BV15+BZ15+CD15+CK15 -> 128 | CP15: 117845 | CQ15: =CP15-CP14 -> 350 | CR15: =CQ15/G15 -> 0.61082024 | CS15: ='[2]Reading.5.23'!CN15 -> 201 | CT15: ='[2]Reading.5.23'!CO13 -> 0.31588785 | CV15: 5285 | CW15: =CV15-CV14 -> 0 | CX15: ='[2]Reading.5.23'!CT15 -> 5 | CZ15: 1014 | DA15: =CZ15-CZ14 -> 6 | DB15: ='[2]Reading.5.23'!CX15 -> 4 | DD15: 1454425 | DE15: =DD15-DD14 -> 987 | DF15: ='[2]Reading.5.23'!DB15 -> 1013 | DH15: 3387067 | DI15: =DH15-DH14 -> 2086 | DJ15: ='[2]Reading.5.23'!DF15 -> 2214 | DL15: 2937994 | DM15: =DL15-DL14 -> 4404 | DN15: ='[2]Reading.5.23'!DJ15 -> 32 | DP15: 2307673 | DQ15: =DP15-DP14 -> 33 | DR15: ='[2]Reading.5.23'!DN15 -> 3188 | DT15: 3151519 | DU15: =DT15-DT14 -> 32 | DV15: ='[2]Reading.5.23'!DR15 -> 1421 | DX15: 720 | DZ15: =DM15+DQ15+DU15+DX15 -> 5189 | EA15: ='[2]Reading.5.23'!DW15 -> 5361 | EC15: =C15*5.2 -> 3187.6 | ED15: ='[2]Reading.5.23'!C15*5.2 -> 2979.6 | EF15: 61665 | EG15: =EF15-EF14 -> 54 | EJ15: 24696 | EK15: =EJ15-EJ14 -> 21
A16: 45423 | B16: 301200 | C16: =B16-B15 -> 534 | E16: 0 | F16: 825 | G16: =C16+D16-E16+F15-F16 -> 544 | H16: ='[2]Reading.5.23'!G16 -> 539 | J16: 208402 | K16: =(J16-J15)*4.668 -> 200.724 | L16: ='[2]Reading.5.23'!K16 -> 182.052 | N16: 735160 | O16: =(N16-N15)*4.61 -> 479.44 | P16: ='[2]Reading.5.23'!O16 -> 479.44 | R16: 42700 | T16: =(R15+S15)-R16 -> 0 | U16: ='[2]Reading.5.23'!T16 -> 0 | W16: 45998.97 | X16: =(W16-W15)*4000 -> 33120 | Y16: ='[2]Reading.5.23'!X16 -> 35320 | AA16: 520040 | AB16: =AA16-AA15 -> 0 | AC16: ='[2]Reading.5.23'!AB16 -> 0 | AE16: =+X16+AB16 -> 33120 | AF16: ='[2]Reading.5.23'!AE16 -> 35320 | AG16: =1090308/30 -> 36343.6 | AI16: 0.4449 | AJ16: ='[2]Reading.5.23'!AI16 -> 0.6521 | AK16: 0.687 | AM16: 234 | AN16: ='[2]Reading.5.23'!AM16 -> 343 | AO16: =11205/30 -> 373.5 | AQ16: =475*4 -> 1900 | AR16: ='[2]Reading.5.23'!AQ16 -> 1956 | AT16: 7181.13 | AU16: =(AT16-AT15)*4000 -> 6000 | AV16: =+X16/SQRT(((POWER((X16),2)+(POWER((AU16),2))))) -> 0.9839838 | AY16: ='[2]Reading.5.23'!X16 -> 35320 | AZ16: ='[2]Reading.5.23'!AB16 -> 0 | BA16: =AY16+AZ16 -> 35320 | BC16: 25 | BD16: 21 | BE16: 17 | BF16: 49 | BG16: 82 | BH16: ='[2]Reading.5.23'!BD16 -> 29 | BI16: ='[2]Reading.5.23'!BE16 -> 26 | BJ16: ='[2]Reading.5.23'!BF16 -> 65 | BL16: 526 | BN16: ='[2]Reading.5.23'!E14 -> 0 | BP16: 67600 | BQ16: =BP16-BP15 -> 27 | BR16: ='[2]Reading.5.23'!BQ16 -> 39 | BT16: 82662 | BU16: =BT16-BT15 -> 43 | BV16: ='[2]Reading.5.23'!BU16 -> 30 | BX16: 4053 | BY16: =BX16-BX15 -> 0 | BZ16: ='[2]Reading.5.23'!BY16 -> 0 | CB16: 235110 | CC16: =CB16-CB15 -> 40 | CD16: ='[2]Reading.5.23'!CC16 -> 90 | CF16: 6385 | CG16: =CF16-CF15 -> 5 | CH16: ='[2]Reading.5.23'!CG16 -> 0 | CI16: 19770 | CJ16: =CI16-CI15 -> 0 | CK16: ='[2]Reading.5.23'!CG16 -> 0 | CM16: =BQ16+BU16+BY16+CC16+CJ16 -> 110 | CN16: =BR16+BV16+BZ16+CD16+CK16 -> 159 | CP16: 118165 | CQ16: =CP16-CP15 -> 320 | CR16: =CQ16/G16 -> 0.58823529 | CS16: ='[2]Reading.5.23'!CN16 -> 220 | CT16: ='[2]Reading.5.23'!CO14 -> 0.38791423 | CV16: 5285 | CW16: =CV16-CV15 -> 0 | CX16: ='[2]Reading.5.23'!CT16 -> 3 | CZ16: 1018 | DA16: =CZ16-CZ15 -> 4 | DB16: ='[2]Reading.5.23'!CX16 -> 7 | DD16: 1455438 | DE16: =DD16-DD15 -> 1013 | DF16: ='[2]Reading.5.23'!DB16 -> 969 | DH16: 3388807 | DI16: =DH16-DH15 -> 1740 | DJ16: ='[2]Reading.5.23'!DF16 -> 2114 | DL16: 2939647 | DM16: =DL16-DL15 -> 1653 | DN16: ='[2]Reading.5.23'!DJ16 -> 33 | DP16: 2310752 | DQ16: =DP16-DP15 -> 3079 | DR16: ='[2]Reading.5.23'!DN16 -> 3283 | DT16: 3151550 | DU16: =DT16-DT15 -> 31 | DV16: ='[2]Reading.5.23'!DR16 -> 1525 | DX16: 720 | DZ16: =DM16+DQ16+DU16+DX16 -> 5483 | EA16: ='[2]Reading.5.23'!DW16 -> 5561 | EC16: =C16*5.2 -> 2776.8 | ED16: ='[2]Reading.5.23'!C16*5.2 -> 2828.8 | EF16: 61727 | EG16: =EF16-EF15 -> 62 | EJ16: 24720 | EK16: =EJ16-EJ15 -> 24
A17: 45424 | B17: 301709 | C17: =B17-B16 -> 509 | E17: 0 | F17: 820 | G17: =C17+D17-E17+F16-F17 -> 514 | H17: ='[2]Reading.5.23'!G17 -> 523 | J17: 208436 | K17: =(J17-J16)*4.668 -> 158.712 | L17: ='[2]Reading.5.23'!K17 -> 144.708 | N17: 735247 | O17: =(N17-N16)*4.61 -> 401.07 | P17: ='[2]Reading.5.23'!O17 -> 461 | R17: 42700 | T17: =(R16+S16)-R17 -> 0 | U17: ='[2]Reading.5.23'!T17 -> 0 | W17: 46006.88 | X17: =(W17-W16)*4000 -> 31640 | Y17: ='[2]Reading.5.23'!X17 -> 35640 | AA17: 520034 | AB17: =AA17-AA16 -> -6 | AC17: ='[2]Reading.5.23'!AB17 -> 0 | AE17: =+X17+AB17 -> 31634 | AF17: ='[2]Reading.5.23'!AE17 -> 35640 | AG17: =1090308/30 -> 36343.6 | AI17: 0.4411 | AJ17: ='[2]Reading.5.23'!AI17 -> 0.6293 | AK17: 0.687 | AM17: 232 | AN17: ='[2]Reading.5.23'!AM17 -> 331 | AO17: =11205/30 -> 373.5 | AQ17: =475*4 -> 1900 | AR17: ='[2]Reading.5.23'!AQ17 -> 1956 | AT17: 7182.63 | AU17: =(AT17-AT16)*4000 -> 6000 | AV17: =+X17/SQRT(((POWER((X17),2)+(POWER((AU17),2))))) -> 0.98249044 | AY17: ='[2]Reading.5.23'!X17 -> 35640 | AZ17: ='[2]Reading.5.23'!AB17 -> 0 | BA17: =AY17+AZ17 -> 35640 | BC17: 25 | BD17: 21 | BE17: 17 | BF17: 49 | BG17: 82 | BH17: ='[2]Reading.5.23'!BD17 -> 27 | BI17: ='[2]Reading.5.23'!BE17 -> 21 | BJ17: ='[2]Reading.5.23'!BF17 -> 65 | BL17: 526 | BN17: ='[2]Reading.5.23'!E15 -> 0 | BP17: 67630 | BQ17: =BP17-BP16 -> 30 | BR17: ='[2]Reading.5.23'!BQ17 -> 28 | BT17: 82696 | BU17: =BT17-BT16 -> 34 | BV17: ='[2]Reading.5.23'!BU17 -> 35 | BX17: 4053 | BY17: =BX17-BX16 -> 0 | BZ17: ='[2]Reading.5.23'!BY17 -> 2 | CB17: 235150 | CC17: =CB17-CB16 -> 40 | CD17: ='[2]Reading.5.23'!CC17 -> 40 | CF17: 6390 | CG17: =CF17-CF16 -> 5 | CH17: ='[2]Reading.5.23'!CG17 -> 0 | CI17: 19770 | CJ17: =CI17-CI16 -> 0 | CK17: ='[2]Reading.5.23'!CG17 -> 0 | CM17: =BQ17+BU17+BY17+CC17+CJ17 -> 104 | CN17: =BR17+BV17+BZ17+CD17+CK17 -> 105 | CP17: 118505 | CQ17: =CP17-CP16 -> 340 | CR17: =CQ17/G17 -> 0.6614786 | CS17: ='[2]Reading.5.23'!CN17 -> 249 | CT17: ='[2]Reading.5.23'!CO15 -> 0.37016575 | CV17: 5285 | CW17: =CV17-CV16 -> 0 | CX17: ='[2]Reading.5.23'!CT17 -> 3 | CZ17: 1022 | DA17: =CZ17-CZ16 -> 4 | DB17: ='[2]Reading.5.23'!CX17 -> 5 | DD17: 1456409 | DE17: =DD17-DD16 -> 971 | DF17: ='[2]Reading.5.23'!DB17 -> 1047 | DH17: 3389941 | DI17: =DH17-DH16 -> 1134 | DJ17: ='[2]Reading.5.23'!DF17 -> 1712 | DL17: 2939678 | DM17: =DL17-DL16 -> 31 | DN17: ='[2]Reading.5.23'!DJ17 -> 33 | DP17: 2315262 | DQ17: =DP17-DP16 -> 4510 | DR17: ='[2]Reading.5.23'!DN17 -> 4240 | DT17: 3151581 | DU17: =DT17-DT16 -> 31 | DV17: ='[2]Reading.5.23'!DR17 -> 1685 | DX17: 720 | DZ17: =DM17+DQ17+DU17+DX17 -> 5292 | EA17: ='[2]Reading.5.23'!DW17 -> 6678 | EC17: =C17*5.2 -> 2646.8 | ED17: ='[2]Reading.5.23'!C17*5.2 -> 2823.6 | EF17: 61797 | EG17: =EF17-EF16 -> 70 | EJ17: 24740 | EK17: =EJ17-EJ16 -> 20
A18: 45425 | B18: 302261 | C18: =B18-B17 -> 552 | E18: 0 | F18: 780 | G18: =C18+D18-E18+F17-F18 -> 592 | H18: ='[2]Reading.5.23'!G18 -> 533 | J18: 208475 | K18: =(J18-J17)*4.668 -> 182.052 | L18: ='[2]Reading.5.23'!K18 -> 182.052 | N18: 735344 | O18: =(N18-N17)*4.61 -> 447.17 | P18: ='[2]Reading.5.23'!O18 -> 548.59 | R18: 42700 | T18: =(R17+S17)-R18 -> 0 | U18: ='[2]Reading.5.23'!T18 -> 0 | W18: 46015.11 | X18: =(W18-W17)*4000 -> 32920 | Y18: ='[2]Reading.5.23'!X18 -> 36560 | AA18: 520034 | AB18: =AA18-AA17 -> 0 | AC18: ='[2]Reading.5.23'!AB18 -> 0 | AE18: =+X18+AB18 -> 32920 | AF18: ='[2]Reading.5.23'!AE18 -> 36560 | AG18: =1090308/30 -> 36343.6 | AI18: 0.443 | AJ18: ='[2]Reading.5.23'!AI18 -> 0.6958 | AK18: 0.687 | AM18: 233 | AN18: ='[2]Reading.5.23'!AM18 -> 366 | AO18: =11205/30 -> 373.5 | AQ18: =475*4 -> 1900 | AR18: ='[2]Reading.5.23'!AQ18 -> 1956 | AT18: 7184.23 | AU18: =(AT18-AT17)*4000 -> 6400 | AV18: =+X18/SQRT(((POWER((X18),2)+(POWER((AU18),2))))) -> 0.9816216 | AY18: ='[2]Reading.5.23'!X18 -> 36560 | AZ18: ='[2]Reading.5.23'!AB18 -> 0 | BA18: =AY18+AZ18 -> 36560 | BC18: 25 | BD18: 21 | BE18: 17 | BF18: 49 | BG18: 82 | BH18: ='[2]Reading.5.23'!BD18 -> 27 | BI18: ='[2]Reading.5.23'!BE18 -> 22 | BJ18: ='[2]Reading.5.23'!BF18 -> 65 | BL18: 526 | BN18: ='[2]Reading.5.23'!E16 -> 0 | BP18: 67663 | BQ18: =BP18-BP17 -> 33 | BR18: ='[2]Reading.5.23'!BQ18 -> 39 | BT18: 82733 | BU18: =BT18-BT17 -> 37 | BV18: ='[2]Reading.5.23'!BU18 -> 43 | BX18: 4053 | BY18: =BX18-BX17 -> 0 | BZ18: ='[2]Reading.5.23'!BY18 -> 0 | CB18: 235230 | CC18: =CB18-CB17 -> 80 | CD18: ='[2]Reading.5.23'!CC18 -> 30 | CF18: 6395 | CG18: =CF18-CF17 -> 5 | CH18: ='[2]Reading.5.23'!CG18 -> 0 | CI18: 19770 | CJ18: =CI18-CI17 -> 0 | CK18: ='[2]Reading.5.23'!CG18 -> 0 | CM18: =BQ18+BU18+BY18+CC18+CJ18 -> 150 | CN18: =BR18+BV18+BZ18+CD18+CK18 -> 112 | CP18: 118905 | CQ18: =CP18-CP17 -> 400 | CR18: =CQ18/G18 -> 0.67567568 | CS18: ='[2]Reading.5.23'!CN18 -> 248 | CT18: ='[2]Reading.5.23'!CO16 -> 0.40816327 | CV18: 5285 | CW18: =CV18-CV17 -> 0 | CX18: ='[2]Reading.5.23'!CT18 -> 4 | CZ18: 1028 | DA18: =CZ18-CZ17 -> 6 | DB18: ='[2]Reading.5.23'!CX18 -> 6 | DD18: 1457315 | DE18: =DD18-DD17 -> 906 | DF18: ='[2]Reading.5.23'!DB18 -> 1156 | DH18: 3392344 | DI18: =DH18-DH17 -> 2403 | DJ18: ='[2]Reading.5.23'!DF18 -> 2586 | DL18: 2939710 | DM18: =DL18-DL17 -> 32 | DN18: ='[2]Reading.5.23'!DJ18 -> 33 | DP18: 2319335 | DQ18: =DP18-DP17 -> 4073 | DR18: ='[2]Reading.5.23'!DN18 -> 2157 | DT18: 3151612 | DU18: =DT18-DT17 -> 31 | DV18: ='[2]Reading.5.23'!DR18 -> 1708 | DX18: 720 | DZ18: =DM18+DQ18+DU18+DX18 -> 4856 | EA18: ='[2]Reading.5.23'!DW18 -> 4618 | EC18: =C18*5.2 -> 2870.4 | ED18: ='[2]Reading.5.23'!C18*5.2 -> 2875.6 | EF18: 61820 | EG18: =EF18-EF17 -> 23 | EJ18: 24763 | EK18: =EJ18-EJ17 -> 23
A19: 45426 | B19: 302858 | C19: =B19-B18 -> 597 | E19: 0 | F19: 810 | G19: =C19+D19-E19+F18-F19 -> 567 | H19: ='[2]Reading.5.23'!G19 -> 602 | J19: 208511 | K19: =(J19-J18)*4.668 -> 168.048 | L19: ='[2]Reading.5.23'!K19 -> 205.392 | N19: 735437 | O19: =(N19-N18)*4.61 -> 428.73 | P19: ='[2]Reading.5.23'!O19 -> 507.1 | R19: 42700 | T19: =(R18+S18)-R19 -> 0 | U19: ='[2]Reading.5.23'!T19 -> 0 | W19: 46022.53 | X19: =(W19-W18)*4000 -> 29680 | Y19: ='[2]Reading.5.23'!X19 -> 36000 | AA19: 520034 | AB19: =AA19-AA18 -> 0 | AC19: ='[2]Reading.5.23'!AB19 -> 0 | AE19: =+X19+AB19 -> 29680 | AF19: ='[2]Reading.5.23'!AE19 -> 36000 | AG19: =1090308/30 -> 36343.6 | AI19: 0.4392 | AJ19: ='[2]Reading.5.23'!AI19 -> 0.7072 | AK19: 0.687 | AM19: 231 | AN19: ='[2]Reading.5.23'!AM19 -> 372 | AO19: =11205/30 -> 373.5 | AQ19: =475*4 -> 1900 | AR19: ='[2]Reading.5.23'!AQ19 -> 1956 | AT19: 7184.89 | AU19: =(AT19-AT18)*4000 -> 2640 | AV19: =+X19/SQRT(((POWER((X19),2)+(POWER((AU19),2))))) -> 0.99606738 | AY19: ='[2]Reading.5.23'!X19 -> 36000 | AZ19: ='[2]Reading.5.23'!AB19 -> 0 | BA19: =AY19+AZ19 -> 36000 | BC19: 25 | BD19: 21 | BE19: 17 | BF19: 49 | BG19: 82 | BH19: ='[2]Reading.5.23'!BD19 -> 27 | BI19: ='[2]Reading.5.23'!BE19 -> 22 | BJ19: ='[2]Reading.5.23'!BF19 -> 69 | BL19: 526 | BN19: ='[2]Reading.5.23'!E17 -> 0 | BP19: 67694 | BQ19: =BP19-BP18 -> 31 | BR19: ='[2]Reading.5.23'!BQ19 -> 31 | BT19: 82770 | BU19: =BT19-BT18 -> 37 | BV19: ='[2]Reading.5.23'!BU19 -> 36 | BX19: 4053 | BY19: =BX19-BX18 -> 0 | BZ19: ='[2]Reading.5.23'!BY19 -> 0 | CB19: 235290 | CC19: =CB19-CB18 -> 60 | CD19: ='[2]Reading.5.23'!CC19 -> 60 | CF19: 6400 | CG19: =CF19-CF18 -> 5 | CH19: ='[2]Reading.5.23'!CG19 -> 0 | CI19: 19770 | CJ19: =CI19-CI18 -> 0 | CK19: ='[2]Reading.5.23'!CG19 -> 0 | CM19: =BQ19+BU19+BY19+CC19+CJ19 -> 128 | CN19: =BR19+BV19+BZ19+CD19+CK19 -> 127 | CP19: 119400 | CQ19: =CP19-CP18 -> 495 | CR19: =CQ19/G19 -> 0.87301587 | CS19: ='[2]Reading.5.23'!CN19 -> 225 | CT19: ='[2]Reading.5.23'!CO17 -> 0.47609943 | CV19: 5285 | CW19: =CV19-CV18 -> 0 | CX19: ='[2]Reading.5.23'!CT19 -> 3 | CZ19: 1034 | DA19: =CZ19-CZ18 -> 6 | DB19: ='[2]Reading.5.23'!CX19 -> 6 | DD19: 1458116 | DE19: =DD19-DD18 -> 801 | DF19: ='[2]Reading.5.23'!DB19 -> 1048 | DH19: 3394066 | DI19: =DH19-DH18 -> 1722 | DJ19: ='[2]Reading.5.23'!DF19 -> 1909 | DL19: 2939742 | DM19: =DL19-DL18 -> 32 | DN19: ='[2]Reading.5.23'!DJ19 -> 33 | DP19: 2323406 | DQ19: =DP19-DP18 -> 4071 | DR19: ='[2]Reading.5.23'!DN19 -> 3142 | DT19: 3151644 | DU19: =DT19-DT18 -> 32 | DV19: ='[2]Reading.5.23'!DR19 -> 1573 | DX19: 720 | DZ19: =DM19+DQ19+DU19+DX19 -> 4855 | EA19: ='[2]Reading.5.23'!DW19 -> 5468 | EC19: =C19*5.2 -> 3104.4 | ED19: ='[2]Reading.5.23'!C19*5.2 -> 2948.4 | EF19: 61868 | EG19: =EF19-EF18 -> 48 | EJ19: 24783 | EK19: =EJ19-EJ18 -> 20
... A22: 45429 | B22: 304574 | C22: =B22-B21 -> 596 | E22: 0 | F22: 770 | G22: =C22+D22-E22+F21-F22 -> 581 | H22: ='[2]Reading.5.23'!G22 -> 575 | J22: 208615 | K22: =(J22-J21)*4.668 -> 144.708 | L22: ='[2]Reading.5.23'!K22 -> 196.056 | N22: 735726 | O22: =(N22-N21)*4.61 -> 447.17 | P22: ='[2]Reading.5.23'!O22 -> 502.49 | R22: 42700 | T22: =(R21+S21)-R22 -> 0 | U22: ='[2]Reading.5.23'!T22 -> 0 | W22: 46048.38 | X22: =(W22-W21)*4000 -> 34600 | Y22: ='[2]Reading.5.23'!X22 -> 38320 | AA22: 520034 | AB22: =AA22-AA21 -> 0 | AC22: ='[2]Reading.5.23'!AB22 -> 0 | AE22: =+X22+AB22 -> 34600 | AF22: ='[2]Reading.5.23'!AE22 -> 38320 | AG22: =1090308/30 -> 36343.6 | AI22: 0.5209 | AJ22: ='[2]Reading.5.23'!AI22 -> 0.814 | AK22: 0.687 | AM22: 274 | AN22: ='[2]Reading.5.23'!AM22 -> 428 | AO22: =11205/30 -> 373.5 | AQ22: =475*4 -> 1900 | AR22: ='[2]Reading.5.23'!AQ22 -> 2064 | AT22: 7191.93 | AU22: =(AT22-AT21)*4000 -> 9360 | AV22: =+X22/SQRT(((POWER((X22),2)+(POWER((AU22),2))))) -> 0.96530259 | AY22: ='[2]Reading.5.23'!X22 -> 38320 | AZ22: ='[2]Reading.5.23'!AB22 -> 0 | BA22: =AY22+AZ22 -> 38320 | BC22: 25 | BD22: 21 | BE22: 17 | BF22: 49 | BG22: 82 | BH22: ='[2]Reading.5.23'!BD22 -> 29.2 | BI22: ='[2]Reading.5.23'!BE22 -> 26 | BJ22: ='[2]Reading.5.23'!BF22 -> 89 | BL22: 526 | BN22: ='[2]Reading.5.23'!E20 -> 0 | BP22: 67785 | BQ22: =BP22-BP21 -> 28 | BR22: ='[2]Reading.5.23'!BQ22 -> 37 | BT22: 82887 | BU22: =BT22-BT21 -> 35 | BV22: ='[2]Reading.5.23'!BU22 -> 35 | BX22: 4053 | BY22: =BX22-BX21 -> 0 | BZ22: ='[2]Reading.5.23'!BY22 -> 0 | CB22: 235490 | CC22: =CB22-CB21 -> 50 | CD22: ='[2]Reading.5.23'!CC22 -> 50 | CF22: 6415 | CG22: =CF22-CF21 -> 10 | CH22: ='[2]Reading.5.23'!CG22 -> 0 | CI22: 19770 | CJ22: =CI22-CI21 -> 0 | CK22: ='[2]Reading.5.23'!CG22 -> 0 | CM22: =BQ22+BU22+BY22+CC22+CJ22 -> 113 | CN22: =BR22+BV22+BZ22+CD22+CK22 -> 122 | CP22: 120873 | CQ22: =CP22-CP21 -> 518 | CR22: =CQ22/G22 -> 0.89156627 | CS22: ='[2]Reading.5.23'!CN22 -> 250 | CT22: ='[2]Reading.5.23'!CO20 -> 0.42424242 | CV22: 5285 | CW22: =CV22-CV21 -> 0 | CX22: ='[2]Reading.5.23'!CT22 -> 4 | CZ22: 1049 | DA22: =CZ22-CZ21 -> 5 | DB22: ='[2]Reading.5.23'!CX22 -> 4 | DD22: 1460495 | DE22: =DD22-DD21 -> 789 | DF22: ='[2]Reading.5.23'!DB22 -> 1176 | DH22: 3398875 | DI22: =DH22-DH21 -> 1565 | DJ22: ='[2]Reading.5.23'!DF22 -> 1879 | DL22: 2944102 | DM22: =DL22-DL21 -> 1370 | DN22: ='[2]Reading.5.23'!DJ22 -> 30 | DP22: 2330198 | DQ22: =DP22-DP21 -> 1381 | DR22: ='[2]Reading.5.23'!DN22 -> 2366 | DT22: 3153517 | DU22: =DT22-DT21 -> 1817 | DV22: ='[2]Reading.5.23'!DR22 -> 3259 | DX22: 720 | DZ22: =DM22+DQ22+DU22+DX22 -> 5288 | EA22: ='[2]Reading.5.23'!DW22 -> 6375 | EC22: =C22*5.2 -> 3099.2 | ED22: ='[2]Reading.5.23'!C22*5.2 -> 2964 | EF22: 62040 | EG22: =EF22-EF21 -> 49 | EJ22: 24850 | EK22: =EJ22-EJ21 -> 21
A23: 45430 | B23: 305169 | C23: =B23-B22 -> 595 | E23: 0 | F23: 770 | G23: =C23+D23-E23+F22-F23 -> 595 | H23: ='[2]Reading.5.23'!G23 -> 616 | J23: 208650 | K23: =(J23-J22)*4.668 -> 163.38 | L23: ='[2]Reading.5.23'!K23 -> 214.728 | N23: 735824 | O23: =(N23-N22)*4.61 -> 451.78 | P23: ='[2]Reading.5.23'!O23 -> 659.23 | R23: 42700 | T23: =(R22+S22)-R23 -> 0 | U23: ='[2]Reading.5.23'!T23 -> 0 | W23: 46057.03 | X23: =(W23-W22)*4000 -> 34600 | Y23: ='[2]Reading.5.23'!X23 -> 39880 | AA23: 520034 | AB23: =AA23-AA22 -> 0 | AC23: ='[2]Reading.5.23'!AB23 -> 0 | AE23: =+X23+AB23 -> 34600 | AF23: ='[2]Reading.5.23'!AE23 -> 39880 | AG23: =1090308/30 -> 36343.6 | AI23: 0.5209 | AJ23: ='[2]Reading.5.23'!AI23 -> 0.8023 | AK23: 0.687 | AM23: 274 | AN23: ='[2]Reading.5.23'!AM23 -> 422 | AO23: =11205/30 -> 373.5 | AQ23: =478*4 -> 1912 | AR23: ='[2]Reading.5.23'!AQ23 -> 2092 | AT23: 7194.14 | AU23: =(AT23-AT22)*4000 -> 8840 | AV23: =+X23/SQRT(((POWER((X23),2)+(POWER((AU23),2))))) -> 0.96887771 | AY23: ='[2]Reading.5.23'!X23 -> 39880 | AZ23: ='[2]Reading.5.23'!AB23 -> 0 | BA23: =AY23+AZ23 -> 39880 | BC23: 25 | BD23: 21 | BE23: 17 | BF23: 49 | BG23: 82 | BH23: ='[2]Reading.5.23'!BD23 -> 27.8 | BI23: ='[2]Reading.5.23'!BE23 -> 23 | BJ23: ='[2]Reading.5.23'!BF23 -> 100 | BL23: 526 | BN23: ='[2]Reading.5.23'!E21 -> 0 | BP23: 67827 | BQ23: =BP23-BP22 -> 42 | BR23: ='[2]Reading.5.23'!BQ23 -> 47 | BT23: 82922 | BU23: =BT23-BT22 -> 35 | BV23: ='[2]Reading.5.23'!BU23 -> 53 | BX23: 4053 | BY23: =BX23-BX22 -> 0 | BZ23: ='[2]Reading.5.23'!BY23 -> 0 | CB23: 235550 | CC23: =CB23-CB22 -> 60 | CD23: ='[2]Reading.5.23'!CC23 -> 50 | CF23: 6420 | CG23: =CF23-CF22 -> 5 | CH23: ='[2]Reading.5.23'!CG23 -> 0 | CI23: 19770 | CJ23: =CI23-CI22 -> 0 | CK23: ='[2]Reading.5.23'!CG23 -> 0 | CM23: =BQ23+BU23+BY23+CC23+CJ23 -> 137 | CN23: =BR23+BV23+BZ23+CD23+CK23 -> 150 | CP23: 121343 | CQ23: =CP23-CP22 -> 470 | CR23: =CQ23/G23 -> 0.78991597 | CS23: ='[2]Reading.5.23'!CN23 -> 280 | CT23: ='[2]Reading.5.23'!CO21 -> 0.41894353 | CV23: 5285 | CW23: =CV23-CV22 -> 0 | CX23: ='[2]Reading.5.23'!CT23 -> 5 | CZ23: 1054 | DA23: =CZ23-CZ22 -> 5 | DB23: ='[2]Reading.5.23'!CX23 -> 8 | DD23: 1461684 | DE23: =DD23-DD22 -> 1189 | DF23: ='[2]Reading.5.23'!DB23 -> 1058 | DH23: 3400989 | DI23: =DH23-DH22 -> 2114 | DJ23: ='[2]Reading.5.23'!DF23 -> 2338 | DL23: 2944146 | DM23: =DL23-DL22 -> 44 | DN23: ='[2]Reading.5.23'!DJ23 -> 32 | DP23: 2330243 | DQ23: =DP23-DP22 -> 45 | DR23: ='[2]Reading.5.23'!DN23 -> 3361 | DT23: 3159692 | DU23: =DT23-DT22 -> 6175 | DV23: ='[2]Reading.5.23'!DR23 -> 2294 | DX23: 720 | DZ23: =DM23+DQ23+DU23+DX23 -> 6984 | EA23: ='[2]Reading.5.23'!DW23 -> 6407 | EC23: =C23*5.2 -> 3094 | ED23: ='[2]Reading.5.23'!C23*5.2 -> 3541.2 | EF23: 62126 | EG23: =EF23-EF22 -> 86 | EJ23: 24878 | EK23: =EJ23-EJ22 -> 28
A24: 45431 | B24: 305769 | C24: =B24-B23 -> 600 | E24: 0 | F24: 835 | G24: =C24+D24-E24+F23-F24 -> 535 | H24: ='[2]Reading.5.23'!G24 -> 598 | J24: 208689 | K24: =(J24-J23)*4.668 -> 182.052 | L24: ='[2]Reading.5.23'!K24 -> 205.392 | N24: 735926 | O24: =(N24-N23)*4.61 -> 470.22 | P24: ='[2]Reading.5.23'!O24 -> 553.2 | R24: 42700 | T24: =(R23+S23)-R24 -> 0 | U24: ='[2]Reading.5.23'!T24 -> 0 | W24: 46066.59 | X24: =(W24-W23)*4000 -> 38240 | Y24: ='[2]Reading.5.23'!X24 -> 38680 | AA24: 520034 | AB24: =AA24-AA23 -> 0 | AC24: ='[2]Reading.5.23'!AB24 -> 0 | AE24: =+X24+AB24 -> 38240 | AF24: ='[2]Reading.5.23'!AE24 -> 38680 | AG24: =1090308/30 -> 36343.6 | AI24: 0.4677 | AJ24: ='[2]Reading.5.23'!AI24 -> 0.7662 | AK24: 0.687 | AM24: 246 | AN24: ='[2]Reading.5.23'!AM24 -> 403 | AO24: =11205/30 -> 373.5 | AQ24: =499*4 -> 1996 | AR24: ='[2]Reading.5.23'!AQ24 -> 2092 | AT24: 7196.7 | AU24: =(AT24-AT23)*4000 -> 10240 | AV24: =+X24/SQRT(((POWER((X24),2)+(POWER((AU24),2))))) -> 0.96596609 | AY24: ='[2]Reading.5.23'!X24 -> 38680 | AZ24: ='[2]Reading.5.23'!AB24 -> 0 | BA24: =AY24+AZ24 -> 38680 | BC24: 25 | BD24: 21 | BE24: 17 | BF24: 49 | BG24: 82 | BH24: ='[2]Reading.5.23'!BD24 -> 30 | BI24: ='[2]Reading.5.23'!BE24 -> 24 | BJ24: ='[2]Reading.5.23'!BF24 -> 83 | BL24: 526 | BN24: ='[2]Reading.5.23'!E22 -> 0 | BP24: 67846 | BQ24: =BP24-BP23 -> 19 | BR24: ='[2]Reading.5.23'!BQ24 -> 33 | BT24: 82969 | BU24: =BT24-BT23 -> 47 | BV24: ='[2]Reading.5.23'!BU24 -> 43 | BX24: 4053 | BY24: =BX24-BX23 -> 0 | BZ24: ='[2]Reading.5.23'!BY24 -> 0 | CB24: 235610 | CC24: =CB24-CB23 -> 60 | CD24: ='[2]Reading.5.23'!CC24 -> 70 | CF24: 6425 | CG24: =CF24-CF23 -> 5 | CH24: ='[2]Reading.5.23'!CG24 -> 0 | CI24: 19770 | CJ24: =CI24-CI23 -> 0 | CK24: ='[2]Reading.5.23'!CG24 -> 0 | CM24: =BQ24+BU24+BY24+CC24+CJ24 -> 126 | CN24: =BR24+BV24+BZ24+CD24+CK24 -> 146 | CP24: 121774 | CQ24: =CP24-CP23 -> 431 | CR24: =CQ24/G24 -> 0.80560748 | CS24: ='[2]Reading.5.23'!CN24 -> 250 | CT24: ='[2]Reading.5.23'!CO22 -> 0.43478261 | CV24: 5285 | CW24: =CV24-CV23 -> 0 | CX24: ='[2]Reading.5.23'!CT24 -> 4 | CZ24: 1056 | DA24: =CZ24-CZ23 -> 2 | DB24: ='[2]Reading.5.23'!CX24 -> 4 | DD24: 1462712 | DE24: =DD24-DD23 -> 1028 | DF24: ='[2]Reading.5.23'!DB24 -> 1100 | DH24: 3402170 | DI24: =DH24-DH23 -> 1181 | DJ24: ='[2]Reading.5.23'!DF24 -> 1649 | DL24: 2944162 | DM24: =DL24-DL23 -> 16 | DN24: ='[2]Reading.5.23'!DJ24 -> 31 | DP24: 2330250 | DQ24: =DP24-DP23 -> 7 | DR24: ='[2]Reading.5.23'!DN24 -> 3593 | DT24: 3163586 | DU24: =DT24-DT23 -> 3894 | DV24: ='[2]Reading.5.23'!DR24 -> 1543 | DX24: 720 | DZ24: =DM24+DQ24+DU24+DX24 -> 4637 | EA24: ='[2]Reading.5.23'!DW24 -> 5887 | EC24: =C24*5.2 -> 3120 | ED24: ='[2]Reading.5.23'!C24*5.2 -> 2953.6 | EF24: 62156 | EG24: =EF24-EF23 -> 30 | EJ24: 24890 | EK24: =EJ24-EJ23 -> 12
A25: 45432 | B25: 306339 | C25: =B25-B24 -> 570 | E25: 0 | F25: 785 | G25: =C25+D25-E25+F24-F25 -> 620 | H25: ='[2]Reading.5.23'!G25 -> 655 | J25: 208722 | K25: =(J25-J24)*4.668 -> 154.044 | L25: ='[2]Reading.5.23'!K25 -> 196.056 | N25: 736023 | O25: =(N25-N24)*4.61 -> 447.17 | P25: ='[2]Reading.5.23'!O25 -> 539.37 | R25: 42700 | T25: =(R24+S24)-R25 -> 0 | U25: ='[2]Reading.5.23'!T25 -> 0 | W25: 46075.78 | X25: =(W25-W24)*4000 -> 36760 | Y25: ='[2]Reading.5.23'!X25 -> 37120 | AA25: 520034 | AB25: =AA25-AA24 -> 0 | AC25: ='[2]Reading.5.23'!AB25 -> 0 | AE25: =+X25+AB25 -> 36760 | AF25: ='[2]Reading.5.23'!AE25 -> 37120 | AG25: =1090308/30 -> 36343.6 | AI25: 0.4677 | AJ25: ='[2]Reading.5.23'!AI25 -> 0.7985 | AK25: 0.687 | AM25: 247 | AN25: ='[2]Reading.5.23'!AM25 -> 420 | AO25: =11205/30 -> 373.5 | AQ25: =499*4 -> 1996 | AR25: ='[2]Reading.5.23'!AQ25 -> 2092 | AT25: 7199.33 | AU25: =(AT25-AT24)*4000 -> 10520 | AV25: =+X25/SQRT(((POWER((X25),2)+(POWER((AU25),2))))) -> 0.96140543 | AY25: ='[2]Reading.5.23'!X25 -> 37120 | AZ25: ='[2]Reading.5.23'!AB25 -> 0 | BA25: =AY25+AZ25 -> 37120 | BC25: 25 | BD25: 21 | BE25: 17 | BF25: 49 | BG25: 82 | BH25: ='[2]Reading.5.23'!BD25 -> 27 | BI25: ='[2]Reading.5.23'!BE25 -> 23 | BJ25: ='[2]Reading.5.23'!BF25 -> 57 | BL25: 526 | BN25: ='[2]Reading.5.23'!E23 -> 0 | BP25: 67875 | BQ25: =BP25-BP24 -> 29 | BR25: ='[2]Reading.5.23'!BQ25 -> 59 | BT25: 83010 | BU25: =BT25-BT24 -> 41 | BV25: ='[2]Reading.5.23'!BU25 -> 50 | BX25: 4053 | BY25: =BX25-BX24 -> 0 | BZ25: ='[2]Reading.5.23'!BY25 -> 0 | CB25: 235670 | CC25: =CB25-CB24 -> 60 | CD25: ='[2]Reading.5.23'!CC25 -> 70 | CF25: 6440 | CG25: =CF25-CF24 -> 15 | CH25: ='[2]Reading.5.23'!CG25 -> 0 | CI25: 19770 | CJ25: =CI25-CI24 -> 0 | CK25: ='[2]Reading.5.23'!CG25 -> 0 | CM25: =BQ25+BU25+BY25+CC25+CJ25 -> 130 | CN25: =BR25+BV25+BZ25+CD25+CK25 -> 179 | CP25: 122217 | CQ25: =CP25-CP24 -> 443 | CR25: =CQ25/G25 -> 0.71451613 | CS25: ='[2]Reading.5.23'!CN25 -> 266 | CT25: ='[2]Reading.5.23'!CO23 -> 0.45454545 | CV25: 5285 | CW25: =CV25-CV24 -> 0 | CX25: ='[2]Reading.5.23'!CT25 -> 5 | CZ25: 1061 | DA25: =CZ25-CZ24 -> 5 | DB25: ='[2]Reading.5.23'!CX25 -> 7 | DD25: 1463735 | DE25: =DD25-DD24 -> 1023 | DF25: ='[2]Reading.5.23'!DB25 -> 1019 | DH25: 3403689 | DI25: =DH25-DH24 -> 1519 | DJ25: ='[2]Reading.5.23'!DF25 -> 2648 | DL25: 2944192 | DM25: =DL25-DL24 -> 30 | DN25: ='[2]Reading.5.23'!DJ25 -> 32 | DP25: 2331633 | DQ25: =DP25-DP24 -> 1383 | DR25: ='[2]Reading.5.23'!DN25 -> 3039 | DT25: 3167396 | DU25: =DT25-DT24 -> 3810 | DV25: ='[2]Reading.5.23'!DR25 -> 1611 | DX25: 720 | DZ25: =DM25+DQ25+DU25+DX25 -> 5943 | EA25: ='[2]Reading.5.23'!DW25 -> 5402 | EC25: =C25*5.2 -> 2964 | ED25: ='[2]Reading.5.23'!C25*5.2 -> 3302 | EF25: 62206 | EG25: =EF25-EF24 -> 50 | EJ25: 24911 | EK25: =EJ25-EJ24 -> 21
A26: 45433 | B26: 306843 | C26: =B26-B25 -> 504 | E26: 0 | F26: 785 | G26: =C26+D26-E26+F25-F26 -> 504 | H26: ='[2]Reading.5.23'!G26 -> 630 | J26: 208759 | K26: =(J26-J25)*4.668 -> 172.716 | L26: ='[2]Reading.5.23'!K26 -> 228.732 | N26: 736124 | O26: =(N26-N25)*4.61 -> 465.61 | P26: ='[2]Reading.5.23'!O26 -> 534.76 | R26: 42700 | T26: =(R25+S25)-R26 -> 0 | U26: ='[2]Reading.5.23'!T26 -> 0 | W26: 46085.92 | X26: =(W26-W25)*4000 -> 40560 | Y26: ='[2]Reading.5.23'!X26 -> 38080 | AA26: 520034 | AB26: =AA26-AA25 -> 0 | AC26: ='[2]Reading.5.23'!AB26 -> 0 | AE26: =+X26+AB26 -> 40560 | AF26: ='[2]Reading.5.23'!AE26 -> 38080 | AG26: =1090308/30 -> 36343.6 | AI26: 0.4563 | AJ26: ='[2]Reading.5.23'!AI26 -> 0.7896 | AK26: 0.687 | AM26: 240 | AN26: ='[2]Reading.5.23'!AM26 -> 415 | AO26: =11205/30 -> 373.5 | AQ26: =499*4 -> 1996 | AR26: ='[2]Reading.5.23'!AQ26 -> 2092 | AT26: 7202.16 | AU26: =(AT26-AT25)*4000 -> 11320 | AV26: =+X26/SQRT(((POWER((X26),2)+(POWER((AU26),2))))) -> 0.96319058 | AY26: ='[2]Reading.5.23'!X26 -> 38080 | AZ26: ='[2]Reading.5.23'!AB26 -> 0 | BA26: =AY26+AZ26 -> 38080 | BC26: 23 | BD26: 22 | BE26: 18 | BF26: 62 | BG26: 83 | BH26: ='[2]Reading.5.23'!BD26 -> 26.2 | BI26: ='[2]Reading.5.23'!BE26 -> 22 | BJ26: ='[2]Reading.5.23'!BF26 -> 64 | BL26: 526 | BN26: ='[2]Reading.5.23'!E24 -> 0 | BP26: 67904 | BQ26: =BP26-BP25 -> 29 | BR26: ='[2]Reading.5.23'!BQ26 -> 38 | BT26: 83045 | BU26: =BT26-BT25 -> 35 | BV26: ='[2]Reading.5.23'!BU26 -> 42 | BX26: 4053 | BY26: =BX26-BX25 -> 0 | BZ26: ='[2]Reading.5.23'!BY26 -> 0 | CB26: 235730 | CC26: =CB26-CB25 -> 60 | CD26: ='[2]Reading.5.23'!CC26 -> 70 | CF26: 6450 | CG26: =CF26-CF25 -> 10 | CH26: ='[2]Reading.5.23'!CG26 -> 0 | CI26: 19770 | CJ26: =CI26-CI25 -> 0 | CK26: ='[2]Reading.5.23'!CG26 -> 0 | CM26: =BQ26+BU26+BY26+CC26+CJ26 -> 124 | CN26: =BR26+BV26+BZ26+CD26+CK26 -> 150 | CP26: 122624 | CQ26: =CP26-CP25 -> 407 | CR26: =CQ26/G26 -> 0.80753968 | CS26: ='[2]Reading.5.23'!CN26 -> 250 | CT26: ='[2]Reading.5.23'!CO24 -> 0.4180602 | CV26: 5285 | CW26: =CV26-CV25 -> 0 | CX26: ='[2]Reading.5.23'!CT26 -> 4 | CZ26: 1064 | DA26: =CZ26-CZ25 -> 3 | DB26: ='[2]Reading.5.23'!CX26 -> 6 | DD26: 1464879 | DE26: =DD26-DD25 -> 1144 | DF26: ='[2]Reading.5.23'!DB26 -> 958 | DH26: 3405252 | DI26: =DH26-DH25 -> 1563 | DJ26: ='[2]Reading.5.23'!DF26 -> 1927 | DL26: 2944222 | DM26: =DL26-DL25 -> 30 | DN26: ='[2]Reading.5.23'!DJ26 -> 31 | DP26: 2334020 | DQ26: =DP26-DP25 -> 2387 | DR26: ='[2]Reading.5.23'!DN26 -> 3042 | DT26: 3178686 | DU26: =DT26-DT25 -> 11290 | DV26: ='[2]Reading.5.23'!DR26 -> 1857 | DX26: 720 | DZ26: =DM26+DQ26+DU26+DX26 -> 14427 | EA26: ='[2]Reading.5.23'!DW26 -> 5650 | EC26: =C26*5.2 -> 2620.8 | ED26: ='[2]Reading.5.23'!C26*5.2 -> 3588 | EF26: 62252 | EG26: =EF26-EF25 -> 46 | EJ26: 24932 | EK26: =EJ26-EJ25 -> 21
A27: 45434 | B27: 307438 | C27: =B27-B26 -> 595 | E27: 0 | F27: 820 | G27: =C27+D27-E27+F26-F27 -> 560 | H27: ='[2]Reading.5.23'!G27 -> 680 | J27: 208793 | K27: =(J27-J26)*4.668 -> 158.712 | L27: ='[2]Reading.5.23'!K27 -> 205.392 | N27: 736203 | O27: =(N27-N26)*4.61 -> 364.19 | P27: ='[2]Reading.5.23'!O27 -> 543.98 | R27: 42300 | T27: =(R26+S26)-R27 -> 400 | U27: ='[2]Reading.5.23'!T27 -> 0 | W27: 46095.52 | X27: =(W27-W26)*4000 -> 38400 | Y27: ='[2]Reading.5.23'!X27 -> 38240 | AA27: 520039 | AB27: =AA27-AA26 -> 5 | AC27: ='[2]Reading.5.23'!AB27 -> 0 | AE27: =+X27+AB27 -> 38405 | AF27: ='[2]Reading.5.23'!AE27 -> 38240 | AG27: =1090308/30 -> 36343.6 | AI27: 0.4563 | AJ27: ='[2]Reading.5.23'!AI27 -> 0.8099 | AK27: 0.687 | AM27: 240 | AN27: ='[2]Reading.5.23'!AM27 -> 426 | AO27: =11205/30 -> 373.5 | AQ27: =500*4 -> 2000 | AR27: ='[2]Reading.5.23'!AQ27 -> 2092 | AT27: 7204.98 | AU27: =(AT27-AT26)*4000 -> 11280 | AV27: =+X27/SQRT(((POWER((X27),2)+(POWER((AU27),2))))) -> 0.95946093 | AY27: ='[2]Reading.5.23'!X27 -> 38240 | AZ27: ='[2]Reading.5.23'!AB27 -> 0 | BA27: =AY27+AZ27 -> 38240 | BC27: 23 | BD27: 22 | BE27: 18 | BF27: 62 | BG27: 83 | BH27: ='[2]Reading.5.23'!BD27 -> 28.6 | BI27: ='[2]Reading.5.23'!BE27 -> 24 | BJ27: ='[2]Reading.5.23'!BF27 -> 57 | BL27: 526 | BN27: ='[2]Reading.5.23'!E25 -> 0 | BP27: 67936 | BQ27: =BP27-BP26 -> 32 | BR27: ='[2]Reading.5.23'!BQ27 -> 35 | BT27: 83087 | BU27: =BT27-BT26 -> 42 | BV27: ='[2]Reading.5.23'!BU27 -> 40 | BX27: 4053 | BY27: =BX27-BX26 -> 0 | BZ27: ='[2]Reading.5.23'!BY27 -> 0 | CB27: 235780 | CC27: =CB27-CB26 -> 50 | CD27: ='[2]Reading.5.23'!CC27 -> 100 | CF27: 6460 | CG27: =CF27-CF26 -> 10 | CH27: ='[2]Reading.5.23'!CG27 -> 0 | CI27: 19770 | CJ27: =CI27-CI26 -> 0 | CK27: ='[2]Reading.5.23'!CG27 -> 0 | CM27: =BQ27+BU27+BY27+CC27+CJ27 -> 124 | CN27: =BR27+BV27+BZ27+CD27+CK27 -> 175 | CP27: 123037 | CQ27: =CP27-CP26 -> 413 | CR27: =CQ27/G27 -> 0.7375 | CS27: ='[2]Reading.5.23'!CN27 -> 293 | CT27: ='[2]Reading.5.23'!CO25 -> 0.40610687 | CV27: 5285 | CW27: =CV27-CV26 -> 0 | CX27: ='[2]Reading.5.23'!CT27 -> 3 | CZ27: 1067 | DA27: =CZ27-CZ26 -> 3 | DB27: ='[2]Reading.5.23'!CX27 -> 5 | DD27: 1465908 | DE27: =DD27-DD26 -> 1029 | DF27: ='[2]Reading.5.23'!DB27 -> 1016 | DH27: 3406714 | DI27: =DH27-DH26 -> 1462 | DJ27: ='[2]Reading.5.23'!DF27 -> 1681 | DL27: 2944250 | DM27: =DL27-DL26 -> 28 | DN27: ='[2]Reading.5.23'!DJ27 -> 33 | DP27: 2336103 | DQ27: =DP27-DP26 -> 2083 | DR27: ='[2]Reading.5.23'!DN27 -> 3174 | DT27: 3179346 | DU27: =DT27-DT26 -> 660 | DV27: ='[2]Reading.5.23'!DR27 -> 2152 | DX27: 720 | DZ27: =DM27+DQ27+DU27+DX27 -> 3491 | EA27: ='[2]Reading.5.23'!DW27 -> 6079 | EC27: =C27*5.2 -> 3094 | ED27: ='[2]Reading.5.23'!C27*5.2 -> 2912 | EF27: 62298 | EG27: =EF27-EF26 -> 46 | EJ27: 24955 | EK27: =EJ27-EJ26 -> 23
A28: 45435 | B28: 307954 | C28: =B28-B27 -> 516 | E28: 0 | F28: 810 | G28: =C28+D28-E28+F27-F28 -> 526 | H28: ='[2]Reading.5.23'!G28 -> 559 | J28: 208824 | K28: =(J28-J27)*4.668 -> 144.708 | L28: ='[2]Reading.5.23'!K28 -> 219.396 | N28: 736302 | O28: =(N28-N27)*4.61 -> 456.39 | P28: ='[2]Reading.5.23'!O28 -> 530.15 | R28: 42300 | T28: =(R27+S27)-R28 -> 0 | U28: ='[2]Reading.5.23'!T28 -> 0 | W28: 46104.46 | X28: =(W28-W27)*4000 -> 35760 | Y28: ='[2]Reading.5.23'!X28 -> 38120 | AA28: 520039 | AB28: =AA28-AA27 -> 0 | AC28: ='[2]Reading.5.23'!AB28 -> 0 | AE28: =+X28+AB28 -> 35760 | AF28: ='[2]Reading.5.23'!AE28 -> 38120 | AG28: =1090308/30 -> 36343.6 | AI28: 0.4663 | AJ28: ='[2]Reading.5.23'!AI28 -> 0.8099 | AK28: 0.687 | AM28: 245 | AN28: ='[2]Reading.5.23'!AM28 -> 426 | AO28: =11205/30 -> 373.5 | AQ28: =507*4 -> 2028 | AR28: ='[2]Reading.5.23'!AQ28 -> 2092 | AT28: 7207.52 | AU28: =(AT28-AT27)*4000 -> 10160 | AV28: =+X28/SQRT(((POWER((X28),2)+(POWER((AU28),2))))) -> 0.96192893 | AY28: ='[2]Reading.5.23'!X28 -> 38120 | AZ28: ='[2]Reading.5.23'!AB28 -> 0 | BA28: =AY28+AZ28 -> 38120 | BC28: 23 | BD28: 22 | BE28: 18 | BF28: 62 | BG28: 83 | BH28: ='[2]Reading.5.23'!BD28 -> 28.6 | BI28: ='[2]Reading.5.23'!BE28 -> 24 | BJ28: ='[2]Reading.5.23'!BF28 -> 57 | BL28: 526 | BN28: ='[2]Reading.5.23'!E26 -> 0 | BP28: 67967 | BQ28: =BP28-BP27 -> 31 | BR28: ='[2]Reading.5.23'!BQ28 -> 45 | BT28: 83128 | BU28: =BT28-BT27 -> 41 | BV28: ='[2]Reading.5.23'!BU28 -> 40 | BX28: 4053 | BY28: =BX28-BX27 -> 0 | BZ28: ='[2]Reading.5.23'!BY28 -> 0 | CB28: 235840 | CC28: =CB28-CB27 -> 60 | CD28: ='[2]Reading.5.23'!CC28 -> 80 | CF28: 6465 | CG28: =CF28-CF27 -> 5 | CH28: ='[2]Reading.5.23'!CG28 -> 0 | CI28: 19770 | CJ28: =CI28-CI27 -> 0 | CK28: ='[2]Reading.5.23'!CG28 -> 0 | CM28: =BQ28+BU28+BY28+CC28+CJ28 -> 132 | CN28: =BR28+BV28+BZ28+CD28+CK28 -> 165 | CP28: 123454 | CQ28: =CP28-CP27 -> 417 | CR28: =CQ28/G28 -> 0.79277567 | CS28: ='[2]Reading.5.23'!CN28 -> 260 | CT28: ='[2]Reading.5.23'!CO26 -> 0.3968254 | CV28: 5285 | CW28: =CV28-CV27 -> 0 | CX28: ='[2]Reading.5.23'!CT28 -> 3 | CZ28: 1071 | DA28: =CZ28-CZ27 -> 4 | DB28: ='[2]Reading.5.23'!CX28 -> 6 | DD28: 1466928 | DE28: =DD28-DD27 -> 1020 | DF28: ='[2]Reading.5.23'!DB28 -> 1080 | DH28: 3408203 | DI28: =DH28-DH27 -> 1489 | DJ28: ='[2]Reading.5.23'!DF28 -> 2191 | DL28: 2944282 | DM28: =DL28-DL27 -> 32 | DN28: ='[2]Reading.5.23'!DJ28 -> 31 | DP28: 2336408 | DQ28: =DP28-DP27 -> 305 | DR28: ='[2]Reading.5.23'!DN28 -> 3281 | DT28: 3181000 | DU28: =DT28-DT27 -> 1654 | DV28: ='[2]Reading.5.23'!DR28 -> 2224 | DX28: 720 | DZ28: =DM28+DQ28+DU28+DX28 -> 2711 | EA28: ='[2]Reading.5.23'!DW28 -> 6256 | EC28: =C28*5.2 -> 2683.2 | ED28: ='[2]Reading.5.23'!C28*5.2 -> 3530.8 | EF28: 62347 | EG28: =EF28-EF27 -> 49 | EJ28: 24974 | EK28: =EJ28-EJ27 -> 19
A29: 45436 | B29: 308536 | C29: =B29-B28 -> 582 | E29: 0 | F29: 800 | G29: =C29+D29-E29+F28-F29 -> 592 | H29: ='[2]Reading.5.23'!G29 -> 591 | J29: 208859 | K29: =(J29-J28)*4.668 -> 163.38 | L29: ='[2]Reading.5.23'!K29 -> 196.056 | N29: 736399 | O29: =(N29-N28)*4.61 -> 447.17 | P29: ='[2]Reading.5.23'!O29 -> 479.44 | R29: 42300 | T29: =(R28+S28)-R29 -> 0 | U29: ='[2]Reading.5.23'!T29 -> 0 | V29: 46114.06 | W29: 46114.06 | X29: =(W29-W28)*4000 -> 38400 | Y29: ='[2]Reading.5.23'!X29 -> 38520 | AA29: 520039 | AB29: =AA29-AA28 -> 0 | AC29: ='[2]Reading.5.23'!AB29 -> 0 | AE29: =+X29+AB29 -> 38400 | AF29: ='[2]Reading.5.23'!AE29 -> 38520 | AG29: =1090308/30 -> 36343.6 | AI29: 0.443 | AJ29: ='[2]Reading.5.23'!AI29 -> 0.7814 | AK29: 0.687 | AM29: 233 | AN29: ='[2]Reading.5.23'!AM29 -> 411 | AO29: =11205/30 -> 373.5 | AQ29: =507*4 -> 2028 | AR29: ='[2]Reading.5.23'!AQ29 -> 2092 | AT29: 7210.11 | AU29: =(AT29-AT28)*4000 -> 10360 | AV29: =+X29/SQRT(((POWER((X29),2)+(POWER((AU29),2))))) -> 0.96547968 | AY29: ='[2]Reading.5.23'!X29 -> 38520 | AZ29: ='[2]Reading.5.23'!AB29 -> 0 | BA29: =AY29+AZ29 -> 38520 | BC29: 23 | BD29: 22 | BE29: 18 | BF29: 62 | BG29: 83 | BH29: ='[2]Reading.5.23'!BD29 -> 29.4 | BI29: ='[2]Reading.5.23'!BE29 -> 25 | BJ29: ='[2]Reading.5.23'!BF29 -> 78 | BL29: 526 | BN29: ='[2]Reading.5.23'!E27 -> 0 | BP29: 67998 | BQ29: =BP29-BP28 -> 31 | BR29: ='[2]Reading.5.23'!BQ29 -> 40 | BT29: 83167 | BU29: =BT29-BT28 -> 39 | BV29: ='[2]Reading.5.23'!BU29 -> 42 | BX29: 4053 | BY29: =BX29-BX28 -> 0 | BZ29: ='[2]Reading.5.23'!BY29 -> 0 | CB29: 235900 | CC29: =CB29-CB28 -> 60 | CD29: ='[2]Reading.5.23'!CC29 -> 100 | CF29: 6470 | CG29: =CF29-CF28 -> 5 | CH29: ='[2]Reading.5.23'!CG29 -> 0 | CI29: 19770 | CJ29: =CI29-CI28 -> 0 | CK29: ='[2]Reading.5.23'!CG29 -> 0 | CM29: =BQ29+BU29+BY29+CC29+CJ29 -> 130 | CN29: =BR29+BV29+BZ29+CD29+CK29 -> 182 | CP29: 123862 | CQ29: =CP29-CP28 -> 408 | CR29: =CQ29/G29 -> 0.68918919 | CS29: ='[2]Reading.5.23'!CN29 -> 280 | CT29: ='[2]Reading.5.23'!CO27 -> 0.43088235 | CV29: 5285 | CW29: =CV29-CV28 -> 0 | CX29: ='[2]Reading.5.23'!CT29 -> 4 | CZ29: 1076 | DA29: =CZ29-CZ28 -> 5 | DB29: ='[2]Reading.5.23'!CX29 -> 6 | DD29: 1467953 | DE29: =DD29-DD28 -> 1025 | DF29: ='[2]Reading.5.23'!DB29 -> 1094 | DH29: 3409802 | DI29: =DH29-DH28 -> 1599 | DJ29: ='[2]Reading.5.23'!DF29 -> 1936 | DL29: 2944309 | DM29: =DL29-DL28 -> 27 | DN29: ='[2]Reading.5.23'!DJ29 -> 31 | DP29: 2340642 | DQ29: =DP29-DP28 -> 4234 | DR29: ='[2]Reading.5.23'!DN29 -> 3497 | DT29: 3181030 | DU29: =DT29-DT28 -> 30 | DV29: ='[2]Reading.5.23'!DR29 -> 1978 | DX29: 720 | DZ29: =DM29+DQ29+DU29+DX29 -> 5011 | EA29: ='[2]Reading.5.23'!DW29 -> 6226 | EC29: =C29*5.2 -> 3026.4 | ED29: ='[2]Reading.5.23'!C29*5.2 -> 2839.2 | EF29: 62400 | EG29: =EF29-EF28 -> 53 | EJ29: 24995 | EK29: =EJ29-EJ28 -> 21
A30: 45437 | B30: 309068 | C30: =B30-B29 -> 532 | E30: 0 | F30: 815 | G30: =C30+D30-E30+F29-F30 -> 517 | H30: ='[2]Reading.5.23'!G30 -> 536 | J30: 208890 | K30: =(J30-J29)*4.668 -> 144.708 | L30: ='[2]Reading.5.23'!K30 -> 191.388 | N30: 736476 | O30: =(N30-N29)*4.61 -> 354.97 | P30: ='[2]Reading.5.23'!O30 -> 502.49 | R30: 42300 | T30: =(R29+S29)-R30 -> 0 | U30: ='[2]Reading.5.23'!T30 -> 0 | V30: 46114.06 | W30: 46122.85 | X30: =(W30-W29)*4000 -> 35160 | Y30: ='[2]Reading.5.23'!X30 -> 39280 | AA30: 520039 | AB30: =AA30-AA29 -> 0 | AC30: ='[2]Reading.5.23'!AB30 -> 0 | AE30: =+X30+AB30 -> 35160 | AF30: ='[2]Reading.5.23'!AE30 -> 39280 | AG30: =1090308/30 -> 36343.6 | AI30: 0.403 | AJ30: ='[2]Reading.5.23'!AI30 -> 0.7452 | AK30: 0.687 | AM30: 212 | AN30: ='[2]Reading.5.23'!AM30 -> 392 | AO30: =11205/30 -> 373.5 | AQ30: =507*4 -> 2028 | AR30: ='[2]Reading.5.23'!AQ30 -> 2092 | AT30: 7211.55 | AU30: =(AT30-AT29)*4000 -> 5760 | AV30: =+X30/SQRT(((POWER((X30),2)+(POWER((AU30),2))))) -> 0.98684529 | AY30: ='[2]Reading.5.23'!X30 -> 39280 | AZ30: ='[2]Reading.5.23'!AB30 -> 0 | BA30: =AY30+AZ30 -> 39280 | BC30: 23 | BD30: 22 | BE30: 18 | BF30: 62 | BG30: 83 | BH30: ='[2]Reading.5.23'!BD30 -> 32.1 | BI30: ='[2]Reading.5.23'!BE30 -> 26 | BJ30: ='[2]Reading.5.23'!BF30 -> 54 | BL30: 526 | BN30: ='[2]Reading.5.23'!E28 -> 0 | BP30: 68031 | BQ30: =BP30-BP29 -> 33 | BR30: ='[2]Reading.5.23'!BQ30 -> 39 | BT30: 83194 | BU30: =BT30-BT29 -> 27 | BV30: ='[2]Reading.5.23'!BU30 -> 41 | BX30: 4053 | BY30: =BX30-BX29 -> 0 | BZ30: ='[2]Reading.5.23'!BY30 -> 0 | CB30: 235960 | CC30: =CB30-CB29 -> 60 | CD30: ='[2]Reading.5.23'!CC30 -> 60 | CF30: 6475 | CG30: =CF30-CF29 -> 5 | CH30: ='[2]Reading.5.23'!CG30 -> 0 | CI30: 19770 | CJ30: =CI30-CI29 -> 0 | CK30: ='[2]Reading.5.23'!CG30 -> 0 | CM30: =BQ30+BU30+BY30+CC30+CJ30 -> 120 | CN30: =BR30+BV30+BZ30+CD30+CK30 -> 140 | CP30: 124257 | CQ30: =CP30-CP29 -> 395 | CR30: =CQ30/G30 -> 0.76402321 | CS30: ='[2]Reading.5.23'!CN30 -> 251 | CT30: ='[2]Reading.5.23'!CO28 -> 0.46511628 | CV30: 5285 | CW30: =CV30-CV29 -> 0 | CX30: ='[2]Reading.5.23'!CT30 -> 3 | CZ30: 1080 | DA30: =CZ30-CZ29 -> 4 | DB30: ='[2]Reading.5.23'!CX30 -> 6 | DD30: 1468731 | DE30: =DD30-DD29 -> 778 | DF30: ='[2]Reading.5.23'!DB30 -> 1090 | DH30: 3411370 | DI30: =DH30-DH29 -> 1568 | DJ30: ='[2]Reading.5.23'!DF30 -> 1915 | DL30: 2944338 | DM30: =DL30-DL29 -> 29 | DN30: ='[2]Reading.5.23'!DJ30 -> 31 | DP30: 2342570 | DQ30: =DP30-DP29 -> 1928 | DR30: ='[2]Reading.5.23'!DN30 -> 3422 | DT30: 3181034 | DU30: =DT30-DT29 -> 4 | DV30: ='[2]Reading.5.23'!DR30 -> 2170 | DX30: 720 | DZ30: =DM30+DQ30+DU30+DX30 -> 2681 | EA30: ='[2]Reading.5.23'!DW30 -> 6343 | EC30: =C30*5.2 -> 2766.4 | ED30: ='[2]Reading.5.23'!C30*5.2 -> 2709.2 | EF30: 62458 | EG30: =EF30-EF29 -> 58 | EJ30: 25017 | EK30: =EJ30-EJ29 -> 22
A31: 45438 | B31: 309665 | C31: =B31-B30 -> 597 | E31: 0 | F31: 845 | G31: =C31+D31-E31+F30-F31 -> 567 | H31: ='[2]Reading.5.23'!G31 -> 570 | J31: 208923 | K31: =(J31-J30)*4.668 -> 154.044 | L31: ='[2]Reading.5.23'!K31 -> 182.052 | N31: 736573 | O31: =(N31-N30)*4.61 -> 447.17 | P31: ='[2]Reading.5.23'!O31 -> 461 | R31: 42300 | T31: =(R30+S30)-R31 -> 0 | U31: ='[2]Reading.5.23'!T31 -> 0 | V31: 46114.06 | W31: 46131.47 | X31: =(W31-W30)*4000 -> 34480 | Y31: ='[2]Reading.5.23'!X31 -> 37960 | AA31: 520039 | AB31: =AA31-AA30 -> 0 | AC31: ='[2]Reading.5.23'!AB31 -> 0 | AE31: =+X31+AB31 -> 34480 | AF31: ='[2]Reading.5.23'!AE31 -> 37960 | AG31: =1090308/30 -> 36343.6 | AI31: 0.3384 | AJ31: ='[2]Reading.5.23'!AI31 -> 0.6958 | AK31: 0.687 | AM31: 178 | AN31: ='[2]Reading.5.23'!AM31 -> 366 | AO31: =11205/30 -> 373.5 | AQ31: =507*4 -> 2028 | AR31: ='[2]Reading.5.23'!AQ31 -> 2092 | AT31: 7213.22 | AU31: =(AT31-AT30)*4000 -> 6680 | AV31: =+X31/SQRT(((POWER((X31),2)+(POWER((AU31),2))))) -> 0.98174556 | AY31: ='[2]Reading.5.23'!X31 -> 37960 | AZ31: ='[2]Reading.5.23'!AB31 -> 0 | BA31: =AY31+AZ31 -> 37960 | BC31: 28 | BD31: 22 | BE31: 18 | BF31: 62 | BG31: 83 | BH31: ='[2]Reading.5.23'!BD31 -> 31.1 | BI31: ='[2]Reading.5.23'!BE31 -> 27 | BJ31: ='[2]Reading.5.23'!BF31 -> 54 | BL31: 526 | BN31: ='[2]Reading.5.23'!E29 -> 0 | BP31: 68055 | BQ31: =BP31-BP30 -> 24 | BR31: ='[2]Reading.5.23'!BQ31 -> 40 | BT31: 83230 | BU31: =BT31-BT30 -> 36 | BV31: ='[2]Reading.5.23'!BU31 -> 32 | BX31: 4053 | BY31: =BX31-BX30 -> 0 | BZ31: ='[2]Reading.5.23'!BY31 -> 0 | CB31: 236060 | CC31: =CB31-CB30 -> 100 | CD31: ='[2]Reading.5.23'!CC31 -> 50 | CF31: 6480 | CG31: =CF31-CF30 -> 5 | CH31: ='[2]Reading.5.23'!CG31 -> 0 | CI31: 19770 | CJ31: =CI31-CI30 -> 0 | CK31: ='[2]Reading.5.23'!CG31 -> 0 | CM31: =BQ31+BU31+BY31+CC31+CJ31 -> 160 | CN31: =BR31+BV31+BZ31+CD31+CK31 -> 122 | CP31: 124647 | CQ31: =CP31-CP30 -> 390 | CR31: =CQ31/G31 -> 0.68783069 | CS31: ='[2]Reading.5.23'!CN31 -> 218 | CT31: ='[2]Reading.5.23'!CO29 -> 0.47377327 | CV31: 5285 | CW31: =CV31-CV30 -> 0 | CX31: ='[2]Reading.5.23'!CT31 -> 4 | CZ31: 1083 | DA31: =CZ31-CZ30 -> 3 | DB31: ='[2]Reading.5.23'!CX31 -> 5 | DD31: 1469725 | DE31: =DD31-DD30 -> 994 | DF31: ='[2]Reading.5.23'!DB31 -> 1000 | DH31: 3412767 | DI31: =DH31-DH30 -> 1397 | DJ31: ='[2]Reading.5.23'!DF31 -> 1787 | DL31: 2944369 | DM31: =DL31-DL30 -> 31 | DN31: ='[2]Reading.5.23'!DJ31 -> 30 | DP31: 2344683 | DQ31: =DP31-DP30 -> 2113 | DR31: ='[2]Reading.5.23'!DN31 -> 3296 | DT31: 3186445 | DU31: =DT31-DT30 -> 5411 | DV31: ='[2]Reading.5.23'!DR31 -> 1970 | DX31: 720 | DZ31: =DM31+DQ31+DU31+DX31 -> 8275 | EA31: ='[2]Reading.5.23'!DW31 -> 6016 | EC31: =C31*5.2 -> 3104.4 | ED31: ='[2]Reading.5.23'!C31*5.2 -> 3224 | EF31: 62501 | EG31: =EF31-EF30 -> 43 | EJ31: 25036 | EK31: =EJ31-EJ30 -> 19
A32: 45439 | B32: 310123 | C32: =B32-B31 -> 458 | E32: 0 | F32: 845 | G32: =C32+D32-E32+F31-F32 -> 458 | H32: ='[2]Reading.5.23'!G32 -> 538 | J32: 208955 | K32: =(J32-J31)*4.668 -> 149.376 | L32: ='[2]Reading.5.23'!K32 -> 177.384 | N32: 736664 | O32: =(N32-N31)*4.61 -> 419.51 | P32: ='[2]Reading.5.23'!O32 -> 525.54 | R32: 42300 | T32: =(R31+S31)-R32 -> 0 | U32: ='[2]Reading.5.23'!T32 -> 0 | W32: 46140.1 | X32: =(W32-W31)*4000 -> 34520 | Y32: ='[2]Reading.5.23'!X32 -> 37960 | AA32: 520039 | AB32: =AA32-AA31 -> 0 | AC32: ='[2]Reading.5.23'!AB32 -> 0 | AE32: =+X32+AB32 -> 34520 | AF32: ='[2]Reading.5.23'!AE32 -> 37960 | AG32: =1090308/30 -> 36343.6 | AI32: 0.3764 | AJ32: ='[2]Reading.5.23'!AI32 -> 0.6103 | AK32: 0.687 | AM32: 198 | AN32: ='[2]Reading.5.23'!AM32 -> 321 | AO32: =11205/30 -> 373.5 | AQ32: =507*4 -> 2028 | AR32: ='[2]Reading.5.23'!AQ32 -> 2092 | AT32: 7214.94 | AU32: =(AT32-AT31)*4000 -> 6880 | AV32: =+X32/SQRT(((POWER((X32),2)+(POWER((AU32),2))))) -> 0.98071158 | AY32: ='[2]Reading.5.23'!X32 -> 37960 | AZ32: ='[2]Reading.5.23'!AB32 -> 0 | BA32: =AY32+AZ32 -> 37960 | BC32: 28 | BD32: 22 | BE32: 18 | BF32: 62 | BG32: 83 | BH32: ='[2]Reading.5.23'!BD32 -> 31.1 | BI32: ='[2]Reading.5.23'!BE32 -> 27 | BJ32: ='[2]Reading.5.23'!BF32 -> 54 | BL32: 526 | BN32: ='[2]Reading.5.23'!E30 -> 0 | BP32: 68079 | BQ32: =BP32-BP31 -> 24 | BR32: ='[2]Reading.5.23'!BQ32 -> 20 | BT32: 83263 | BU32: =BT32-BT31 -> 33 | BV32: ='[2]Reading.5.23'!BU32 -> 41 | BX32: 4053 | BY32: =BX32-BX31 -> 0 | BZ32: ='[2]Reading.5.23'!BY32 -> 37 | CB32: 236110 | CC32: =CB32-CB31 -> 50 | CD32: ='[2]Reading.5.23'!CC32 -> 70 | CF32: 6490 | CG32: =CF32-CF31 -> 10 | CH32: ='[2]Reading.5.23'!CG32 -> 0 | CI32: 19771 | CJ32: =CI32-CI31 -> 1 | CK32: ='[2]Reading.5.23'!CG32 -> 0 | CM32: =BQ32+BU32+BY32+CC32+CJ32 -> 108 | CN32: =BR32+BV32+BZ32+CD32+CK32 -> 168 | CP32: 125047 | CQ32: =CP32-CP31 -> 400 | CR32: =CQ32/G32 -> 0.87336245 | CS32: ='[2]Reading.5.23'!CN32 -> 241 | CT32: ='[2]Reading.5.23'!CO30 -> 0.46828358 | CV32: 5285 | CW32: =CV32-CV31 -> 0 | CX32: ='[2]Reading.5.23'!CT32 -> 2 | CZ32: 1086 | DA32: =CZ32-CZ31 -> 3 | DB32: ='[2]Reading.5.23'!CX32 -> 4 | DD32: 1470615 | DE32: =DD32-DD31 -> 890 | DF32: ='[2]Reading.5.23'!DB32 -> 979 | DH32: 3414164 | DI32: =DH32-DH31 -> 1397 | DJ32: ='[2]Reading.5.23'!DF32 -> 1175 | DL32: 2944398 | DM32: =DL32-DL31 -> 29 | DN32: ='[2]Reading.5.23'!DJ32 -> 32 | DP32: 2346666 | DQ32: =DP32-DP31 -> 1983 | DR32: ='[2]Reading.5.23'!DN32 -> 3306 | DT32: 3189338 | DU32: =DT32-DT31 -> 2893 | DV32: ='[2]Reading.5.23'!DR32 -> 2021 | DX32: 720 | DZ32: =DM32+DQ32+DU32+DX32 -> 5625 | EA32: ='[2]Reading.5.23'!DW32 -> 6079 | EC32: =C32*5.2 -> 2381.6 | ED32: ='[2]Reading.5.23'!C32*5.2 -> 2615.6 | EF32: 62544 | EG32: =EF32-EF31 -> 43 | EJ32: 25055 | EK32: =EJ32-EJ31 -> 19
A33: 45440 | B33: 310673 | C33: =B33-B32 -> 550 | E33: 0 | F33: 840 | G33: =C33+D33-E33+F32-F33 -> 555 | H33: ='[2]Reading.5.23'!G33 -> 613 | J33: 208986 | K33: =(J33-J32)*4.668 -> 144.708 | L33: ='[2]Reading.5.23'!K33 -> 172.716 | N33: 736751 | O33: =(N33-N32)*4.61 -> 401.07 | P33: ='[2]Reading.5.23'!O33 -> 484.05 | R33: 42300 | T33: =(R32+S32)-R33 -> 0 | U33: ='[2]Reading.5.23'!T33 -> 0 | W33: 46148.65 | X33: =(W33-W32)*4000 -> 34200 | Y33: ='[2]Reading.5.23'!X33 -> 36880 | AA33: 520066 | AB33: =AA33-AA32 -> 27 | AC33: ='[2]Reading.5.23'!AB33 -> 0 | AE33: =+X33+AB33 -> 34227 | AF33: ='[2]Reading.5.23'!AE33 -> 36880 | AG33: =1090308/30 -> 36343.6 | AI33: 0.365 | AJ33: ='[2]Reading.5.23'!AI33 -> 0.57 | AK33: 0.687 | AM33: 192 | AN33: ='[2]Reading.5.23'!AM33 -> 298 | AO33: =11205/30 -> 373.5 | AQ33: =507*4 -> 2028 | AR33: ='[2]Reading.5.23'!AQ33 -> 2092 | AT33: 7215.92 | AU33: =(AT33-AT32)*4000 -> 3920 | AV33: =+X33/SQRT(((POWER((X33),2)+(POWER((AU33),2))))) -> 0.99349517 | AY33: ='[2]Reading.5.23'!X33 -> 36880 | AZ33: ='[2]Reading.5.23'!AB33 -> 0 | BA33: =AY33+AZ33 -> 36880 | BC33: 28 | BD33: 22 | BE33: 18 | BF33: 62 | BG33: 83 | BH33: ='[2]Reading.5.23'!BD33 -> 31.4 | BI33: ='[2]Reading.5.23'!BE33 -> 27 | BJ33: ='[2]Reading.5.23'!BF33 -> 54 | BL33: 526 | BN33: ='[2]Reading.5.23'!E31 -> 0 | BP33: 68127 | BQ33: =BP33-BP32 -> 48 | BR33: ='[2]Reading.5.23'!BQ33 -> 40 | BT33: 83293 | BU33: =BT33-BT32 -> 30 | BV33: ='[2]Reading.5.23'!BU33 -> 40 | BX33: 4053 | BY33: =BX33-BX32 -> 0 | BZ33: ='[2]Reading.5.23'!BY33 -> 0 | CB33: 236140 | CC33: =CB33-CB32 -> 30 | CD33: ='[2]Reading.5.23'!CC33 -> 130 | CF33: 6500 | CG33: =CF33-CF32 -> 10 | CH33: ='[2]Reading.5.23'!CG33 -> 0 | CI33: 19771 | CJ33: =CI33-CI32 -> 0 | CK33: ='[2]Reading.5.23'!CG33 -> 0 | CM33: =BQ33+BU33+BY33+CC33+CJ33 -> 108 | CN33: =BR33+BV33+BZ33+CD33+CK33 -> 210 | CP33: 125439 | CQ33: =CP33-CP32 -> 392 | CR33: =CQ33/G33 -> 0.70630631 | CS33: ='[2]Reading.5.23'!CN33 -> 260 | CT33: ='[2]Reading.5.23'!CO31 -> 0.38245614 | CV33: 5285 | CW33: =CV33-CV32 -> 0 | CX33: ='[2]Reading.5.23'!CT33 -> 4 | CZ33: 1090 | DA33: =CZ33-CZ32 -> 4 | DB33: ='[2]Reading.5.23'!CX33 -> 7 | DD33: 1471721 | DE33: =DD33-DD32 -> 1106 | DF33: ='[2]Reading.5.23'!DB33 -> 1017 | DH33: 3415793 | DI33: =DH33-DH32 -> 1629 | DJ33: ='[2]Reading.5.23'!DF33 -> 1934 | DL33: 2946620 | DM33: =DL33-DL32 -> 2222 | DN33: ='[2]Reading.5.23'!DJ33 -> 34 | DP33: 2348735 | DQ33: =DP33-DP32 -> 2069 | DR33: ='[2]Reading.5.23'!DN33 -> 3556 | DT33: 3190374 | DU33: =DT33-DT32 -> 1036 | DV33: ='[2]Reading.5.23'!DR33 -> 2166 | DX33: 720 | DZ33: =DM33+DQ33+DU33+DX33 -> 6047 | EA33: ='[2]Reading.5.23'!DW33 -> 6476 | EC33: =C33*5.2 -> 2860 | ED33: ='[2]Reading.5.23'!C33*5.2 -> 3213.6 | EF33: 62587 | EG33: =EF33-EF32 -> 43 | EJ33: 25074 | EK33: =EJ33-EJ32 -> 19
A34: 45441 | B34: 311206 | C34: =B34-B33 -> 533 | E34: 0 | F34: 835 | G34: =C34+D34-E34+F33-F34 -> 538 | H34: ='[2]Reading.5.23'!G34 -> 516 | J34: 209020 | K34: =(J34-J33)*4.668 -> 158.712 | L34: ='[2]Reading.5.23'!K34 -> 186.72 | N34: 736827 | O34: =(N34-N33)*4.61 -> 350.36 | P34: ='[2]Reading.5.23'!O34 -> 511.71 | R34: 42300 | T34: =(R33+S33)-R34 -> 0 | U34: ='[2]Reading.5.23'!T34 -> 0 | W34: 46157.29 | X34: =(W34-W33)*4000 -> 34560 | Y34: ='[2]Reading.5.23'!X34 -> 36640 | AA34: 520066 | AB34: =AA34-AA33 -> 0 | AC34: ='[2]Reading.5.23'!AB34 -> 0 | AE34: =+X34+AB34 -> 34560 | AF34: ='[2]Reading.5.23'!AE34 -> 36640 | AG34: =1090308/30 -> 36343.6 | AI34: 0.365 | AJ34: ='[2]Reading.5.23'!AI34 -> 0.59 | AK34: 0.687 | AM34: 192 | AN34: ='[2]Reading.5.23'!AM34 -> 308 | AO34: =11205/30 -> 373.5 | AQ34: =507*4 -> 2028 | AR34: ='[2]Reading.5.23'!AQ34 -> 2092 | AT34: 7217.87 | AU34: =(AT34-AT33)*4000 -> 7800 | AV34: =+X34/SQRT(((POWER((X34),2)+(POWER((AU34),2))))) -> 0.97546447 | AY34: ='[2]Reading.5.23'!X34 -> 36640 | AZ34: ='[2]Reading.5.23'!AB34 -> 0 | BA34: =AY34+AZ34 -> 36640 | BC34: 28 | BD34: 22 | BE34: 18 | BF34: 62 | BG34: 83 | BH34: ='[2]Reading.5.23'!BD34 -> 31.4 | BI34: ='[2]Reading.5.23'!BE34 -> 27 | BJ34: ='[2]Reading.5.23'!BF34 -> 54 | BL34: 526 | BN34: ='[2]Reading.5.23'!E32 -> 0 | BP34: 68150 | BQ34: =BP34-BP33 -> 23 | BR34: ='[2]Reading.5.23'!BQ34 -> 41 | BT34: 83321 | BU34: =BT34-BT33 -> 28 | BV34: ='[2]Reading.5.23'!BU34 -> 35 | BX34: 4053 | BY34: =BX34-BX33 -> 0 | BZ34: ='[2]Reading.5.23'!BY34 -> 0 | CB34: 236170 | CC34: =CB34-CB33 -> 30 | CD34: ='[2]Reading.5.23'!CC34 -> 60 | CF34: 6510 | CG34: =CF34-CF33 -> 10 | CH34: ='[2]Reading.5.23'!CG34 -> 0 | CI34: 19771 | CJ34: =CI34-CI33 -> 0 | CK34: ='[2]Reading.5.23'!CG34 -> 0 | CM34: =BQ34+BU34+BY34+CC34+CJ34 -> 81 | CN34: =BR34+BV34+BZ34+CD34+CK34 -> 136 | CP34: 125834 | CQ34: =CP34-CP33 -> 395 | CR34: =CQ34/G34 -> 0.73420074 | CS34: ='[2]Reading.5.23'!CN34 -> 267 | CT34: ='[2]Reading.5.23'!CO32 -> 0.44795539 | CV34: 5285 | CW34: =CV34-CV33 -> 0 | CX34: ='[2]Reading.5.23'!CT34 -> 2 | CZ34: 1093 | DA34: =CZ34-CZ33 -> 3 | DB34: ='[2]Reading.5.23'!CX34 -> 11 | DD34: 1472569 | DE34: =DD34-DD33 -> 848 | DF34: ='[2]Reading.5.23'!DB34 -> 1185 | DH34: 3417072 | DI34: =DH34-DH33 -> 1279 | DJ34: ='[2]Reading.5.23'!DF34 -> 1826 | DL34: 2948897 | DM34: =DL34-DL33 -> 2277 | DN34: ='[2]Reading.5.23'!DJ34 -> 30 | DP34: 2350889 | DQ34: =DP34-DP33 -> 2154 | DR34: ='[2]Reading.5.23'!DN34 -> 3439 | DT34: 3190406 | DU34: =DT34-DT33 -> 32 | DV34: ='[2]Reading.5.23'!DR34 -> 2212 | DX34: 720 | DZ34: =DM34+DQ34+DU34+DX34 -> 5183 | EA34: ='[2]Reading.5.23'!DW34 -> 6401 | EC34: =C34*5.2 -> 2771.6 | ED34: ='[2]Reading.5.23'!C34*5.2 -> 2683.2 | EF34: 62640 | EG34: =EF34-EF33 -> 53 | EJ34: 25088 | EK34: =EJ34-EJ33 -> 14
A35: 45442 | B35: 311730 | C35: =B35-B34 -> 524 | E35: 0 | F35: 830 | G35: =C35+D35-E35+F34-F35 -> 529 | H35: ='[2]Reading.5.23'!G35 -> 555 | J35: 209051 | K35: =(J35-J34)*4.668 -> 144.708 | L35: ='[2]Reading.5.23'!K35 -> 182.052 | N35: 736915 | O35: =(N35-N34)*4.61 -> 405.68 | P35: ='[2]Reading.5.23'!O35 -> 520.93 | R35: 42300 | T35: =(R34+S34)-R35 -> 0 | U35: ='[2]Reading.5.23'!T35 -> 0 | W35: 46165.54 | X35: =(W35-W34)*4000 -> 33000 | Y35: ='[2]Reading.5.23'!X35 -> 37840 | AA35: 520066 | AB35: =AA35-AA34 -> 0 | AC35: ='[2]Reading.5.23'!AB35 -> 0 | AE35: =+X35+AB35 -> 33000 | AF35: ='[2]Reading.5.23'!AE35 -> 37840 | AG35: =1090308/30 -> 36343.6 | AI35: 0.3852 | AJ35: ='[2]Reading.5.23'!AI35 -> 0.54 | AK35: 0.687 | AM35: 203 | AN35: ='[2]Reading.5.23'!AM35 -> 284 | AO35: =11205/30 -> 373.5 | AQ35: =507*4 -> 2028 | AR35: ='[2]Reading.5.23'!AQ35 -> 2092 | AT35: 7215.7 | AU35: =(AT35-AT34)*4000 -> -8680 | AV35: =+X35/SQRT(((POWER((X35),2)+(POWER((AU35),2))))) -> 0.9671049 | AY35: ='[2]Reading.5.23'!X35 -> 37840 | AZ35: ='[2]Reading.5.23'!AB35 -> 0 | BA35: =AY35+AZ35 -> 37840 | BC35: 28 | BD35: 22 | BE35: 18 | BF35: 62 | BG35: 83 | BH35: ='[2]Reading.5.23'!BD35 -> 29 | BI35: ='[2]Reading.5.23'!BE35 -> 26 | BJ35: ='[2]Reading.5.23'!BF35 -> 54 | BL35: 526 | BN35: ='[2]Reading.5.23'!E33 -> 0 | BP35: 68183 | BQ35: =BP35-BP34 -> 33 | BR35: ='[2]Reading.5.23'!BQ35 -> 39 | BT35: 83351 | BU35: =BT35-BT34 -> 30 | BV35: ='[2]Reading.5.23'!BU35 -> 40 | BX35: 4053 | BY35: =BX35-BX34 -> 0 | BZ35: ='[2]Reading.5.23'!BY35 -> 0 | CB35: 236210 | CC35: =CB35-CB34 -> 40 | CD35: ='[2]Reading.5.23'!CC35 -> 50 | CF35: 6520 | CG35: =CF35-CF34 -> 10 | CH35: ='[2]Reading.5.23'!CG35 -> 0 | CI35: 19771 | CJ35: =CI35-CI34 -> 0 | CK35: ='[2]Reading.5.23'!CG35 -> 0 | CM35: =BQ35+BU35+BY35+CC35+CJ35 -> 103 | CN35: =BR35+BV35+BZ35+CD35+CK35 -> 129 | CP35: 126232 | CQ35: =CP35-CP34 -> 398 | CR35: =CQ35/G35 -> 0.75236295 | CS35: ='[2]Reading.5.23'!CN35 -> 231 | CT35: ='[2]Reading.5.23'!CO33 -> 0.42414356 | CV35: 5285 | CW35: =CV35-CV34 -> 0 | CX35: ='[2]Reading.5.23'!CT35 -> 4 | CZ35: 1097 | DA35: =CZ35-CZ34 -> 4 | DB35: ='[2]Reading.5.23'!CX35 -> 6 | DD35: 1473484 | DE35: =DD35-DD34 -> 915 | DF35: ='[2]Reading.5.23'!DB35 -> 1117 | DH35: 3418691 | DI35: =DH35-DH34 -> 1619 | DJ35: ='[2]Reading.5.23'!DF35 -> 1966 | DL35: 2950449 | DM35: =DL35-DL34 -> 1552 | DN35: ='[2]Reading.5.23'!DJ35 -> 32 | DP35: 2354610 | DQ35: =DP35-DP34 -> 3721 | DR35: ='[2]Reading.5.23'!DN35 -> 3387 | DT35: 3190438 | DU35: =DT35-DT34 -> 32 | DV35: ='[2]Reading.5.23'!DR35 -> 2207 | DX35: 720 | DZ35: =DM35+DQ35+DU35+DX35 -> 6025 | EA35: ='[2]Reading.5.23'!DW35 -> 6346 | EC35: =C35*5.2 -> 2724.8 | ED35: ='[2]Reading.5.23'!C35*5.2 -> 2990 | EF35: 62694 | EG35: =EF35-EF34 -> 54 | EJ35: 25114 | EK35: =EJ35-EJ34 -> 26
A36: 45443
C37: =AVERAGE(C6:C36) -> 559.93333 | E37: =SUM(E6:E36) -> 0 | G37: =SUM(G6:G36) -> 16748 | H37: =SUM(H6:H36) -> 17362 | K37: =SUM(K6:K36) -> 5097.456 | L37: =SUM(L6:L36) -> 5531.58 | O37: =SUM(O6:O36) -> 13479.64 | P37: =SUM(P6:P36) -> 15208.39 | S37: =SUM(S6:S36) -> 0 | T37: =SUM(T6:T36) -> 400 | U37: =SUM(U6:U36) -> 210 | X37: =SUM(X6:X36) -> 1038720 | Y37: =SUM(Y6:Y36) -> 1104280 | AB37: =SUM(AB6:AB36) -> 16 | AC37: =SUM(AC6:AC36) -> 5300 | AE37: =SUM(AE6:AE36) -> 1038736 | AF37: =SUM(AF6:AF36) -> 1109580 | AG37: =SUM(AG6:AG36) -> 1090308 | AI37: =AVERAGE(AI6:AI36) -> 0.47368333 | AJ37: =AVERAGE(AJ6:AJ36) -> 0.67346667 | AK37: =AVERAGE(AK6:AK36) -> 0.687 | AM37: =SUM(AM6:AM36) -> 7464 | AN37: =SUM(AN6:AN36) -> 10624 | AO37: =SUM(AO6:AO36) -> 11205 | AQ37: =MAX(AQ6:AQ36) -> 2028 | AR37: =MAX(AR6:AR36) -> 2092 | AV37: =AVERAGE(AV6:AV36) -> 0.97765769 | AY37: =SUM(AY6:AY36) -> 1104280 | AZ37: =SUM(AZ6:AZ36) -> 5300 | BA37: =SUM(BA6:BA36) -> 1109580 | BC37: =AVERAGE(BC6:BC36) -> 24.433333 | BD37: =AVERAGE(BD6:BD36) -> 20.506667 | BE37: =AVERAGE(BE6:BE36) -> 16.6 | BF37: =AVERAGE(BF6:BF36) -> 53.966667 | BG37: =AVERAGE(BG6:BG36) -> 81.933333 | BH37: =AVERAGE(BH6:BH36) -> 28.49 | BI37: =AVERAGE(BI6:BI36) -> 24 | BJ37: =AVERAGE(BJ6:BJ36) -> 61.666667 | BL37: =SUM(BL6:BL36) -> 15780 | BN37: =SUM(BN6:BN36) -> 0 | BQ37: =SUM(BQ6:BQ36) -> 934 | BR37: =SUM(BR6:BR36) -> 1143 | BU37: =SUM(BU6:BU36) -> 1130 | BV37: =SUM(BV6:BV36) -> 1169 | BY37: =SUM(BY6:BY36) -> 8 | BZ37: =SUM(BZ6:BZ36) -> 114 | CC37: =SUM(CC6:CC36) -> 1590 | CD37: =SUM(CD6:CD36) -> 2136 | CG37: =SUM(CG6:CG36) -> 210 | CH37: =SUM(CH6:CH36) -> 0 | CJ37: =SUM(CJ6:CJ36) -> 1 | CK37: =SUM(CK6:CK36) -> 0 | CM37: =SUM(CM6:CM36) -> 3663 | CN37: =SUM(CN6:CN36) -> 4562 | CQ37: =SUM(CQ6:CQ36) -> 12654 | CR37: =AVERAGE(CR6:CR36) -> 0.75945566 | CS37: ='[2]Reading.5.23'!CN35 -> 231 | CT37: ='[2]Reading.5.23'!CO35 -> 0.41621622 | CW37: =SUM(CW6:CW36) -> 9 | CX37: =SUM(CX6:CX36) -> 99 | DA37: =SUM(DA6:DA36) -> 131 | DB37: =SUM(DB6:DB36) -> 178 | DE37: =SUM(DE6:DE36) -> 28225 | DF37: =SUM(DF6:DF36) -> 31363 | DI37: =SUM(DI6:DI36) -> 50046 | DJ37: =SUM(DJ6:DJ36) -> 60316 | DM37: =SUM(DM6:DM36) -> 31283 | DN37: =SUM(DN6:DN36) -> 927 | DQ37: =SUM(DQ6:DQ36) -> 55284 | DR37: =SUM(DR6:DR36) -> 100868 | DU37: =SUM(DU6:DU36) -> 53149 | DV37: =SUM(DV6:DV36) -> 47875 | DZ37: =SUM(DZ6:DZ36) -> 161316 | EA37: =SUM(EA6:EA36) -> 171270 | EC37: =SUM(EC6:EC36) -> 87349.6 | ED37: =SUM(ED6:ED36) -> 90438.4 | EG37: =SUM(EG6:EG36) -> 1528 | EH37: =SUM(EH6:EH36) -> 0 | EK37: =SUM(EK6:EK36) -> 642 | EL37: =SUM(EL6:EL36) -> 0
C38: Average/Day | AP38: Last Period Max. Demand: | AQ38: 2216 | CQ38: 0
C39: =SUM(C6:C36) -> 16798 | AP39: This Period Max. Demand: | AQ39: 2160
U40: ENERGY COST / OCCUPIED ROOM - LAST YEAR = | AB40: ='[2]Cost.5.24'!BG39 -> 150.08855 | AC40: L.E. | AF40: OCCUPANCY - LAST YEAR = | AJ40: =AJ37 -> 0.67346667 | AM40: KWH / OCCUPIED ROOM - LAST YEAR | AR40: =AF37/AN37 -> 104.44089 | AY40: https://www.wunderground.com/history/monthly/eg/sharm-el-sheikh/HESH/date/2024-02
U41: ENERGY COST / OCCUPIED ROOM - THIS YEAR = | AB41: ='[2]Cost.5.24'!BI39 -> 219.97542 | AC41: L.E. | AF41: OCCUPANCY - THIS YEAR = | AJ41: =AI37 -> 0.47368333 | AM41: KWH / OCCU[PIED ROOM - THIS YEAR | AR41: =AE37/AM37 -> 139.16613
U42: ENERGY COST / OCCUPIED ROOM - BUDGET = | AB42: ='[2]Cost.5.24'!BH39 -> 141.94343 | AC42: L.E. | AF42: OCCUPANCY - BUDGET= | AJ42: =AK37 -> 0.687 | AM42: KWH / OCCUPIED ROOM - BUDGET | AR42: =AG37/AO37 -> 97.305489 | CC42: =229975+25 -> 230000
AM44: KWH / AVAILABLE ROOM - LAST YEAR | AR44: =AF37/BL37 -> 70.315589
AM45: KWH / AVAILABLE ROOM - THIS YEAR | AR45: =AE37/BL37 -> 65.826109
AM46: KWH / AVAILABLE ROOM - BUDGET | AR46: =AG37/BL37 -> 69.094297
BQ151: .

Sheet Cost.4.24
H1: =H8*31 -> 10400.5 | K1: =K8*31 -> 1349554 | P1: =P8*31 -> 2290.9 | R1: =R8*31 -> 14983.333 | W1: =W8*31 -> 18547.3 | X1: =X8*31 -> 90137.667 | AD1: =AD8*31 -> 12041.95 | AJ1: =AJ8*31 -> 4013.9833 | AP1: =AP8*31 -> 16055.933 | AQ1: =AQ8*31 -> 60689.733
A2: Energy Cost April 2024 | AV2: Energy Cost - October 2023
B3: 1 | C3: 2 | D3: 3 | E3: 4 | F3: 5 | G3: 6 | H3: 7 | I3: 8 | J3: 9 | K3: 10 | L3: 11 | M3: 12 | N3: 13 | O3: 14 | P3: 15 | Q3: 16 | R3: 17 | S3: 18 | T3: 19 | U3: 20 | V3: 21 | W3: 22 | X3: 23 | Y3: 24 | Z3: 25 | AA3: 26 | AB3: 27 | AC3: 28 | AD3: 29 | AE3: 30 | AF3: 31 | AG3: 32 | AH3: 33 | AI3: 34 | AJ3: 35 | AK3: 36 | AL3: 37 | AM3: 38 | AN3: 39 | AO3: 40 | AP3: 41 | AQ3: 42 | AR3: 43 | AS3: 44 | AT3: 45 | AU3: 46 | AV3: 47 | AW3: 48 | AX3: 49 | AY3: 50 | AZ3: 51 | BA3: 52 | BB3: 53 | BC3: 54 | BD3: 55 | BE3: 56 | BF3: 57 | BG3: 58 | BH3: 59 | BI3: 60
J5: ELECTRICITY | O5: FUEL | V5: WATER | AB5: NATURAL GAS | AV5: ELECTRICITY | AX5: WATER | AZ5: NATURAL GAS | BC5: LAST YEAR TOTAL ENERGY L.E. | BD5: BUDGET TOTAL ENERGY L.E. | BE5: ACTUAL TOTAL ENERGY L.E. | BG5: ENERGY LAST YEAR / OCCUPIED ROOM | BH5: ENERGY BUDGET / OCCUPIED ROOM | BI5: ENERGY ACTUAL / OCCUPIED ROOM
B6: DATE | D6: Occ. | F6: Occupied Rooms | H6: Occupied Rooms Budget | J6: CONSUMP. KWH | K6: BUDGET L.E. | L6: LAST YEAR ACTUAL L.E. | M6: ACTUAL L.E. | O6: CONSUMP. LITRE | P6: BUDGET LITRE | Q6: GENERATOR KWH | R6: BUDGET L.E. | S6: LAST YEAR ACTUAL L.E. | T6: ACTUAL L.E. | V6: CONSUMP. M³ | W6: BUDGET M³ | X6: BUDGET L.E. | Y6: LAST YEAR ACTUAL L.E. | Z6: ACTUAL L.E. | AB6: BOILER CONSUMP. M³ | AC6: BOILER COST L.E. | AD6: BOILER BUDGET CONSUMP. M³ | AE6: BOILER BUDGET COST L.E. | AF6: BOILER CONSUMP. LAST YEAR M³ | AG6: BOILER COST LAST YEAR L.E. | AH6: KITCHEN CONSUMP. M³ | AI6: KITCHEN COST L.E. | AJ6: KITCHEN BUDGET CONSUMP. M³ | AK6: KITCHEN BUDGET COST L.E. | AL6: KITCHEN CONSUMP. LAST YEAR M³ | AM6: KITCHEN COST LAST YEAR L.E. | AN6: TOTAL CONSUMP. M³ | AO6: TOTAL CONSUMP. LAST YEAR M³ | AP6: BUDGET TOTAL CONSUMP. M³ | AQ6: BUDGET L.E. | AR6: LAST YEAR ACTUAL L.E. | AS6: ACTUAL L.E. | AV6: KWH / Occupied Room | AW6: L.E. / Occupied Room | AX6: Cu.Mt. / Occupied Room | AY6: L.E. / Occupied Room | AZ6: Cu.Mt. / Occupied Room | BA6: L.E. / Occupied Room
B8: 45383 | D8: 0.5209 | F8: 274 | H8: 335.5 | J8: 27720 | K8: =1306020/30 -> 43534 | L8: 32760 | M8: =J8*1.39 -> 38530.8 | O8: 0 | P8: =2217/30 -> 73.9 | Q8: 0 | R8: =14500/30 -> 483.33333 | S8: 0 | T8: =O8*5.86 -> 0 | V8: 505 | W8: =17949/30 -> 598.3 | X8: =87230/30 -> 2907.6667 | Y8: 2889.12 | Z8: 2454.3 | AB8: 391.85 | AC8: =AB8*3.73 -> 1461.6005 | AD8: =((15538/4)*3)/30 -> 388.45 | AE8: =((58732/4)*3)/30 -> 1468.3 | AF8: 419.51 | AG8: 1564.7723 | AH8: 112.032 | AI8: =AH8*3.73 -> 417.87936 | AJ8: =(15538/4)/30 -> 129.48333 | AK8: =(58732/4)/30 -> 489.43333 | AL8: 149.376 | AM8: 557.17248 | AN8: =AB8+AH8 -> 503.882 | AO8: =AF8+AL8 -> 568.886 | AP8: =AD8+AJ8 -> 517.93333 | AQ8: =58732/30 -> 1957.7333 | AR8: 2121.9448 | AS8: =AC8+AI8 -> 1879.4799 | AV8: 101.16788 | AW8: =(M8+T8)/F8 -> 140.62336 | AX8: =V8/F8 -> 1.8430657 | AY8: =Z8/F8 -> 8.9572993 | AZ8: =AN8/F8 -> 1.8389854 | BA8: =AS8/F8 -> 6.8594155 | BC8: 37771.065 | BD8: =K8+R8+X8+AQ8 -> 48882.733 | BE8: =M8+T8+Z8+AS8 -> 42864.58 | BG8: 165.66256 | BH8: =BD8/H8 -> 145.70114 | BI8: =BE8/F8 -> 156.44007
B9: 45384 | D9: 0.4924 | F9: 259 | H9: 335.5 | J9: 28600 | K9: =1306020/30 -> 43534 | L9: 33332 | M9: =J9*1.39 -> 39754 | O9: 0 | P9: =2217/30 -> 73.9 | Q9: 0 | R9: =14500/30 -> 483.33333 | S9: 0 | T9: =O9*5.86 -> 0 | V9: 460 | W9: =17949/30 -> 598.3 | X9: =87230/30 -> 2907.6667 | Y9: 2495.57 | Z9: 2235.6 | AB9: 410.29 | AC9: =AB9*3.73 -> 1530.3817 | AD9: =((15538/4)*3)/30 -> 388.45 | AE9: =((58732/4)*3)/30 -> 1468.3 | AF9: 410.29 | AG9: 1530.3817 | AH9: 121.368 | AI9: =AH9*3.73 -> 452.70264 | AJ9: =(15538/4)/30 -> 129.48333 | AK9: =(58732/4)/30 -> 489.43333 | AL9: 135.372 | AM9: 504.93756 | AN9: =AB9+AH9 -> 531.658 | AO9: =AF9+AL9 -> 545.662 | AP9: =AD9+AJ9 -> 517.93333 | AQ9: =58732/30 -> 1957.7333 | AR9: 2035.3193 | AS9: =AC9+AI9 -> 1983.0843 | AV9: 110.42471 | AW9: =(M9+T9)/F9 -> 153.49035 | AX9: =V9/F9 -> 1.7760618 | AY9: =Z9/F9 -> 8.6316602 | AZ9: =AN9/F9 -> 2.0527336 | BA9: =AS9/F9 -> 7.6566963 | BC9: 37862.889 | BD9: =K9+R9+X9+AQ9 -> 48882.733 | BE9: =M9+T9+Z9+AS9 -> 43972.684 | BG9: 179.44497 | BH9: =BD9/H9 -> 145.70114 | BI9: =BE9/F9 -> 169.7787
B10: 45385 | D10: 0.4943 | F10: 260 | H10: 335.5 | J10: 29160 | K10: =1306020/30 -> 43534 | L10: 33488 | M10: =J10*1.39 -> 40532.4 | O10: 0 | P10: =2217/30 -> 73.9 | Q10: 0 | R10: =14500/30 -> 483.33333 | S10: 0 | T10: =O10*5.86 -> 0 | V10: 552 | W10: =17949/30 -> 598.3 | X10: =87230/30 -> 2907.6667 | Y10: 2435.38 | Z10: 2682.72 | AB10: 387.24 | AC10: =AB10*3.73 -> 1444.4052 | AD10: =((15538/4)*3)/30 -> 388.45 | AE10: =((58732/4)*3)/30 -> 1468.3 | AF10: 401.07 | AG10: 1495.9911 | AH10: 149.376 | AI10: =AH10*3.73 -> 557.17248 | AJ10: =(15538/4)/30 -> 129.48333 | AK10: =(58732/4)/30 -> 489.43333 | AL10: 144.708 | AM10: 539.76084 | AN10: =AB10+AH10 -> 536.616 | AO10: =AF10+AL10 -> 545.778 | AP10: =AD10+AJ10 -> 517.93333 | AQ10: =58732/30 -> 1957.7333 | AR10: 2035.7519 | AS10: =AC10+AI10 -> 2001.5777 | AV10: 112.15385 | AW10: =(M10+T10)/F10 -> 155.89385 | AX10: =V10/F10 -> 2.1230769 | AY10: =Z10/F10 -> 10.318154 | AZ10: =AN10/F10 -> 2.0639077 | BA10: =AS10/F10 -> 7.6983757 | BC10: 37959.132 | BD10: =K10+R10+X10+AQ10 -> 48882.733 | BE10: =M10+T10+Z10+AS10 -> 45216.698 | BG10: 162.21851 | BH10: =BD10/H10 -> 145.70114 | BI10: =BE10/F10 -> 173.91038
B11: 45386 | D11: 0.54 | F11: 286 | H11: 335.5 | J11: 28200 | K11: =1306020/30 -> 43534 | L11: 33124 | M11: =J11*1.39 -> 39198 | O11: 0 | P11: =2217/30 -> 73.9 | Q11: 0 | R11: =14500/30 -> 483.33333 | S11: 0 | T11: =O11*5.86 -> 0 | V11: 519 | W11: =17949/30 -> 598.3 | X11: =87230/30 -> 2907.6667 | Y11: 2463.16 | Z11: 2522.34 | AB11: 368.8 | AC11: =AB11*3.73 -> 1375.624 | AD11: =((15538/4)*3)/30 -> 388.45 | AE11: =((58732/4)*3)/30 -> 1468.3 | AF11: 391.85 | AG11: 1461.6005 | AH11: 158.712 | AI11: =AH11*3.73 -> 591.99576 | AJ11: =(15538/4)/30 -> 129.48333 | AK11: =(58732/4)/30 -> 489.43333 | AL11: 149.376 | AM11: 557.17248 | AN11: =AB11+AH11 -> 527.512 | AO11: =AF11+AL11 -> 541.226 | AP11: =AD11+AJ11 -> 517.93333 | AQ11: =58732/30 -> 1957.7333 | AR11: 2018.773 | AS11: =AC11+AI11 -> 1967.6198 | AV11: 98.601399 | AW11: =(M11+T11)/F11 -> 137.05594 | AX11: =V11/F11 -> 1.8146853 | AY11: =Z11/F11 -> 8.8193706 | AZ11: =AN11/F11 -> 1.8444476 | BA11: =AS11/F11 -> 6.8797894 | BC11: 37605.933 | BD11: =K11+R11+X11+AQ11 -> 48882.733 | BE11: =M11+T11+Z11+AS11 -> 43687.96 | BG11: 151.02784 | BH11: =BD11/H11 -> 145.70114 | BI11: =BE11/F11 -> 152.7551
B12: 45387 | D12: 0.481 | F12: 253 | H12: 335.5 | J12: 30080 | K12: =1306020/30 -> 43534 | L12: 35880 | M12: =J12*1.39 -> 41811.2 | O12: 0 | P12: =2217/30 -> 73.9 | Q12: 0 | R12: =14500/30 -> 483.33333 | S12: 0 | T12: =O12*5.86 -> 0 | V12: 549 | W12: =17949/30 -> 598.3 | X12: =87230/30 -> 2907.6667 | Y12: 2268.7 | Z12: 2668.14 | AB12: 414.9 | AC12: =AB12*3.73 -> 1547.577 | AD12: =((15538/4)*3)/30 -> 388.45 | AE12: =((58732/4)*3)/30 -> 1468.3 | AF12: 414.9 | AG12: 1547.577 | AH12: 158.712 | AI12: =AH12*3.73 -> 591.99576 | AJ12: =(15538/4)/30 -> 129.48333 | AK12: =(58732/4)/30 -> 489.43333 | AL12: 163.38 | AM12: 609.4074 | AN12: =AB12+AH12 -> 573.612 | AO12: =AF12+AL12 -> 578.28 | AP12: =AD12+AJ12 -> 517.93333 | AQ12: =58732/30 -> 1957.7333 | AR12: 2156.9844 | AS12: =AC12+AI12 -> 2139.5728 | AV12: 118.89328 | AW12: =(M12+T12)/F12 -> 165.26166 | AX12: =V12/F12 -> 2.1699605 | AY12: =Z12/F12 -> 10.546008 | AZ12: =AN12/F12 -> 2.2672411 | BA12: =AS12/F12 -> 8.4568093 | BC12: 40305.684 | BD12: =K12+R12+X12+AQ12 -> 48882.733 | BE12: =M12+T12+Z12+AS12 -> 46618.913 | BG12: 161.87022 | BH12: =BD12/H12 -> 145.70114 | BI12: =BE12/F12 -> 184.26448
B13: 45388 | D13: 0.519 | F13: 273 | H13: 335.5 | J13: 30160 | K13: =1306020/30 -> 43534 | L13: 35932 | M13: =J13*1.39 -> 41922.4 | O13: 0 | P13: =2217/30 -> 73.9 | Q13: 0 | R13: =14500/30 -> 483.33333 | S13: 0 | T13: =O13*5.86 -> 0 | V13: 525 | W13: =17949/30 -> 598.3 | X13: =87230/30 -> 2907.6667 | Y13: 2694.66 | Z13: 2551.5 | AB13: 428.73 | AC13: =AB13*3.73 -> 1599.1629 | AD13: =((15538/4)*3)/30 -> 388.45 | AE13: =((58732/4)*3)/30 -> 1468.3 | AF13: 378.02 | AG13: 1410.0146 | AH13: 149.376 | AI13: =AH13*3.73 -> 557.17248 | AJ13: =(15538/4)/30 -> 129.48333 | AK13: =(58732/4)/30 -> 489.43333 | AL13: 149.376 | AM13: 557.17248 | AN13: =AB13+AH13 -> 578.106 | AO13: =AF13+AL13 -> 527.396 | AP13: =AD13+AJ13 -> 517.93333 | AQ13: =58732/30 -> 1957.7333 | AR13: 1967.1871 | AS13: =AC13+AI13 -> 2156.3354 | AV13: 110.47619 | AW13: =(M13+T13)/F13 -> 153.5619 | AX13: =V13/F13 -> 1.9230769 | AY13: =Z13/F13 -> 9.3461538 | AZ13: =AN13/F13 -> 2.1176044 | BA13: =AS13/F13 -> 7.8986644 | BC13: 40593.847 | BD13: =K13+R13+X13+AQ13 -> 48882.733 | BE13: =M13+T13+Z13+AS13 -> 46630.235 | BG13: 150.34758 | BH13: =BD13/H13 -> 145.70114 | BI13: =BE13/F13 -> 170.80672
B14: 45389 | D14: 0.4753 | F14: 250 | H14: 335.5 | J14: 28680 | K14: =1306020/30 -> 43534 | L14: 39052 | M14: =J14*1.39 -> 39865.2 | O14: 0 | P14: =2217/30 -> 73.9 | Q14: 20 | R14: =14500/30 -> 483.33333 | S14: 0 | T14: =O14*5.86 -> 0 | V14: 508 | W14: =17949/30 -> 598.3 | X14: =87230/30 -> 2907.6667 | Y14: 2222.4 | Z14: 2468.88 | AB14: 414.9 | AC14: =AB14*3.73 -> 1547.577 | AD14: =((15538/4)*3)/30 -> 388.45 | AE14: =((58732/4)*3)/30 -> 1468.3 | AF14: 405.68 | AG14: 1513.1864 | AH14: 158.712 | AI14: =AH14*3.73 -> 591.99576 | AJ14: =(15538/4)/30 -> 129.48333 | AK14: =(58732/4)/30 -> 489.43333 | AL14: 177.384 | AM14: 661.64232 | AN14: =AB14+AH14 -> 573.612 | AO14: =AF14+AL14 -> 583.064 | AP14: =AD14+AJ14 -> 517.93333 | AQ14: =58732/30 -> 1957.7333 | AR14: 2174.8287 | AS14: =AC14+AI14 -> 2139.5728 | AV14: 114.8 | AW14: =(M14+T14)/F14 -> 159.4608 | AX14: =V14/F14 -> 2.032 | AY14: =Z14/F14 -> 9.87552 | AZ14: =AN14/F14 -> 2.294448 | BA14: =AS14/F14 -> 8.558291 | BC14: 43449.229 | BD14: =K14+R14+X14+AQ14 -> 48882.733 | BE14: =M14+T14+Z14+AS14 -> 44473.653 | BG14: 164.58041 | BH14: =BD14/H14 -> 145.70114 | BI14: =BE14/F14 -> 177.89461
B15: 45390 | D15: 0.4848 | F15: 255 | H15: 335.5 | J15: 26560 | K15: =1306020/30 -> 43534 | L15: 39156 | M15: =J15*1.39 -> 36918.4 | O15: 0 | P15: =2217/30 -> 73.9 | Q15: 0 | R15: =14500/30 -> 483.33333 | S15: 0 | T15: =O15*5.86 -> 0 | V15: 527 | W15: =17949/30 -> 598.3 | X15: =87230/30 -> 2907.6667 | Y15: 2074.24 | Z15: 2561.22 | AB15: 401.07 | AC15: =AB15*3.73 -> 1495.9911 | AD15: =((15538/4)*3)/30 -> 388.45 | AE15: =((58732/4)*3)/30 -> 1468.3 | AF15: 424.12 | AG15: 1581.9676 | AH15: 144.708 | AI15: =AH15*3.73 -> 539.76084 | AJ15: =(15538/4)/30 -> 129.48333 | AK15: =(58732/4)/30 -> 489.43333 | AL15: 144.708 | AM15: 539.76084 | AN15: =AB15+AH15 -> 545.778 | AO15: =AF15+AL15 -> 568.828 | AP15: =AD15+AJ15 -> 517.93333 | AQ15: =58732/30 -> 1957.7333 | AR15: 2121.7284 | AS15: =AC15+AI15 -> 2035.7519 | AV15: 104.15686 | AW15: =(M15+T15)/F15 -> 144.77804 | AX15: =V15/F15 -> 2.0666667 | AY15: =Z15/F15 -> 10.044 | AZ15: =AN15/F15 -> 2.1403059 | BA15: =AS15/F15 -> 7.9833409 | BC15: 43351.968 | BD15: =K15+R15+X15+AQ15 -> 48882.733 | BE15: =M15+T15+Z15+AS15 -> 41515.372 | BG15: 157.07235 | BH15: =BD15/H15 -> 145.70114 | BI15: =BE15/F15 -> 162.80538
B16: 45391 | D16: 0.5513 | F16: 290 | H16: 335.5 | J16: 29960 | K16: =1306020/30 -> 43534 | L16: 39260 | M16: =J16*1.39 -> 41644.4 | O16: 0 | P16: =2217/30 -> 73.9 | Q16: 0 | R16: =14500/30 -> 483.33333 | S16: 0 | T16: =O16*5.86 -> 0 | V16: 540 | W16: =17949/30 -> 598.3 | X16: =87230/30 -> 2907.6667 | Y16: 2486.31 | Z16: 2624.4 | AB16: 419.51 | AC16: =AB16*3.73 -> 1564.7723 | AD16: =((15538/4)*3)/30 -> 388.45 | AE16: =((58732/4)*3)/30 -> 1468.3 | AF16: 391.85 | AG16: 1461.6005 | AH16: 154.044 | AI16: =AH16*3.73 -> 574.58412 | AJ16: =(15538/4)/30 -> 129.48333 | AK16: =(58732/4)/30 -> 489.43333 | AL16: 130.704 | AM16: 487.52592 | AN16: =AB16+AH16 -> 573.554 | AO16: =AF16+AL16 -> 522.554 | AP16: =AD16+AJ16 -> 517.93333 | AQ16: =58732/30 -> 1957.7333 | AR16: 1949.1264 | AS16: =AC16+AI16 -> 2139.3564 | AV16: 103.31034 | AW16: =(M16+T16)/F16 -> 143.60138 | AX16: =V16/F16 -> 1.862069 | AY16: =Z16/F16 -> 9.0496552 | AZ16: =AN16/F16 -> 1.9777724 | BA16: =AS16/F16 -> 7.3770911 | BC16: 43695.436 | BD16: =K16+R16+X16+AQ16 -> 48882.733 | BE16: =M16+T16+Z16+AS16 -> 46408.156 | BG16: 166.77647 | BH16: =BD16/H16 -> 145.70114 | BI16: =BE16/F16 -> 160.02813
B17: 45392 | D17: 0.692 | F17: 364 | H17: 335.5 | J17: 33080 | K17: =1306020/30 -> 43534 | L17: 41132 | M17: =J17*1.39 -> 45981.2 | O17: 0 | P17: =2217/30 -> 73.9 | Q17: 0 | R17: =14500/30 -> 483.33333 | S17: 0 | T17: =O17*5.86 -> 0 | V17: 599 | W17: =17949/30 -> 598.3 | X17: =87230/30 -> 2907.6667 | Y17: 2176.1 | Z17: 2911.14 | AB17: 497.88 | AC17: =AB17*3.73 -> 1857.0924 | AD17: =((15538/4)*3)/30 -> 388.45 | AE17: =((58732/4)*3)/30 -> 1468.3 | AF17: 414.9 | AG17: 1547.577 | AH17: 247.404 | AI17: =AH17*3.73 -> 922.81692 | AJ17: =(15538/4)/30 -> 129.48333 | AK17: =(58732/4)/30 -> 489.43333 | AL17: 149.376 | AM17: 557.17248 | AN17: =AB17+AH17 -> 745.284 | AO17: =AF17+AL17 -> 564.276 | AP17: =AD17+AJ17 -> 517.93333 | AQ17: =58732/30 -> 1957.7333 | AR17: 2104.7495 | AS17: =AC17+AI17 -> 2779.9093 | AV17: 90.879121 | AW17: =(M17+T17)/F17 -> 126.32198 | AX17: =V17/F17 -> 1.6456044 | AY17: =Z17/F17 -> 7.9976374 | AZ17: =AN17/F17 -> 2.0474835 | BA17: =AS17/F17 -> 7.6371135 | BC17: 45412.849 | BD17: =K17+R17+X17+AQ17 -> 48882.733 | BE17: =M17+T17+Z17+AS17 -> 51672.249 | BG17: 181.6514 | BH17: =BD17/H17 -> 145.70114 | BI17: =BE17/F17 -> 141.95673
B18: 45393 | D18: 0.8384 | F18: 441 | H18: 335.5 | J18: 34240 | K18: =1306020/30 -> 43534 | L18: 39208 | M18: =J18*1.39 -> 47593.6 | O18: 0 | P18: =2217/30 -> 73.9 | Q18: 0 | R18: =14500/30 -> 483.33333 | S18: 0 | T18: =O18*5.86 -> 0 | V18: 596 | W18: =17949/30 -> 598.3 | X18: =87230/30 -> 2907.6667 | Y18: 2185.36 | Z18: 2896.56 | AB18: 525.54 | AC18: =AB18*3.73 -> 1960.2642 | AD18: =((15538/4)*3)/30 -> 388.45 | AE18: =((58732/4)*3)/30 -> 1468.3 | AF18: 401.07 | AG18: 1495.9911 | AH18: 196.056 | AI18: =AH18*3.73 -> 731.28888 | AJ18: =(15538/4)/30 -> 129.48333 | AK18: =(58732/4)/30 -> 489.43333 | AL18: 149.376 | AM18: 557.17248 | AN18: =AB18+AH18 -> 721.596 | AO18: =AF18+AL18 -> 550.446 | AP18: =AD18+AJ18 -> 517.93333 | AQ18: =58732/30 -> 1957.7333 | AR18: 2053.1636 | AS18: =AC18+AI18 -> 2691.5531 | AV18: 77.641723 | AW18: =(M18+T18)/F18 -> 107.922 | AX18: =V18/F18 -> 1.3514739 | AY18: =Z18/F18 -> 6.5681633 | AZ18: =AN18/F18 -> 1.6362721 | BA18: =AS18/F18 -> 6.103295 | BC18: 43446.524 | BD18: =K18+R18+X18+AQ18 -> 48882.733 | BE18: =M18+T18+Z18+AS18 -> 53181.713 | BG18: 171.04931 | BH18: =BD18/H18 -> 145.70114 | BI18: =BE18/F18 -> 120.59345
B19: 45394 | D19: 0.8574 | F19: 451 | H19: 335.5 | J19: 35560 | K19: =1306020/30 -> 43534 | L19: 37596 | M19: =J19*1.39 -> 49428.4 | O19: 0 | P19: =2217/30 -> 73.9 | Q19: 0 | R19: =14500/30 -> 483.33333 | S19: 0 | T19: =O19*5.86 -> 0 | V19: 683 | W19: =17949/30 -> 598.3 | X19: =87230/30 -> 2907.6667 | Y19: 2375.19 | Z19: 3319.38 | AB19: 534.76 | AC19: =AB19*3.73 -> 1994.6548 | AD19: =((15538/4)*3)/30 -> 388.45 | AE19: =((58732/4)*3)/30 -> 1468.3 | AF19: 461 | AG19: 1719.53 | AH19: 200.724 | AI19: =AH19*3.73 -> 748.70052 | AJ19: =(15538/4)/30 -> 129.48333 | AK19: =(58732/4)/30 -> 489.43333 | AL19: 168.048 | AM19: 626.81904 | AN19: =AB19+AH19 -> 735.484 | AO19: =AF19+AL19 -> 629.048 | AP19: =AD19+AJ19 -> 517.93333 | AQ19: =58732/30 -> 1957.7333 | AR19: 2346.349 | AS19: =AC19+AI19 -> 2743.3553 | AV19: 78.847007 | AW19: =(M19+T19)/F19 -> 109.59734 | AX19: =V19/F19 -> 1.5144124 | AY19: =Z19/F19 -> 7.3600443 | AZ19: =AN19/F19 -> 1.6307849 | BA19: =AS19/F19 -> 6.0828278 | BC19: 42317.539 | BD19: =K19+R19+X19+AQ19 -> 48882.733 | BE19: =M19+T19+Z19+AS19 -> 55491.135 | BG19: 169.27016 | BH19: =BD19/H19 -> 145.70114 | BI19: =BE19/F19 -> 123.04021
... B37: 45412 | D37: 0.5551 | F37: 291 | H37: 335.5 | J37: 32560 | K37: =1306020/30 -> 43534 | L37: 41652 | M37: =J37*1.39 -> 45258.4 | O37: 0 | P37: =2217/30 -> 73.9 | Q37: 0 | R37: =14500/30 -> 483.33333 | S37: 0 | T37: =O37*5.86 -> 0 | V37: 512 | W37: =17949/30 -> 598.3 | X37: =87230/30 -> 2907.6667 | Y37: 1930.71 | Z37: 2488.32 | AB37: 461 | AC37: =AB37*3.73 -> 1719.53 | AD37: =((15538/4)*3)/30 -> 388.45 | AE37: =((58732/4)*3)/30 -> 1468.3 | AF37: 516.32 | AG37: 1925.8736 | AH37: 154.044 | AI37: =AH37*3.73 -> 574.58412 | AJ37: =(15538/4)/30 -> 129.48333 | AK37: =(58732/4)/30 -> 489.43333 | AL37: 168.048 | AM37: 626.81904 | AN37: =AB37+AH37 -> 615.044 | AO37: =AF37+AL37 -> 684.368 | AP37: =AD37+AJ37 -> 517.93333 | AQ37: =58732/30 -> 1957.7333 | AR37: 2552.6926 | AS37: =AC37+AI37 -> 2294.1141 | AV37: 111.89003 | AW37: =(M37+T37)/F37 -> 155.52715 | AX37: =V37/F37 -> 1.7594502 | AY37: =Z37/F37 -> 8.5509278 | AZ37: =AN37/F37 -> 2.1135533 | BA37: =AS37/F37 -> 7.8835537 | BC37: 46135.403 | BD37: =K37+R37+X37+AQ37 -> 48882.733 | BE37: =M37+T37+Z37+AS37 -> 50040.834 | BG37: 160.75053 | BH37: =BD37/H37 -> 145.70114 | BI37: =BE37/F37 -> 171.96163
B39: TOTAL | D39: =AVERAGE(D8:D38) -> 0.63662 | F39: =SUM(F8:F38) -> 10046 | H39: =SUM(H8:H38) -> 10065 | J39: =SUM(J8:J38) -> 997240 | K39: =SUM(K8:K38) -> 1306020 | L39: =SUM(L8:L38) -> 1250028 | M39: =SUM(M8:M38) -> 1386163.6 | O39: =SUM(O8:O38) -> 0 | P39: =SUM(P8:P38) -> 2217 | Q39: =SUM(Q8:Q38) -> 20 | R39: =SUM(R8:R38) -> 14500 | S39: =SUM(S8:S38) -> 0 | T39: =SUM(T8:T38) -> 0 | V39: =SUM(V8:V38) -> 17102 | W39: =SUM(W8:W38) -> 17949 | X39: =SUM(X8:X38) -> 87230 | Y39: =SUM(Y8:Y38) -> 75274.54 | Z39: =SUM(Z8:Z38) -> 83115.72 | AB39: =SUM(AB8:AB38) -> 13899.15 | AC39: =SUM(AC8:AC38) -> 51843.829 | AD39: =SUM(AD8:AD38) -> 11653.5 | AE39: =SUM(AE8:AE38) -> 44049 | AF39: =SUM(AF8:AF38) -> 13779.29 | AG39: =SUM(AG8:AG38) -> 51396.752 | AH39: =SUM(AH8:AH38) -> 5111.46 | AI39: =SUM(AI8:AI38) -> 19065.746 | ... AS39: =SUM(AS8:AS38) -> 70909.575 | AV39: =AVERAGE(AV8:AV38) -> 100.78468 | AW39: =AVERAGE(AW8:AW38) -> 140.087 | AX39: =AVERAGE(AX8:AX38) -> 1.727975 | AY39: =AVERAGE(AY8:AY38) -> 8.3979585 | AZ39: =AVERAGE(AZ8:AZ38) -> 1.9173273 | BA39: =AVERAGE(BA8:BA38) -> 7.1516307 | BC39: =SUM(BC8:BC38) -> 1396687.9 | BD39: =SUM(BD8:BD38) -> 1466482 | BE39: =SUM(BE8:BE38) -> 1540188.9 | BG39: 155.41202 | BH39: =AVERAGE(BH8:BH38) -> 145.70114 | BI39: =AVERAGE(BI8:BI38) -> 155.63659
J42: =+J39/30 -> 33241.333 | K42: 0.64
J43: =+J42*K43 -> 27257.893 | K43: 0.82
J44: =+J43/K42 -> 42590.458 | L44: =+J44*30 -> 1277713.7
L46: =+L44*1.94 -> 2478764.7

Sheet Sheet1
B5: Daily Observations
B6: Time | C6: Temperature (° C) | F6: Dew Point (° C) | I6: Humidity (%) | L6: Wind Speed (mph) | O6: Pressure (Hg) | R6: Precipitation (in)
B7: Jun | C7: Max | D7: Avg | E7: Min | F7: Max | G7: Avg | H7: Min | I7: Max | J7: Avg | K7: Min | L7: Max | M7: Avg | N7: Min | O7: Max | P7: Avg | Q7: Min
B8: 1 | C8: 35 | D8: 29.8 | E8: 25 | F8: 14 | G8: 10.3 | H8: 7 | I8: 50 | J8: 31 | K8: 20 | L8: 37 | M8: 23.4 | N8: 4 | O8: 1003.9 | P8: 1002.9 | Q8: 1001.9
B9: 2 | C9: 39 | D9: 33.4 | E9: 26 | F9: 12 | G9: 8.6 | H9: 4 | I9: 42 | J9: 22.9 | K9: 14 | L9: 33 | M9: 13.8 | N9: 0 | O9: 1001.9 | P9: 1000.2 | Q9: 998.9
B10: 3 | C10: 33 | D10: 28.9 | E10: 24 | F10: 17 | G10: 12.1 | H10: 7 | I10: 65 | J10: 37.2 | K10: 20 | L10: 30 | M10: 16.3 | N10: 0 | O10: 1005.9 | P10: 1003.7 | Q10: 1001.9
B11: 4 | C11: 36 | D11: 31.1 | E11: 26 | F11: 15 | G11: 11.7 | H11: 10 | I11: 51 | J11: 31.3 | K11: 20 | L11: 30 | M11: 16.1 | N11: 6 | O11: 1004.9 | P11: 1003.4 | Q11: 1001.9
B12: 5 | C12: 36 | D12: 30.8 | E12: 26 | F12: 18 | G12: 15.1 | H12: 12 | I12: 61 | J12: 39.5 | K12: 28 | L12: 35 | M12: 25.1 | N12: 11 | O12: 1004.9 | P12: 1002.9 | Q12: 1000.9
B13: 6 | C13: 37 | D13: 31.4 | E13: 27 | F13: 17 | G13: 14.7 | H13: 11 | I13: 54 | J13: 37.6 | K13: 21 | L13: 28 | M13: 14.5 | N13: 0 | O13: 1004.9 | P13: 1002.6 | Q13: 1000.9
B14: 7 | C14: 39 | D14: 32.2 | E14: 28 | F14: 18 | G14: 15.3 | H14: 13 | I14: 48 | J14: 36.9 | K14: 22 | L14: 22 | M14: 9.2 | N14: 0 | O14: 1002.9 | P14: 1001 | Q14: 999.9
B15: 8 | C15: 39 | D15: 33.7 | E15: 26 | F15: 21 | G15: 15.5 | H15: 12 | I15: 51 | J15: 34.5 | K15: 20 | L15: 19 | M15: 8.4 | N15: 0 | O15: 1000.9 | P15: 999.3 | Q15: 997.9
B16: 9 | C16: 38 | D16: 33 | E16: 29 | F16: 16 | G16: 14.1 | H16: 12 | I16: 45 | J16: 32.3 | K16: 21 | L16: 28 | M16: 15.9 | N16: 6 | O16: 1001.9 | P16: 1000.1 | Q16: 998.9
B17: 10 | C17: 38 | D17: 33 | E17: 28 | F17: 17 | G17: 13.5 | H17: 9 | I17: 51 | J17: 32 | K17: 18 | L17: 37 | M17: 22.5 | N17: 9 | O17: 1002.9 | P17: 1001.9 | Q17: 1000.9
B18: 11 | C18: 38 | D18: 33.5 | E18: 29 | F18: 17 | G18: 14.2 | H18: 12 | I18: 45 | J18: 31.5 | K18: 22 | L18: 31 | M18: 23.9 | N18: 19 | O18: 1003.9 | P18: 1002.1 | Q18: 1000.9
B19: 12 | C19: 37 | D19: 31.9 | E19: 26 | F19: 17 | G19: 15.6 | H19: 14 | I19: 51 | J19: 37.9 | K19: 29 | L19: 44 | M19: 32.5 | N19: 20 | O19: 1002.9 | P19: 1001.6 | Q19: 1000.9
... B37: 30 | C37: 37 | D37: 33.7 | E37: 29 | F37: 15 | G37: 11.5 | H37: 8 | I37: 40 | J37: 26.3 | K37: 19 | L37: 26 | M37: 17.1 | N37: 7 | O37: 998.9 | P37: 997 | Q37: 996

Sheet Daily Consumption new
A2: Date: | B2: =TODAY()-1 -> 45786
A4: Energy Consumption
I5: Month To Date Energy Cost per Occupied Room
B6: Today | E6: Month To Date
B7: Actual | C7: Budget | D7: Last Year | E7: Actual | F7: Budget | G7: Last Year
A9: Occupied Rooms | B9: 274 | C9: ='Reading.5.25'!AO6 -> 286.45161 | D9: 225 | E9: ='Reading.5.25'!AM37 -> 3337.0492 | F9: ='cost.5.25'!H39 -> 1707.4286 | G9: ='Reading.5.25'!AN37 -> 2371
A10: Occupancy | B10: 0.58 | C10: ='Reading.5.25'!AK6 -> 0.545 | D10: 0.43 | E10: ='Reading.5.25'!AI37 -> 0.793025 | F10: ='Reading.5.25'!AK37:AK37 -> 0.545 | G10: ='Reading.5.25'!AJ37 -> 0.5671875
A12: Electricity - KWH | B12: ='Reading.5.25'!AE30 -> 0 | C12: ='Reading.5.25'!AG6 -> 38659.097 | D12: ='Reading.5.25'!AF30 -> 0 | E12: ='Reading.5.25'!AE37 -> 295880 | F12: ='Reading.5.25'!AG37 -> 309272.77 | G12: ='Reading.5.25'!AF37 -> 267520
A13: Fuel - Liter | B13: 0 | C13: ='cost.5.25'!P8 -> 0 | D13: 0 | E13: ='Reading.5.25'!T37 -> 0 | F13: ='cost.5.25'!P39 -> 0 | G13: ='Reading.5.25'!U37 -> 0
A15: Boilers Gas - Cu.Mt. | B15: ='Reading.5.25'!O30 -> 0 | C15: ='cost.5.25'!AD8 -> 522.72581 | D15: ='Reading.5.25'!P30 -> 0 | E15: ='Reading.5.25'!O37 -> 5306.11 | F15: ='cost.5.25'!AD39 -> 4181.8065 | G15: ='Reading.5.25'!P37 -> 3881.62
A16: Kitchens Gas - Cu. Mt. | B16: ='Reading.5.25'!K30 -> 0 | C16: ='cost.5.25'!AJ8 -> 174.24194 | D16: ='Reading.5.25'!L30 -> 0 | E16: ='Reading.5.25'!K37 -> 2067.924 | F16: ='cost.5.25'!AJ39 -> 1393.9355 | G16: ='Reading.5.25'!L37 -> 1423.74
A18: Water To Staff House - Cu.Mt. | B18: ='Reading.5.25'!CJ30 -> 0 | C18: 0 | D18: 0 | E18: ='Reading.5.25'!#REF! -> #REF! | F18: 0 | G18: ='Reading.5.25'!BN37 -> 0
A19: Hotel Water - Cu.Mt. | B19: 493 | C19: 496 | D19: 529 | E19: ='Reading.5.25'!G37 -> 5442 | F19: ='cost.5.25'!W39 -> 4863.2258 | G19: ='Reading.5.25'!H37 -> 4450
A21: Total Energy Cost - L.E. | B21: ='cost.5.25'!BE32 -> 0 | C21: ='cost.5.25'!BD8 -> 86204.29 | D21: ='cost.5.25'!BC32 -> 0 | E21: ='cost.5.25'!BE39 -> 629824.89 | F21: ='cost.5.25'!BD39 -> 689634.32 | G21: ='cost.5.25'!BC39 -> 313464.72
A22: Energy Cost per Occupied Room | B22: =B21/B9 -> 0 | C22: =C21/C9 -> 300.9384 | D22: =D21/D9 -> 0 | E22: ='cost.5.25'!BI39 -> 189.86451 | F22: =F21/F9 -> 403.9023 | G22: =G21/G9 -> 132.20781
A23: Energy Cost per Available Room | B23: =B21/526 -> 0 | C23: =C21/526 -> 163.88648 | D23: =D22/D10 -> 0 | E23: =E21/(526*25) -> 47.895429 | F23: =F21/11572 -> 59.595085 | G23: =G22/G10 -> 233.09366
A24: Energy Forcast per Occupied Room | B24: =B22 -> 0 | C24: 213 | D24: =D23/D11 -> #DIV/0! | E24: =E22 -> 189.86451 | F24: =C24 -> 213 | G24: =G23/G11 -> #DIV/0!
A25: Energy Forcast per Available Room | B25: =B23 -> 0 | C25: 76.82 | D25: =D23/D11 -> #DIV/0! | E25: =E23 -> 47.895429 | F25: =C25 -> 76.82 | G25: =G23/G11 -> #DIV/0!
A46: Month To Date Electricity Consumption | D46: Month To Date Boilers' Gas Consumption | I46: Month To Date Kitchens' Gas Consumption
D47: Laundry Performance | I47: Kitchens Performance
A48: Electricity Maximum Demand KW | B48: Today | D48: Target | E48: Last Year
B49: Actual | C49: Last Period | D49: This Period | E49: This Period
B50: ='Reading.5.25'!AQ37 -> 2056 | C50: ='Reading.5.25'!AQ38 -> 2216 | D50: 2180 | E50: 2120
A52: Weather Temperature ⁰C | B52: Today | D52: Month To Date
B53: Actual | C53: Last year | D53: Actual | E53: Last Year
B54: 36 | C54: 31 | D54: ='Reading.5.25'!BC37 -> 28.375 | E54: ='Reading.5.25'!BG37 -> 80
A55: Humidity % | B55: 50 | C55: 60 | D55: ='Reading.5.25'!BF37 -> 23.75 | E55: ='Reading.5.25'!BJ37 -> 51.375
A57: Comments:

Sheet Sheet2

Sheet Sheet3
